Workbook

Sheet 2019 - 2025 PVT Budget Chp-1 
A2: Future-02 | B2: Chapter-01
A4: Row Labels | B4: 2019 Actual | C4: 2020 Actual | D4: 2021 Actual | E4: 2022 Budget | F4: 2022 Estimates Full Year Actual | G4: 2022 - Jun Actual | H4: 2022 PR | I4: 2022 PO | J4: Sum of 2023 Budget | K4: Sum of 2024 Budget | L4: Sum of 2025 Budget
A5: Chapter-01 | B5: 734104574 | C5: 541385100 | D5: 583579295 | E5: 622545692 | F5: 601695721 | G5: 273667080 | H5: 1643996 | I5: 7959693 | J5: 6.9619905e+08 | K5: 714862760 | L5: 779727079
A6: Grand Total | B6: 734104574 | C6: 541385100 | D6: 583579295 | E6: 622545692 | F6: 601695721 | G6: 273667080 | H6: 1643996 | I6: 7959693 | J6: 6.9619905e+08 | K6: 714862760 | L6: 779727079
A12: 2022 - Proposal | F12: 2022 - Revised | K12: 2023 - Proposal
C13: Budget | D13: Count | H13: Budget | I13: Counts | M13: Budget | N13: Count
A14: KU | B14: Current Employees | C14: 519842486 | D14: 776 | F14: Initial Budget | H14: 621695721 | K14: Exisiting Employees (May 2022) | L14: Salaries & Allowances | M14: 4.7495487e+08 | N14: 782
L15: Benefits | M15: 50564576
B16: Total | C16: =C14 -> 519842486 | D16: 776 | F16: Current Existing Costs (May 2022) | H16: =516184646.27-18000000 -> 4.9818465e+08 | I16: 799 | L16: Total | M16: 5.2551945e+08 | N16: 782 | O16: 378 Faculty, 389 Staff, 15 Off-Chart
A18: Expected Hires | B18: Hires 2021 | C18: 38335362 | D18: 68 | F18: New Hires Costs | G18: Hires 2022 | H18: 10917438 | I18: 91 | J18: =I16+I18 -> 890 | K18: Expected Hires | L18: To be Hired in 2022 | M18: 55245963 | N18: 80 | O18: 30 Faculty, 50 Staff
B19: Hires 2022 | C19: 39782098 | D19: 112 | L19: Manpower Plan 2023 | M19: 55306324 | N19: 139 | O19: 65 Faculty, 74 Staff
B20: Total | C20: =C18+C19 -> 78117460 | D20: 180 | E20: =D16+D20 -> 956 | L20: Total | M20: 1.1055229e+08 | N20: 219 | O20: =N16+N20 -> 1001
A21: Outsourced Employees | B21: Current Employees - Ankabut | C21: 22024007 | D21: 43 | F21: Outsourced Employees | H21: 36000000 | I21: IT 43 staff and Other staff | K21: Outsourced Employees | L21: Ankabut Employees | M21: 23136769 | N21: 43 | O21: Total current 43 in KUST + 23 in KUA (Total positions on chart 71)
B22: Hires 2022 - Ankabut | C22: 1112762 | D22: 4 | L22: Other Outsourced | M22: 13105000
B23: Total | C23: 23136769 | D23: 47 | L23: Total | M23: =SUM(M21:M22) -> 36241769 | N23: 43
A25: Central Budget and Other | B25: Total | C25: 2953893 | F25: Central Budget and Other | H25: 56593636 | K25: Central Budget and Other | L25: Total | M25: 23885544
F27: Grand Total | G27: Total | H27: 601695721
A28: Grand Total | B28: Total | C28: 624050608 | K28: Grand Total | L28: Total | M28: =M16+M20+M23+M25 -> 6.9619905e+08
F29: ** surplus budget | H29: =H14-H27 -> 20000000
N32: 45119736
N33: =N32-M21 -> 21982967

Sheet Analysis Opex
C1: Chapter 2 (operating):
C2: Grand Total | D2: =SUM(D4:D92) -> 579850000 | E2: =SUM(E4:E92) -> 2.7320624e+08 | F2: =SUM(F4:F92) -> 8.9798134e+08 | G2: =SUM(G4:G92) -> 3.1813134e+08
A3: Chp | B3: Account Code | C3: Account | D3: 2022 Budget | E3: Jun 2022 (Actula , PR, PO) | F3: 2023 Budget | G3: Sum of Diff | H3: 2023 % Compared to Budget 2022 | I3: 2023 % Budget Difference compared to total difference | J3: Comments
A4: FA179-Opex Expense | B4: 425749 | C4: 425749-Postgraduate Student Salaries | D4: 135037862 | E4: 66630460 | F4: 244626000 | G4: =F4-D4 -> 109588138 | H4: =G4/D4 -> 0.81153638 | I4: =G4/$G$2 -> 0.34447451 | J4: Compared to FY2022 budgeted graduate salary has increased by 81% and new intake students -2022 Fall = 303 -2023 Spring = 152 -2023 Fall = 303 Exiting students as of Jun 2022 = 492 | K4: Compared to year 2021-22 intake increaed in 2022-23 in percentage 76%. 2021-2022 PG students intkae 431, in 2022-23 PG students 758
A5: FA179-Opex Expense | B5: 420811 | C5: 420811-IT Systems & Support expenses-Application/Systems Operation | D5: 12949400 | E5: 276944.2 | F5: 27999051 | G5: =F5-D5 -> 15049651 | H5: =G5/D5 -> 1.162189 | I5: =G5/$G$2 -> 0.047306408 | J5: Opex IT systems & support expense compared to FY2022 increased 116%. Ankbout27M SLA adding 20M SLA support and Research computing AED 5M | K5: UPDATED
A6: FA179-Opex Expense | B6: 420570 | C6: 420570-Academic Collaborative Partnership Services | D6: 26364292 | E6: 64153.81 | F6: 56595297 | G6: =F6-D6 -> 30231005 | H6: =G6/D6 -> 1.1466648 | I6: =G6/$G$2 -> 0.095026805 | J6: Academic Collaborative Partnership Services Opex: it increased by 53% compared to FY2022. • CoM AED 33M SSMC-SEHA agreement AED 33m • The office of EVP: potential affiliation partnership for the graduate school AED 15M • President office 5M, Provost Office 3m | K6: UPDATED
A7: FA179-Opex Expense | B7: 430120 | C7: 430120-Rental - Buildings, other than staff residences | D7: 0 | E7: 0 | F7: 22219870 | G7: =F7-D7 -> 22219870 | H7: 1 | I7: =G7/$G$2 -> 0.069844958 | J7: • MASDER complex 2022 rental AED 4.587M • MASDER complex 2023 rental AED 4.632M • MASDER complex 2023 rental shortage for 275 students - new requirement from student services FY22/23 AED 5M • SAN Student Rental Accommodation four month for total of 700 students FY23 (Sep-23 to Dec-23), per project plan SAN accommodation will hand over for contractor in Sep-23
A8: FA179-Opex Expense | B8: 425741 | C8: 425741-Student stipend | D8: 80501600 | E8: 38326680 | F8: 98652604 | G8: =F8-D8 -> 18151004 | H8: =G8/D8 -> 0.22547383 | I8: =G8/$G$2 -> 0.057055064 | J8: UG stipend budget increased by 18%, Due to 2022 intake increaed by 923 and student moved to higher GPA. FY2023 new intake 650
A9: FA179-Opex Expense | B9: 435508 | C9: 435508-Laboratory - Scientific | D9: 7985186 | E9: 4531173.7 | F9: 33397354 | G9: =F9-D9 -> 25412168 | H9: =G9/D9 -> 3.182414 | I9: =G9/$G$2 -> 0.079879486 | J9: The 435508-Laboratory - Scientific increased 318% compared to FY2022 budget increased, • CoM 644% and AED 14M budgeted • CoAS 82% AED 2M • CoE 24% AED 2M • Research Lab 410% AED 1.3M | K9: UPDATED
A10: FA179-Opex Expense | B10: 435523 | C10: 435523-Scientific | D10: 100917600 | E10: 40551573 | F10: 113648860 | G10: =F10-D10 -> 12731260 | H10: =G10/D10 -> 0.126155 | I10: =G10/$G$2 -> 0.04001888 | J10: Compared FY2022 overall budget increased by 13%, exiting project 81M and new FY2023 projects awards 31M | K10: Intake year - UG and Student 2019-2020 - 798 2020-2021- 1144 2021-2022- 923 2022-2023- 650 Total - 3515
A11: FA179-Opex Expense | B11: 432120 | C11: 432120-Bldg maintenance-Business premises | D11: 22798578 | E11: 21138493 | F11: 34225569 | G11: =F11-D11 -> 11426991 | H11: =G11/D11 -> 0.50121508 | I11: =G11/$G$2 -> 0.035919099 | J11: Opex Building Maintenance overall 50% increase compared to FY2022. • It consist of Hard Service agreement 30M • Property maintaining budget for upgrade, replaced and Refurbishment AED 4M
A12: FA179-Opex Expense | B12: 425100 | C12: 425100-Advertising Services (General) | D12: 6447464 | E12: 4732387.4 | F12: 15916000 | G12: =F12-D12 -> 9468536 | H12: =G12/D12 -> 1.4685675 | I12: =G12/$G$2 -> 0.029762978 | J12: Communication budget has overall increased in FY2023 147%, it more of budget in Advertisement services which increased in compared to FY2022 157%: • General DM campaign, news content preparation, magazine content development,etc, AED 2M • Updating content in the website, creating pages, creating websites and new system AED 1M • Branding for the university rank AED 2.4M • Monthly basis operations which is varies from (TV commercials, radio, Social Media) AED 5.4M
A13: FA179-Opex Expense | B13: 421000 | C13: 421000-Management consultancy | D13: 2525900 | E13: 1542000 | F13: 8290000 | G13: =F13-D13 -> 5764100 | H13: =G13/D13 -> 2.2819985 | I13: =G13/$G$2 -> 0.018118617 | J13: Overall increased 228% compared to FY2022, • FMS consultancy service for Qruin AlAish Masterplan AED5 • PMO FM projects (Open blanket agreement) AED2
A14: FA179-Opex Expense | B14: 426610 | C14: 426610-Computer software licenses-Software License Renewal | D14: 17172519 | E14: 11830690 | F14: 21231889 | G14: =F14-D14 -> 4059370 | H14: =G14/D14 -> 0.23638757 | I14: =G14/$G$2 -> 0.012760044 | J14: Significant increase in the research computer compared FY2022 it increased by AED2.7M budget amount AED5.4m
A15: FA179-Opex Expense | B15: 428640 | C15: 428640-Events - Awards, prizes & gifts | D15: 1588000 | E15: 242575.55 | F15: 4947721 | G15: =F15-D15 -> 3359721 | H15: =G15/D15 -> 2.1156933 | I15: =G15/$G$2 -> 0.010560799 | J15: • Office of the Provost AED 2M • HR AED 1M • Communication AED 998K • Electrical & Computer Engineering AED 302K • Others 13 department budgeted AED 647
A16: FA179-Opex Expense | B16: 425550 | C16: 425550-Conferences, seminars and exhibitions and other events: - Overseas event | D16: 1796957 | E16: 87596.72 | F16: 5035030 | G16: =F16-D16 -> 3238073 | H16: =G16/D16 -> 1.8019758 | I16: =G16/$G$2 -> 0.010178416 | J16: Communication budgeted AED 2.1M and CoM budgeted AED 1.1
A17: FA179-Opex Expense | B17: 428111 | C17: 428111-Electricity consumption charges | D17: 15465717 | E17: 4197494.3 | F17: 18698211 | G17: =F17-D17 -> 3232494 | H17: =G17/D17 -> 0.20901029 | I17: =G17/$G$2 -> 0.010160879 | J17: Due to increased in the rental
A18: FA179-Opex Expense | B18: 429900 | C18: 429900-Other services, not specifically mentioned elsewhere | D18: 99510 | E18: 41250 | F18: 3288000 | G18: =F18-D18 -> 3188490 | H18: =G18/D18 -> 32.041905 | I18: =G18/$G$2 -> 0.010022559 | J18: KUST - Executive Vice President Office budgeted AED 3M for Special Projects (Projects that gets assigned by the chairman and the board) Like Khalifa COVID FACE MASK and Satellites.
A19: FA179-Opex Expense | B19: 421700 | C19: 421700-Standards Certification Services (e.g. ISO) | D19: 2271312 | E19: 368465.86 | F19: 5220000 | G19: =F19-D19 -> 2948688 | H19: =G19/D19 -> 1.2982312 | I19: =G19/$G$2 -> 0.0092687756 | J19: Provost office: 23 x CAA accreditation of programs @ 150K each + 5 x new Programs @ 150K each AED 3.45M
A20: FA179-Opex Expense | B20: 425740 | C20: 425740-Scholarships & other financial aid | D20: 694710 | E20: 0 | F20: 3600012 | G20: =F20-D20 -> 2905302 | H20: =G20/D20 -> 4.1820357 | I20: =G20/$G$2 -> 0.0091323979 | J20: KUST - Office of the Provost AED 3.6M
A21: FA179-Opex Expense | B21: 425510 | C21: 425510-Conferences, seminars and exhibitions and other events: - Local Events | D21: 8184179 | E21: 6097762.2 | F21: 10949900 | G21: =F21-D21 -> 2765721 | H21: =G21/D21 -> 0.33793506 | I21: =G21/$G$2 -> 0.0086936452 | J21: • This includes the major Events hosted such as (Graduation, National Day,KU Century Challenge ) AED 5M • KUST - Dean Of Medicine: Communication Dept. - This includes the major exhibitions participation such as (ADIPEC, IDEX, NAJAH, AD Book Fair) AED 1.12M • KUST - Career Services: Career Fair, Alumni Re-union, etc AED 1M
A22: FA179-Opex Expense | B22: 432209 | C22: 432209-Laboratory equipment | D22: 17441427 | E22: 13569787 | F22: 21267845 | G22: =F22-D22 -> 3826418 | H22: =G22/D22 -> 0.21938675 | I22: =G22/$G$2 -> 0.012027793 | J22: Compared to FY2022 budget in 2023 budget increased 22%; • CoAS:Chemistry 226% AED 980,000 • CoE:Petroleum Engineering 221% AED 979,000 • Research Laboratories 16% AED 17,597,270
... A27: FA179-Opex Expense | B27: 428090 | C27: 428090-Business Travel - Combined expenses | D27: 3458093 | E27: 76231.87 | F27: 5535090 | G27: =F27-D27 -> 2076997 | H27: =G27/D27 -> 0.60061919 | I27: =G27/$G$2 -> 0.0065287406 | J27: KUST - Executive Vice President Office Budgeted AED 1M and KUST - Office of the President AED 1M, remaining all other college budget AED 3M
A28: FA179-Opex Expense | B28: 425770 | C28: 425770-Academic Missions - Combined expenses | D28: 5589749 | E28: 519162.08 | F28: 7561925 | G28: =F28-D28 -> 1972176 | H28: =G28/D28 -> 0.35282014 | I28: =G28/$G$2 -> 0.0061992509
A29: FA179-Opex Expense | B29: 420900 | C29: 420900-Legal services | D29: 3355444 | E29: 2498518.7 | F29: 5298500 | G29: =F29-D29 -> 1943056 | H29: =G29/D29 -> 0.57907568 | I29: =G29/$G$2 -> 0.0061077164
A30: FA179-Opex Expense | B30: 425900 | C30: 425900-Entertainment and hospitality | D30: 1480064 | E30: 125625.32 | F30: 3419632 | G30: =F30-D30 -> 1939568 | H30: =G30/D30 -> 1.3104623 | I30: =G30/$G$2 -> 0.0060967524
A31: FA179-Opex Expense | B31: 425745 | C31: 425745-Student relocation & travel exps | D31: 1995663 | E31: 841645 | F31: 3929115 | G31: =F31-D31 -> 1933452 | H31: =G31/D31 -> 0.9688269 | I31: =G31/$G$2 -> 0.0060775276
A32: FA179-Opex Expense | B32: 425750 | C32: 425750-Skill assessment service | D32: 887069 | E32: 92850.06 | F32: 2704485 | G32: =F32-D32 -> 1817416 | H32: =G32/D32 -> 2.0487876 | I32: =G32/$G$2 -> 0.0057127852
A33: FA179-Opex Expense | B33: 425720 | C33: 425720-Education-Outsourced training service | D33: 2677815 | E33: 1834395.3 | F33: 4400850 | G33: =F33-D33 -> 1723035 | H33: =G33/D33 -> 0.64344811 | I33: =G33/$G$2 -> 0.0054161121
A34: FA179-Opex Expense | B34: 420550 | C34: 420550-Academic Advisory Service | D34: 1917312 | E34: 156883.8 | F34: 3540830 | G34: =F34-D34 -> 1623518 | H34: =G34/D34 -> 0.84676777 | I34: =G34/$G$2 -> 0.0051032947
A35: FA179-Opex Expense | B35: 435350 | C35: 435350-Academic Publications | D35: 2894920 | E35: 575666.04 | F35: 4515000 | G35: =F35-D35 -> 1620080 | H35: =G35/D35 -> 0.55962859 | I35: =G35/$G$2 -> 0.0050924879
A36: FA179-Opex Expense | B36: 427100 | C36: 427100-Public relations | D36: 1157850 | E36: 909458.75 | F36: 2500000 | G36: =F36-D36 -> 1342150 | H36: =G36/D36 -> 1.1591743 | I36: =G36/$G$2 -> 0.004218855
A37: FA179-Opex Expense | B37: 422900 | C37: 422900-Other specialised professional services, not mentioned elsewhere | D37: 416100 | E37: 416100 | F37: 1710000 | G37: =F37-D37 -> 1293900 | H37: =G37/D37 -> 3.109589 | I37: =G37/$G$2 -> 0.0040671881
A38: FA179-Opex Expense | B38: 430330 | C38: 430330-Rental - Motor vehicles | D38: 967680 | E38: 771960 | F38: 1870125 | G38: =F38-D38 -> 902445 | H38: =G38/D38 -> 0.93258619 | I38: =G38/$G$2 -> 0.0028367057
A39: FA179-Opex Expense | B39: 430250 | C39: 430250-Rental - Computer hardware-Rental/Subscription - Computer hardware | D39: 1021317 | E39: 1019273.8 | F39: 1864650 | G39: =F39-D39 -> 843333 | H39: =G39/D39 -> 0.82573089 | I39: =G39/$G$2 -> 0.0026508957
... A62: FA179-Opex Expense | B62: 425763 | C62: 425763-Student Project Expenses | D62: 2802590 | E62: 988267.84 | F62: 2809795 | G62: =F62-D62 -> 7205 | H62: =G62/D62 -> 0.0025708363 | I62: =G62/$G$2 -> 2.2647879e-05
A63: FA179-Opex Expense | B63: 420810 | C63: 420810-IT Systems & Support expenses | D63: 0 | E63: 0 | F63: 0 | G63: =F63-D63 -> 0 | H63: 0 | I63: =G63/$G$2 -> 0
A64: FA179-Opex Expense | B64: 422100 | C64: 422100-Waste management service | D64: 12000 | E64: 0 | F64: 12000 | G64: =F64-D64 -> 0 | H64: =G64/D64 -> 0 | I64: =G64/$G$2 -> 0
A65: FA179-Opex Expense | B65: 422400 | C65: 422400-Medical services | D65: 0 | E65: 0 | F65: 0 | G65: =F65-D65 -> 0 | H65: 0 | I65: =G65/$G$2 -> 0
A66: FA179-Opex Expense | B66: 426210 | C66: 426210-Insurance - Cash and fidelity | D66: 0 | E66: 0 | F66: 0 | G66: =F66-D66 -> 0 | H66: 0 | I66: =G66/$G$2 -> 0
A67: FA179-Opex Expense | B67: 426220 | C67: 426220-Insurance - Fire and allied perils | D67: 984151 | E67: 44981.51 | F67: 984151 | G67: =F67-D67 -> 0 | H67: =G67/D67 -> 0 | I67: =G67/$G$2 -> 0
A68: FA179-Opex Expense | B68: 426250 | C68: 426250-Insurance - Motor vehicles | D68: 50000 | E68: 14718 | F68: 50000 | G68: =F68-D68 -> 0 | H68: =G68/D68 -> 0 | I68: =G68/$G$2 -> 0
A69: FA179-Opex Expense | B69: 426290 | C69: 426290-Insurance - Other | D69: 0 | E69: 0 | F69: 0 | G69: =F69-D69 -> 0 | H69: 0 | I69: =G69/$G$2 -> 0
A70: FA179-Opex Expense | B70: 426800 | C70: 426800-Motor vehicle registration and inspection charges | D70: 10000 | E70: 848 | F70: 10000 | G70: =F70-D70 -> 0 | H70: =G70/D70 -> 0 | I70: =G70/$G$2 -> 0
A71: FA179-Opex Expense | B71: 427900 | C71: 427900-Translation and interpretation service | D71: 15000 | E71: 0 | F71: 15000 | G71: =F71-D71 -> 0 | H71: =G71/D71 -> 0 | I71: =G71/$G$2 -> 0
A72: FA179-Opex Expense | B72: 428400 | C72: 428400-Sponsorship expenses/contributions | D72: 50000 | E72: 0 | F72: 50000 | G72: =F72-D72 -> 0 | H72: =G72/D72 -> 0 | I72: =G72/$G$2 -> 0
A73: FA179-Opex Expense | B73: 430230 | C73: 430230-Rental - Equipment | D73: 0 | E73: 0 | F73: 0 | G73: =F73-D73 -> 0 | H73: 0 | I73: =G73/$G$2 -> 0
A74: FA179-Opex Expense | B74: 432540 | C74: 432540-Motor vehicles (non-military) | D74: 140000 | E74: 20578.84 | F74: 140000 | G74: =F74-D74 -> 0 | H74: =G74/D74 -> 0 | I74: =G74/$G$2 -> 0
A75: FA179-Opex Expense | B75: 432690 | C75: 432690-Plant, machinery and heavy equipment, not mentioned elsewhere | D75: 0 | E75: 0 | F75: 0 | G75: =F75-D75 -> 0 | H75: 0 | I75: =G75/$G$2 -> 0
A76: FA179-Opex Expense | B76: 435410 | C76: 435410-Catering supplies: Offices | D76: 840000 | E76: 357963.58 | F76: 840000 | G76: =F76-D76 -> 0 | H76: =G76/D76 -> 0 | I76: =G76/$G$2 -> 0
A77: FA179-Opex Expense | B77: 435510 | C77: 435510-Landscaping and other horticulture | D77: 0 | E77: 0 | F77: 0 | G77: =F77-D77 -> 0 | H77: 0 | I77: =G77/$G$2 -> 0
A78: FA179-Opex Expense | B78: 435740 | C78: 435740-Fuel, oil and lubricants: Motor vehicles | D78: 336000 | E78: 266719.75 | F78: 336000 | G78: =F78-D78 -> 0 | H78: =G78/D78 -> 0 | I78: =G78/$G$2 -> 0
A79: FA179-Opex Expense | B79: 436220 | C79: 436220-Road signs | D79: 0 | E79: 0 | F79: 0 | G79: =F79-D79 -> 0 | H79: 0 | I79: =G79/$G$2 -> 0
A80: FA179-Opex Expense | B80: 425300 | C80: 425300-Banking service charges / Fees | D80: 3600 | E80: 246.14 | F80: 2400 | G80: =F80-D80 -> -1200 | H80: =G80/D80 -> -0.33333333 | I80: =G80/$G$2 -> -3.772027e-06
A81: FA179-Opex Expense | B81: 426900 | C81: 426900-Postal, courier and other document delivery expenses | D81: 72000 | E81: 11503.29 | F81: 56190 | G81: =F81-D81 -> -15810 | H81: =G81/D81 -> -0.21958333 | I81: =G81/$G$2 -> -4.9696455e-05
A82: FA179-Opex Expense | B82: 436340 | C82: 436340 - Sports and other recreational supplies: Students | D82: 20000 | E82: 0 | F82: 0 | G82: =F82-D82 -> -20000 | H82: =G82/D82 -> -1 | I82: =G82/$G$2 -> -6.2867116e-05
A83: FA179-Opex Expense | B83: 435519 | C83: 435519-Photography - Consumable materials /Tools | D83: 155000 | E83: 43812 | F83: 135000 | G83: =F83-D83 -> -20000 | H83: =G83/D83 -> -0.12903226 | I83: =G83/$G$2 -> -6.2867116e-05
A84: FA179-Opex Expense | B84: 420130 | C84: 420130-External Audit service | D84: 295000 | E84: 171100 | F84: 236850 | G84: =F84-D84 -> -58150 | H84: =G84/D84 -> -0.19711864 | I84: =G84/$G$2 -> -0.00018278614
A85: FA179-Opex Expense | B85: 428200 | C85: 428200-Health,safety&environment awareness | D85: 890000 | E85: 638092.87 | F85: 690000 | G85: =F85-D85 -> -200000 | H85: =G85/D85 -> -0.2247191 | I85: =G85/$G$2 -> -0.00062867116
A86: FA179-Opex Expense | B86: 425747 | C86: 425747-Student Accommodation | D86: 225000 | E86: 81632 | F86: 0 | G86: =F86-D86 -> -225000 | H86: =G86/D86 -> -1 | I86: =G86/$G$2 -> -0.00070725506
A87: FA179-Opex Expense | B87: 425743 | C87: 425743-Graduation rewards | D87: 240000 | E87: 240000 | F87: 0 | G87: =F87-D87 -> -240000 | H87: =G87/D87 -> -1 | I87: =G87/$G$2 -> -0.0007544054
A88: FA179-Opex Expense | B88: 420310 | C88: 420310-Cleaning Services: Business premises | D88: 9167788 | E88: 9126376.8 | F88: 8921788 | G88: =F88-D88 -> -246000 | H88: =G88/D88 -> -0.026833081 | I88: =G88/$G$2 -> -0.00077326553
A89: FA179-Opex Expense | B89: 421600 | C89: 421600-Security service | D89: 9282680 | E89: 8651860.5 | F89: 8915130 | G89: =F89-D89 -> -367550 | H89: =G89/D89 -> -0.039595246 | I89: =G89/$G$2 -> -0.0011553404
A90: FA179-Opex Expense | B90: 427850 | C90: 427850-Data Transmission charges-Data Transmission charges | D90: 2618028 | E90: 744317 | F90: 2018028 | G90: =F90-D90 -> -600000 | H90: =G90/D90 -> -0.22918013 | I90: =G90/$G$2 -> -0.0018860135
A91: FA179-Opex Expense | B91: 425744 | C91: 425744-Student medical insurance | D91: 4816800 | E91: 588624.57 | F91: 3700000 | G91: =F91-D91 -> -1116800 | H91: =G91/D91 -> -0.23185517 | I91: =G91/$G$2 -> -0.0035104998
A92: FA179-Opex Expense | B92: 421100 | C92: 421100-Manpower supply "Other Than IT Related" | D92: 1418480 | E92: 1155070.2 | F92: 0 | G92: =F92-D92 -> -1418480 | H92: =G92/D92 -> -1 | I92: =G92/$G$2 -> -0.0044587874
D93: =SUM(D4:D92) -> 579850000 | E93: =SUM(E4:E92) -> 2.7320624e+08 | F93: =SUM(F4:F92) -> 8.9798134e+08 | G93: =SUM(G4:G92) -> 3.1813134e+08

Sheet Analysis Capex
C1: Chapter 3 (Capex):
C2: Grand Total | D2: =SUM(D4:D13) -> 110301000 | E2: =SUM(E4:E13) -> 1.0108274e+08 | F2: =SUM(F4:F13) -> 279895425 | G2: =SUM(G4:G13) -> 169594425
A3: Chp | B3: Account Code | C3: Account | D3: 2022 Budget | E3: Jun 2022 (Actula , PR, PO) | F3: 2023 Budget | G3: 2023 and 2022 Difference | H3: 2023 % Compared to Budget 2022 | I3: 2023 Budget Difference compared to total difference in % | J3: Comments
A4: FA180-Capex Expense | B4: 492316 | C4: 492316-Laboratory equipment | D4: 54372197 | E4: 48639176 | F4: 150888360 | G4: =F4-D4 -> 96516163 | H4: =G4/D4 -> 1.7751014 | I4: =G4/$G$2 -> 0.56909986 | J4: Capex 492316-Laboratory equip compared to FY2022 overall increased in percentage 178%. FY2023 Budget compared to FY2022 increased; • Research Lab Cost Center 413% AED 81M • Research Computing 570% AED 22M. • CoE 66% AED 5.5M. • CoAS 89% AED 5M • CoM 35% AED 23M.
A5: FA180-Capex Expense | B5: 492200 | C5: 492200-Capital expense - Buildings | D5: 46279509 | E5: 44899320 | F5: 104517560 | G5: =F5-D5 -> 58238051 | H5: =G5/D5 -> 1.2583982 | I5: =G5/$G$2 -> 0.34339602 | J5: • Capex Building increased compared to FY2022 by 126%, due to multiple building renovation. • Habshan Building Renovation AED 36M. • Technology and Innovation Center Phase-2 AED 11M • Central Gas network for arzanah lab (Phase 2/1) AED 6m and Road connection SAN to Arzanah 5M. Many other sundry renovations adding up to AED 44M
A6: FA180-Capex Expense | B6: 492610 | C6: 492610-Furniture & Fixtures - Offices | D6: 2099461 | E6: 884839 | F6: 6326594 | G6: =F6-D6 -> 4227133 | H6: =G6/D6 -> 2.0134373 | I6: =G6/$G$2 -> 0.024924953 | J6: FMS has significant amount in budget AED 6 M Medical equipment, High Fidelity Simulators, Task Trainers Construction supply and installation of self-contained cold store for 8 bodies (MS) Class room fit out and office, labs
A7: FA180-Capex Expense | B7: 495113 | C7: 495113-Computer software-Application, Platform | D7: 1630974 | E7: 1263794.8 | F7: 5722572 | G7: =F7-D7 -> 4091598 | H7: =G7/D7 -> 2.5086838 | I7: =G7/$G$2 -> 0.024125781 | J7: • Human resource has budget for 4.4M and it increaed by 100%,ERP Solution AED 3M • New implementation of system for Archiving Solution AED 1M
A8: FA180-Capex Expense | B8: 492356 | C8: 492356-Hardware & peripherals-Conferencing & AV | D8: 650000 | E8: 583836 | F8: 4018539 | G8: =F8-D8 -> 3368539 | H8: =G8/D8 -> 5.1823677 | I8: =G8/$G$2 -> 0.019862322 | J8: • Major Classroom Renovations to adopt hybrid learning in classrooms: AED3.3 • AV equipment for Merged Classrooms in SAN Campus and Main Campus - Part 2. AV Equipment AED 702
A9: FA180-Capex Expense | B9: 492354 | C9: 492354-Hardware & peripherals-Peripherals & Infrastructure Components | D9: 321500 | E9: 321320 | F9: 2238800 | G9: =F9-D9 -> 1917300 | H9: =G9/D9 -> 5.9636081 | I9: =G9/$G$2 -> 0.011305207
A10: FA180-Capex Expense | B10: 495110 | C10: 495110-Computer software | D10: 0 | E10: 0 | F10: 1859500 | G10: =F10-D10 -> 1859500 | H10: 1 | I10: =G10/$G$2 -> 0.010964393
A11: FA180-Capex Expense | B11: 492310 | C11: 492310-Hardware & peripherals | D11: 2884648 | E11: 2444879 | F11: 2916500 | G11: =F11-D11 -> 31852 | H11: =G11/D11 -> 0.011041902 | I11: =G11/$G$2 -> 0.00018781278
A12: FA180-Capex Expense | B12: 495140 | C12: 495140-Copyrights, patents and licenses | D12: 46409 | E12: 30302.25 | F12: 18000 | G12: =F12-D12 -> -28409 | H12: =G12/D12 -> -0.6121442 | I12: =G12/$G$2 -> -0.0001675114
A13: FA180-Capex Expense | B13: 492352 | C13: 492352-Hardware & peripherals-Network Devices | D13: 2016302 | E13: 2015272.6 | F13: 1389000 | G13: =F13-D13 -> -627302 | H13: =G13/D13 -> -0.3111151 | I13: =G13/$G$2 -> -0.0036988362
D14: =SUM(D4:D13) -> 110301000 | E14: =SUM(E4:E13) -> 1.0108274e+08 | F14: =SUM(F4:F13) -> 279895425 | G14: =SUM(G4:G13) -> 169594425
E15: 2.7320624e+08
E16: =SUM(E14:E15) -> 3.7428898e+08

Sheet 2019 - 2025 DB Master
A1: Cost Center Code - Group | B1: GL Account Combination | C1: Cost Center Code | D1: Cost Center Description | E1: Account Code | F1: Account Code and Description | G1: Future-01 | H1: Future-01 Description | I1: Future-02 | J1: Future-02 Description | K1: 2019 Actual | L1: 2020 Actual | M1: 2021 Actual | N1: 2022 Budget | O1: 2022 Estimates Full Year Actual | P1: 2022 - Jun Actual | Q1: 2022 PR | R1: 2022 PO | S1: 2023 Budget | T1: 2023 Budget Scenario 90% | U1: 2023 Budget Scenario 80% | V1: 2023 Budget Scenario 70% | W1: 2024 Budget | X1: 2025 Budget | Y1: Diff
A2: Chapter-01 | B2: Chapter-01 | C2: Chapter-01 | D2: Chapter-01 | E2: Chapter-01 | F2: Chapter-01 | G2: Chapter-01 | H2: Chapter-01 | I2: Chapter-01 | J2: Chapter-01 | K2: 734104574 | L2: 541385100 | M2: 583579295 | N2: 622545692 | O2: 601695721 | P2: 273667080 | Q2: 1643996 | R2: 7959693 | S2: 6.9619905e+08 | W2: 714862760 | X2: 779727079 | Y2: 0
A3: Academic and Student Services Office | B3: 847.8470230.1.420550.000000.847001.200179 | C3: 8470230 | D3: KUST - Graduate Studies | E3: 420550 | F3: 420550-Academic Advisory Service | G3: 847001 | H3: KUST - General | I3: 200179 | J3: FA179-Opex Expense | K3: 346386 | L3: 79120 | M3: 56949 | N3: 1020620 | O3: 1020620 | P3: 0 | Q3: 0 | R3: 0 | S3: 2009826 | T3: 1808843 | U3: 1607861 | V3: 1406878 | W3: 2764960 | X3: 5655600 | Y3: =S3-N3 -> 989206
A4: Academic and Student Services Office | B4: 847.8470230.1.425100.000000.847001.200179 | C4: 8470230 | D4: KUST - Graduate Studies | E4: 425100 | F4: 425100-Advertising Services (General) | G4: 847001 | H4: KUST - General | I4: 200179 | J4: FA179-Opex Expense | K4: 251555 | L4: 0 | M4: 0 | N4: 300000 | O4: 300000 | P4: 0 | Q4: 0 | R4: 0 | S4: 300000 | T4: 270000 | U4: 240000 | V4: 210000 | W4: 300000 | X4: 300000 | Y4: =S4-N4 -> 0
A5: Academic and Student Services Office | B5: 847.8470230.1.425510.000000.847001.200179 | C5: 8470230 | D5: KUST - Graduate Studies | E5: 425510 | F5: 425510-Conferences, seminars and exhibitions and other events: - Local Events | G5: 847001 | H5: KUST - General | I5: 200179 | J5: FA179-Opex Expense | K5: 46161 | L5: 17919 | M5: 3706 | N5: 34000 | O5: 34000 | P5: 0 | Q5: 0 | R5: 0 | S5: 38400 | T5: 34560 | U5: 30720 | V5: 26880 | W5: 48000 | X5: 64000 | Y5: =S5-N5 -> 4400
A6: Academic and Student Services Office | B6: 847.8470230.1.425550.000000.847001.200179 | C6: 8470230 | D6: KUST - Graduate Studies | E6: 425550 | F6: 425550-Conferences, seminars and exhibitions and other events: - Overseas event | G6: 847001 | H6: KUST - General | I6: 200179 | J6: FA179-Opex Expense | K6: 347020 | L6: 25200 | M6: 3326 | N6: 222000 | O6: 222000 | P6: 22420.5 | Q6: 0 | R6: 0 | S6: 355200 | T6: 319680 | U6: 284160 | V6: 248640 | W6: 444000 | X6: 592000 | Y6: =S6-N6 -> 133200
A7: Academic and Student Services Office | B7: 847.8470230.1.425743.000000.847001.200179 | C7: 8470230 | D7: KUST - Graduate Studies | E7: 425743 | F7: 425743-Graduation rewards | G7: 847001 | H7: KUST - General | I7: 200179 | J7: FA179-Opex Expense | K7: 7340000 | L7: 2010000 | M7: 960000 | N7: 240000 | O7: 240000 | P7: 240000 | Q7: 0 | R7: 0 | S7: 0 | T7: 0 | U7: 0 | V7: 0 | W7: 0 | X7: 0 | Y7: =S7-N7 -> -240000
A8: Academic and Student Services Office | B8: 847.8470230.1.425744.000000.847001.200179 | C8: 8470230 | D8: KUST - Graduate Studies | E8: 425744 | F8: 425744-Student medical insurance | G8: 847001 | H8: KUST - General | I8: 200179 | J8: FA179-Opex Expense | K8: 0 | L8: 0 | M8: 0 | N8: 4816800 | O8: 4816800 | P8: 588624.57 | Q8: 0 | R8: 0 | S8: 3700000 | T8: 3330000 | U8: 2960000 | V8: 2590000 | W8: 4380000 | X8: 4824000 | Y8: =S8-N8 -> -1116800
A9: Academic and Student Services Office | B9: 847.8470230.1.425745.000000.847001.200179 | C9: 8470230 | D9: KUST - Graduate Studies | E9: 425745 | F9: 425745-Student relocation & travel exps | G9: 847001 | H9: KUST - General | I9: 200179 | J9: FA179-Opex Expense | K9: 2585909 | L9: 1706509 | M9: 1286175 | N9: 1971263 | O9: 1971263 | P9: 817645 | Q9: 0 | R9: 0 | S9: 3104115 | T9: 2793704 | U9: 2483292 | V9: 2172881 | W9: 3663925 | X9: 3931250 | Y9: =S9-N9 -> 1132852
A10: Academic and Student Services Office | B10: 847.8470230.1.425749.000000.847001.200179 | C10: 8470230 | D10: KUST - Graduate Studies | E10: 425749 | F10: 425749-Postgraduate Student Salaries | G10: 847001 | H10: KUST - General | I10: 200179 | J10: FA179-Opex Expense | K10: 0 | L10: 22420057 | M10: 84701166 | N10: 110824684 | O10: 110824684 | P10: 55768460 | Q10: 0 | R10: 0 | S10: 203750000 | T10: 183375000 | U10: 163000000 | V10: 142625000 | W10: 249200000 | X10: 274120000 | Y10: =S10-N10 -> 92925316
A11: Academic and Student Services Office | B11: 847.8470230.1.425761.000000.847001.200179 | C11: 8470230 | D11: KUST - Graduate Studies | E11: 425761 | F11: 425761-Student Field trips | G11: 847001 | H11: KUST - General | I11: 200179 | J11: FA179-Opex Expense | K11: 0 | L11: 0 | M11: 0 | N11: 150000 | O11: 150000 | P11: 0 | Q11: 0 | R11: 0 | S11: 180000 | T11: 162000 | U11: 144000 | V11: 126000 | W11: 225000 | X11: 300000 | Y11: =S11-N11 -> 30000
A12: Academic and Student Services Office | B12: 847.8470230.1.425762.000000.847001.200179 | C12: 8470230 | D12: KUST - Graduate Studies | E12: 425762 | F12: 425762-Student Internship | G12: 847001 | H12: KUST - General | I12: 200179 | J12: FA179-Opex Expense | K12: 0 | L12: 0 | M12: 0 | N12: 150000 | O12: 150000 | P12: 0 | Q12: 0 | R12: 0 | S12: 180000 | T12: 162000 | U12: 144000 | V12: 126000 | W12: 225000 | X12: 300000 | Y12: =S12-N12 -> 30000
A13: Academic and Student Services Office | B13: 847.8470230.1.425900.000000.847001.200179 | C13: 8470230 | D13: KUST - Graduate Studies | E13: 425900 | F13: 425900-Entertainment and hospitality | G13: 847001 | H13: KUST - General | I13: 200179 | J13: FA179-Opex Expense | K13: 16320 | L13: 6993 | M13: 0 | N13: 45648 | O13: 45648 | P13: 0 | Q13: 0 | R13: 0 | S13: 60078 | T13: 54070 | U13: 48062 | V13: 42055 | W13: 64320 | X13: 77720 | Y13: =S13-N13 -> 14430
A14: Academic and Student Services Office | B14: 847.8470230.1.426610.000000.847001.200179 | C14: 8470230 | D14: KUST - Graduate Studies | E14: 426610 | F14: 426610-Computer software licenses-Software License Renewal | G14: 847001 | H14: KUST - General | I14: 200179 | J14: FA179-Opex Expense | K14: 0 | L14: 0 | M14: 0 | N14: 10000 | O14: 10000 | P14: 0 | Q14: 0 | R14: 0 | S14: 10000 | T14: 9000 | U14: 8000 | V14: 7000 | W14: 10000 | X14: 10000 | Y14: =S14-N14 -> 0
... A108: College of Arts & Science | B108: 847.8470415.1.428640.000000.847001.200179 | C108: 8470415 | D108: KUST - Chemistry | E108: 428640 | F108: 428640-Events - Awards, prizes & gifts | G108: 847001 | H108: KUST - General | I108: 200179 | J108: FA179-Opex Expense | K108: 426 | L108: 0 | M108: 0 | N108: 15000 | O108: 15000 | P108: 0 | Q108: 0 | R108: 0 | S108: 20000 | T108: 18000 | U108: 16000 | V108: 14000 | W108: 20000 | X108: 25000 | Y108: =S108-N108 -> 5000
A109: College of Arts & Science | B109: 847.8470415.1.432209.000000.847001.200179 | C109: 8470415 | D109: KUST - Chemistry | E109: 432209 | F109: 432209-Laboratory equipment | G109: 847001 | H109: KUST - General | I109: 200179 | J109: FA179-Opex Expense | K109: 130434 | L109: 71550 | M109: 85887 | N109: 301000 | O109: 301000 | P109: 39104 | Q109: 82964.1 | R109: 82628.61 | S109: 980000 | T109: 391500 | U109: 348000 | V109: 304500 | W109: 478500 | X109: 526000 | Y109: =S109-N109 -> 679000 | Z109: =Y109/N109 -> 2.255814
A110: College of Arts & Science | B110: 847.8470415.1.435350.000000.847001.200179 | C110: 8470415 | D110: KUST - Chemistry | E110: 435350 | F110: 435350-Academic Publications | G110: 847001 | H110: KUST - General | I110: 200179 | J110: FA179-Opex Expense | K110: 0 | L110: 18074 | M110: 15798 | N110: 70000 | O110: 70000 | P110: 5138 | Q110: 0 | R110: 0 | S110: 180000 | T110: 162000 | U110: 144000 | V110: 126000 | W110: 240000 | X110: 300000 | Y110: =S110-N110 -> 110000
A111: College of Arts & Science | B111: 847.8470415.1.435508.000000.847001.200179 | C111: 8470415 | D111: KUST - Chemistry | E111: 435508 | F111: 435508-Laboratory - Scientific | G111: 847001 | H111: KUST - General | I111: 200179 | J111: FA179-Opex Expense | K111: 374661 | L111: 267320 | M111: 146217 | N111: 525000 | O111: 525000 | P111: 89206.58 | Q111: 36675 | R111: 76210 | S111: 1200000 | T111: 675000 | U111: 600000 | V111: 525000 | W111: 925000 | X111: 900000 | Y111: =S111-N111 -> 675000
A112: College of Arts & Science | B112: 847.8470415.1.492316.000000.847001.300180 | C112: 8470415 | D112: KUST - Chemistry | E112: 492316 | F112: 492316-Laboratory equipment | G112: 847001 | H112: KUST - General | I112: 300180 | J112: FA180-Capex Expense | K112: 129251 | L112: 0 | M112: 751050 | N112: 1891417 | O112: 1891417 | P112: 0 | Q112: 1774402 | R112: 102313 | S112: 3386780 | T112: 103856 | U112: 92316 | V112: 80777 | W112: 4494200 | X112: 346260 | Y112: =S112-N112 -> 1495363
A113: College of Arts & Science | B113: 847.8470425.1.425510.000000.847001.200179 | C113: 8470425 | D113: KUST - Physics | E113: 425510 | F113: 425510-Conferences, seminars and exhibitions and other events: - Local Events | G113: 847001 | H113: KUST - General | I113: 200179 | J113: FA179-Opex Expense | K113: 0 | L113: 0 | M113: 0 | N113: 45000 | O113: 45000 | P113: 0 | Q113: 0 | R113: 0 | S113: 290000 | T113: 40500 | U113: 36000 | V113: 31500 | W113: 275000 | X113: 295000 | Y113: =S113-N113 -> 245000
A114: College of Arts & Science | B114: 847.8470425.1.425550.000000.847001.200179 | C114: 8470425 | D114: KUST - Physics | E114: 425550 | F114: 425550-Conferences, seminars and exhibitions and other events: - Overseas event | G114: 847001 | H114: KUST - General | I114: 200179 | J114: FA179-Opex Expense | K114: 0 | L114: 0 | M114: 0 | N114: 225000 | O114: 225000 | P114: 0 | Q114: 0 | R114: 0 | S114: 247500 | T114: 222750 | U114: 198000 | V114: 173250 | W114: 270000 | X114: 337500 | Y114: =S114-N114 -> 22500
A115: College of Arts & Science | B115: 847.8470425.1.425770.000000.847001.200179 | C115: 8470425 | D115: KUST - Physics | E115: 425770 | F115: 425770-Academic Missions - Combined expenses | G115: 847001 | H115: KUST - General | I115: 200179 | J115: FA179-Opex Expense | K115: 126527 | L115: 66413 | M115: 717 | N115: 60000 | O115: 60000 | P115: 11830 | Q115: 0 | R115: 0 | S115: 67500 | T115: 60750 | U115: 54000 | V115: 47250 | W115: 90000 | X115: 112500 | Y115: =S115-N115 -> 7500
A116: College of Arts & Science | B116: 847.8470425.1.425900.000000.847001.200179 | C116: 8470425 | D116: KUST - Physics | E116: 425900 | F116: 425900-Entertainment and hospitality | G116: 847001 | H116: KUST - General | I116: 200179 | J116: FA179-Opex Expense | K116: 5798 | L116: 5058 | M116: 0 | N116: 10116 | O116: 10116 | P116: 0 | Q116: 0 | R116: 0 | S116: 145000 | T116: 112500 | U116: 100000 | V116: 87500 | W116: 120000 | X116: 120000 | Y116: =S116-N116 -> 134884
A117: College of Arts & Science | B117: 847.8470425.1.426610.000000.847001.200179 | C117: 8470425 | D117: KUST - Physics | E117: 426610 | F117: 426610-Computer software licenses-Software License Renewal | G117: 847001 | H117: KUST - General | I117: 200179 | J117: FA179-Opex Expense | K117: 0 | L117: 0 | M117: 0 | N117: 212000 | O117: 212000 | P117: 0 | Q117: 0 | R117: 22497.13 | S117: 200000 | T117: 180000 | U117: 160000 | V117: 140000 | W117: 450000 | X117: 400000 | Y117: =S117-N117 -> -12000
A118: College of Arts & Science | B118: 847.8470425.1.428090.000000.847001.200179 | C118: 8470425 | D118: KUST - Physics | E118: 428090 | F118: 428090-Business Travel - Combined expenses | G118: 847001 | H118: KUST - General | I118: 200179 | J118: FA179-Opex Expense | K118: 0 | L118: 0 | M118: 0 | N118: 128000 | O118: 128000 | P118: 0 | Q118: 0 | R118: 0 | S118: 128000 | T118: 115200 | U118: 102400 | V118: 89600 | W118: 192000 | X118: 112500 | Y118: =S118-N118 -> 0
A119: College of Arts & Science | B119: 847.8470425.1.435350.000000.847001.200179 | C119: 8470425 | D119: KUST - Physics | E119: 435350 | F119: 435350-Academic Publications | G119: 847001 | H119: KUST - General | I119: 200179 | J119: FA179-Opex Expense | K119: 14753 | L119: 39563 | M119: 31871 | N119: 120000 | O119: 120000 | P119: 21287.77 | Q119: 0 | R119: 0 | S119: 150000 | T119: 135000 | U119: 120000 | V119: 105000 | W119: 150000 | X119: 250000 | Y119: =S119-N119 -> 30000
A120: College of Arts & Science | B120: 847.8470425.1.435508.000000.847001.200179 | C120: 8470425 | D120: KUST - Physics | E120: 435508 | F120: 435508-Laboratory - Scientific | G120: 847001 | H120: KUST - General | I120: 200179 | J120: FA179-Opex Expense | K120: 4600 | L120: 42606 | M120: 227 | N120: 551566 | O120: 551566 | P120: 0 | Q120: 0 | R120: 152675 | S120: 854700 | T120: 35100 | U120: 31200 | V120: 27300 | W120: 840000 | X120: 1000000 | Y120: =S120-N120 -> 303134
A121: College of Arts & Science | B121: 847.8470425.1.492310.000000.847001.300180 | C121: 8470425 | D121: KUST - Physics | E121: 492310 | F121: 492310-Hardware & peripherals | G121: 847001 | H121: KUST - General | I121: 300180 | J121: FA180-Capex Expense | K121: 0 | L121: 0 | M121: 0 | N121: 151348 | O121: 151348 | P121: 35280 | Q121: 0 | R121: 0 | S121: 800000 | T121: 720000 | U121: 640000 | V121: 560000 | W121: 750000 | X121: 750000 | Y121: =S121-N121 -> 648652
... A177: College of Arts & Science | B177: 847.8470455.1.435350.000000.847001.200179 | C177: 8470455 | D177: KUST – Biology | E177: 435350 | F177: 435350-Academic Publications | G177: 847001 | H177: KUST - General | I177: 200179 | J177: FA179-Opex Expense | K177: 0 | L177: 0 | M177: 0 | N177: 80000 | O177: 80000 | P177: 25142.2 | Q177: 0 | R177: 0 | S177: 140000 | T177: 126000 | U177: 112000 | V177: 98000 | W177: 170000 | X177: 200000 | Y177: =S177-N177 -> 60000
A178: College of Arts & Science | B178: 847.8470455.1.435508.000000.847001.200179 | C178: 8470455 | D178: KUST – Biology | E178: 435508 | F178: 435508-Laboratory - Scientific | G178: 847001 | H178: KUST - General | I178: 200179 | J178: FA179-Opex Expense | K178: 0 | L178: 0 | M178: 0 | N178: 675000 | O178: 675000 | P178: 9208.45 | Q178: 432250 | R178: 0 | S178: 781000 | T178: 702900 | U178: 624800 | V178: 546700 | W178: 275000 | X178: 1122000 | Y178: =S178-N178 -> 106000 | Z178: =Y92+Y111+Y120+Y128+Y131+Y167+Y178 -> 1517634 | AA178: =N92+N111+N120+N128+N131+N167+N178 -> 1852666 | AB178: `
A179: College of Arts & Science | B179: 847.8470455.1.436110.000000.847001.200179 | C179: 8470455 | D179: KUST – Biology | E179: 436110 | F179: 436110-Printing supplies | G179: 847001 | H179: KUST - General | I179: 200179 | J179: FA179-Opex Expense | K179: 0 | L179: 0 | M179: 0 | N179: 5000 | O179: 5000 | P179: 0 | Q179: 0 | R179: 0 | S179: 7000 | T179: 6300 | U179: 5600 | V179: 4900 | W179: 9000 | X179: 10000 | Y179: =S179-N179 -> 2000
A180: College of Arts & Science | B180: 847.8470455.1.492316.000000.847001.300180 | C180: 8470455 | D180: KUST – Biology | E180: 492316 | F180: 492316-Laboratory equipment | G180: 847001 | H180: KUST - General | I180: 300180 | J180: FA180-Capex Expense | K180: 0 | L180: 0 | M180: 0 | N180: 1754263 | O180: 1754263 | P180: 0 | Q180: 1603654 | R180: 106062.5 | S180: 2014622 | T180: 1813160 | U180: 1611698 | V180: 1410235 | W180: 2700000 | X180: 3000000 | Y180: =S180-N180 -> 260359 | Z180: =Y82+Y112+Y122+Y169+Y180 -> 4763255 | AA180: =N82+N112+N122+N169+N180 -> 5350397 | AB180: =Z180/AA180 -> 0.89026197
A181: College of Engineering | B181: 847.8470305.1.420550.000000.847001.200179 | C181: 8470305 | D181: KUST - Dean Of Engineering | E181: 420550 | F181: 420550-Academic Advisory Service | G181: 847001 | H181: KUST - General | I181: 200179 | J181: FA179-Opex Expense | K181: 0 | L181: 0 | M181: 0 | N181: 100000 | O181: 100000 | P181: 92165.34 | Q181: 0 | R181: 0 | S181: 100000 | T181: 90000 | U181: 0 | V181: 70000 | W181: 100000 | X181: 100000 | Y181: =S181-N181 -> 0
A182: College of Engineering | B182: 847.8470305.1.420570.000000.847001.200179 | C182: 8470305 | D182: KUST - Dean Of Engineering | E182: 420570 | F182: 420570-Academic Collaborative Partnership Services | G182: 847001 | H182: KUST - General | I182: 200179 | J182: FA179-Opex Expense | K182: 4591 | L182: 4591 | M182: 4591 | N182: 10000 | O182: 10000 | P182: 0 | Q182: 0 | R182: 0 | S182: 10000 | T182: 9000 | U182: 0 | V182: 7000 | W182: 10000 | X182: 15000 | Y182: =S182-N182 -> 0
A183: College of Engineering | B183: 847.8470305.1.421700.000000.847001.200179 | C183: 8470305 | D183: KUST - Dean Of Engineering | E183: 421700 | F183: 421700-Standards Certification Services (e.g. ISO) | G183: 847001 | H183: KUST - General | I183: 200179 | J183: FA179-Opex Expense | K183: 391361 | L183: 597851 | M183: 123489 | N183: 506004 | O183: 506004 | P183: 32000 | Q183: 0 | R183: 0 | S183: 300000 | T183: 270000 | U183: 0 | V183: 210000 | W183: 90000 | X183: 150000 | Y183: =S183-N183 -> -206004
A184: College of Engineering | B184: 847.8470305.1.425510.000000.847001.200179 | C184: 8470305 | D184: KUST - Dean Of Engineering | E184: 425510 | F184: 425510-Conferences, seminars and exhibitions and other events: - Local Events | G184: 847001 | H184: KUST - General | I184: 200179 | J184: FA179-Opex Expense | K184: 38554 | L184: 10444 | M184: -252 | N184: 20000 | O184: 20000 | P184: 5286 | Q184: 0 | R184: 0 | S184: 20000 | T184: 18000 | U184: 0 | V184: 14000 | W184: 30000 | X184: 60000 | Y184: =S184-N184 -> 0
A185: College of Engineering | B185: 847.8470305.1.425720.000000.847001.200179 | C185: 8470305 | D185: KUST - Dean Of Engineering | E185: 425720 | F185: 425720-Education-Outsourced training service | G185: 847001 | H185: KUST - General | I185: 200179 | J185: FA179-Opex Expense | K185: 29384 | L185: 0 | M185: -3416 | N185: 0 | O185: 0 | P185: 0 | Q185: 0 | R185: 0 | S185: 40000 | T185: 36000 | U185: 0 | V185: 28000 | W185: 80000 | X185: 40000 | Y185: =S185-N185 -> 40000
A186: College of Engineering | B186: 847.8470305.1.425763.000000.847001.200179 | C186: 8470305 | D186: KUST - Dean Of Engineering | E186: 425763 | F186: 425763-Student Project Expenses | G186: 847001 | H186: KUST - General | I186: 200179 | J186: FA179-Opex Expense | K186: 19184 | L186: 617638 | M186: 55390 | N186: 170000 | O186: 170000 | P186: 20000 | Q186: 112260.3 | R186: 0 | S186: 120000 | T186: 108000 | U186: 0 | V186: 84000 | W186: 120000 | X186: 120000 | Y186: =S186-N186 -> -50000
A187: College of Engineering | B187: 847.8470305.1.425770.000000.847001.200179 | C187: 8470305 | D187: KUST - Dean Of Engineering | E187: 425770 | F187: 425770-Academic Missions - Combined expenses | G187: 847001 | H187: KUST - General | I187: 200179 | J187: FA179-Opex Expense | K187: 96239 | L187: 7219 | M187: 22015 | N187: 579499 | O187: 579499 | P187: 51565 | Q187: 0 | R187: 0 | S187: 1000000 | T187: 900000 | U187: 0 | V187: 700000 | W187: 1160000 | X187: 1100000 | Y187: =S187-N187 -> 420501
A188: College of Engineering | B188: 847.8470305.1.425900.000000.847001.200179 | C188: 8470305 | D188: KUST - Dean Of Engineering | E188: 425900 | F188: 425900-Entertainment and hospitality | G188: 847001 | H188: KUST - General | I188: 200179 | J188: FA179-Opex Expense | K188: 19369 | L188: -10521 | M188: -131 | N188: 18000 | O188: 18000 | P188: 2625 | Q188: 0 | R188: 0 | S188: 30000 | T188: 27000 | U188: 0 | V188: 21000 | W188: 40000 | X188: 30000 | Y188: =S188-N188 -> 12000
A189: College of Engineering | B189: 847.8470305.1.426610.000000.847001.200179 | C189: 8470305 | D189: KUST - Dean Of Engineering | E189: 426610 | F189: 426610-Computer software licenses-Software License Renewal | G189: 847001 | H189: KUST - General | I189: 200179 | J189: FA179-Opex Expense | K189: 185613 | L189: 236658 | M189: 62198 | N189: 100000 | O189: 100000 | P189: 3874.85 | Q189: 0 | R189: 39668.4 | S189: 120000 | T189: 108000 | U189: 0 | V189: 84000 | W189: 150000 | X189: 120000 | Y189: =S189-N189 -> 20000
A190: College of Engineering | B190: 847.8470305.1.428090.000000.847001.200179 | C190: 8470305 | D190: KUST - Dean Of Engineering | E190: 428090 | F190: 428090-Business Travel - Combined expenses | G190: 847001 | H190: KUST - General | I190: 200179 | J190: FA179-Opex Expense | K190: 0 | L190: 0 | M190: 0 | N190: 35000 | O190: 35000 | P190: 0 | Q190: 0 | R190: 0 | S190: 90000 | T190: 81000 | U190: 0 | V190: 63000 | W190: 90000 | X190: 60000 | Y190: =S190-N190 -> 55000
A191: College of Engineering | B191: 847.8470305.1.428640.000000.847001.200179 | C191: 8470305 | D191: KUST - Dean Of Engineering | E191: 428640 | F191: 428640-Events - Awards, prizes & gifts | G191: 847001 | H191: KUST - General | I191: 200179 | J191: FA179-Opex Expense | K191: 11200 | L191: -3637 | M191: 0 | N191: 45000 | O191: 45000 | P191: 0 | Q191: 0 | R191: 0 | S191: 30000 | T191: 27000 | U191: 0 | V191: 21000 | W191: 36000 | X191: 30000 | Y191: =S191-N191 -> -15000
A192: College of Engineering | B192: 847.8470305.1.432209.000000.847001.200179 | C192: 8470305 | D192: KUST - Dean Of Engineering | E192: 432209 | F192: 432209-Laboratory equipment | G192: 847001 | H192: KUST - General | I192: 200179 | J192: FA179-Opex Expense | K192: 979024 | L192: 786039 | M192: 201150 | N192: 45292 | O192: 45292 | P192: 35796.32 | Q192: 0 | R192: 8000 | S192: 220000 | T192: 198000 | U192: 0 | V192: 154000 | W192: 319000 | X192: 297000 | Y192: =S192-N192 -> 174708
... A307: College of Engineering | B307: 847.8470350.1.426610.000000.847001.200179 | C307: 8470350 | D307: KUST - Petroleum Engineering | E307: 426610 | F307: 426610-Computer software licenses-Software License Renewal | G307: 847001 | H307: KUST - General | I307: 200179 | J307: FA179-Opex Expense | K307: 61238 | L307: 10055 | M307: 114405 | N307: 210200 | O307: 210200 | P307: 23675.11 | Q307: 0 | R307: 172888.11 | S307: 280200 | T307: 4680 | U307: 0 | V307: 3640 | W307: 413000 | X307: 323000 | Y307: =S307-N307 -> 70000
A308: College of Engineering | B308: 847.8470350.1.432209.000000.847001.200179 | C308: 8470350 | D308: KUST - Petroleum Engineering | E308: 432209 | F308: 432209-Laboratory equipment | G308: 847001 | H308: KUST - General | I308: 200179 | J308: FA179-Opex Expense | K308: 352318 | L308: 413126 | M308: 215417 | N308: 305000 | O308: 305000 | P308: 0 | Q308: 0 | R308: 143841.45 | S308: 979000 | T308: 315000 | U308: 0 | V308: 245000 | W308: 510000 | X308: 425000 | Y308: =S308-N308 -> 674000 | Z308: =Y308/N308 -> 2.2098361
A309: College of Engineering | B309: 847.8470350.1.435340.000000.847001.200179 | C309: 8470350 | D309: KUST - Petroleum Engineering | E309: 435340 | F309: 435340-Text books and library books | G309: 847001 | H309: KUST - General | I309: 200179 | J309: FA179-Opex Expense | K309: 0 | L309: 0 | M309: 0 | N309: 10000 | O309: 10000 | P309: 0 | Q309: 0 | R309: 0 | S309: 10000 | T309: 9000 | U309: 0 | V309: 7000 | W309: 20000 | X309: 30000 | Y309: =S309-N309 -> 0
A310: College of Engineering | B310: 847.8470350.1.435350.000000.847001.200179 | C310: 8470350 | D310: KUST - Petroleum Engineering | E310: 435350 | F310: 435350-Academic Publications | G310: 847001 | H310: KUST - General | I310: 200179 | J310: FA179-Opex Expense | K310: 8202 | L310: 18571 | M310: 31762 | N310: 50000 | O310: 50000 | P310: 0 | Q310: 0 | R310: 0 | S310: 90000 | T310: 81000 | U310: 0 | V310: 63000 | W310: 120000 | X310: 156000 | Y310: =S310-N310 -> 40000
A311: College of Engineering | B311: 847.8470350.1.435508.000000.847001.200179 | C311: 8470350 | D311: KUST - Petroleum Engineering | E311: 435508 | F311: 435508-Laboratory - Scientific | G311: 847001 | H311: KUST - General | I311: 200179 | J311: FA179-Opex Expense | K311: 142169 | L311: 25049 | M311: 29960 | N311: 100000 | O311: 100000 | P311: 14966.9 | Q311: 0 | R311: 13002.42 | S311: 110000 | T311: 22500 | U311: 0 | V311: 17500 | W311: 132000 | X311: 132000 | Y311: =S311-N311 -> 10000 | Z311: =Y178+Y196+Y208+Y222+Y235+Y250+Y262+Y274+Y288+Y298+Y311 -> 521642 | AA311: =N178+N196+N208+N222+N235+N250+N262+N274+N288+N298+N311 -> 2162050 | AB311: =Z311/AA311 -> 0.24127194
A312: College of Engineering | B312: 847.8470350.1.436110.000000.847001.200179 | C312: 8470350 | D312: KUST - Petroleum Engineering | E312: 436110 | F312: 436110-Printing supplies | G312: 847001 | H312: KUST - General | I312: 200179 | J312: FA179-Opex Expense | K312: 700 | L312: 0 | M312: 0 | N312: 7500 | O312: 7500 | P312: 0 | Q312: 0 | R312: 0 | S312: 7500 | T312: 6750 | U312: 0 | V312: 5250 | W312: 5000 | X312: 5000 | Y312: =S312-N312 -> 0
A313: College of Engineering | B313: 847.8470350.1.436600.000000.847001.200179 | C313: 8470350 | D313: KUST - Petroleum Engineering | E313: 436600 | F313: 436600-Training/Teaching equipment and other educational aid | G313: 847001 | H313: KUST - General | I313: 200179 | J313: FA179-Opex Expense | K313: 0 | L313: 0 | M313: 0 | N313: 60000 | O313: 60000 | P313: 0 | Q313: 0 | R313: 0 | S313: 100000 | T313: 90000 | U313: 0 | V313: 70000 | W313: 100000 | X313: 108000 | Y313: =S313-N313 -> 40000
A314: College of Engineering | B314: 847.8470350.1.492316.000000.847001.300180 | C314: 8470350 | D314: KUST - Petroleum Engineering | E314: 492316 | F314: 492316-Laboratory equipment | G314: 847001 | H314: KUST - General | I314: 300180 | J314: FA180-Capex Expense | K314: 191760 | L314: 584893 | M314: 0 | N314: 1446520 | O314: 1446520 | P314: 862373.2 | Q314: 578702.18 | R314: 0 | S314: 1969500 | T314: 146250 | U314: 0 | V314: 113750 | W314: 2200000 | X314: 3190000 | Y314: =S314-N314 -> 522980 | Z314: =Y211+Y225+Y251+Y277+Y301+Y314 -> 5453408 | AA314: =Z314/N314 -> 3.7700191 | AB314: =Z314/(S211+S225+S251+S277+S301) -> 0.66480426
A315: College of Engineering | B315: 847.8470350.1.495110.000000.847001.300180 | C315: 8470350 | D315: KUST - Petroleum Engineering | E315: 495110 | F315: 495110-Computer software | G315: 847001 | H315: KUST - General | I315: 300180 | J315: FA180-Capex Expense | K315: 0 | L315: 0 | M315: 0 | N315: 0 | O315: 0 | P315: 0 | Q315: 0 | R315: 0 | S315: 59500 | T315: 40500 | U315: 0 | V315: 31500 | W315: 0 | X315: 0 | Y315: =S315-N315 -> 59500
A316: College of Medicine & Health Sciences | B316: 847.8471305.1.420570.000000.847001.200179 | C316: 8471305 | D316: KUST - Dean Of Medicine | E316: 420570 | F316: 420570-Academic Collaborative Partnership Services | G316: 847001 | H316: KUST - General | I316: 200179 | J316: FA179-Opex Expense | K316: 0 | L316: 0 | M316: 16778285 | N316: 21895944 | O316: 21895944 | P316: 0 | Q316: 0 | R316: 0 | S316: 33130272 | T316: 29817245 | U316: 0 | V316: 23191190 | W316: 34786786 | X316: 36443299 | Y316: =S316-N316 -> 11234328 | AA316: =Y316/S316 -> 0.33909556
A317: College of Medicine & Health Sciences | B317: 847.8471305.1.420811.000000.847001.200179 | C317: 8471305 | D317: KUST - Dean Of Medicine | E317: 420811 | F317: 420811-IT Systems & Support expenses-Application/Systems Operation | G317: 847001 | H317: KUST - General | I317: 200179 | J317: FA179-Opex Expense | K317: 0 | L317: 0 | M317: 0 | N317: 0 | O317: 0 | P317: 0 | Q317: 0 | R317: 0 | S317: 408900 | T317: 368010 | U317: 0 | V317: 286230 | W317: 429356 | X317: 449801 | Y317: =S317-N317 -> 408900
A318: College of Medicine & Health Sciences | B318: 847.8471305.1.421000.000000.847001.200179 | C318: 8471305 | D318: KUST - Dean Of Medicine | E318: 421000 | F318: 421000-Management consultancy | G318: 847001 | H318: KUST - General | I318: 200179 | J318: FA179-Opex Expense | K318: 74170 | L318: 332159 | M318: 0 | N318: 271000 | O318: 271000 | P318: 100000 | Q318: 0 | R318: 0 | S318: 400000 | T318: 360000 | U318: 0 | V318: 280000 | W318: 420000 | X318: 500000 | Y318: =S318-N318 -> 129000
A319: College of Medicine & Health Sciences | B319: 847.8471305.1.421700.000000.847001.200179 | C319: 8471305 | D319: KUST - Dean Of Medicine | E319: 421700 | F319: 421700-Standards Certification Services (e.g. ISO) | G319: 847001 | H319: KUST - General | I319: 200179 | J319: FA179-Opex Expense | K319: 156500 | L319: 196900 | M319: 85014 | N319: 170000 | O319: 170000 | P319: 43531.6 | Q319: 0 | R319: 0 | S319: 360000 | T319: 324000 | U319: 0 | V319: 252000 | W319: 378000 | X319: 440000 | Y319: =S319-N319 -> 190000
A320: College of Medicine & Health Sciences | B320: 847.8471305.1.422100.000000.847001.200179 | C320: 8471305 | D320: KUST - Dean Of Medicine | E320: 422100 | F320: 422100-Waste management service | G320: 847001 | H320: KUST - General | I320: 200179 | J320: FA179-Opex Expense | K320: 0 | L320: 0 | M320: 31000 | N320: 12000 | O320: 12000 | P320: 0 | Q320: 0 | R320: 0 | S320: 12000 | T320: 10800 | U320: 0 | V320: 8400 | W320: 12600 | X320: 396000 | Y320: =S320-N320 -> 0
A321: College of Medicine & Health Sciences | B321: 847.8471305.1.422900.000000.847001.200179 | C321: 8471305 | D321: KUST - Dean Of Medicine | E321: 422900 | F321: 422900-Other specialised professional services, not mentioned elsewhere | G321: 847001 | H321: KUST - General | I321: 200179 | J321: FA179-Opex Expense | K321: 0 | L321: 15989 | M321: 53742 | N321: 0 | O321: 0 | P321: 0 | Q321: 0 | R321: 0 | S321: 225000 | T321: 202500 | U321: 0 | V321: 157500 | W321: 236250 | X321: 275000 | Y321: =S321-N321 -> 225000
A322: College of Medicine & Health Sciences | B322: 847.8471305.1.425100.000000.847001.200179 | C322: 8471305 | D322: KUST - Dean Of Medicine | E322: 425100 | F322: 425100-Advertising Services (General) | G322: 847001 | H322: KUST - General | I322: 200179 | J322: FA179-Opex Expense | K322: 0 | L322: 129219 | M322: 258 | N322: 0 | O322: 0 | P322: 0 | Q322: 0 | R322: 0 | S322: 250000 | T322: 225000 | U322: 0 | V322: 175000 | W322: 315000 | X322: 1122000 | Y322: =S322-N322 -> 250000
A323: College of Medicine & Health Sciences | B323: 847.8471305.1.425510.000000.847001.200179 | C323: 8471305 | D323: KUST - Dean Of Medicine | E323: 425510 | F323: 425510-Conferences, seminars and exhibitions and other events: - Local Events | G323: 847001 | H323: KUST - General | I323: 200179 | J323: FA179-Opex Expense | K323: 4713 | L323: 114960 | M323: 83486 | N323: 670000 | O323: 670000 | P323: 45221 | Q323: 0 | R323: 15500 | S323: 1020000 | T323: 918000 | U323: 0 | V323: 714000 | W323: 1071000 | X323: 1020000 | Y323: =S323-N323 -> 350000
A324: College of Medicine & Health Sciences | B324: 847.8471305.1.425550.000000.847001.200179 | C324: 8471305 | D324: KUST - Dean Of Medicine | E324: 425550 | F324: 425550-Conferences, seminars and exhibitions and other events: - Overseas event | G324: 847001 | H324: KUST - General | I324: 200179 | J324: FA179-Opex Expense | K324: 45316 | L324: 38256 | M324: 47147 | N324: 622000 | O324: 622000 | P324: 32900 | Q324: 0 | R324: 0 | S324: 1140000 | T324: 1026000 | U324: 0 | V324: 798000 | W324: 1197000 | X324: 1140000 | Y324: =S324-N324 -> 518000
A325: College of Medicine & Health Sciences | B325: 847.8471305.1.425720.000000.847001.200179 | C325: 8471305 | D325: KUST - Dean Of Medicine | E325: 425720 | F325: 425720-Education-Outsourced training service | G325: 847001 | H325: KUST - General | I325: 200179 | J325: FA179-Opex Expense | K325: 739107 | L325: 1194435 | M325: 1377538 | N325: 2424345 | O325: 2424345 | P325: 682810.28 | Q325: 0 | R325: 1130000 | S325: 3000000 | T325: 2700000 | U325: 0 | V325: 2100000 | W325: 3150000 | X325: 3100000 | Y325: =S325-N325 -> 575655
A326: College of Medicine & Health Sciences | B326: 847.8471305.1.425742.000000.847001.200179 | C326: 8471305 | D326: KUST - Dean Of Medicine | E326: 425742 | F326: 425742-Enrollment expenses | G326: 847001 | H326: KUST - General | I326: 200179 | J326: FA179-Opex Expense | K326: 0 | L326: 0 | M326: 74620 | N326: 180000 | O326: 180000 | P326: 78512.25 | Q326: 0 | R326: 0 | S326: 297975 | T326: 268178 | U326: 0 | V326: 208583 | W326: 312874 | X326: 304500 | Y326: =S326-N326 -> 117975
A327: College of Medicine & Health Sciences | B327: 847.8471305.1.425745.000000.847001.200179 | C327: 8471305 | D327: KUST - Dean Of Medicine | E327: 425745 | F327: 425745-Student relocation & travel exps | G327: 847001 | H327: KUST - General | I327: 200179 | J327: FA179-Opex Expense | K327: 225790 | L327: 23762 | M327: 16828 | N327: 24400 | O327: 24400 | P327: 24000 | Q327: 0 | R327: 0 | S327: 825000 | T327: 742500 | U327: 0 | V327: 577500 | W327: 866250 | X327: 825000 | Y327: =S327-N327 -> 800600
A328: College of Medicine & Health Sciences | B328: 847.8471305.1.425746.000000.847001.200179 | C328: 8471305 | D328: KUST - Dean Of Medicine | E328: 425746 | F328: 425746-Student Transport | G328: 847001 | H328: KUST - General | I328: 200179 | J328: FA179-Opex Expense | K328: 0 | L328: 0 | M328: 0 | N328: 292600 | O328: 292600 | P328: 0 | Q328: 0 | R328: 0 | S328: 376200 | T328: 338580 | U328: 0 | V328: 263340 | W328: 395010 | X328: 378000 | Y328: =S328-N328 -> 83600
... A346: College of Medicine & Health Sciences | B346: 847.8471305.1.435350.000000.847001.200179 | C346: 8471305 | D346: KUST - Dean Of Medicine | E346: 435350 | F346: 435350-Academic Publications | G346: 847001 | H346: KUST - General | I346: 200179 | J346: FA179-Opex Expense | K346: 0 | L346: 0 | M346: 74471 | N346: 359100 | O346: 359100 | P346: 182938.65 | Q346: 0 | R346: 0 | S346: 1260000 | T346: 1134000 | U346: 0 | V346: 882000 | W346: 315000 | X346: 1386000 | Y346: =S346-N346 -> 900900
A347: College of Medicine & Health Sciences | B347: 847.8471305.1.435508.000000.847001.200179 | C347: 8471305 | D347: KUST - Dean Of Medicine | E347: 435508 | F347: 435508-Laboratory - Scientific | G347: 847001 | H347: KUST - General | I347: 200179 | J347: FA179-Opex Expense | K347: 909033 | L347: 897989 | M347: 241815 | N347: 1892072 | O347: 1892072 | P347: 314264.18 | Q347: 5630 | R347: 1347219.4 | S347: 14077987 | T347: 12670188 | U347: 0 | V347: 9854591 | W347: 1323000 | X347: 15485786 | Y347: =S347-N347 -> 12185915 | AB347: =Y347/N347 -> 6.4405134
A348: College of Medicine & Health Sciences | B348: 847.8471305.1.435530.000000.847001.200179 | C348: 8471305 | D348: KUST - Dean Of Medicine | E348: 435530 | F348: 435530-School consumables, not specifically mentioned elsewhere | G348: 847001 | H348: KUST - General | I348: 200179 | J348: FA179-Opex Expense | K348: 228 | L348: 851 | M348: 924 | N348: 10000 | O348: 10000 | P348: 80 | Q348: 0 | R348: 0 | S348: 225000 | T348: 202500 | U348: 0 | V348: 157500 | W348: 14781886 | X348: 247500 | Y348: =S348-N348 -> 215000
A349: College of Medicine & Health Sciences | B349: 847.8471305.1.436110.000000.847001.200179 | C349: 8471305 | D349: KUST - Dean Of Medicine | E349: 436110 | F349: 436110-Printing supplies | G349: 847001 | H349: KUST - General | I349: 200179 | J349: FA179-Opex Expense | K349: 2359 | L349: 0 | M349: 22000 | N349: 0 | O349: 0 | P349: 0 | Q349: 0 | R349: 0 | S349: 300000 | T349: 270000 | U349: 0 | V349: 210000 | W349: 236250 | X349: 330000 | Y349: =S349-N349 -> 300000
A350: College of Medicine & Health Sciences | B350: 847.8471305.1.436120.000000.847001.200179 | C350: 8471305 | D350: KUST - Dean Of Medicine | E350: 436120 | F350: 436120-Stationery | G350: 847001 | H350: KUST - General | I350: 200179 | J350: FA179-Opex Expense | K350: 5604 | L350: 6669 | M350: 7188 | N350: 112000 | O350: 112000 | P350: 0 | Q350: 0 | R350: 0 | S350: 320000 | T350: 288000 | U350: 0 | V350: 224000 | W350: 236250 | X350: 352000 | Y350: =S350-N350 -> 208000
A351: College of Medicine & Health Sciences | B351: 847.8471305.1.492316.000000.847001.300180 | C351: 8471305 | D351: KUST - Dean Of Medicine | E351: 492316 | F351: 492316-Laboratory equipment | G351: 847001 | H351: KUST - General | I351: 300180 | J351: FA180-Capex Expense | K351: 57068649 | L351: 15725666 | M351: 11810091 | N351: 17513291 | O351: 17513291 | P351: 1538887.7 | Q351: 411735 | R351: 14689538 | S351: 23622096 | T351: 1620000 | U351: 0 | V351: 1260000 | W351: 0 | X351: 0 | Y351: =S351-N351 -> 6108805 | Z351: =Y351 -> 6108805 | AA351: =Z351/N351 -> 0.34880966 | AB351: =Y351/N351 -> 0.34880966
A352: College of Medicine & Health Sciences | B352: 847.8471305.1.492354.000000.847001.300180 | C352: 8471305 | D352: KUST - Dean Of Medicine | E352: 492354 | F352: 492354-Hardware & peripherals-Peripherals & Infrastructure Components | G352: 847001 | H352: KUST - General | I352: 300180 | J352: FA180-Capex Expense | K352: 0 | L352: 0 | M352: 0 | N352: 0 | O352: 0 | P352: 0 | Q352: 0 | R352: 0 | S352: 1098800 | T352: 988920 | U352: 0 | V352: 769160 | W352: 0 | X352: 0 | Y352: =S352-N352 -> 1098800
A353: College of Medicine & Health Sciences | B353: 847.8471305.1.495113.000000.847001.300180 | C353: 8471305 | D353: KUST - Dean Of Medicine | E353: 495113 | F353: 495113-Computer software-Application, Platform | G353: 847001 | H353: KUST - General | I353: 300180 | J353: FA180-Capex Expense | K353: 0 | L353: 0 | M353: 0 | N353: 0 | O353: 0 | P353: 0 | Q353: 0 | R353: 0 | S353: 250000 | T353: 225000 | U353: 0 | V353: 175000 | W353: 0 | X353: 0 | Y353: =S353-N353 -> 250000
A354: Continuing Education | B354: 847.8471010.1.425100.000000.847001.200179 | C354: 8471010 | D354: KUST - Continuing Education Office | E354: 425100 | F354: 425100-Advertising Services (General) | G354: 847001 | H354: KUST - General | I354: 200179 | J354: FA179-Opex Expense | K354: 0 | L354: 0 | M354: 86900 | N354: 107500 | O354: 107500 | P354: 0 | Q354: 0 | R354: 0 | S354: 120000 | T354: 108000 | U354: 96000 | V354: 84000 | W354: 130000 | X354: 140000 | Y354: =S354-N354 -> 12500
A355: Continuing Education | B355: 847.8471010.1.425510.000000.847001.200179 | C355: 8471010 | D355: KUST - Continuing Education Office | E355: 425510 | F355: 425510-Conferences, seminars and exhibitions and other events: - Local Events | G355: 847001 | H355: KUST - General | I355: 200179 | J355: FA179-Opex Expense | K355: 0 | L355: 0 | M355: 0 | N355: 100000 | O355: 100000 | P355: 0 | Q355: 0 | R355: 0 | S355: 100000 | T355: 90000 | U355: 80000 | V355: 70000 | W355: 100000 | X355: 100000 | Y355: =S355-N355 -> 0
A356: Continuing Education | B356: 847.8471010.1.425720.000000.847001.200179 | C356: 8471010 | D356: KUST - Continuing Education Office | E356: 425720 | F356: 425720-Education-Outsourced training service | G356: 847001 | H356: KUST - General | I356: 200179 | J356: FA179-Opex Expense | K356: 0 | L356: 0 | M356: 23528 | N356: 76120 | O356: 76120 | P356: 20760 | Q356: 0 | R356: 0 | S356: 76120 | T356: 68508 | U356: 60896 | V356: 53284 | W356: 145320 | X356: 166080 | Y356: =S356-N356 -> 0
A357: Continuing Education | B357: 847.8471010.1.425900.000000.847001.200179 | C357: 8471010 | D357: KUST - Continuing Education Office | E357: 425900 | F357: 425900-Entertainment and hospitality | G357: 847001 | H357: KUST - General | I357: 200179 | J357: FA179-Opex Expense | K357: 0 | L357: 0 | M357: 26586 | N357: 162500 | O357: 162500 | P357: 0 | Q357: 0 | R357: 0 | S357: 88400 | T357: 79560 | U357: 70720 | V357: 61880 | W357: 97500 | X357: 105000 | Y357: =S357-N357 -> -74100
A358: Continuing Education | B358: 847.8471010.1.436110.000000.847001.200179 | C358: 8471010 | D358: KUST - Continuing Education Office | E358: 436110 | F358: 436110-Printing supplies | G358: 847001 | H358: KUST - General | I358: 200179 | J358: FA179-Opex Expense | K358: 0 | L358: 0 | M358: 0 | N358: 50625 | O358: 50625 | P358: 0 | Q358: 0 | R358: 0 | S358: 20000 | T358: 18000 | U358: 16000 | V358: 14000 | W358: 32000 | X358: 32000 | Y358: =S358-N358 -> -30625
A359: Continuing Education | B359: 847.8471010.1.436120.000000.847001.200179 | C359: 8471010 | D359: KUST - Continuing Education Office | E359: 436120 | F359: 436120-Stationery | G359: 847001 | H359: KUST - General | I359: 200179 | J359: FA179-Opex Expense | K359: 0 | L359: 0 | M359: 0 | N359: 5625 | O359: 5625 | P359: 0 | Q359: 0 | R359: 0 | S359: 6000 | T359: 5400 | U359: 4800 | V359: 4200 | W359: 6000 | X359: 6000 | Y359: =S359-N359 -> 375
A360: Executive Vice President Office | B360: 847.8470130.1.421000.000000.847001.200179 | C360: 8470130 | D360: KUST - Institutional Research & Planning | E360: 421000 | F360: 421000-Management consultancy | G360: 847001 | H360: KUST - General | I360: 200179 | J360: FA179-Opex Expense | K360: 0 | L360: 28466 | M360: 690716 | N360: 604900 | O360: 604900 | P360: 0 | Q360: 0 | R360: 0 | S360: 540000 | T360: 486000 | U360: 432000 | V360: 378000 | W360: 540000 | X360: 540000 | Y360: =S360-N360 -> -64900
A361: Executive Vice President Office | B361: 847.8470130.1.426610.000000.847001.200179 | C361: 8470130 | D361: KUST - Institutional Research & Planning | E361: 426610 | F361: 426610-Computer software licenses-Software License Renewal | G361: 847001 | H361: KUST - General | I361: 200179 | J361: FA179-Opex Expense | K361: 0 | L361: 0 | M361: 0 | N361: 735000 | O361: 735000 | P361: 0 | Q361: 0 | R361: 0 | S361: 180000 | T361: 162000 | U361: 144000 | V361: 126000 | W361: 180000 | X361: 180000 | Y361: =S361-N361 -> -555000
A362: Executive Vice President Office | B362: 847.8470130.1.428090.000000.847001.200179 | C362: 8470130 | D362: KUST - Institutional Research & Planning | E362: 428090 | F362: 428090-Business Travel - Combined expenses | G362: 847001 | H362: KUST - General | I362: 200179 | J362: FA179-Opex Expense | K362: 0 | L362: 0 | M362: 1100 | N362: 180000 | O362: 180000 | P362: 1650 | Q362: 0 | R362: 0 | S362: 551250 | T362: 496125 | U362: 441000 | V362: 385875 | W362: 551250 | X362: 551250 | Y362: =S362-N362 -> 371250
A363: Executive Vice President Office | B363: 847.8470140.1.425100.000000.847001.200179 | C363: 8470140 | D363: KUST - Communication | E363: 425100 | F363: 425100-Advertising Services (General) | G363: 847001 | H363: KUST - General | I363: 200179 | J363: FA179-Opex Expense | K363: 5116144 | L363: 2353627 | M363: 1900038 | N363: 5827464 | O363: 5827464 | P363: 1140556 | Q363: 3357368 | R363: 234463.48 | S363: 14983000 | T363: 1800000 | U363: 1600000 | V363: 1400000 | W363: 14404666 | X363: 16429640 | Y363: =S363-N363 -> 9155536 | Z363: =Y363/N363 -> 1.5711013
A364: Executive Vice President Office | B364: 847.8470140.1.425510.000000.847001.200179 | C364: 8470140 | D364: KUST - Communication | E364: 425510 | F364: 425510-Conferences, seminars and exhibitions and other events: - Local Events | G364: 847001 | H364: KUST - General | I364: 200179 | J364: FA179-Opex Expense | K364: 9740820 | L364: 2727959 | M364: 3922844 | N364: 5025358 | O364: 5025358 | P364: 1818995 | Q364: 2745800 | R364: 405340 | S364: 6585400 | T364: 180000 | U364: 160000 | V364: 140000 | W364: 8025304 | X364: 8985370 | Y364: =S364-N364 -> 1560042
A365: Executive Vice President Office | B365: 847.8470140.1.425550.000000.847001.200179 | C365: 8470140 | D365: KUST - Communication | E365: 425550 | F365: 425550-Conferences, seminars and exhibitions and other events: - Overseas event | G365: 847001 | H365: KUST - General | I365: 200179 | J365: FA179-Opex Expense | K365: 73717 | L365: 0 | M365: 0 | N365: 2955 | O365: 2955 | P365: 2942.71 | Q365: 0 | R365: 0 | S365: 2150328 | T365: 1935295 | U365: 1720262 | V365: 1505230 | W365: 3000000 | X365: 3001800 | Y365: =S365-N365 -> 2147373
A366: Executive Vice President Office | B366: 847.8470140.1.425763.000000.847050.200179 | C366: 8470140 | D366: KUST - Communication | E366: 425763 | F366: 425763-Student Project Expenses | G366: 847050 | H366: KUST - CSR Activities | I366: 200179 | J366: FA179-Opex Expense | K366: 0 | L366: 0 | M366: 0 | N366: 400000 | O366: 400000 | P366: 42319.6 | Q366: 0 | R366: 45809.52 | S366: 400000 | T366: 360000 | U366: 320000 | V366: 280000 | W366: 0 | X366: 0 | Y366: =S366-N366 -> 0
A367: Executive Vice President Office | B367: 847.8470140.1.427100.000000.847001.200179 | C367: 8470140 | D367: KUST - Communication | E367: 427100 | F367: 427100-Public relations | G367: 847001 | H367: KUST - General | I367: 200179 | J367: FA179-Opex Expense | K367: 1380274 | L367: 129310 | M367: -820 | N367: 1157850 | O367: 1157850 | P367: 0 | Q367: 909458.75 | R367: 0 | S367: 2500000 | T367: 90000 | U367: 80000 | V367: 70000 | W367: 2500000 | X367: 2500000 | Y367: =S367-N367 -> 1342150
A368: Executive Vice President Office | B368: 847.8470140.1.427200.000000.847001.200179 | C368: 8470140 | D368: KUST - Communication | E368: 427200 | F368: 427200-Printing and publishing | G368: 847001 | H368: KUST - General | I368: 200179 | J368: FA179-Opex Expense | K368: 332619 | L368: 125003 | M368: -7379 | N368: 750000 | O368: 750000 | P368: 17150.01 | Q368: 0 | R368: 0 | S368: 750005 | T368: 121500 | U368: 108000 | V368: 94500 | W368: 750000 | X368: 750000 | Y368: =S368-N368 -> 5
A369: Executive Vice President Office | B369: 847.8470140.1.428640.000000.847001.200179 | C369: 8470140 | D369: KUST - Communication | E369: 428640 | F369: 428640-Events - Awards, prizes & gifts | G369: 847001 | H369: KUST - General | I369: 200179 | J369: FA179-Opex Expense | K369: 0 | L369: 0 | M369: 0 | N369: 538000 | O369: 538000 | P369: 4594 | Q369: 0 | R369: 177011 | S369: 998000 | T369: 99000 | U369: 88000 | V369: 77000 | W369: 998000 | X369: 920000 | Y369: =S369-N369 -> 460000
A370: Executive Vice President Office | B370: 847.8470140.1.435310.000000.847001.200179 | C370: 8470140 | D370: KUST - Communication | E370: 435310 | F370: 435310-Newspapers, magazines, journals, etc | G370: 847001 | H370: KUST - General | I370: 200179 | J370: FA179-Opex Expense | K370: 17260 | L370: 13568 | M370: 0 | N370: 10000 | O370: 10000 | P370: 0 | Q370: 0 | R370: 0 | S370: 10000 | T370: 9000 | U370: 8000 | V370: 7000 | W370: 10000 | X370: 10000 | Y370: =S370-N370 -> 0
A371: Executive Vice President Office | B371: 847.8470140.1.435519.000000.847001.200179 | C371: 8470140 | D371: KUST - Communication | E371: 435519 | F371: 435519-Photography - Consumable materials /Tools | G371: 847001 | H371: KUST - General | I371: 200179 | J371: FA179-Opex Expense | K371: 0 | L371: 53870 | M371: 0 | N371: 135000 | O371: 135000 | P371: 43812 | Q371: 0 | R371: 0 | S371: 135000 | T371: 121500 | U371: 108000 | V371: 94500 | W371: 135000 | X371: 135000 | Y371: =S371-N371 -> 0
A372: Executive Vice President Office | B372: 847.8470140.1.492310.000000.847001.300180 | C372: 8470140 | D372: KUST - Communication | E372: 492310 | F372: 492310-Hardware & peripherals | G372: 847001 | H372: KUST - General | I372: 300180 | J372: FA180-Capex Expense | K372: 0 | L372: 0 | M372: 248690 | N372: 137589 | O372: 137589 | P372: 0 | Q372: 0 | R372: 0 | S372: 200000 | T372: 180000 | U372: 160000 | V372: 140000 | W372: 200000 | X372: 200000 | Y372: =S372-N372 -> 62411
A373: Executive Vice President Office | B373: 847.8470910.1.420570.000000.847001.200179 | C373: 8470910 | D373: KUST - Executive Vice President Office | E373: 420570 | F373: 420570-Academic Collaborative Partnership Services | G373: 847001 | H373: KUST - General | I373: 200179 | J373: FA179-Opex Expense | K373: 0 | L373: 0 | M373: 0 | N373: 0 | O373: 0 | P373: 0 | Q373: 0 | R373: 0 | S373: 15000000 | T373: 13500000 | U373: 12000000 | V373: 10500000 | W373: 15000000 | X373: 15000000 | Y373: =S373-N373 -> 15000000 | AA373: 1
A374: Executive Vice President Office | B374: 847.8470910.1.425900.000000.847001.200179 | C374: 8470910 | D374: KUST - Executive Vice President Office | E374: 425900 | F374: 425900-Entertainment and hospitality | G374: 847001 | H374: KUST - General | I374: 200179 | J374: FA179-Opex Expense | K374: 0 | L374: 0 | M374: 0 | N374: 0 | O374: 0 | P374: 0 | Q374: 0 | R374: 0 | S374: 50000 | T374: 45000 | U374: 40000 | V374: 35000 | W374: 50000 | X374: 50000 | Y374: =S374-N374 -> 50000
A375: Executive Vice President Office | B375: 847.8470910.1.428090.000000.847001.200179 | C375: 8470910 | D375: KUST - Executive Vice President Office | E375: 428090 | F375: 428090-Business Travel - Combined expenses | G375: 847001 | H375: KUST - General | I375: 200179 | J375: FA179-Opex Expense | K375: 0 | L375: 0 | M375: 0 | N375: 0 | O375: 0 | P375: 0 | Q375: 0 | R375: 0 | S375: 1000000 | T375: 900000 | U375: 800000 | V375: 700000 | W375: 1000000 | X375: 1000000 | Y375: =S375-N375 -> 1000000
A376: Executive Vice President Office | B376: 847.8470910.1.429900.000000.847001.200179 | C376: 8470910 | D376: KUST - Executive Vice President Office | E376: 429900 | F376: 429900-Other services, not specifically mentioned elsewhere | G376: 847001 | H376: KUST - General | I376: 200179 | J376: FA179-Opex Expense | K376: 0 | L376: 0 | M376: 0 | N376: 0 | O376: 0 | P376: 0 | Q376: 0 | R376: 0 | S376: 3000000 | T376: 2700000 | U376: 2400000 | V376: 2100000 | W376: 3000000 | X376: 3000000 | Y376: =S376-N376 -> 3000000
A377: President's Office | B377: 847.8470110.1.420550.000000.847001.200179 | C377: 8470110 | D377: KUST - Office of the President | E377: 420550 | F377: 420550-Academic Advisory Service | G377: 847001 | H377: KUST - General | I377: 200179 | J377: FA179-Opex Expense | K377: 0 | L377: 29118 | M377: 0 | N377: 30000 | O377: 30000 | P377: 0 | Q377: 0 | R377: 0 | S377: 100000 | T377: 90000 | U377: 80000 | V377: 70000 | W377: 100000 | X377: 100000 | Y377: =S377-N377 -> 70000
A378: President's Office | B378: 847.8470110.1.420570.000000.847001.200179 | C378: 8470110 | D378: KUST - Office of the President | E378: 420570 | F378: 420570-Academic Collaborative Partnership Services | G378: 847001 | H378: KUST - General | I378: 200179 | J378: FA179-Opex Expense | K378: 0 | L378: 0 | M378: 0 | N378: 3684121 | O378: 3684121 | P378: 0 | Q378: 0 | R378: 0 | S378: 5000000 | T378: 4500000 | U378: 4000000 | V378: 3500000 | W378: 5000000 | X378: 5000000 | Y378: =S378-N378 -> 1315879 | AA378: =Y378/S378 -> 0.2631758
A379: President's Office | B379: 847.8470110.1.421000.000000.847001.200179 | C379: 8470110 | D379: KUST - Office of the President | E379: 421000 | F379: 421000-Management consultancy | G379: 847001 | H379: KUST - General | I379: 200179 | J379: FA179-Opex Expense | K379: 204013 | L379: 0 | M379: 0 | N379: 200000 | O379: 200000 | P379: 0 | Q379: 0 | R379: 0 | S379: 200000 | T379: 180000 | U379: 160000 | V379: 140000 | W379: 200000 | X379: 200000 | Y379: =S379-N379 -> 0
...

Sheet XXPVT 2023
A1: Future-02 | B1: (All)
A3: Future-02 Description | B3: Account Code and Description | C3: Account Code | D3: Sum of 2023 Budget
A4: Chapter-01 | B4: Chapter-01 | C4: Chapter-01 | D4: 6.9619905e+08
A5: FA179-Opex Expense | B5: 420120-Internal Audit service | C5: 420120 | D5: 520000
A6: FA179-Opex Expense | B6: 420130-External Audit service | C6: 420130 | D6: 236850
A7: FA179-Opex Expense | B7: 420310-Cleaning Services: Business premises | C7: 420310 | D7: 8921788
A8: FA179-Opex Expense | B8: 420550-Academic Advisory Service | C8: 420550 | D8: 3540830
A9: FA179-Opex Expense | B9: 420570-Academic Collaborative Partnership Services | C9: 420570 | D9: 56595297
A10: FA179-Opex Expense | B10: 420810-IT Systems & Support expenses | C10: 420810 | D10: 0
A11: FA179-Opex Expense | B11: 420811-IT Systems & Support expenses-Application/Systems Operation | C11: 420811 | D11: 27999051
A12: FA179-Opex Expense | B12: 420900-Legal services | C12: 420900 | D12: 5298500
A13: FA179-Opex Expense | B13: 421000-Management consultancy | C13: 421000 | D13: 8290000
A14: FA179-Opex Expense | B14: 421100-Manpower supply "Other Than IT Related" | C14: 421100 | D14: 0
A15: FA179-Opex Expense | B15: 421600-Security service | C15: 421600 | D15: 8915130
A16: FA179-Opex Expense | B16: 421700-Standards Certification Services (e.g. ISO) | C16: 421700 | D16: 5220000
... A103: FA180-Capex Expense | B103: 495140-Copyrights, patents and licenses | C103: 495140 | D103: 18000
A104: Grand Total | D104: 1874075813

Sheet 2019 - 2025 PVT Budget Summary
A4: Row Labels | B4: 2019 Actual | C4: 2020 Actual | D4: 2021 Actual | E4: 2022 Budget | F4: 2022 Estimates Full Year Actual | G4: 2022 - Jun Actual | H4: 2022 PR | I4: 2022 PO | J4: 2023 Budget | K4: 2023 budget % | L4: Sum of 2023 Budget Scenario 90% | M4: Sum of 2023 Budget Scenario 80% | N4: Sum of 2023 Budget Scenario 70% | O4: 2024 Budget | P4: 2025 Budget
A5: Chapter-01 | B5: 734104574 | C5: 541385100 | D5: 583579295 | E5: 622545692 | F5: 601695721 | G5: 273667080 | H5: 1643996 | I5: 7959693 | J5: 6.9619905e+08 | K5: 0.11830996 | O5: 714862760 | P5: 779727079
A6: FA179-Opex Expense | B6: 453454660 | C6: 436208140 | D6: 441110791 | E6: 579850000 | F6: 579850000 | G6: 1.8911659e+08 | H6: 33388070 | I6: 50701580 | J6: 8.9798134e+08 | K6: 0.5486442 | L6: 7.2668401e+08 | M6: 4.4706592e+08 | N6: 5.6583185e+08 | O6: 1016511648 | P6: 1116963424
A7: FA180-Capex Expense | B7: 156951792 | C7: 84546442 | D7: 82262231 | E7: 110301000 | F7: 110301000 | G7: 22847250 | H7: 40206186 | I7: 38029304 | J7: 279895425 | K7: 1.5375602 | L7: 1.5353053e+08 | M7: 1.0605958e+08 | N7: 1.2106332e+08 | O7: 133843452 | P7: 85950261
A8: Grand Total | B8: 1344511026 | C8: 1062139682 | D8: 1106952317 | E8: 1312696692 | F8: 1291846721 | G8: 4.8563092e+08 | H8: 75238252 | I8: 96690577 | J8: 1874075813 | K8: 0.42765334 | L8: 8.8021453e+08 | M8: 5.5312551e+08 | N8: 6.8689517e+08 | O8: 1865217860 | P8: 1982640764

Sheet 2019 - 2025 PVT Budget Master
A2: Future-02 Description | B2: FA179-Opex Expense
A3: Grand Total | B3: 453454660 | C3: 436208140 | D3: 441110791 | E3: 579850000 | F3: 579850000 | G3: 187138724 | H3: 32891483 | I3: 50586956 | J3: 9.1060796e+08 | K3: 7.2995401e+08 | L3: 4.138768e+08 | M3: 5.6774201e+08 | N3: 981703638 | O3: 1078691613
A4: Row Labels | B4: 2019 Actual | C4: 2020 Actual | D4: 2021 Actual | E4: 2022 Budget | F4: 2022 Estimates Full Year Actual | G4: 2022 - Jun Actual | H4: 2022 PR | I4: 2022 PO | J4: 2023 Budget | K4: 2023 Budget Scenario 90% | L4: Sum of 2023 Budget Scenario 80% | M4: Sum of 2023 Budget Scenario 70% | N4: 2024 Budget | O4: 2025 Budget
A5: Academic and Student Services Office | B5: 172187679 | C5: 146304242 | D5: 163185443 | E5: 243450134 | F5: 243450134 | G5: 1.0819914e+08 | H5: 2840501.8 | I5: 6961704.4 | J5: 364075874 | K5: 3.260365e+08 | L5: 2.8981022e+08 | M5: 2.5358394e+08 | N5: 438825848 | O5: 497434881
A6: Senior Vice President, Research Office | B6: 86138315 | C6: 113736508 | D6: 113399833 | E6: 129843909 | F6: 129843909 | G6: 39615564 | H6: 8839209.5 | I6: 10502599 | J6: 163100430 | K6: 1.1777973e+08 | L6: 25327181 | M6: 92239635 | N6: 185279342 | O6: 207394237
A7: SVP/ Support Services Office | B7: 135037634 | C7: 127285760 | D7: 115378848 | E7: 95346032 | F7: 95346032 | G7: 21689077 | H7: 11781162 | I7: 27404447 | J7: 1.5346846e+08 | K7: 1.1220246e+08 | L7: 92977350 | M7: 87268580 | N7: 172307627 | O7: 172132859
A8: College of Medicine & Health Sciences | B8: 6964244 | C8: 13219211 | D8: 35241461 | E8: 61076587 | F8: 61076587 | G8: 13193664 | H8: 1126199.7 | I8: 2982880.2 | J8: 111377365 | K8: 100239631 | L8: 0 | M8: 77964157 | N8: 117633995 | O8: 123318820
A9: Executive Vice President Office | B9: 18081624 | C9: 5434003 | D9: 6636134 | E9: 15481527 | F9: 15481527 | G9: 3186778.2 | H9: 7012626.8 | I9: 862624 | J9: 48832983 | K9: 23005420 | L9: 20449262 | M9: 17893105 | N9: 50144220 | O9: 53053060
A10: College of Engineering | B10: 7538448 | C10: 5920794 | D10: 6067820 | E10: 13353579 | F10: 13353579 | G10: 2240265.3 | H10: 658897.37 | I10: 1524753.9 | J10: 17321285 | K10: 14699057 | L10: 0 | M10: 11432600 | N10: 17570423 | O10: 17626371
A11: College of Arts & Science | B11: 3165325 | C11: 1656687 | D11: 803563 | E11: 12241156 | F11: 12241156 | G11: 825355.75 | H11: 629472.87 | I11: 462571.83 | J11: 16260022 | K11: 11980780 | L11: 10649582 | M11: 9318385 | N11: 12760754 | O11: 21945034
A12: Provost | B12: 0 | C12: 0 | D12: 0 | E12: 1814597 | F12: 1814597 | G12: 45405 | H12: 0 | I12: 0 | J12: 13229516 | K12: 11906565 | L12: 0 | M12: 9260661 | N12: 10957230 | O12: 11736443
A13: President's Office | B13: 24341391 | C13: 22650935 | D13: 260675 | E13: 6740109 | F13: 6740109 | G13: 100575.82 | H13: 500000 | I13: 0 | J13: 9904889 | K13: 8464400 | L13: 7523911 | M13: 6583422 | N13: 10521389 | O13: 11772639
A14: Continuing Education | B14: 0 | C14: 0 | D14: 137014 | E14: 502370 | F14: 502370 | G14: 20760 | H14: 0 | I14: 0 | J14: 410520 | K14: 369468 | L14: 328416 | M14: 287364 | N14: 510820 | O14: 549080
A15: Grand Total | B15: 453454660 | C15: 436208140 | D15: 441110791 | E15: 579850000 | F15: 579850000 | G15: 1.8911659e+08 | H15: 33388070 | I15: 50701580 | J15: 8.9798134e+08 | K15: 7.2668401e+08 | L15: 4.4706592e+08 | M15: 5.6583185e+08 | N15: 1016511648 | O15: 1116963424

Sheet UG & PG Summary Table
B2: 2021-2022 | C2: 2022-2023 | D2: 2023-2024 | E2: 2024-2025 | F2: 2025-2026 | G2: 2026-2027 | H2: 2027-2028
A3: Continuing Students - UG | B3: 2381 | C3: 2957.22 | D3: =D7-D5 -> 3257 | E3: =E7-E5 -> 3444 | F3: =F7-F5 -> 3619 | G3: =G7-G5 -> 3793 | H3: =H7-H5 -> 3976
A4: Continuing Students - PG | B4: 560 | C4: =SUM([2]UGProjections!J31,[2]UGProjections!J40)-C6 -> 819.53 | D4: =SUM([2]UGProjections!L31,[2]UGProjections!L40)-D6 -> 1042.5293 | E4: =SUM([2]UGProjections!N31,[2]UGProjections!N40)-E6 -> 1197.4187 | F4: =SUM([2]UGProjections!P31,[2]UGProjections!P40)-F6 -> 1322.2992 | G4: =SUM([2]UGProjections!R31,[2]UGProjections!R40)-G6 -> 1459.2723 | H4: =SUM([2]UGProjections!T31,[2]UGProjections!T40)-H6 -> 1573.6406
A5: Intake - UG | B5: 923 | C5: 650 | D5: 550 | E5: =SUM([2]UGProjections!L9:M9) -> 550 | F5: =SUM([2]UGProjections!M9:N9) -> 550 | G5: =SUM([2]UGProjections!N9:O9) -> 550 | H5: =SUM([2]UGProjections!O9:P9) -> 550
A6: Intake - PG | B6: 417 | C6: 460 | D6: 460 | E6: 460 | F6: 500 | G6: 500 | H6: 500
A7: Total UG | B7: =SUM(B5,B3) -> 3304 | C7: 3607.22 | D7: 3807 | E7: 3994 | F7: 4169 | G7: 4343 | H7: 4526
A8: Total PG | B8: =SUM(B4,B6) -> 977 | C8: =SUM(C4,C6) -> 1279.53 | D8: =SUM(D4,D6) -> 1502.5293 | E8: =SUM(E4,E6) -> 1657.4187 | F8: =SUM(F4,F6) -> 1822.2992 | G8: =SUM(G4,G6) -> 1959.2723 | H8: =SUM(H4,H6) -> 2073.6406
A9: Grand Total | B9: =SUM(B7:B8) -> 4281 | C9: =SUM(C7:C8) -> 4886.75 | D9: =SUM(D7:D8) -> 5309.5293 | E9: =SUM(E7:E8) -> 5651.4187 | F9: =SUM(F7:F8) -> 5991.2992 | G9: =SUM(G7:G8) -> 6302.2723 | H9: =SUM(H7:H8) -> 6599.6406
A10: UG | B10: =B7/B9 -> 0.77178229 | C10: =C7/C9 -> 0.7381634 | D10: =D7/D9 -> 0.71701271 | E10: =E7/E9 -> 0.70672519 | F10: =F7/F9 -> 0.6958424 | G10: =G7/G9 -> 0.68911652 | H10: =H7/H9 -> 0.68579492
A11: PG | B11: =B8/B9 -> 0.22821771 | C11: =C8/C9 -> 0.2618366 | D11: =D8/D9 -> 0.28298729 | E11: =E8/E9 -> 0.29327481 | F11: =F8/F9 -> 0.3041576 | G11: =G8/G9 -> 0.31088348 | H11: =H8/H9 -> 0.31420508
A13: Actual Intake
B14: 2019-2020 | C14: 2020-2021 | D14: 2021-2022 | E14: 2022-2023 | F14: Compared to 2022 Intake | G14: Diff | I14: Compared to year 2021-22 increaed 76%. 2021-2022 PG students 431, in 20212022 PG students 758
A15: Intake - UG | B15: 798 | C15: 1144 | D15: 923 | E15: 650 | F15: =(E15-D15)/E15 -> -0.42 | G15: =E15-D15 -> -273
A16: Intake - PG | B16: 287 | C16: 386 | D16: 431 | E16: 758 | F16: =(E16-D16)/431 -> 0.7587007 | G16: =E16-D16 -> 327
A17: Medical | B17: 30 | C17: 36 | D17: 49 | E17: 60 | F17: =(E17-D17)/D17 -> 0.2244898 | G17: =E17-D17 -> 11
A26: Intake - UG | B26: Student Numbers
A27: 2019-2020 | B27: 798
A28: 2020-2021 | B28: 1144
A29: 2021-2022 | B29: 923
A30: 2022-2023 | B30: 650
B31: =SUM(B27:B30) -> 3515

Sheet 2023 Iteamized Capex and Opex
A2: Future-2 Description | B2: (All)
A4: Account Code and Description | B4: Itemised Details/Calculation method | C4: Quantity of measruing units | D4: Rate (expected) | E4: Sum of 2023 Budget
A5: 425749-Postgraduate Student Salaries | E5: 244626000
A6: 492316-Laboratory equipment | E6: 1.5088836e+08
A7: 435523-Scientific | E7: 1.1364886e+08
A8: 492200-Capital expense - Buildings | E8: 104517560
A9: 425741-Student stipend | E9: 98652604
A10: 420570-Academic Collaborative Partnership Services | E10: 56595297
A11: 432120-Bldg maintenance-Business premises | E11: 34225569
A12: 435508-Laboratory - Scientific | E12: 33397354
A13: 420811-IT Systems & Support expenses-Application/Systems Operation | E13: 27999050
A14: 430120-Rental - Buildings, other than staff residences | E14: 22219870
A15: 432209-Laboratory equipment | E15: 21267845
A16: 426610-Computer software licenses | E16: 20346378
... A100: 425300-Banking service charges / Fees | E100: 2400
A101: 420811-- | B101: Not requested | C101: 1 | D101: 1 | E101: 1
A102: 426210-Insurance - Cash and fidelity | E102: 0
A103: 430230-Rental - Equipment | E103: 0
A104: 422400-- | E104: 0
A105: 425743-Graduation rewards | E105: 0
A106: 436220-Road signs | E106: 0
A107: 425747-Student Accommodation | E107: 0
A108: (blank) | B108: (blank) | C108: (blank) | D108: (blank)
A109: 432690-Plant, machinery and heavy equipment, not mentioned elsewhere | E109: 0
A110: 421100-Manpower supply | E110: 0
A111: 420810-IT Systems & Support expenses | E111: 0
A112: Grand Total | E112: 1.1901755e+09

Sheet 2023 Detail B-01
A1: Account Group | B1: Content Expert | C1: Cost Center Code - Group | D1: Entity | E1: Cost Center Code | F1: Cost Center Description | G1: BG | H1: Account Code | I1: Account Code and Description | J1: Activity | K1: Future-1 Description | L1: Future-1 | M1: Future-2 Description | N1: Future-2 | O1: GL Account Combination | P1: 2021Actual | Q1: 2022 Budget | R1: 2022 Estimates Full Year Actual | S1: Budget Driver | T1: Measruing unit | U1: Quantity of measruing units | V1: Rate (expected) | W1: Itemised Details/Calculation method | X1: 2023 Budget | Y1: Budget Activity Type | Z1: Expenditure Frequency | AA1: 2023 Budget Scenario 90% | AB1: 2023 Budget Scenario 80% | AC1: 2023 Budget Scenario 70% | AD1: 90% Budget Scenario Impact | AE1: 80% Budget Impact | AF1: 70% Budget Impact | AG1: Jan-23 | AH1: Feb-23 | AI1: Mar-23 | AJ1: Apr-23 | AK1: May-23 | AL1: Jun-23 | AM1: Jul-23 | AN1: Aug-23 | AO1: Sep-23 | AP1: Oct-23 | AQ1: Nov-23 | AR1: Dec-23 | AS1: Total | AT1: KU Strategy | AU1: Comments
A2: - | B2: - | C2: SVP/ Support Services Office | D2: 847 | E2: 8470810 | F2: KUST - Ankabut office | G2: 1 | H2: 413328 | I2: 413328 - IT Manpower supply-IT Support resources | J2: 000000 | K2: KUST - General | L2: 847001 | M2: FA178-Manpower Expense | N2: 100178 | O2: 847.8470810.1.413328.000000.847001.100178 | R2: 8000000 | S2: Manpower Resources as per DGS Contract | T2: Months | U2: 12 | V2: 832200 | W2: Manpower Outsourcing as per DGS contract for 2023 - List Attached | X2: 9986400 | Y2: KU Regular operations | Z2: Recurring | AA2: =X2*0.9 -> 8987760 | AB2: =X2*0.8 -> 7989120 | AC2: =X2*0.7 -> 6990480 | AD2: Affects KU Core Operations and Non Compliance with contract terms | AE2: Affects KU Core Operations and Non Compliance with contract terms | AF2: Affects KU Core Operations and Non Compliance with contract terms | AG2: 832200 | AH2: 832200 | AI2: 832200 | AJ2: 832200 | AK2: 832200 | AL2: 832200 | AM2: 832200 | AN2: 832200 | AO2: 832200 | AP2: 832200 | AQ2: 832200 | AR2: 832200 | AS2: 9986400 | AU2: IT manpower should be moved to Chp-01
A3: 0 | B3: No Applicable | C3: SVP/ Support Services Office | D3: 847 | E3: 8470810 | F3: KUST - Ankabut office | G3: 1 | H3: 420810 | I3: 420810-IT Systems & Support expenses | J3: 000000 | K3: KUST - General | L3: 847001 | M3: FA179-Opex Expense | N3: 200179 | O3: 847.8470810.1.420810.000000.847001.200179 | P3: 300000 | Q3: 0 | T3: -_ | U3: 1 | X3: 0 | AA3: =X3*0.9 -> 0 | AB3: =X3*0.8 -> 0 | AC3: =X3*0.7 -> 0 | AH3: 0 | AS3: 0
A4: IT | B4: Director, Technology Development | C4: SVP/ Support Services Office | D4: 847 | E4: 8470810 | F4: KUST - Ankabut office | G4: 1 | H4: 420811 | I4: 420811-IT Systems & Support expenses-Application/Systems Operation | J4: 000000 | K4: KUST - General | L4: 847001 | M4: FA179-Opex Expense | N4: 200179 | O4: 847.8470810.1.420811.000000.847001.200179 | P4: - | Q4: 10351793 | R4: 10351793 | S4: 420811.IT Systems & Support expenses-Application/Systems Operation-professional services scope/deliverables-Month | T4: Month | U4: 12 | V4: 3759978 | W4: Managed IT Services Contract between KU and Ankabut | X4: 21982967 | Y4: KU Regular operations | Z4: Recurring | AA4: =X4*0.9 -> 19784670 | AB4: =X4*0.8 -> 17586374 | AC4: =X4*0.7 -> 15388077 | AD4: Affects KU Core Operations and Non Compliance with contract terms | AE4: Affects KU Core Operations and Non Compliance with contract terms | AF4: Affects KU Core Operations and Non Compliance with contract terms | AG4: 45119736 | AS4: 45119736 | AT4: Utilize state-of-the-art technologies and facilities in an optimal and efficient manner | AU4: Ankoubt Service agreement including Chp-01 manapower and other IT services
A5: HR | B5: No Applicable | C5: SVP/ Support Services Office | D5: 847 | E5: 8470810 | F5: KUST - Ankabut office | G5: 1 | H5: 421100 | I5: 421100-Manpower supply | J5: 000000 | K5: KUST - General | L5: 847001 | M5: FA179-Opex Expense | N5: 200179 | O5: 847.8470810.1.421100.000000.847001.200179 | P5: 1705887.1 | Q5: 445192 | R5: 445192 | T5: -_ | X5: 0 | AA5: =X5*0.9 -> 0 | AB5: =X5*0.8 -> 0 | AC5: =X5*0.7 -> 0 | AH5: 0 | AS5: 0
A6: IT | B6: Director, Technology Development | C6: SVP/ Support Services Office | D6: 847 | E6: 8470810 | F6: KUST - Ankabut office | G6: 1 | H6: 426610 | I6: 426610-Computer software licenses | J6: 000000 | K6: KUST - General | L6: 847001 | M6: FA179-Opex Expense | N6: 200179 | O6: 847.8470810.1.426610.000000.847001.200179 | P6: 8722313.4 | Q6: 7632571 | R6: 7632571 | S6: 426610.Computer software licenses-Software License Renewal-service level agreement-Service | T6: Service | U6: 1 | V6: 1235304 | W6: Microsoft Licensing Agreement Renewal (EES - 3 Years) - Licenses for multiple products | X6: 1235304 | Y6: KU Regular operations | Z6: Recurring | AA6: =X6*0.9 -> 1111773.6 | AB6: =X6*0.8 -> 988243.2 | AC6: =X6*0.7 -> 864712.8 | AD6: Affects KU Core Operations and Non Compliance with contract terms | AE6: Affects KU Core Operations and Non Compliance with contract terms | AF6: Affects KU Core Operations and Non Compliance with contract terms | AH6: 0 | AK6: 1235304 | AS6: 1235304 | AT6: Utilize state-of-the-art technologies and facilities in an optimal and efficient manner
A7: IT | B7: Director, Technology Development | C7: SVP/ Support Services Office | D7: 847 | E7: 8470810 | F7: KUST - Ankabut office | G7: 1 | H7: 426610 | I7: 426610-Computer software licenses | J7: 000000 | K7: KUST - General | L7: 847001 | M7: FA179-Opex Expense | N7: 200179 | O7: 847.8470810.1.426610.000000.847001.200179 | S7: 426610.Computer software licenses-Software License Renewal-service level agreement-Service | T7: Service | U7: 1 | V7: 856000 | W7: Learning Management System Blackboard LMS License Renewal and Annual Support (License based on storage and number of users - rate based on 8000 slab limit) | X7: 856000 | Y7: KU Regular operations | Z7: Recurring | AA7: =X7*0.9 -> 770400 | AB7: =X7*0.8 -> 684800 | AC7: =X7*0.7 -> 599200 | AD7: Affects KU Core Operations and Non Compliance with contract terms | AE7: Affects KU Core Operations and Non Compliance with contract terms | AF7: Affects KU Core Operations and Non Compliance with contract terms | AH7: 0 | AI7: 856000 | AS7: 856000 | AT7: Utilize state-of-the-art technologies and facilities in an optimal and efficient manner
A8: IT | B8: Director, Technology Development | C8: SVP/ Support Services Office | D8: 847 | E8: 8470810 | F8: KUST - Ankabut office | G8: 1 | H8: 426610 | I8: 426610-Computer software licenses | J8: 000000 | K8: KUST - General | L8: 847001 | M8: FA179-Opex Expense | N8: 200179 | O8: 847.8470810.1.426610.000000.847001.200179 | S8: 426610.Computer software licenses-Software License Renewal-service level agreement-Service | T8: Service | U8: 1 | V8: 756066 | W8: Manage Engine subscriptions for ServideskPlus, Desktop Central, OpManager, AD Manager, Exchange Reporter, App Manager and other Infrastructure Monitoring Tools. | X8: 756066 | Y8: KU Regular operations | Z8: Recurring | AA8: =X8*0.9 -> 680459.4 | AB8: =X8*0.8 -> 604852.8 | AC8: =X8*0.7 -> 529246.2 | AD8: Affects KU Core IT Operations and Non Compliance with contract terms | AE8: Affects KU Core IT Operations and Non Compliance with contract terms | AF8: Affects KU Core IT Operations and Non Compliance with contract terms | AH8: 0 | AM8: 756066 | AS8: 756066 | AT8: Utilize state-of-the-art technologies and facilities in an optimal and efficient manner
A9: IT | B9: Director, Technology Development | C9: SVP/ Support Services Office | D9: 847 | E9: 8470810 | F9: KUST - Ankabut office | G9: 1 | H9: 426610 | I9: 426610-Computer software licenses | J9: 000000 | K9: KUST - General | L9: 847001 | M9: FA179-Opex Expense | N9: 200179 | O9: 847.8470810.1.426610.000000.847001.200179 | S9: 426610.Computer software licenses-Software License Renewal-service level agreement-Service | T9: Service | U9: 1 | V9: 589375 | W9: Student Admissions Slate License and Support Renewal (5Y Service Order)- License based on number of applicants for UG/PG | X9: 589375 | Y9: KU Regular operations | Z9: Recurring | AA9: =X9*0.9 -> 530437.5 | AB9: =X9*0.8 -> 471500 | AC9: =X9*0.7 -> 412562.5 | AD9: Affects KU Core Operations and Non Compliance with contract terms | AE9: Affects KU Core Operations and Non Compliance with contract terms | AF9: Affects KU Core Operations and Non Compliance with contract terms | AH9: 0 | AK9: 589375 | AS9: 589375 | AT9: Utilize state-of-the-art technologies and facilities in an optimal and efficient manner
A10: IT | B10: Director, Technology Development | C10: SVP/ Support Services Office | D10: 847 | E10: 8470810 | F10: KUST - Ankabut office | G10: 1 | H10: 426610 | I10: 426610-Computer software licenses | J10: 000000 | K10: KUST - General | L10: 847001 | M10: FA179-Opex Expense | N10: 200179 | O10: 847.8470810.1.426610.000000.847001.200179 | S10: 426610.Computer software licenses-Software License Renewal-service level agreement-Service | T10: Service | U10: 1 | V10: 617276 | W10: Student Information System (SIS) License Renewal and Support from Elucian Banner | X10: 617276 | Y10: KU Regular operations | Z10: Recurring | AA10: =X10*0.9 -> 555548.4 | AB10: =X10*0.8 -> 493820.8 | AC10: =X10*0.7 -> 432093.2 | AD10: License cannot be reduced. Affects KU Core Operations and Non Compliance with contract terms | AE10: License cannot be reduced. Affects KU Core Operations and Non Compliance with contract terms | AF10: License cannot be reduced. Affects KU Core Operations and Non Compliance with contract terms | AH10: 0 | AK10: 617276 | AS10: 617276 | AT10: Utilize state-of-the-art technologies and facilities in an optimal and efficient manner
A11: IT | B11: Director, Technology Development | C11: SVP/ Support Services Office | D11: 847 | E11: 8470810 | F11: KUST - Ankabut office | G11: 1 | H11: 426610 | I11: 426610-Computer software licenses | J11: 000000 | K11: KUST - General | L11: 847001 | M11: FA179-Opex Expense | N11: 200179 | O11: 847.8470810.1.426610.000000.847001.200179 | S11: 426610.Computer software licenses-Software License Renewal-service level agreement-Service | T11: Service | U11: 1 | V11: 909500 | W11: Fortinet Systems Subscription Renewals for FortiClient EMS FortiEDR, FortiAnalyzer, FortiGate 101F FortiGate 40F-3G4G, FortiGate 601E FortiGate 61E, FortiManager, FortiSOAR and Incident Response Services Subscription | X11: 909500 | Y11: KU Regular operations | Z11: Recurring | AA11: =X11*0.9 -> 818550 | AB11: =X11*0.8 -> 727600 | AC11: =X11*0.7 -> 636650 | AD11: Affects KU Core IT Operations and Non Compliance with contract terms | AE11: Affects KU Core IT Operations and Non Compliance with contract terms | AF11: Affects KU Core IT Operations and Non Compliance with contract terms | AH11: 0 | AM11: 909500 | AS11: 909500 | AT11: Utilize state-of-the-art technologies and facilities in an optimal and efficient manner
A12: - | B12: - | C12: SVP/ Support Services Office | D12: 847 | E12: 8470810 | F12: KUST - Ankabut office | G12: 1 | H12: 426610 | I12: 426610-Computer software licenses | J12: 000000 | K12: KUST - General | L12: 847001 | M12: FA179-Opex Expense | N12: 200179 | O12: 847.8470810.1.426610.000000.847001.200179 | S12: 426610.Computer software licenses-Software License Renewal-service level agreement-Service | T12: Service | U12: 1 | V12: 479306 | W12: Oracle Support Renewal | X12: 479306 | Y12: KU Regular operations | Z12: Recurring | AA12: =X12*0.9 -> 431375.4 | AB12: =X12*0.8 -> 383444.8 | AC12: =X12*0.7 -> 335514.2 | AD12: License cannot be reduced. Affects KU Core Operations and Non Compliance with contract terms | AE12: License cannot be reduced. Affects KU Core Operations and Non Compliance with contract terms | AF12: License cannot be reduced. Affects KU Core Operations and Non Compliance with contract terms | AH12: 0 | AK12: 479306 | AS12: 479306 | AT12: Utilize state-of-the-art technologies and facilities in an optimal and efficient manner
A13: - | B13: - | C13: SVP/ Support Services Office | D13: 847 | E13: 8470810 | F13: KUST - Ankabut office | G13: 1 | H13: 426610 | I13: 426610-Computer software licenses | J13: 000000 | K13: KUST - General | L13: 847001 | M13: FA179-Opex Expense | N13: 200179 | O13: 847.8470810.1.426610.000000.847001.200179 | S13: 426610.Computer software licenses-Software License Renewal-service level agreement-Service | T13: Service | U13: 1 | V13: 400000 | W13: Aruba Wireless Infrastructure Software Subscriptions renewals | X13: 400000 | Y13: KU Regular operations | Z13: Recurring | AA13: =X13*0.9 -> 360000 | AB13: =X13*0.8 -> 320000 | AC13: =X13*0.7 -> 280000 | AD13: Affects KU Core Operations | AE13: Affects KU Core Operations | AF13: Affects KU Core Operations | AH13: 0 | AK13: 400000 | AS13: 400000 | AT13: Utilize state-of-the-art technologies and facilities in an optimal and efficient manner
A14: - | B14: - | C14: SVP/ Support Services Office | D14: 847 | E14: 8470810 | F14: KUST - Ankabut office | G14: 1 | H14: 426610 | I14: 426610-Computer software licenses | J14: 000000 | K14: KUST - General | L14: 847001 | M14: FA179-Opex Expense | N14: 200179 | O14: 847.8470810.1.426610.000000.847001.200179 | S14: 426610.Computer software licenses-Software License Renewal-service level agreement-Service | T14: Service | U14: 1 | V14: 126098 | W14: Vmware Virtualization Infrastructure Software License | X14: 126098 | Y14: KU Regular operations | Z14: Recurring | AA14: =X14*0.9 -> 113488.2 | AB14: =X14*0.8 -> 100878.4 | AC14: =X14*0.7 -> 88268.6 | AD14: Affects partially KU applications | AE14: Affects partially KU applications | AF14: Affects partially KU applications | AH14: 0 | AK14: 126098 | AS14: 126098 | AT14: Utilize state-of-the-art technologies and facilities in an optimal and efficient manner
A15: - | B15: - | C15: SVP/ Support Services Office | D15: 847 | E15: 8470810 | F15: KUST - Ankabut office | G15: 1 | H15: 426610 | I15: 426610-Computer software licenses | J15: 000000 | K15: KUST - General | L15: 847001 | M15: FA179-Opex Expense | N15: 200179 | O15: 847.8470810.1.426610.000000.847001.200179 | S15: 426610.Computer software licenses-Software License Renewal-service level agreement-Service | T15: Service | U15: 1 | V15: 327443 | W15: ElasticSearch Security Operations Analysis Software Subscription Renewal | X15: 327443 | Y15: KU Regular operations | Z15: Recurring | AA15: =X15*0.9 -> 294698.7 | AB15: =X15*0.8 -> 261954.4 | AC15: =X15*0.7 -> 229210.1 | AD15: License cannot be reduced. Affects Information Security Operations for analysing security incidents and logs | AE15: License cannot be reduced. Affects Information Security Operations for analysing security incidents and logs | AF15: License cannot be reduced. Affects Information Security Operations for analysing security incidents and logs | AH15: 0 | AK15: 327443 | AS15: 327443 | AT15: Utilize state-of-the-art technologies and facilities in an optimal and efficient manner
A16: - | B16: - | C16: SVP/ Support Services Office | D16: 847 | E16: 8470810 | F16: KUST - Ankabut office | G16: 1 | H16: 426610 | I16: 426610-Computer software licenses | J16: 000000 | K16: KUST - General | L16: 847001 | M16: FA179-Opex Expense | N16: 200179 | O16: 847.8470810.1.426610.000000.847001.200179 | S16: 426610.Computer software licenses-Software License Renewal-service level agreement-Service | T16: Service | U16: 1 | V16: 240623 | W16: Allienvault SIEM Subscription Renewal | X16: 240623 | Y16: KU Regular operations | Z16: Recurring | AA16: =X16*0.9 -> 216560.7 | AB16: =X16*0.8 -> 192498.4 | AC16: =X16*0.7 -> 168436.1 | AD16: Site License cannot be reduced. Affects Information Security Operations for analysing security incidents and logs | AE16: Site License cannot be reduced. Affects Information Security Operations for analysing security incidents and logs | AF16: Site License cannot be reduced. Affects Information Security Operations for analysing security incidents and logs | AH16: 0 | AK16: 240623 | AS16: 240623 | AT16: Utilize state-of-the-art technologies and facilities in an optimal and efficient manner
A17: - | B17: - | C17: SVP/ Support Services Office | D17: 847 | E17: 8470810 | F17: KUST - Ankabut office | G17: 1 | H17: 426610 | I17: 426610-Computer software licenses | J17: 000000 | K17: KUST - General | L17: 847001 | M17: FA179-Opex Expense | N17: 200179 | O17: 847.8470810.1.426610.000000.847001.200179 | S17: 426610.Computer software licenses-Software License Renewal-service level agreement-Service | T17: Service | U17: 1 | V17: 184964 | W17: Application Virtualization - Software2 AppsAnyWhere | X17: 184964 | Y17: KU Regular operations | Z17: Recurring | AA17: =X17*0.9 -> 166467.6 | AB17: =X17*0.8 -> 147971.2 | AC17: =X17*0.7 -> 129474.8 | AD17: License cannot be reduced. Affects access to academic software | AE17: License cannot be reduced. Affects access to academic software | AF17: License cannot be reduced. Affects access to academic software | AH17: 0 | AK17: 184964 | AS17: 184964 | AT17: Utilize state-of-the-art technologies and facilities in an optimal and efficient manner
A18: - | B18: - | C18: SVP/ Support Services Office | D18: 847 | E18: 8470810 | F18: KUST - Ankabut office | G18: 1 | H18: 426610 | I18: 426610-Computer software licenses | J18: 000000 | K18: KUST - General | L18: 847001 | M18: FA179-Opex Expense | N18: 200179 | O18: 847.8470810.1.426610.000000.847001.200179 | S18: 426610.Computer software licenses-Software License Renewal-service level agreement-Service | T18: Service | U18: 1 | V18: 231000 | W18: Email Archiving solution (Commvault) | X18: 231000 | Y18: KU Regular operations | Z18: Recurring | AA18: =X18*0.9 -> 207900 | AB18: =X18*0.8 -> 184800 | AC18: =X18*0.7 -> 161700 | AD18: Access to email archive not available | AE18: Access to email archive not available | AF18: Access to email archive not available | AH18: 0 | AK18: 231000 | AS18: 231000 | AT18: Utilize state-of-the-art technologies and facilities in an optimal and efficient manner
A19: - | B19: - | C19: SVP/ Support Services Office | D19: 847 | E19: 8470810 | F19: KUST - Ankabut office | G19: 1 | H19: 426610 | I19: 426610-Computer software licenses | J19: 000000 | K19: KUST - General | L19: 847001 | M19: FA179-Opex Expense | N19: 200179 | O19: 847.8470810.1.426610.000000.847001.200179 | S19: 426610.Computer software licenses-Software License Renewal-service level agreement-Service | T19: Service | U19: 1 | V19: 182648 | W19: Symplicity CSM Enterprise yearly license for Student Internship, Career, Alumni, Job portal, Events/Activities and Contract Management Services | X19: 182648 | Y19: KU Regular operations | Z19: Recurring | AA19: =X19*0.9 -> 164383.2 | AB19: =X19*0.8 -> 146118.4 | AC19: =X19*0.7 -> 127853.6 | AD19: Site License cannot be reduced. Affects access to Application | AE19: Site License cannot be reduced. Affects access to Application | AF19: Site License cannot be reduced. Affects access to Application | AH19: 0 | AK19: 182648 | AS19: 182648 | AT19: Utilize state-of-the-art technologies and facilities in an optimal and efficient manner
A20: - | B20: - | C20: SVP/ Support Services Office | D20: 847 | E20: 8470810 | F20: KUST - Ankabut office | G20: 1 | H20: 426610 | I20: 426610-Computer software licenses | J20: 000000 | K20: KUST - General | L20: 847001 | M20: FA179-Opex Expense | N20: 200179 | O20: 847.8470810.1.426610.000000.847001.200179 | S20: 426610.Computer software licenses-Software License Renewal-service level agreement-Service | T20: Service | U20: 1 | V20: 165600 | W20: Gartner Technologies subscription renewal | X20: 165600 | Y20: KU Regular operations | Z20: Recurring | AA20: =X20*0.9 -> 149040 | AB20: =X20*0.8 -> 132480 | AC20: =X20*0.7 -> 115920 | AD20: Affect Access to IT advisory services | AE20: Affect Access to IT advisory services | AF20: Affect Access to IT advisory services | AH20: 0 | AK20: 165600 | AS20: 165600 | AT20: Utilize state-of-the-art technologies and facilities in an optimal and efficient manner
A21: - | B21: - | C21: SVP/ Support Services Office | D21: 847 | E21: 8470810 | F21: KUST - Ankabut office | G21: 1 | H21: 426610 | I21: 426610-Computer software licenses | J21: 000000 | K21: KUST - General | L21: 847001 | M21: FA179-Opex Expense | N21: 200179 | O21: 847.8470810.1.426610.000000.847001.200179 | S21: 426610.Computer software licenses-Software License Renewal-service level agreement-Service | T21: Service | U21: 1 | V21: 174360 | W21: Plagiarism Proofing License renewal - TurnitIn, iThenticate | X21: 174360 | Y21: KU Regular operations | Z21: Recurring | AA21: =X21*0.9 -> 156924 | AB21: =X21*0.8 -> 139488 | AC21: =X21*0.7 -> 122052 | AD21: Affects KU Core Operations and Non Compliance with contract terms | AE21: Affects KU Core Operations and Non Compliance with contract terms | AF21: Affects KU Core Operations and Non Compliance with contract terms | AH21: 0 | AK21: 174360 | AS21: 174360 | AT21: Utilize state-of-the-art technologies and facilities in an optimal and efficient manner
A22: - | B22: - | C22: SVP/ Support Services Office | D22: 847 | E22: 8470810 | F22: KUST - Ankabut office | G22: 1 | H22: 426610 | I22: 426610-Computer software licenses | J22: 000000 | K22: KUST - General | L22: 847001 | M22: FA179-Opex Expense | N22: 200179 | O22: 847.8470810.1.426610.000000.847001.200179 | S22: 426610.Computer software licenses-Software License Renewal-service level agreement-Service | T22: Service | U22: 1 | V22: 107347 | W22: Video Communication Platform License Renewal and Support from Sonifoundry Mediasite | X22: 107347 | Y22: KU Regular operations | Z22: Recurring | AA22: =X22*0.9 -> 96612.3 | AB22: =X22*0.8 -> 85877.6 | AC22: =X22*0.7 -> 75142.9 | AD22: Site License cannot be reduced. Affects access to lecture recording content | AE22: Site License cannot be reduced. Affects access to lecture recording content | AF22: Site License cannot be reduced. Affects access to lecture recording content | AH22: 0 | AK22: 107347 | AS22: 107347 | AT22: Utilize state-of-the-art technologies and facilities in an optimal and efficient manner
A23: - | B23: - | C23: SVP/ Support Services Office | D23: 847 | E23: 8470810 | F23: KUST - Ankabut office | G23: 1 | H23: 426610 | I23: 426610-Computer software licenses | J23: 000000 | K23: KUST - General | L23: 847001 | M23: FA179-Opex Expense | N23: 200179 | O23: 847.8470810.1.426610.000000.847001.200179 | S23: 426610.Computer software licenses-Software License Renewal-service level agreement-Service | T23: Service | U23: 1 | V23: 45000 | W23: Ascertia SigningHub AATL Signing Certificate and Signature Pack Renewal | X23: 45000 | Y23: KU Regular operations | Z23: Recurring | AA23: =X23*0.9 -> 40500 | AB23: =X23*0.8 -> 36000 | AC23: =X23*0.7 -> 31500 | AD23: Site License cannot be reduced. Affects access to application | AE23: Site License cannot be reduced. Affects access to application | AF23: Site License cannot be reduced. Affects access to application | AH23: 0 | AK23: 45000 | AS23: 45000 | AT23: Utilize state-of-the-art technologies and facilities in an optimal and efficient manner
... A32: - | B32: - | C32: SVP/ Support Services Office | D32: 847 | E32: 8470810 | F32: KUST - Ankabut office | G32: 1 | H32: 426610 | I32: 426610-Computer software licenses | J32: 000000 | K32: KUST - General | L32: 847001 | M32: FA179-Opex Expense | N32: 200179 | O32: 847.8470810.1.426610.000000.847001.200179 | S32: 426610.Computer software licenses-Software License Renewal-service level agreement-Service | T32: Service | U32: 1 | V32: 28950 | W32: RedHat Linux Subscription Renewal | X32: 28950 | Y32: KU Regular operations | Z32: Recurring | AA32: =X32*0.9 -> 26055 | AB32: =X32*0.8 -> 23160 | AC32: =X32*0.7 -> 20265 | AD32: Affects Support for core IT infrastructure | AE32: Affects Support for core IT infrastructure | AF32: Affects Support for core IT infrastructure | AH32: 0 | AK32: 28950 | AS32: 28950 | AT32: Utilize state-of-the-art technologies and facilities in an optimal and efficient manner
A33: - | B33: - | C33: SVP/ Support Services Office | D33: 847 | E33: 8470810 | F33: KUST - Ankabut office | G33: 1 | H33: 426610 | I33: 426610-Computer software licenses | J33: 000000 | K33: KUST - General | L33: 847001 | M33: FA179-Opex Expense | N33: 200179 | O33: 847.8470810.1.426610.000000.847001.200179 | S33: 426610.Computer software licenses-Software License Renewal-service level agreement-Service | T33: Service | U33: 1 | V33: 25000 | W33: Blockchain solution for issuing digital records (Student Tarnscripts) for KU Registrar's Office | X33: 25000 | Y33: KU Regular operations | Z33: Recurring | AA33: =X33*0.9 -> 22500 | AB33: =X33*0.8 -> 20000 | AC33: =X33*0.7 -> 17500 | AD33: Affects access to application | AE33: Affects access to application | AF33: Affects access to application | AH33: 0 | AL33: 25000 | AS33: 25000 | AT33: Utilize state-of-the-art technologies and facilities in an optimal and efficient manner
A34: - | B34: - | C34: SVP/ Support Services Office | D34: 847 | E34: 8470810 | F34: KUST - Ankabut office | G34: 1 | H34: 426610 | I34: 426610-Computer software licenses | J34: 000000 | K34: KUST - General | L34: 847001 | M34: FA179-Opex Expense | N34: 200179 | O34: 847.8470810.1.426610.000000.847001.200179 | S34: 426610.Computer software licenses-Software License Renewal-service level agreement-Service | T34: Service | U34: 1 | V34: 20000 | W34: Subscription to Apple Store, Windows App Store, Google Store and App Development program | X34: 20000 | Y34: KU Regular operations | Z34: Recurring | AA34: =X34*0.9 -> 18000 | AB34: =X34*0.8 -> 16000 | AC34: =X34*0.7 -> 14000 | AD34: Affects IT Software Development process | AE34: Affects IT Software Development process | AF34: Affects IT Software Development process | AH34: 0 | AL34: 20000 | AS34: 20000 | AT34: Utilize state-of-the-art technologies and facilities in an optimal and efficient manner
A35: - | B35: - | C35: SVP/ Support Services Office | D35: 847 | E35: 8470810 | F35: KUST - Ankabut office | G35: 1 | H35: 426610 | I35: 426610-Computer software licenses | J35: 000000 | K35: KUST - General | L35: 847001 | M35: FA179-Opex Expense | N35: 200179 | O35: 847.8470810.1.426610.000000.847001.200179 | S35: 426610.Computer software licenses-Software License Renewal-service level agreement-Service | T35: Service | U35: 1 | V35: 20000 | W35: Threat Intelligence Subscription/Domain Monitoring | X35: 20000 | Y35: KU Regular operations | Z35: Recurring | AA35: =X35*0.9 -> 18000 | AB35: =X35*0.8 -> 16000 | AC35: =X35*0.7 -> 14000 | AD35: Affects cybersecurity monitoring operations | AE35: Affects cybersecurity monitoring operations | AF35: Affects cybersecurity monitoring operations | AH35: 0 | AL35: 20000 | AS35: 20000 | AT35: Utilize state-of-the-art technologies and facilities in an optimal and efficient manner
A36: - | B36: - | C36: SVP/ Support Services Office | D36: 847 | E36: 8470810 | F36: KUST - Ankabut office | G36: 1 | H36: 426610 | I36: 426610-Computer software licenses | J36: 000000 | K36: KUST - General | L36: 847001 | M36: FA179-Opex Expense | N36: 200179 | O36: 847.8470810.1.426610.000000.847001.200179 | S36: 426610.Computer software licenses-Software License Renewal-service level agreement-Service | T36: Service | U36: 1 | V36: 25000 | W36: Server Certificate SSL | X36: 25000 | Y36: KU Regular operations | Z36: Recurring | AA36: =X36*0.9 -> 22500 | AB36: =X36*0.8 -> 20000 | AC36: =X36*0.7 -> 17500 | AD36: Affects access to KU applications | AE36: Affects access to KU applications | AF36: Affects access to KU applications | AH36: 0 | AL36: 25000 | AS36: 25000 | AT36: Utilize state-of-the-art technologies and facilities in an optimal and efficient manner
A37: - | B37: - | C37: SVP/ Support Services Office | D37: 847 | E37: 8470810 | F37: KUST - Ankabut office | G37: 1 | H37: 426610 | I37: 426610-Computer software licenses | J37: 000000 | K37: KUST - General | L37: 847001 | M37: FA179-Opex Expense | N37: 200179 | O37: 847.8470810.1.426610.000000.847001.200179 | S37: 426610.Computer software licenses-Software License Renewal-service level agreement-Service | T37: Service | U37: 1 | V37: 14046 | W37: CIS (Center for Internet Security) Security Baseline Scripts | X37: 14046 | Y37: KU Regular operations | Z37: Recurring | AA37: =X37*0.9 -> 12641.4 | AB37: =X37*0.8 -> 11236.8 | AC37: =X37*0.7 -> 9832.2 | AD37: Affects cybersecurity monitoring operations | AE37: Affects cybersecurity monitoring operations | AF37: Affects cybersecurity monitoring operations | AH37: 0 | AL37: 14046 | AS37: 14046 | AT37: Utilize state-of-the-art technologies and facilities in an optimal and efficient manner
A38: - | B38: - | C38: SVP/ Support Services Office | D38: 847 | E38: 8470810 | F38: KUST - Ankabut office | G38: 1 | H38: 426610 | I38: 426610-Computer software licenses | J38: 000000 | K38: KUST - General | L38: 847001 | M38: FA179-Opex Expense | N38: 200179 | O38: 847.8470810.1.426610.000000.847001.200179 | S38: 426610.Computer software licenses-Software License Renewal-service level agreement-Service | T38: Service | U38: 1 | V38: 14000 | W38: NetCobol | X38: 14000 | Y38: KU Regular operations | Z38: Recurring | AA38: =X38*0.9 -> 12600 | AB38: =X38*0.8 -> 11200 | AC38: =X38*0.7 -> 9800 | AD38: Affects IT Software Development process | AE38: Affects IT Software Development process | AF38: Affects IT Software Development process | AH38: 0 | AL38: 14000 | AS38: 14000 | AT38: Utilize state-of-the-art technologies and facilities in an optimal and efficient manner
A39: - | B39: - | C39: SVP/ Support Services Office | D39: 847 | E39: 8470810 | F39: KUST - Ankabut office | G39: 1 | H39: 426610 | I39: 426610-Computer software licenses | J39: 000000 | K39: KUST - General | L39: 847001 | M39: FA179-Opex Expense | N39: 200179 | O39: 847.8470810.1.426610.000000.847001.200179 | S39: 426610.Computer software licenses-Software License Renewal-service level agreement-Service | T39: Service | U39: 1 | V39: 11156 | W39: CreativeCloud for Communications Team | X39: 11156 | Y39: KU Regular operations | Z39: Recurring | AA39: =X39*0.9 -> 10040.4 | AB39: =X39*0.8 -> 8924.8 | AC39: =X39*0.7 -> 7809.2 | AD39: Affects access to application | AE39: Affects access to application | AF39: Affects access to application | AH39: 0 | AL39: 11156 | AS39: 11156 | AT39: Utilize state-of-the-art technologies and facilities in an optimal and efficient manner
A40: - | B40: - | C40: SVP/ Support Services Office | D40: 847 | E40: 8470810 | F40: KUST - Ankabut office | G40: 1 | H40: 426610 | I40: 426610-Computer software licenses | J40: 000000 | K40: KUST - General | L40: 847001 | M40: FA179-Opex Expense | N40: 200179 | O40: 847.8470810.1.426610.000000.847001.200179 | S40: 426610.Computer software licenses-Software License Renewal-service level agreement-Service | T40: Service | U40: 1 | V40: 10000 | W40: TOAD For Oracle Professional Edition Per Seat Maintenance Renewal | X40: 10000 | Y40: KU Regular operations | Z40: Recurring | AA40: =X40*0.9 -> 9000 | AB40: =X40*0.8 -> 8000 | AC40: =X40*0.7 -> 7000 | AD40: Affects access to application | AE40: Affects access to application | AF40: Affects access to application | AH40: 0 | AL40: 10000 | AS40: 10000 | AT40: Utilize state-of-the-art technologies and facilities in an optimal and efficient manner
A41: - | B41: - | C41: SVP/ Support Services Office | D41: 847 | E41: 8470810 | F41: KUST - Ankabut office | G41: 1 | H41: 426610 | I41: 426610-Computer software licenses | J41: 000000 | K41: KUST - General | L41: 847001 | M41: FA179-Opex Expense | N41: 200179 | O41: 847.8470810.1.426610.000000.847001.200179 | S41: 426610.Computer software licenses-Software License Renewal-service level agreement-Service | T41: Service | U41: 1 | V41: 10000 | W41: Interactive Voice Response - Vocalcom IVR Support | X41: 10000 | Y41: KU Regular operations | Z41: Recurring | AA41: =X41*0.9 -> 9000 | AB41: =X41*0.8 -> 8000 | AC41: =X41*0.7 -> 7000 | AD41: Affects access to application | AE41: Affects access to application | AF41: Affects access to application | AH41: 0 | AL41: 10000 | AS41: 10000 | AT41: Utilize state-of-the-art technologies and facilities in an optimal and efficient manner
A42: - | B42: - | C42: SVP/ Support Services Office | D42: 847 | E42: 8470810 | F42: KUST - Ankabut office | G42: 1 | H42: 426610 | I42: 426610-Computer software licenses | J42: 000000 | K42: KUST - General | L42: 847001 | M42: FA179-Opex Expense | N42: 200179 | O42: 847.8470810.1.426610.000000.847001.200179 | S42: 426610.Computer software licenses-Software License Renewal-service level agreement-Service | T42: Service | U42: 1 | V42: 7500 | W42: Educause subscription | X42: 7500 | Y42: KU Regular operations | Z42: Recurring | AA42: =X42*0.9 -> 6750 | AB42: =X42*0.8 -> 6000 | AC42: =X42*0.7 -> 5250 | AD42: Affect Access to IT advisory services | AE42: Affect Access to IT advisory services | AF42: Affect Access to IT advisory services | AH42: 0 | AL42: 7500 | AS42: 7500 | AT42: Utilize state-of-the-art technologies and facilities in an optimal and efficient manner
A43: - | B43: - | C43: SVP/ Support Services Office | D43: 847 | E43: 8470810 | F43: KUST - Ankabut office | G43: 1 | H43: 426610 | I43: 426610-Computer software licenses | J43: 000000 | K43: KUST - General | L43: 847001 | M43: FA179-Opex Expense | N43: 200179 | O43: 847.8470810.1.426610.000000.847001.200179 | S43: 426610.Computer software licenses-Software License Renewal-service level agreement-Service | T43: Service | U43: 1 | V43: 4500 | W43: Academic Software License Management using OpenLM | X43: 4500 | Y43: KU Regular operations | Z43: Recurring | AA43: =X43*0.9 -> 4050 | AB43: =X43*0.8 -> 3600 | AC43: =X43*0.7 -> 3150 | AD43: Affects access to application | AE43: Affects access to application | AF43: Affects access to application | AH43: 0 | AL43: 4500 | AS43: 4500 | AT43: Utilize state-of-the-art technologies and facilities in an optimal and efficient manner
A44: - | B44: - | C44: SVP/ Support Services Office | D44: 847 | E44: 8470810 | F44: KUST - Ankabut office | G44: 1 | H44: 426610 | I44: 426610-Computer software licenses | J44: 000000 | K44: KUST - General | L44: 847001 | M44: FA179-Opex Expense | N44: 200179 | O44: 847.8470810.1.426610.000000.847001.200179 | S44: 426610.Computer software licenses-Software License Renewal-service level agreement-Service | T44: Service | U44: 1 | V44: 4000 | W44: Code Two Auto Email Signature software license maintenance | X44: 4000 | Y44: KU Regular operations | Z44: Recurring | AA44: =X44*0.9 -> 3600 | AB44: =X44*0.8 -> 3200 | AC44: =X44*0.7 -> 2800 | AD44: Affects KU email auto-signature | AE44: Affects KU email auto-signature | AF44: Affects KU email auto-signature | AH44: 0 | AL44: 4000 | AS44: 4000 | AT44: Utilize state-of-the-art technologies and facilities in an optimal and efficient manner
... A49: - | B49: - | C49: SVP/ Support Services Office | D49: 847 | E49: 8470810 | F49: KUST - Ankabut office | G49: 1 | H49: 426610 | I49: 426610-Computer software licenses | J49: 000000 | K49: KUST - General | L49: 847001 | M49: FA179-Opex Expense | N49: 200179 | O49: 847.8470810.1.426610.000000.847001.200179 | S49: 426610.Computer software licenses-Software License Renewal-service level agreement-Service | T49: Service | U49: 1 | V49: 35000 | W49: Autodesk AutoCad for Facilities Management - Space Planning Users | X49: 35000 | Y49: KU Regular operations | Z49: Recurring | AA49: =X49*0.9 -> 31500 | AB49: =X49*0.8 -> 28000 | AC49: =X49*0.7 -> 24500 | AD49: Affects access to application | AE49: Affects access to application | AF49: Affects access to application | AH49: 0 | AL49: 35000 | AS49: 35000 | AT49: Utilize state-of-the-art technologies and facilities in an optimal and efficient manner
A50: IT | B50: No Applicable | C50: SVP/ Support Services Office | D50: 847 | E50: 8470810 | F50: KUST - Ankabut office | G50: 1 | H50: 427810 | I50: 427810-Telephone and telefax charges | J50: 000000 | K50: KUST - General | L50: 847001 | M50: FA179-Opex Expense | N50: 200179 | O50: 847.8470810.1.427810.000000.847001.200179 | P50: 1000636.4 | Q50: 800000 | R50: 800000 | S50: 427810.Telephone and telefax charges-Telecommunication, Satellite services-number of telephone lines-Month | T50: Month | U50: 12 | V50: 30000 | W50: Telephoone Line usage and DID extensions rental | X50: 360000 | Y50: KU Regular operations | Z50: Recurring | AA50: =X50*0.9 -> 324000 | AB50: =X50*0.8 -> 288000 | AC50: =X50*0.7 -> 252000 | AD50: Affects KU communications | AE50: Affects KU communications | AF50: Affects KU communications | AG50: 30000 | AH50: 30000 | AI50: 30000 | AJ50: 30000 | AK50: 30000 | AL50: 30000 | AM50: 30000 | AN50: 30000 | AO50: 30000 | AP50: 30000 | AQ50: 30000 | AR50: 30000 | AS50: 360000 | AT50: Utilize state-of-the-art technologies and facilities in an optimal and efficient manner
A51: IT | B51: No Applicable | C51: SVP/ Support Services Office | D51: 847 | E51: 8470810 | F51: KUST - Ankabut office | G51: 1 | H51: 427810 | I51: 427810-Telephone and telefax charges | J51: 000000 | K51: KUST - General | L51: 847001 | M51: FA179-Opex Expense | N51: 200179 | O51: 847.8470810.1.427810.000000.847001.200179 | S51: 427810.Telephone and telefax charges-Telecommunication, Satellite services-number of mobile numbers-Month | T51: Month | U51: 12 | V51: 38400 | W51: Mobile Services for KU eligible | X51: 460800 | AA51: =X51*0.9 -> 414720 | AB51: =X51*0.8 -> 368640 | AC51: =X51*0.7 -> 322560 | AD51: Affects KU communications | AE51: Affects KU communications | AF51: Affects KU communications | AG51: 38400 | AH51: 38400 | AI51: 38400 | AJ51: 38400 | AK51: 38400 | AL51: 38400 | AM51: 38400 | AN51: 38400 | AO51: 38400 | AP51: 38400 | AQ51: 38400 | AR51: 38400 | AS51: 460800 | AT51: Utilize state-of-the-art technologies and facilities in an optimal and efficient manner
A52: IT | B52: No Applicable | C52: SVP/ Support Services Office | D52: 847 | E52: 8470810 | F52: KUST - Ankabut office | G52: 1 | H52: 427850 | I52: 427850-Data Transmission charges | J52: 000000 | K52: KUST - General | L52: 847001 | M52: FA179-Opex Expense | N52: 200179 | O52: 847.8470810.1.427850.000000.847001.200179 | P52: 2812668.6 | Q52: 2618028 | R52: 2618028 | S52: 427850.Data Transmission charges-Data Transmission charges-number of connection (ADSL/Broadband, etc) lines-Month | T52: Month | U52: 12 | V52: 168169 | W52: Internet Leased Line (1Gbps) and DSL lines for KU Main campus, SAN campus and Student Dorms (12) | X52: 2018028 | Y52: KU Regular operations | Z52: Recurring | AA52: =X52*0.9 -> 1816225.2 | AB52: =X52*0.8 -> 1614422.4 | AC52: =X52*0.7 -> 1412619.6 | AD52: Internet Slowness affecting KU operations | AE52: Internet Slowness affecting KU operations | AF52: Internet Slowness affecting KU operations | AG52: 168169 | AH52: 168169 | AI52: 168169 | AJ52: 168169 | AK52: 168169 | AL52: 168169 | AM52: 168169 | AN52: 168169 | AO52: 168169 | AP52: 168169 | AQ52: 168169 | AR52: 168169 | AS52: 2018028 | AT52: Utilize state-of-the-art technologies and facilities in an optimal and efficient manner
A53: Academic | B53: No Applicable | C53: SVP/ Support Services Office | D53: 847 | E53: 8470810 | F53: KUST - Ankabut office | G53: 1 | H53: 428090 | I53: 428090-Business Travel - Combined expenses | J53: 000000 | K53: KUST - General | L53: 847001 | M53: FA179-Opex Expense | N53: 200179 | O53: 847.8470810.1.428090.000000.847001.200179 | P53: 0 | Q53: 11500 | R53: 11500 | S53: 428090.Business Travel - Combined expenses-Number of Staff-Number | T53: Number | U53: 6 | V53: 4000 | W53: Travel to DR Site at Al Ain and to IT Conferences outside of Abu Dhabi | X53: 24000 | Y53: KU Regular operations | Z53: Recurring | AA53: =X53*0.9 -> 21600 | AB53: =X53*0.8 -> 19200 | AC53: =X53*0.7 -> 16800 | AD53: Limited Impact | AE53: Limited Impact | AF53: Limited Impact | AH53: 0 | AJ53: 8000 | AL53: 8000 | AO53: 8000 | AS53: 24000 | AT53: Utilize state-of-the-art technologies and facilities in an optimal and efficient manner
A54: IT | B54: No Applicable | C54: SVP/ Support Services Office | D54: 847 | E54: 8470810 | F54: KUST - Ankabut office | G54: 1 | H54: 430230 | I54: 430230-Rental - Equipment | J54: 000000 | K54: KUST - General | L54: 847001 | M54: FA179-Opex Expense | N54: 200179 | O54: 847.8470810.1.430230.000000.847001.200179 | P54: 2593733.3 | Q54: 0 | T54: -_ | X54: 0 | AA54: =X54*0.9 -> 0 | AB54: =X54*0.8 -> 0 | AC54: =X54*0.7 -> 0 | AH54: 0 | AS54: 0
A55: Facilities | B55: Director, Technology Development | C55: SVP/ Support Services Office | D55: 847 | E55: 8470810 | F55: KUST - Ankabut office | G55: 1 | H55: 430250 | I55: 430250-Rental - Computer hardware-Rental/Subscription - Computer hardware | J55: 000000 | K55: KUST - General | L55: 847001 | M55: FA179-Opex Expense | N55: 200179 | O55: 847.8470810.1.430250.000000.847001.200179 | P55: - | Q55: 1021317 | R55: 1021317 | S55: 430250.Rental - Computer hardware-Rental/Subscription - Computer hardware-Number of Laptop-Number | T55: Number | U55: 1203 | V55: 1550 | W55: End User Computing Refresh Laptops - Renewal for remaining years of lease for existing computers and additional lease for refresh program and new joiners (Researchers) | X55: 1864650 | Y55: KU Regular operations | Z55: Recurring | AA55: =X55*0.9 -> 1678185 | AB55: =X55*0.8 -> 1491720 | AC55: =X55*0.7 -> 1305255 | AD55: laptops not refreshed as per KU policies and End-User Computing standard | AE55: laptops not refreshed as per KU policies and End-User Computing standard | AF55: laptops not refreshed as per KU policies and End-User Computing standard | AH55: 0 | AJ55: 1864650 | AS55: 1864650 | AT55: Utilize state-of-the-art technologies and facilities in an optimal and efficient manner
A56: IT | B56: Director, Technology Development | C56: SVP/ Support Services Office | D56: 847 | E56: 8470810 | F56: KUST - Ankabut office | G56: 1 | H56: 432205 | I56: 432205-Computers and peripherals | J56: 000000 | K56: KUST - General | L56: 847001 | M56: FA179-Opex Expense | N56: 200179 | O56: 847.8470810.1.432205.000000.847001.200179 | P56: 12846395 | Q56: 1475000 | R56: 1475000 | S56: 432205.Computers and peripherals-End user and Infrastructure components maintenance and support-number of hardware devices-Month | T56: Month | U56: 12 | V56: 20000 | W56: Computer Accessories and hardware spare parts and maintenance for computers, audio visual components out of warranty/support | X56: 240000 | Y56: KU Regular operations | Z56: Recurring | AA56: =X56*0.9 -> 216000 | AB56: =X56*0.8 -> 192000 | AC56: =X56*0.7 -> 168000 | AD56: Limited impact. | AE56: Limited impact. Some hardware failure will not be repaired. | AF56: Limited impact. Some hardware failure will not be repaired. | AG56: 20000 | AH56: 20000 | AI56: 20000 | AJ56: 20000 | AK56: 20000 | AL56: 20000 | AM56: 20000 | AN56: 20000 | AO56: 20000 | AP56: 20000 | AQ56: 20000 | AR56: 20000 | AS56: 240000 | AT56: Utilize state-of-the-art technologies and facilities in an optimal and efficient manner
A57: IT | B57: Director, Technology Development | C57: SVP/ Support Services Office | D57: 847 | E57: 8470810 | F57: KUST - Ankabut office | G57: 1 | H57: 432205 | I57: 432205-Computers and peripherals | J57: 000000 | K57: KUST - General | L57: 847001 | M57: FA179-Opex Expense | N57: 200179 | O57: 847.8470810.1.432205.000000.847001.200179 | S57: 432205.Computers and peripherals-End user and Infrastructure components maintenance and support-service level agreement-Service | T57: Service | U57: 1 | V57: 300000 | W57: Network Cabling and Connectivity Services based on Rate Agreement for network passive components (Agreement attached) | X57: 300000 | Y57: KU Regular operations | Z57: Recurring | AA57: =X57*0.9 -> 270000 | AB57: =X57*0.8 -> 240000 | AC57: =X57*0.7 -> 210000 | AD57: Limited impact | AE57: Limited impact. Some areas will not be having proper networkble | AF57: Limited impact. Some areas will not be having proper networkble | AH57: 0 | AJ57: 100000 | AM57: 100000 | AP57: 100000 | AS57: 300000 | AT57: Utilize state-of-the-art technologies and facilities in an optimal and efficient manner
A58: IT | B58: Director, Technology Development | C58: SVP/ Support Services Office | D58: 847 | E58: 8470810 | F58: KUST - Ankabut office | G58: 1 | H58: 432205 | I58: 432205-Computers and peripherals | J58: 000000 | K58: KUST - General | L58: 847001 | M58: FA179-Opex Expense | N58: 200179 | O58: 847.8470810.1.432205.000000.847001.200179 | S58: 432205.Computers and peripherals-End user and Infrastructure components maintenance and support-service level agreement-Service | T58: Service | U58: 1 | V58: 700000 | W58: Classoom Audio Visual Renovations for merged classrooms in Main and SAN Campuses. Part 1: AV Accessories | X58: 700000 | Y58: KU Regular operations | Z58: Recurring | AA58: =X58*0.9 -> 630000 | AB58: =X58*0.8 -> 560000 | AC58: =X58*0.7 -> 490000 | AD58: Academic Operatiosn Affected due to classroom projection issues | AE58: Academic Operatiosn Affected due to classroom projection issues | AF58: Academic Operatiosn Affected due to classroom projection issues | AH58: 0 | AK58: 700000 | AS58: 700000 | AT58: Utilize state-of-the-art technologies and facilities in an optimal and efficient manner
A59: IT | B59: Director, Technology Development | C59: SVP/ Support Services Office | D59: 847 | E59: 8470810 | F59: KUST - Ankabut office | G59: 1 | H59: 432205 | I59: 432205-Computers and peripherals | J59: 000000 | K59: KUST - General | L59: 847001 | M59: FA179-Opex Expense | N59: 200179 | O59: 847.8470810.1.432205.000000.847001.200179 | S59: 432205.Computers and peripherals-End user and Infrastructure components maintenance and support-service level agreement-Service | T59: Service | U59: 1 | V59: 550000 | W59: Wireless Access Points Maintenance and Unification for KU Main Campus to be based on Aruba Access Points | X59: 550000 | Y59: KU Regular operations | Z59: Recurring | AA59: =X59*0.9 -> 495000 | AB59: =X59*0.8 -> 440000 | AC59: =X59*0.7 -> 385000 | AD59: Limited wireless coverage | AE59: Limited wireless coverage | AF59: Limited wireless coverage | AH59: 0 | AN59: 550000 | AS59: 550000 | AT59: Utilize state-of-the-art technologies and facilities in an optimal and efficient manner
A60: IT | B60: Director, Technology Development | C60: SVP/ Support Services Office | D60: 847 | E60: 8470810 | F60: KUST - Ankabut office | G60: 1 | H60: 432205 | I60: 432205-Computers and peripherals | J60: 000000 | K60: KUST - General | L60: 847001 | M60: FA179-Opex Expense | N60: 200179 | O60: 847.8470810.1.432205.000000.847001.200179 | S60: 432205.Computers and peripherals-End user and Infrastructure components maintenance and support-service level agreement-Service | T60: Service | U60: 1 | V60: 90000 | W60: Network Maintenance for Huawei Equipment out of support (Campus Core/Distribution Switches) | X60: 90000 | Y60: KU Regular operations | Z60: Recurring | AA60: =X60*0.9 -> 81000 | AB60: =X60*0.8 -> 72000 | AC60: =X60*0.7 -> 63000 | AD60: Limited Network support from Vendor | AE60: Limited Network support from Vendor | AF60: Limited Network support from Vendor | AH60: 0 | AK60: 90000 | AS60: 90000 | AT60: Utilize state-of-the-art technologies and facilities in an optimal and efficient manner
A61: IT | B61: Director, Technology Development | C61: SVP/ Support Services Office | D61: 847 | E61: 8470810 | F61: KUST - Ankabut office | G61: 1 | H61: 432205 | I61: 432205-Computers and peripherals | J61: 000000 | K61: KUST - General | L61: 847001 | M61: FA179-Opex Expense | N61: 200179 | O61: 847.8470810.1.432205.000000.847001.200179 | S61: 432205.Computers and peripherals-End user and Infrastructure components maintenance and support-service level agreement-Service | T61: Service | U61: 1 | V61: 450000 | W61: Telephony UCS License renewal | X61: 450000 | Y61: KU Regular operations | Z61: Recurring | AA61: =X61*0.9 -> 405000 | AB61: =X61*0.8 -> 360000 | AC61: =X61*0.7 -> 315000 | AD61: Limited Network support from Vendor | AE61: Limited Network support from Vendor | AF61: Limited Network support from Vendor | AH61: 0 | AK61: 450000 | AS61: 450000
A62: IT | B62: No Applicable | C62: SVP/ Support Services Office | D62: 847 | E62: 8470810 | F62: KUST - Ankabut office | G62: 1 | H62: 432226 | I62: 432226-Computers and peripherals-Printers maintenance and support | J62: 000000 | K62: KUST - General | L62: 847001 | M62: FA179-Opex Expense | N62: 200179 | O62: 847.8470810.1.432226.000000.847001.200179 | P62: - | Q62: 360000 | R62: 360000 | S62: 432226.Computers and peripherals-Printers maintenance and support-Number of paper printing-Month | T62: Month | U62: 12 | V62: 45000 | W62: Printing Charges based on current SLA for Leasing Printers and Maintenance Agreement. (Reference Invoice March 2022 ~40K) | X62: 540000 | Y62: KU Regular operations | Z62: Recurring | AA62: =X62*0.9 -> 486000 | AB62: =X62*0.8 -> 432000 | AC62: =X62*0.7 -> 378000 | AD62: Reduced Quota for printing | AE62: Reduced Quota for printing | AF62: Reduced Quota for printing | AG62: 45000 | AH62: 45000 | AI62: 45000 | AJ62: 45000 | AK62: 45000 | AL62: 45000 | AM62: 45000 | AN62: 45000 | AO62: 45000 | AP62: 45000 | AQ62: 45000 | AR62: 45000 | AS62: 540000 | AT62: Utilize state-of-the-art technologies and facilities in an optimal and efficient manner
A63: Other support | B63: No Applicable | C63: SVP/ Support Services Office | D63: 847 | E63: 8470810 | F63: KUST - Ankabut office | G63: 1 | H63: 436110 | I63: 436110-Printing supplies | J63: 000000 | K63: KUST - General | L63: 847001 | M63: FA179-Opex Expense | N63: 200179 | O63: 847.8470810.1.436110.000000.847001.200179 | P63: - | Q63: 0 | T63: -_ | X63: 0 | AA63: =X63*0.9 -> 0 | AB63: =X63*0.8 -> 0 | AC63: =X63*0.7 -> 0 | AH63: 0 | AS63: 0
A64: IT | B64: Director, Technology Development | C64: SVP/ Support Services Office | D64: 847 | E64: 8470810 | F64: KUST - Ankabut office | G64: 1 | H64: 492310 | I64: 492310-Hardware & peripherals | J64: 000000 | K64: KUST - General | L64: 847001 | M64: FA180-Capex Expense | N64: 300180 | O64: 847.8470810.1.492310.000000.847001.300180 | P64: 3471424 | Q64: 175000 | R64: 175000 | S64: 492310.Hardware & peripherals-warranty period-Warranty | T64: Warranty | U64: 1 | V64: 255000 | W64: Computer Refresh program for Mac/Special Computers for existing users and new Macs for new faculty joiners - Total 30 users @AED8.5K | X64: 255000 | Y64: KU Regular operations | Z64: Non-recurring | AA64: =X64*0.9 -> 229500 | AB64: =X64*0.8 -> 204000 | AC64: =X64*0.7 -> 178500 | AD64: laptops not refreshed as per KU policies and End-User Computing standard | AE64: laptops not refreshed as per KU policies and End-User Computing standard | AF64: laptops not refreshed as per KU policies and End-User Computing standard | AH64: 0 | AK64: 255000 | AS64: 255000 | AT64: Utilize state-of-the-art technologies and facilities in an optimal and efficient manner
A65: IT | B65: Director, Technology Development | C65: SVP/ Support Services Office | D65: 847 | E65: 8470810 | F65: KUST - Ankabut office | G65: 1 | H65: 492352 | I65: 492352-Hardware & peripherals-Network Devices | J65: 000000 | K65: KUST - General | L65: 847001 | M65: FA180-Capex Expense | N65: 300180 | O65: 847.8470810.1.492352.000000.847001.300180 | P65: - | Q65: 1735802 | R65: 1735802 | S65: 492352.Hardware & peripherals-Network Devices-TBD-TBD | T65: TBD | U65: 1 | V65: 1389000 | W65: Campus Network Equipment Refresh Program for: Distribution Switches in Student Dorms (4 Units) Access Network Layer (Out of support lifecycle) - Phase 2 (2023): SAN Campus + New Campus (130 switches) - Phase 3 (2024): KU Main Campus - New Buildings (120 Switches) | X65: 1389000 | Y65: KU Regular operations | Z65: Non-recurring | AA65: =X65*0.9 -> 1250100 | AB65: =X65*0.8 -> 1111200 | AC65: =X65*0.7 -> 972300 | AD65: Limited replacement for old and Obsolete equipment without support | AE65: Limited replacement for old and Obsolete equipment without support | AF65: Limited replacement for old and Obsolete equipment without support | AH65: 0 | AL65: 1389000 | AS65: 1389000 | AT65: Utilize state-of-the-art technologies and facilities in an optimal and efficient manner
A66: IT | B66: Director, Technology Development | C66: SVP/ Support Services Office | D66: 847 | E66: 8470810 | F66: KUST - Ankabut office | G66: 1 | H66: 492354 | I66: 492354-Hardware & peripherals-Peripherals & Infrastructure Components | J66: 000000 | K66: KUST - General | L66: 847001 | M66: FA180-Capex Expense | N66: 300180 | O66: 847.8470810.1.492354.000000.847001.300180 | P66: - | Q66: 240000 | R66: 240000 | S66: 492354.Hardware & peripherals-Peripherals & Infrastructure Components-TBD-TBD | T66: TBD | X66: 0 | AA66: =X66*0.9 -> 0 | AB66: =X66*0.8 -> 0 | AC66: =X66*0.7 -> 0 | AH66: 0 | AS66: 0
A67: IT | B67: Director, Technology Development | C67: SVP/ Support Services Office | D67: 847 | E67: 8470810 | F67: KUST - Ankabut office | G67: 1 | H67: 492356 | I67: 492356-Hardware & peripherals-Conferencing & AV | J67: 000000 | K67: KUST - General | L67: 847001 | M67: FA180-Capex Expense | N67: 300180 | O67: 847.8470810.1.492356.000000.847001.300180 | P67: - | Q67: 650000 | R67: 650000 | S67: 492356.Hardware & peripherals-Conferencing & AV-TBD-TBD | T67: TBD | U67: 1 | V67: 3316413 | W67: Major Classroom Renovations to adopt hybrid learning in classrooms, lecture recording and replace old projectors in SAN and Main campuses. Scope for Phase 1 in 2023 and Phase 2 in 2024 is described in attached sheet (Classroom.xls) | X67: 3316413 | Y67: KU Strategic New Initiative | Z67: Non-recurring | AA67: =X67*0.9 -> 2984771.7 | AB67: =X67*0.8 -> 2653130.4 | AC67: =X67*0.7 -> 2321489.1 | AD67: Limited upgrade of KU Classroom to address teaching requirements | AE67: Limited upgrade of KU Classroom to address teaching requirements | AF67: Limited upgrade of KU Classroom to address teaching requirements | AH67: 0 | AL67: 3316413 | AS67: 3316413 | AT67: Utilize state-of-the-art technologies and facilities in an optimal and efficient manner
A68: IT | B68: Director, Technology Development | C68: SVP/ Support Services Office | D68: 847 | E68: 8470810 | F68: KUST - Ankabut office | G68: 1 | H68: 492356 | I68: 492356-Hardware & peripherals-Conferencing & AV | J68: 000000 | K68: KUST - General | L68: 847001 | M68: FA180-Capex Expense | N68: 300180 | O68: 847.8470810.1.492356.000000.847001.300180 | P68: - | Q68: 650000 | R68: 650000 | S68: 492356.Hardware & peripherals-Conferencing & AV-TBD-TBD | T68: TBD | U68: 1 | V68: 702126 | W68: AV equipment for Merged Classrooms in SAN Campus and Main Campus - Part 2: AV Equipment | X68: 702126 | Y68: KU Regular operations | Z68: Non-recurring | AA68: =X68*0.9 -> 631913.4 | AB68: =X68*0.8 -> 561700.8 | AC68: =X68*0.7 -> 491488.2 | AD68: Limited upgrade of KU Classroom to address teaching requirements | AE68: Limited upgrade of KU Classroom to address teaching requirements | AF68: Limited upgrade of KU Classroom to address teaching requirements | AH68: 0 | AL68: 702126 | AS68: 702126
A69: 0 | B69: No Applicable | C69: SVP/ Support Services Office | D69: 847 | E69: 8470810 | F69: KUST - Ankabut office | G69: 1 | H69: 495110 | I69: 495110-Computer software | J69: 000000 | K69: KUST - General | L69: 847001 | M69: FA180-Capex Expense | N69: 300180 | O69: 847.8470810.1.495110.000000.847001.300180 | P69: 796333.2 | Q69: 0 | T69: -_ | X69: 0 | AA69: =X69*0.9 -> 0 | AB69: =X69*0.8 -> 0 | AC69: =X69*0.7 -> 0 | AH69: 0 | AS69: 0
A70: IT | B70: Director, Technology Development | C70: SVP/ Support Services Office | D70: 847 | E70: 8470810 | F70: KUST - Ankabut office | G70: 1 | H70: 495113 | I70: 495113-Computer software-Application, Platform | J70: 000000 | K70: KUST - General | L70: 847001 | M70: FA180-Capex Expense | N70: 300180 | O70: 847.8470810.1.495113.000000.847001.300180 | P70: - | Q70: 590670 | R70: 590670 | S70: 495113.Computer software-Application, Platform -number of licenses-Number | T70: Number | U70: 1 | V70: 320000 | W70: Mobile App Development Platform Solution for Unified KU Mobile App (e.g Modolabs) | X70: 320000 | Y70: KU Strategic New Initiative | Z70: Non-recurring | AA70: =X70*0.9 -> 288000 | AB70: =X70*0.8 -> 256000 | AC70: =X70*0.7 -> 224000 | AD70: Limited licenses for the application | AE70: Limited licenses for the application | AF70: Limited licenses for the application | AH70: 0 | AJ70: 320000 | AS70: 320000 | AT70: Utilize state-of-the-art technologies and facilities in an optimal and efficient manner
A71: IT | B71: Director, Technology Development | C71: SVP/ Support Services Office | D71: 847 | E71: 8470810 | F71: KUST - Ankabut office | G71: 1 | H71: 495113 | I71: 495113-Computer software-Application, Platform | J71: 000000 | K71: KUST - General | L71: 847001 | M71: FA180-Capex Expense | N71: 300180 | O71: 847.8470810.1.495113.000000.847001.300180 | S71: 495113.Computer software-Application, Platform -number of licenses-Number | T71: Number | U71: 1 | V71: 300000 | W71: Application Integration Platform (API Gateway) for process automations | X71: 300000 | Y71: KU Regular operations | Z71: Recurring | AA71: =X71*0.9 -> 270000 | AB71: =X71*0.8 -> 240000 | AC71: =X71*0.7 -> 210000 | AD71: Limited licenses for the application | AE71: Limited licenses for the application | AF71: Limited licenses for the application | AH71: 0 | AJ71: 300000 | AS71: 300000 | AT71: Utilize state-of-the-art technologies and facilities in an optimal and efficient manner
A72: IT | B72: Director, Technology Development | C72: SVP/ Support Services Office | D72: 847 | E72: 8470810 | F72: KUST - Ankabut office | G72: 1 | H72: 495113 | I72: 495113-Computer software-Application, Platform | J72: 000000 | K72: KUST - General | L72: 847001 | M72: FA180-Capex Expense | N72: 300180 | O72: 847.8470810.1.495113.000000.847001.300180 | S72: 495113.Computer software-Application, Platform -number of licenses-Number | T72: Number | U72: 1 | V72: 152572 | W72: Call Management - Imagicle Applications integrated with KU Telephony System - Quote for USD 124,548 for 3Y | X72: 152572 | Y72: KU Regular operations | Z72: Recurring | AA72: =X72*0.9 -> 137314.8 | AB72: =X72*0.8 -> 122057.6 | AC72: =X72*0.7 -> 106800.4 | AD72: Limited licenses for the application | AE72: Limited licenses for the application | AF72: Limited licenses for the application | AH72: 0 | AJ72: 152572 | AS72: 152572 | AT72: Utilize state-of-the-art technologies and facilities in an optimal and efficient manner
A73: IT | B73: No Applicable | C73: SVP/ Support Services Office | D73: 847 | E73: 8470810 | F73: KUST - Ankabut office | G73: 1 | H73: 427850 | I73: 427850-Data Transmission charges | J73: 000000 | K73: KUST - General | L73: 847001 | M73: FA179-Opex Expense | N73: 200179 | O73: 847.8470810.1.427850.000000.847001.200179 | P73: 1695109.4 | Q73: - | T73: -_ | X73: 0 | AA73: =X73*0.9 -> 0 | AB73: =X73*0.8 -> 0 | AC73: =X73*0.7 -> 0 | AH73: 0 | AS73: 0
A74: Facilities | B74: Director, Research Laboratories | C74: SVP/ Support Services Office | D74: 847 | E74: 8470810 | F74: KUST - Ankabut office | G74: 1 | H74: 492316 | I74: 492316-Laboratory equipment | J74: 000000 | K74: KUST - General | L74: 847001 | M74: FA180-Capex Expense | N74: 300180 | O74: 847.8470810.1.492316.000000.847001.300180 | P74: -53578 | Q74: - | T74: -_ | X74: 0 | AA74: =X74*0.9 -> 0 | AB74: =X74*0.8 -> 0 | AC74: =X74*0.7 -> 0 | AH74: 0 | AS74: 0
A75: Academic | B75: No Applicable | C75: Provost | D75: 847 | E75: 8470220 | F75: KUST - Office of the Provost | G75: 1 | H75: 420550 | I75: 420550-Academic Advisory Service | J75: 000000 | K75: KUST - General | L75: 847001 | M75: FA179-Opex Expense | N75: 200179 | O75: 847.8470220.1.420550.000000.847001.200179 | P75: - | Q75: 60000 | R75: 60000 | S75: 420550.Academic Advisory Service-Number of Services-Number | U75: 145 | V75: 2900 | W75: External Consultants for 5x new Programs @ 40000 Each External Evaluators for Faculty Promotions (35 faculty x 4 evaluators @ $400 (1600AED) each | X75: 420500 | Y75: KU Regular operations | Z75: Recurring | AA75: =X75*0.9 -> 378450 | AB75: =X75*0.8 -> 336400 | AC75: =X75*0.7 -> 294350 | AD75: If we are unable to pay the evaluators and contractors agreed price it will cause reputational damage | AE75: If we are unable to pay the evaluators and contractors agreed price it will cause reputational damage | AF75: If we are unable to pay the evaluators and contractors agreed price it will cause reputational damage | AH75: 44000 | AJ75: 40000 | AL75: 40000 | AN75: 80000 | AQ75: 108250 | AR75: 108250 | AS75: 420500 | AT75: Align academic programs with the local and global labor market needs
A76: Academic | B76: No Applicable | C76: Provost | D76: 847 | E76: 8470220 | F76: KUST - Office of the Provost | G76: 1 | H76: 420570 | I76: 420570-Academic Collaborative Partnership Services | J76: 000000 | K76: KUST - General | L76: 847001 | M76: FA179-Opex Expense | N76: 200179 | O76: 847.8470220.1.420570.000000.847001.200179 | P76: - | Q76: 392387 | R76: 392387 | S76: 420570.Academic Collaborative Partnership Services-Partnership Agreement or Academic Collaboration -No of Partneship/collaboration Agreement | T76: No of Partneship/collaboration Agreement | U76: 1 | V76: 3000000 | W76: Twinning & other partnership initiatives | X76: 3000000 | Y76: KU Regular operations | Z76: Recurring | AA76: =X76*0.9 -> 2700000 | AB76: =X76*0.8 -> 2400000 | AC76: =X76*0.7 -> 2100000 | AD76: Less budget will impact the amount of activities and associated output/benefits | AE76: Less budget will impact the amount of activities and associated output/benefits | AF76: Less budget will impact the amount of activities and associated output/benefits | AG76: 250000 | AH76: 250000 | AI76: 250000 | AJ76: 250000 | AK76: 250000 | AL76: 250000 | AM76: 250000 | AN76: 250000 | AO76: 250000 | AP76: 250000 | AQ76: 250000 | AR76: 250000 | AS76: 3000000 | AT76: Build partnerships with local and international universities
A77: Academic | B77: Director, Institutional Research and Planning | C77: Provost | D77: 847 | E77: 8470220 | F77: KUST - Office of the Provost | G77: 1 | H77: 421700 | I77: 421700-Standards certification (e.g. ISO) | J77: 000000 | K77: KUST - General | L77: 847001 | M77: FA179-Opex Expense | N77: 200179 | O77: 847.8470220.1.421700.000000.847001.200179 | P77: - | Q77: 375000 | R77: 375000 | S77: 421700.Standards Certification Services (e.g. ISO)-Number of Academic programs-Number | T77: Number | U77: 23 | V77: 150000 | W77: 23 x CAA reaccrediation of programs @ 150K each + 5 x new Programs @ 150K each | X77: 3450000 | Y77: KU Regular operations | Z77: Non-recurring | AA77: =X77*0.9 -> 3105000 | AB77: =X77*0.8 -> 2760000 | AC77: =X77*0.7 -> 2415000 | AD77: This is a fee to the CAA, UAE Government entity, this amount must be paid, without reaccrediation it would be hugely damaging | AE77: This is a fee to the CAA, UAE Government entity, this amount must be paid, without reaccrediation it would be hugely damaging | AF77: This is a fee to the CAA, UAE Government entity, this amount must be paid, without reaccrediation it would be hugely damaging | AI77: 0 | AJ77: 3450000 | AK77: 0 | AL77: 0 | AM77: 0 | AN77: 0 | AO77: 0 | AP77: 0 | AQ77: 0 | AR77: 0 | AS77: 3450000 | AT77: Develop a multidimensional program to attract and retain diverse outstanding students
A78: Communiction & Marketing | B78: Director, Marketing and Communication | C78: Provost | D78: 847 | E78: 8470220 | F78: KUST - Office of the Provost | G78: 1 | H78: 425510 | I78: 425510-Conferences, seminars and exhibitions and other events: - Local Events | J78: 000000 | K78: KUST - General | L78: 847001 | M78: FA179-Opex Expense | N78: 200179 | O78: 847.8470220.1.425510.000000.847001.200179 | P78: - | Q78: 10000 | R78: 10000 | S78: 425510.Conferences, seminars and exhibitions and other events: - Local Events-Seminars-Number of Seminars | T78: Number of Seminars | U78: 5 | V78: 20000 | W78: Local events/conferences/seminars etc Hosting well known faculty researchers/faculty for seminars etc 5 @ 20000 each | X78: 100000 | Y78: KU Regular operations | Z78: Recurring | AA78: =X78*0.9 -> 90000 | AB78: =X78*0.8 -> 80000 | AC78: =X78*0.7 -> 70000 | AD78: Less budget will impact the amount of activities and associated output/benefits | AE78: Less budget will impact the amount of activities and associated output/benefits | AF78: Less budget will impact the amount of activities and associated output/benefits | AH78: 20000 | AI78: 20000 | AJ78: 0 | AK78: 20000 | AL78: 0 | AM78: 0 | AN78: 0 | AO78: 0 | AP78: 20000 | AQ78: 20000 | AR78: 0 | AS78: 100000 | AT78: Recruit and retain high caliber faculty, researchers and staff
A79: Communiction & Marketing | B79: No Applicable | C79: Provost | D79: 847 | E79: 8470220 | F79: KUST - Office of the Provost | G79: 1 | H79: 425550 | I79: 425550-Conferences, seminars and exhibitions and other events: - Overseas event | J79: 000000 | K79: KUST - General | L79: 847001 | M79: FA179-Opex Expense | N79: 200179 | O79: 847.8470220.1.425550.000000.847001.200179 | P79: - | Q79: 25000 | R79: 25000 | S79: 425550.Conferences, seminars and exhibitions and other events: - Overseas event-Conferences-Number of Conferences | T79: Number of Conferences | U79: 5 | V79: 20000 | W79: Provost & 4 Assoc. Provost @ 1 conference each @ 20K | X79: 100000 | Y79: KU Regular operations | Z79: Recurring | AA79: =X79*0.9 -> 90000 | AB79: =X79*0.8 -> 80000 | AC79: =X79*0.7 -> 70000 | AD79: Less budget will impact the amount of activities and associated output/benefits | AE79: Less budget will impact the amount of activities and associated output/benefits | AF79: Less budget will impact the amount of activities and associated output/benefits | AH79: 20000 | AI79: 20000 | AK79: 20000 | AP79: 20000 | AQ79: 20000 | AS79: 100000 | AT79: Recruit and retain high caliber faculty, researchers and staff
A80: Student | B80: No Applicable | C80: Provost | D80: 847 | E80: 8470220 | F80: KUST - Office of the Provost | G80: 1 | H80: 425740 | I80: 425740-Scholarships & other financial aid | J80: 000000 | K80: KUST - General | L80: 847001 | M80: FA179-Opex Expense | N80: 200179 | O80: 847.8470220.1.425740.000000.847001.200179 | P80: - | Q80: 694710 | R80: 694710 | S80: 425740.Scholarships & other financial aid-Students-No of Students | T80: No of Students | U80: 26 | V80: 138462 | W80: 6 post docs @ 500K National Post Doc Scheme + 20 faculty @ 30K for Faculty Development Scheme | X80: 3600012 | Y80: KU Regular operations | Z80: Recurring | AA80: =X80*0.9 -> 3240010.8 | AB80: =X80*0.8 -> 2880009.6 | AC80: =X80*0.7 -> 2520008.4 | AD80: Less budget will impact the amount of activities and associated output/benefits | AE80: Less budget will impact the amount of activities and associated output/benefits | AF80: Less budget will impact the amount of activities and associated output/benefits | AG80: 500000 | AH80: 500000 | AI80: 500000 | AJ80: 500000 | AK80: 500000 | AL80: 500000 | AM80: 100000 | AN80: 100000 | AO80: 100000 | AP80: 100000 | AQ80: 100012 | AR80: 100000 | AS80: 3600012 | AT80: Design and implement professional development programs for researchers, faculty, and staff to contribute to the university strategic plan
A81: Other support | B81: Director, Human Resources | C81: Provost | D81: 847 | E81: 8470220 | F81: KUST - Office of the Provost | G81: 1 | H81: 425900 | I81: 425900-Entertainment and hospitality | J81: 000000 | K81: KUST - General | L81: 847001 | M81: FA179-Opex Expense | N81: 200179 | O81: 847.8470220.1.425900.000000.847001.200179 | P81: - | Q81: 12000 | R81: 12000 | S81: 425900.Entertainment and hospitality-1. No of events/workshops planned-count | T81: count | U81: 12 | V81: 10667 | W81: 12 x 1000 per month provost office catering 2 x Faculty Townhalls @ 20K E 2 x Faculty Council @ 3K E FAC x 2 @ 3000 | X81: 128004 | Y81: KU Regular operations | Z81: Recurring | AA81: =X81*0.9 -> 115203.6 | AB81: =X81*0.8 -> 102403.2 | AC81: =X81*0.7 -> 89602.8 | AD81: Less budget will impact the amount of activities and associated feel good factor amoung the community | AE81: Less budget will impact the amount of activities and associated feel good factor amoung the community | AF81: Less budget will impact the amount of activities and associated feel good factor amoung the community | AG81: 10667 | AH81: 10667 | AI81: 10667 | AJ81: 10667 | AK81: 10667 | AL81: 10667 | AM81: 10667 | AN81: 10667 | AO81: 10667 | AP81: 10667 | AQ81: 10667 | AR81: 10667 | AS81: 128004 | AT81: Promote a working culture of excellence and accountability
A82: IT | B82: Director, Technology Development | C82: Provost | D82: 847 | E82: 8470220 | F82: KUST - Office of the Provost | G82: 1 | H82: 426610 | I82: 426610-Computer software licenses | J82: 000000 | K82: KUST - General | L82: 847001 | M82: FA179-Opex Expense | N82: 200179 | O82: 847.8470220.1.426610.000000.847001.200179 | P82: - | Q82: 50000 | R82: 50000 | S82: 426610.Computer software licenses-Software License Renewal-number of licenses-Number | T82: Number | U82: 3 | V82: 15000 | W82: MS Teams Licences for generic accounts, for events etc, Provost office | X82: 45000 | Y82: KU Regular operations | Z82: Non-recurring | AA82: =X82*0.9 -> 40500 | AB82: =X82*0.8 -> 36000 | AC82: =X82*0.7 -> 31500 | AD82: Less licences to purchase | AE82: Less licences to purchase | AF82: Less licences to purchase | AG82: 45000 | AS82: 45000 | AT82: Utilize state-of-the-art technologies and facilities in an optimal and efficient manner
A83: Academic | B83: No Applicable | C83: Provost | D83: 847 | E83: 8470220 | F83: KUST - Office of the Provost | G83: 1 | H83: 428090 | I83: 428090-Business Travel - Combined expenses | J83: 000000 | K83: KUST - General | L83: 847001 | M83: FA179-Opex Expense | N83: 200179 | O83: 847.8470220.1.428090.000000.847001.200179 | P83: - | Q83: 165500 | R83: 165500 | S83: 428090.Business Travel - Combined expenses-Number of Staff-Number | T83: Number | U83: 8 | V83: 40000 | W83: 4 business trips for Provost+ 1 x Biz Travel each per Assoc. Provost , all at 40K each | X83: 320000 | Y83: KU Strategic New Initiative | Z83: Non-recurring | AA83: =X83*0.9 -> 288000 | AB83: =X83*0.8 -> 256000 | AC83: =X83*0.7 -> 224000 | AD83: Less budget will impact the amount of activities and associated output/benefits | AE83: Less budget will impact the amount of activities and associated output/benefits | AF83: Less budget will impact the amount of activities and associated output/benefits | AG83: 40000 | AI83: 40000 | AJ83: 40000 | AK83: 40000 | AP83: 40000 | AQ83: 80000 | AR83: 40000 | AS83: 320000 | AT83: Build partnerships with local and international universities
A84: Communiction & Marketing | B84: Director, Marketing and Communication | C84: Provost | D84: 847 | E84: 8470220 | F84: KUST - Office of the Provost | G84: 1 | H84: 428640 | I84: 428640-Events - Awards, prizes & gifts | J84: 000000 | K84: KUST - General | L84: 847001 | M84: FA179-Opex Expense | N84: 200179 | O84: 847.8470220.1.428640.000000.847001.200179 | P84: - | Q84: 20000 | R84: 20000 | S84: 428640.Events - Awards, prizes & gifts-Number of Events-count | T84: count | U84: 1 | V84: 2000000 | W84: Excellence Awards, Prizes & Plaques | X84: 2000000 | Y84: KU Regular operations | Z84: Non-recurring | AA84: =X84*0.9 -> 1800000 | AB84: =X84*0.8 -> 1600000 | AC84: =X84*0.7 -> 1400000 | AD84: Excellence Awards encourages excellent productivity and performance, less budget diminishes these results | AE84: Excellence Awards encourages excellent productivity and performance, less budget diminishes these results | AF84: Excellence Awards encourages excellent productivity and performance, less budget diminishes these results | AP84: 2000000 | AS84: 2000000 | AT84: Promote a working culture of excellence and accountability
A85: IT | B85: Director, Technology Development | C85: Provost | D85: 847 | E85: 8470220 | F85: KUST - Office of the Provost | G85: 1 | H85: 432205 | I85: 432205-Computers and peripherals | J85: 000000 | K85: KUST - General | L85: 847001 | M85: FA179-Opex Expense | N85: 200179 | O85: 847.8470220.1.432205.000000.847001.200179 | P85: - | Q85: 10000 | R85: 10000 | S85: 432205.Computers and peripherals-End user and Infrastructure components maintenance and support-service level agreement-Service | T85: Service | U85: 6 | V85: 10000 | W85: Computer Equipment/PCs etc for Provost Office Staff | X85: 60000 | Y85: KU Regular operations | Z85: Non-recurring | AA85: =X85*0.9 -> 54000 | AB85: =X85*0.8 -> 48000 | AC85: =X85*0.7 -> 42000 | AD85: Staff need the correct computer equipment to work efficiently | AE85: Staff need the correct computer equipment to work efficiently | AF85: Staff need the correct computer equipment to work efficiently | AG85: 60000 | AS85: 60000 | AT85: Utilize state-of-the-art technologies and facilities in an optimal and efficient manner
A86: Facilities | B86: Director, Research Laboratories | C86: Provost | D86: 847 | E86: 8470220 | F86: KUST - Office of the Provost | G86: 1 | H86: 492316 | I86: 492316-Laboratory equipment | J86: 000000 | K86: KUST - General | L86: 847001 | M86: FA180-Capex Expense | N86: 300180 | O86: 847.8470220.1.492316.000000.847001.300180 | P86: 160720 | Q86: - | S86: 432209.Laboratory equipment-Number of Faculty-Number | T86: Number | U86: 1 | V86: 300000 | W86: Lab Equipment | X86: 300000 | Y86: KU Strategic New Initiative | Z86: Recurring | AA86: =X86*0.9 -> 270000 | AB86: =X86*0.8 -> 240000 | AC86: =X86*0.7 -> 210000 | AD86: Less budget will impact operations, teaching and research | AE86: Less budget will impact operations, teaching and research | AF86: Less budget will impact operations, teaching and research | AG86: 25000 | AH86: 25000 | AI86: 25000 | AJ86: 25000 | AK86: 25000 | AL86: 25000 | AM86: 25000 | AN86: 25000 | AO86: 25000 | AP86: 25000 | AQ86: 25000 | AR86: 25000 | AS86: 300000 | AT86: Utilize state-of-the-art technologies and facilities in an optimal and efficient manner
A87: - | B87: - | C87: Provost | D87: 847 | E87: 8470220 | F87: KUST - Office of the Provost | G87: 1 | H87: 436120 | I87: 436120-Stationery | J87: 000000 | K87: KUST - General | L87: 847001 | M87: FA179-Opex Expense | N87: 200179 | O87: 847.8470220.1.436120.000000.847001.200179 | S87: 436120.Stationery-Number of Staff-Number | T87: Number | U87: 6 | V87: 1000 | W87: Office Stationery | X87: 6000 | Y87: KU Regular operations | Z87: Recurring | AA87: =X87*0.9 -> 5400 | AB87: =X87*0.8 -> 4800 | AC87: =X87*0.7 -> 4200 | AD87: basic operational requirement | AE87: basic operational requirement | AF87: basic operational requirement | AG87: 500 | AH87: 500 | AI87: 500 | AJ87: 500 | AK87: 500 | AL87: 500 | AM87: 500 | AN87: 500 | AO87: 500 | AP87: 500 | AQ87: 500 | AR87: 500 | AS87: 6000 | AT87: Provide reliable, accurate and timely reports to different stakeholders
A88: Academic | B88: No Applicable | C88: College of Engineering | D88: 847 | E88: 8470310 | F88: KUST - Aerospace Engineering | G88: 1 | H88: 420550 | I88: 420550-Academic Advisory Service | J88: 000000 | K88: KUST - General | L88: 847001 | M88: FA179-Opex Expense | N88: 200179 | O88: 847.8470310.1.420550.000000.847001.200179 | P88: - | Q88: 20000 | R88: 20000 | S88: 420550.Academic Advisory Service-Number of Students-Number | T88: Number | U88: 2 | V88: 10000 | W88: 2 Board meetings of about 10 members. AED 10k per meeting. | X88: 20000 | Y88: KU Regular operations | Z88: Recurring | AA88: =X88*0.9 -> 18000 | AB88: =X88*0.8 -> 16000 | AC88: =X88*0.7 -> 14000 | AD88: may happen at reduced budget | AE88: event may not happen | AF88: event may not happen | AI88: 10000 | AO88: 10000 | AS88: 20000 | AT88: Align academic programs with the local and global labor market needs
A89: Communiction & Marketing | B89: Director, Marketing and Communication | C89: College of Engineering | D89: 847 | E89: 8470310 | F89: KUST - Aerospace Engineering | G89: 1 | H89: 425510 | I89: 425510-Conferences, seminars and exhibitions and other events: - Local Events | J89: 000000 | K89: KUST - General | L89: 847001 | M89: FA179-Opex Expense | N89: 200179 | O89: 847.8470310.1.425510.000000.847001.200179 | P89: - | Q89: 15000 | R89: 15000 | S89: 425510.Conferences, seminars and exhibitions and other events: - Local Events-Conferences-Number of Conferences | T89: Number of Conferences | U89: 3 | V89: 10000 | W89: Conferences / Events that KU Aero Department will host | X89: 30000 | Y89: KU Regular operations | Z89: Recurring | AA89: =X89*0.9 -> 27000 | AB89: =X89*0.8 -> 24000 | AC89: =X89*0.7 -> 21000 | AD89: event may happen at reduced budget | AE89: some events may not be possible | AF89: some events may not be possible | AH89: 10000 | AL89: 10000 | AQ89: 10000 | AS89: 30000 | AT89: Establish a mobility program for students, faculty, researchers and staff | AU89: There was one event in FY22 in FY23 two events
A90: Student | B90: Director, Student Services | C90: College of Engineering | D90: 847 | E90: 8470310 | F90: KUST - Aerospace Engineering | G90: 1 | H90: 425760 | I90: 425760-Student activities & field trip expenses | J90: 000000 | K90: KUST - General | L90: 847001 | M90: FA179-Opex Expense | N90: 200179 | O90: 847.8470310.1.425760.000000.847001.200179 | P90: - | Q90: 150000 | R90: 150000 | S90: 425760.Student activities & field trip expenses-Students-No of Students | T90: No of Students | U90: 15 | V90: 10000 | W90: Students travel to the US for Design Build Fly competetion | X90: 150000 | Y90: KU Regular operations | Z90: Recurring | AA90: =X90*0.9 -> 135000 | AB90: =X90*0.8 -> 120000 | AC90: =X90*0.7 -> 105000 | AD90: number of students will need to be reduced | AE90: number of students will need to be reduced | AF90: trip may not be possible | AI90: 150000 | AS90: 150000 | AT90: Establish a mobility program for students, faculty, researchers and staff
A91: Student | B91: No Applicable | C91: College of Engineering | D91: 847 | E91: 8470310 | F91: KUST - Aerospace Engineering | G91: 1 | H91: 425763 | I91: 425763-Student Project Expenses | J91: 000000 | K91: KUST - General | L91: 847001 | M91: FA179-Opex Expense | N91: 200179 | O91: 847.8470310.1.425763.000000.847001.200179 | P91: 113543.11 | Q91: 350000 | R91: 350000 | S91: 425763.Student Project Expenses-Number of Students UG-Month | T91: Month | U91: 12 | V91: 30000 | W91: Assuming 72 SDP students, with AED 5,000 allocated per student | X91: 360000 | Y91: KU Regular operations | Z91: Recurring | AA91: =X91*0.9 -> 324000 | AB91: =X91*0.8 -> 288000 | AC91: =X91*0.7 -> 252000 | AD91: project budget need to be cut | AE91: some projects may not run | AF91: some projects may not run | AH91: 90000 | AJ91: 50000 | AK91: 60000 | AN91: 80000 | AP91: 40000 | AQ91: 40000 | AS91: 360000 | AT91: Develop the university innovation and entrepreneurship system
A92: Academic | B92: No Applicable | C92: College of Engineering | D92: 847 | E92: 8470310 | F92: KUST - Aerospace Engineering | G92: 1 | H92: 425770 | I92: 425770-Academic Missions - Combined expenses | J92: 000000 | K92: KUST - General | L92: 847001 | M92: FA179-Opex Expense | N92: 200179 | O92: 847.8470310.1.425770.000000.847001.200179 | P92: 0 | Q92: 210000 | R92: 210000 | S92: 425770.Academic Missions - Combined expenses-Number of Conference-Number | T92: Number | U92: 17 | V92: 20000 | W92: International conference travel and registration fee. 1 Conference per faculty. | X92: 340000 | Y92: KU Regular operations | Z92: Recurring | AA92: =X92*0.9 -> 306000 | AB92: =X92*0.8 -> 272000 | AC92: =X92*0.7 -> 238000 | AD92: 1-2 faculty may not travel | AE92: few faculty may not travel | AF92: many faculty may not travel | AK92: 150000 | AM92: 70000 | AN92: 60000 | AR92: 60000 | AS92: 340000 | AT92: Establish a mobility program for students, faculty, researchers and staff | AU92: Compared to FY22, the Academic mission expense increased by 32%, and especially the Dean of Engineering and Electrical & computer Engg department increased their statements by 39% to 48%. The rest of the departments in CoE increased by 25% to 33%.
A93: Other support | B93: Director, Human Resources | C93: College of Engineering | D93: 847 | E93: 8470310 | F93: KUST - Aerospace Engineering | G93: 1 | H93: 425900 | I93: 425900-Entertainment and hospitality | J93: 000000 | K93: KUST - General | L93: 847001 | M93: FA179-Opex Expense | N93: 200179 | O93: 847.8470310.1.425900.000000.847001.200179 | P93: - | Q93: 8500 | R93: 8500 | S93: 425900.Entertainment and hospitality-1. No of events/workshops planned-count | T93: count | U93: 17 | V93: 500 | W93: 12 Faculty Meetings (one per month) + 5 visits by professional organizations to the department. | X93: 8500 | Y93: KU Regular operations | Z93: Recurring | AA93: =X93*0.9 -> 7650 | AB93: =X93*0.8 -> 6800 | AC93: =X93*0.7 -> 5950 | AD93: run on reduced budget | AE93: run on reduced budget | AF93: run on reduced budget | AG93: 1000 | AH93: 500 | AI93: 1000 | AJ93: 1000 | AK93: 500 | AL93: 500 | AM93: 500 | AN93: 500 | AO93: 1000 | AP93: 500 | AQ93: 1000 | AR93: 500 | AS93: 8500 | AT93: Enhance the communication plan and outreach activities
A94: IT | B94: Director, Technology Development | C94: College of Engineering | D94: 847 | E94: 8470310 | F94: KUST - Aerospace Engineering | G94: 1 | H94: 426610 | I94: 426610-Computer software licenses | J94: 000000 | K94: KUST - General | L94: 847001 | M94: FA179-Opex Expense | N94: 200179 | O94: 847.8470310.1.426610.000000.847001.200179 | P94: - | Q94: 9114 | R94: 9114 | S94: 426610.Computer software licenses-Software License Renewal-number of licenses-Number | T94: Number | U94: 1 | V94: 10000 | W94: Software renewal as per the CoE list | X94: 10000 | Y94: KU Regular operations | Z94: Recurring | AA94: =X94*0.9 -> 9000 | AB94: =X94*0.8 -> 8000 | AC94: =X94*0.7 -> 7000 | AD94: software renewal not possible | AE94: software renewal not possible | AF94: software renewal not possible | AG94: 10000 | AS94: 10000 | AT94: Widen access to students with outstanding academic potential
A95: Academic | B95: No Applicable | C95: College of Engineering | D95: 847 | E95: 8470310 | F95: KUST - Aerospace Engineering | G95: 1 | H95: 428090 | I95: 428090-Business Travel - Combined expenses | J95: 000000 | K95: KUST - General | L95: 847001 | M95: FA179-Opex Expense | N95: 200179 | O95: 847.8470310.1.428090.000000.847001.200179 | P95: - | Q95: 40000 | R95: 40000 | S95: 428090.Business Travel - Combined expenses-Number of Faculty-Number | T95: Number | U95: 2 | V95: 20000 | W95: 2 business trips by the Chair or a faculty to international universities or organizations to promote the department and KU. | X95: 40000 | Y95: KU Regular operations | Z95: Recurring | AA95: =X95*0.9 -> 36000 | AB95: =X95*0.8 -> 32000 | AC95: =X95*0.7 -> 28000 | AD95: trip may happen at lower cost | AE95: trip maybe cancelled | AF95: trip may not be possible | AL95: 20000 | AM95: 20000 | AS95: 40000 | AT95: Diversify and increase external research funds
A96: Academic | B96: No Applicable | C96: College of Engineering | D96: 847 | E96: 8470310 | F96: KUST - Aerospace Engineering | G96: 1 | H96: 432209 | I96: 432209-Laboratory equipment | J96: 000000 | K96: KUST - General | L96: 847001 | M96: FA179-Opex Expense | N96: 200179 | O96: 847.8470310.1.432209.000000.847001.200179 | P96: - | Q96: 80000 | R96: 80000 | S96: 432209.Laboratory equipment-Number of Faculty-Number | T96: Number | U96: 17 | V96: 5000 | W96: Aerospace Lab Maintenance | X96: 85000 | Y96: KU Regular operations | Z96: Recurring | AA96: =X96*0.9 -> 76500 | AB96: =X96*0.8 -> 68000 | AC96: =X96*0.7 -> 59500 | AD96: may impact operations | AE96: may impact operations | AF96: may impact operations | AG96: 10000 | AJ96: 20000 | AL96: 10000 | AN96: 20000 | AP96: 25000 | AS96: 85000 | AT96: Widen access to students with outstanding academic potential | AU96: Compared to FY22, Laboratory equipment increased 51%, dean of engineering increased by 79%, Petroleum by 69%, and Biomedical 55% increased
A97: Academic | B97: No Applicable | C97: College of Engineering | D97: 847 | E97: 8470310 | F97: KUST - Aerospace Engineering | G97: 1 | H97: 435350 | I97: 435350-Academic Publications | J97: 000000 | K97: KUST - General | L97: 847001 | M97: FA179-Opex Expense | N97: 200179 | O97: 847.8470310.1.435350.000000.847001.200179 | P97: 48731.55 | Q97: 182000 | R97: 182000 | S97: 435350.Academic Publications-Number of Publications-Number | T97: Number | U97: 17 | V97: 13000 | W97: Publications in open access Q1 journals $3500 per paper | X97: 221000 | Y97: KU Regular operations | Z97: Recurring | AA97: =X97*0.9 -> 198900 | AB97: =X97*0.8 -> 176800 | AC97: =X97*0.7 -> 154700 | AD97: reduce publications and will impact university ranking | AE97: reduce publications and will impact university ranking | AF97: reduce publications and will impact university ranking | AG97: 30000 | AH97: 20000 | AI97: 15000 | AJ97: 15000 | AK97: 15000 | AL97: 30000 | AM97: 20000 | AN97: 15000 | AO97: 15000 | AP97: 16000 | AQ97: 15000 | AR97: 15000 | AS97: 221000 | AT97: Widen access to students with outstanding academic potential
A98: Academic | B98: Director, Research Laboratories | C98: College of Engineering | D98: 847 | E98: 8470310 | F98: KUST - Aerospace Engineering | G98: 1 | H98: 435508 | I98: 435508-Laboratory - Scientific | J98: 000000 | K98: KUST - General | L98: 847001 | M98: FA179-Opex Expense | N98: 200179 | O98: 847.8470310.1.435508.000000.847001.200179 | P98: 52948.07 | Q98: 80000 | R98: 80000 | S98: 435508.Laboratory - Scientific-Number of Faculty-Number | T98: Number | U98: 17 | V98: 7824 | W98: Aero Lab consumables (OPEX) | X98: 133008 | Y98: KU Regular operations | Z98: Recurring | AA98: =X98*0.9 -> 119707.2 | AB98: =X98*0.8 -> 106406.4 | AC98: =X98*0.7 -> 93105.6 | AD98: may impact operations | AE98: may impact operations | AF98: may impact operations | AG98: 30000 | AH98: 20000 | AI98: 20000 | AJ98: 10000 | AK98: 20000 | AL98: 10000 | AN98: 10000 | AO98: 13008 | AS98: 133008 | AT98: Widen access to students with outstanding academic potential
A99: Other support | B99: No Applicable | C99: College of Engineering | D99: 847 | E99: 8470310 | F99: KUST - Aerospace Engineering | G99: 1 | H99: 436110 | I99: 436110-Printing supplies | J99: 000000 | K99: KUST - General | L99: 847001 | M99: FA179-Opex Expense | N99: 200179 | O99: 847.8470310.1.436110.000000.847001.200179 | P99: - | Q99: 4000 | R99: 4000 | S99: 436110.Printing supplies-Number of Faculty-Number | T99: Number | U99: 17 | V99: 300 | W99: Printing services to the department (brochures, posters, handouts, etc) | X99: 5100 | Y99: KU Regular operations | Z99: Recurring | AA99: =X99*0.9 -> 4590 | AB99: =X99*0.8 -> 4080 | AC99: =X99*0.7 -> 3570 | AD99: not much impact | AE99: not much impact | AF99: not much impact | AG99: 800 | AI99: 700 | AK99: 600 | AM99: 2000 | AO99: 1000 | AS99: 5100 | AT99: Develop a life-long culture of community service beyond the classroom
A100: Academic | B100: No Applicable | C100: College of Engineering | D100: 847 | E100: 8470310 | F100: KUST - Aerospace Engineering | G100: 1 | H100: 436600 | I100: 436600-Training/Teaching equipment and other educational aid | J100: 000000 | K100: KUST - General | L100: 847001 | M100: FA179-Opex Expense | N100: 200179 | O100: 847.8470310.1.436600.000000.847001.200179 | P100: 505.12 | Q100: 5000 | R100: 5000 | S100: 436600.Training/Teaching equipment and other educational aid-Number of Faculty-Number | T100: Number | U100: 17 | V100: 350 | W100: Training/Teaching equipment and other educational aid | X100: 5950 | Y100: KU Regular operations | Z100: Recurring | AA100: =X100*0.9 -> 5355 | AB100: =X100*0.8 -> 4760 | AC100: =X100*0.7 -> 4165 | AD100: may impact operations | AE100: may impact operations | AF100: may impact operations | AG100: 2950 | AN100: 3000 | AS100: 5950 | AT100: Develop a life-long culture of community service beyond the classroom
A101: Facilities | B101: Director, Research Laboratories | C101: College of Engineering | D101: 847 | E101: 8470310 | F101: KUST - Aerospace Engineering | G101: 1 | H101: 492316 | I101: 492316-Laboratory equipment | J101: 000000 | K101: KUST - General | L101: 847001 | M101: FA180-Capex Expense | N101: 300180 | O101: 847.8470310.1.492316.000000.847001.300180 | P101: 658396 | Q101: 1174460 | R101: 1174460 | S101: 492316.Laboratory equipment-Number of Faculty-Number | T101: Number | U101: 1 | V101: 2526100 | W101: Lab equipments and IT iteams, | X101: 2526100 | Y101: KU Regular operations | Z101: Non-recurring | AA101: =X101*0.9 -> 2273490 | AB101: =X101*0.8 -> 2020880 | AC101: =X101*0.7 -> 1768270 | AD101: purchase not possible | AE101: purchase not possible | AF101: purchase not possible | AG101: 500000 | AH101: 500000 | AI101: 589100 | AJ101: 537000 | AK101: 400000 | AS101: 2526100 | AT101: Widen access to students with outstanding academic potential | AU101: Compared to FY22 budget has significantly increased by 42% for CoE; most of CoE increased their funding in the range of 40%-74%, except for ME and CE.
A102: Academic | B102: No Applicable | C102: College of Engineering | D102: 847 | E102: 8470315 | F102: KUST - Biomedical Engineering | G102: 1 | H102: 420550 | I102: 420550-Academic Advisory Service | J102: 000000 | K102: KUST - General | L102: 847001 | M102: FA179-Opex Expense | N102: 200179 | O102: 847.8470315.1.420550.000000.847001.200179 | P102: - | Q102: 1000 | R102: 3000 | S102: 420550.Academic Advisory Service-Number of Services-Number | T102: Number | U102: 1 | V102: 7000 | W102: Advisory board meeting expenses (2 hours per meeting, 1meeting per year); invitations from abroad, e.g., Cambridge University. | X102: 7000 | Y102: KU Regular operations | Z102: Recurring | AA102: =X102*0.9 -> 6300 | AB102: =X102*0.8 -> 5600 | AC102: =X102*0.7 -> 4900 | AD102: Minimal Impact | AE102: The 20% cut will reduce the flexibility in supporting the advisory board meetings. | AF102: The 30% cut will clearly impact the suppor of the advisory board meetings. | AQ102: 7000 | AS102: 7000 | AT102: Align academic programs with the local and global labor market needs
A103: Communiction & Marketing | B103: Director, Marketing and Communication | C103: College of Engineering | D103: 847 | E103: 8470315 | F103: KUST - Biomedical Engineering | G103: 1 | H103: 425510 | I103: 425510-Conferences, seminars and exhibitions and other events: - Local Events | J103: 000000 | K103: KUST - General | L103: 847001 | M103: FA179-Opex Expense | N103: 200179 | O103: 847.8470315.1.425510.000000.847001.200179 | P103: 100 | Q103: 4000 | R103: 42000 | S103: 425510.Conferences, seminars and exhibitions and other events: - Local Events-Events-Number of Events | T103: Number of Events | U103: 10 | V103: 900 | W103: INTERACTION series: 7 seminars per year; Students' exhibitions (3 per year) | X103: 9000 | Y103: KU Regular operations | Z103: Recurring | AA103: =X103*0.9 -> 8100 | AB103: =X103*0.8 -> 7200 | AC103: =X103*0.7 -> 6300 | AD103: The 10% cut will reduce the number of seminars by one. | AE103: The 20% cut will reduce the number of seminars by two. | AF103: The 30% cut will reduce the number of seminars by three and the students' exhibitions by one. | AG103: 900 | AH103: 900 | AI103: 900 | AJ103: 900 | AK103: 900 | AL103: 900 | AO103: 900 | AP103: 900 | AQ103: 900 | AR103: 900 | AS103: 9000 | AT103: Align academic programs with the local and global labor market needs
A104: Student | B104: Director, Student Services | C104: College of Engineering | D104: 847 | E104: 8470315 | F104: KUST - Biomedical Engineering | G104: 1 | H104: 425760 | I104: 425760-Student activities & field trip expenses | J104: 000000 | K104: KUST - General | L104: 847001 | M104: FA179-Opex Expense | N104: 200179 | O104: 847.8470315.1.425760.000000.847001.200179 | P104: 0 | Q104: 20000 | R104: 72000 | S104: 425760.Student activities & field trip expenses-Events-No of Events | T104: No of Events | U104: 5 | V104: 4000 | W104: Support for IEEE EMBS Chapter (AED10000)+Field trips to hospital labs; students' support in competitions (the total cost is split in five parts). | X104: 20000 | Y104: KU Regular operations | Z104: Recurring | AA104: =X104*0.9 -> 18000 | AB104: =X104*0.8 -> 16000 | AC104: =X104*0.7 -> 14000 | AD104: Minimal impact. | AE104: The 20% cut will reduce the field trip students' capacity, membership in IEEE EMBS, and competition participation support. | AF104: The 30% cut will greately reduce the field trip students' capacity, membership in IEEE EMBS, and competition participation support. | AJ104: 2000 | AK104: 4000 | AL104: 4000 | AO104: 2000 | AP104: 5000 | AQ104: 3000 | AS104: 20000 | AT104: Align academic programs with the local and global labor market needs
A105: Student | B105: No Applicable | C105: College of Engineering | D105: 847 | E105: 8470315 | F105: KUST - Biomedical Engineering | G105: 1 | H105: 425763 | I105: 425763-Student Project Expenses | J105: 000000 | K105: KUST - General | L105: 847001 | M105: FA179-Opex Expense | N105: 200179 | O105: 847.8470315.1.425763.000000.847001.200179 | P105: 56577.42 | Q105: 180000 | R105: 405000 | S105: 425763.Student Project Expenses-Number of Students UG-Month | T105: Month | U105: 68 | V105: 3000 | W105: SDP I and SDP II needs, participation in international competitions (the number of undergraduate Senior students are used for the calculation with a cost of AED3000 per Senior student). | X105: 204000 | Y105: KU Regular operations | Z105: Recurring | AA105: =X105*0.9 -> 183600 | AB105: =X105*0.8 -> 163200 | AC105: =X105*0.7 -> 142800 | AD105: The 10% cut will negatively affect the smooth realization of the BMED curriculum and would not allow the full implementation of the SDPs, in terms of providing the adequate means for their success. | AE105: The 20% cut will greatly affect the smooth realization of the BMED curriculum and would not allow the full implementation of the SDPs, in terms of providing the adequate means for their success. | AF105: Thε 30% cut will severely affect the smooth realization of the BMED curriculum and would not allow the full implementation of the SDPs, in terms of providing the adequate means for their success. | AK105: 90000 | AP105: 114000 | AS105: 204000 | AT105: Align academic programs with the local and global labor market needs
A106: Academic | B106: No Applicable | C106: College of Engineering | D106: 847 | E106: 8470315 | F106: KUST - Biomedical Engineering | G106: 1 | H106: 425770 | I106: 425770-Academic Missions - Combined expenses | J106: 000000 | K106: KUST - General | L106: 847001 | M106: FA179-Opex Expense | N106: 200179 | O106: 847.8470315.1.425770.000000.847001.200179 | P106: 1101.9 | Q106: 180000 | R106: 650000 | S106: 425770.Academic Missions - Combined expenses-Number of Conference-Number | T106: Number | U106: 15 | V106: 20000 | W106: Faculty conferences and meetings | X106: 300000 | Y106: KU Regular operations | Z106: Recurring | AA106: =X106*0.9 -> 270000 | AB106: =X106*0.8 -> 240000 | AC106: =X106*0.7 -> 210000 | AD106: The 10% cut will reduce the support to one faculty to participate in an interantional conference. | AE106: The 20% cut will reduce the support to three faculty to participate in an interantional conference. | AF106: The 30% cut will reduce the support to four faculty to participate in an interantional conference. | AH106: 20000 | AI106: 20000 | AJ106: 40000 | AK106: 20000 | AL106: 40000 | AM106: 40000 | AO106: 20000 | AP106: 40000 | AQ106: 40000 | AR106: 20000 | AS106: 300000 | AT106: Establish a mobility program for students, faculty, researchers and staff | AU106: Compared to FY22, the Academic mission expense increased by 32%, and especially the Dean of Engineering and Electrical & computer Engg department increased their statements by 39% to 48%. The rest of the departments in CoE increased by 25% to 33%.
A107: Other support | B107: Director, Human Resources | C107: College of Engineering | D107: 847 | E107: 8470315 | F107: KUST - Biomedical Engineering | G107: 1 | H107: 425900 | I107: 425900-Entertainment and hospitality | J107: 000000 | K107: KUST - General | L107: 847001 | M107: FA179-Opex Expense | N107: 200179 | O107: 847.8470315.1.425900.000000.847001.200179 | P107: 315 | Q107: 10000 | R107: 16000 | S107: 425900.Entertainment and hospitality-1. No of events/workshops planned-count | T107: count | U107: 16 | V107: 1200 | W107: Retreats, faculty meetings (10 per year) and Invited speakers expenses for seminars caterings | X107: 19200 | Y107: KU Regular operations | Z107: Recurring | AA107: =X107*0.9 -> 17280 | AB107: =X107*0.8 -> 15360 | AC107: =X107*0.7 -> 13440 | AD107: Minimal impact. | AE107: The 20% cut will reduce the flexibility in speakers' invitations. | AF107: The 30% cut will greatly reduce the flexibility in speakers' invitations. | AG107: 700 | AH107: 1500 | AI107: 1500 | AJ107: 3000 | AK107: 2000 | AL107: 1500 | AM107: 1000 | AO107: 1000 | AP107: 3000 | AQ107: 3000 | AR107: 1000 | AS107: 19200 | AT107: Recruit and retain high caliber faculty, researchers and staff
A108: IT | B108: Director, Technology Development | C108: College of Engineering | D108: 847 | E108: 8470315 | F108: KUST - Biomedical Engineering | G108: 1 | H108: 426610 | I108: 426610-Computer software licenses | J108: 000000 | K108: KUST - General | L108: 847001 | M108: FA179-Opex Expense | N108: 200179 | O108: 847.8470315.1.426610.000000.847001.200179 | P108: 3816.25 | Q108: 99576 | R108: 720500 | S108: 426610.Computer software licenses-Software License Renewal-number of licenses-Number | T108: Number | U108: 1 | V108: 104554 | W108: Software licences for eduactional software: AnyBody Modeling System; SPSS | X108: 104554 | Y108: KU Regular operations | Z108: Recurring | AA108: =X108*0.9 -> 94098.6 | AB108: =X108*0.8 -> 83643.2 | AC108: =X108*0.7 -> 73187.8 | AD108: The 10% cut will create obstacles in the renewal of the software needed in courses affecting the smooth realization of the BMED curriculum and related research. | AE108: The 20% cut will create severe obstacles in the renewal of the software needed in courses affecting the smooth realization of the BMED curriculum and related research. | AF108: The 30% cut will block the renewal of at least one category of the software needed in courses affecting the smooth realization of the BMED curriculum and related research. | AH108: 104554 | AS108: 104554 | AT108: Align academic programs with the local and global labor market needs
A109: Academic | B109: No Applicable | C109: College of Engineering | D109: 847 | E109: 8470315 | F109: KUST - Biomedical Engineering | G109: 1 | H109: 428090 | I109: 428090-Business Travel - Combined expenses | J109: 000000 | K109: KUST - General | L109: 847001 | M109: FA179-Opex Expense | N109: 200179 | O109: 847.8470315.1.428090.000000.847001.200179 | P109: - | Q109: 10000 | R109: 302000 | S109: 428090.Business Travel - Combined expenses-Number of Faculty-Number | T109: Number | U109: 2 | V109: 10000 | W109: Addition to department specific development trips | X109: 20000 | Y109: KU Regular operations | Z109: Recurring | AA109: =X109*0.9 -> 18000 | AB109: =X109*0.8 -> 16000 | AC109: =X109*0.7 -> 14000 | AD109: Minimal impact. | AE109: The 20% cut will reduce by one the number of outreaching trips. | AF109: The 30% cut will reduce by three the number of outreaching trips. | AL109: 10000 | AO109: 10000 | AS109: 20000 | AT109: Establish a mobility program for students, faculty, researchers and staff
A110: Academic | B110: No Applicable | C110: College of Engineering | D110: 847 | E110: 8470315 | F110: KUST - Biomedical Engineering | G110: 1 | H110: 432209 | I110: 432209-Laboratory equipment | J110: 000000 | K110: KUST - General | L110: 847001 | M110: FA179-Opex Expense | N110: 200179 | O110: 847.8470315.1.432209.000000.847001.200179 | P110: 5900 | Q110: 90250 | R110: 67400 | S110: 432209.Laboratory equipment-Number of Students-Number | T110: Number | U110: 1 | V110: 200000 | W110: Annual Service Contracts for BME Labs Major Units; re-installation to new location B building second floor. | X110: 200000 | Y110: KU Regular operations | Z110: Recurring | AA110: =X110*0.9 -> 180000 | AB110: =X110*0.8 -> 160000 | AC110: =X110*0.7 -> 140000 | AD110: The 10% cut will affect the acquisition of the item from the provider. | AE110: The 20% cut will severely affect the acquisition of the item from the provider. Most probably we could not purchase the item. | AF110: The 30% cut will block the acquisition of the item from the provider. | AI110: 100000 | AL110: 100000 | AS110: 200000 | AT110: Develop the university innovation and entrepreneurship system | AU110: Compared to FY22, Laboratory equipment increased 51%, dean of engineering increased by 79%, Petroleum by 69%, and Biomedical 55% increased
A111: Academic | B111: No Applicable | C111: College of Engineering | D111: 847 | E111: 8470315 | F111: KUST - Biomedical Engineering | G111: 1 | H111: 435350 | I111: 435350-Academic Publications | J111: 000000 | K111: KUST - General | L111: 847001 | M111: FA179-Opex Expense | N111: 200179 | O111: 847.8470315.1.435350.000000.847001.200179 | P111: 9804.03 | Q111: 38400 | R111: 420000 | S111: 435350.Academic Publications-Number of Publications-Number | T111: Number | U111: 15 | V111: 5000 | W111: Open access publications (one per faculty) | X111: 75000 | Y111: KU Regular operations | Z111: Recurring | AA111: =X111*0.9 -> 67500 | AB111: =X111*0.8 -> 60000 | AC111: =X111*0.7 -> 52500 | AD111: The 10% cut will reduce the support to one faculty to publish in an interantional journal. | AE111: The 20% cut will reduce the support to three faculty to publish in an interantional journal. | AF111: The 30% cut will reduce the support to four faculty to publish in an interantional journal. | AH111: 8000 | AI111: 8000 | AJ111: 20000 | AK111: 10000 | AL111: 4000 | AO111: 5000 | AP111: 10000 | AQ111: 10000 | AS111: 75000 | AT111: Increase publications in journals with high impact factor
A112: Academic | B112: Director, Research Laboratories | C112: College of Engineering | D112: 847 | E112: 8470315 | F112: KUST - Biomedical Engineering | G112: 1 | H112: 435508 | I112: 435508-Laboratory - Scientific | J112: 000000 | K112: KUST - General | L112: 847001 | M112: FA179-Opex Expense | N112: 200179 | O112: 847.8470315.1.435508.000000.847001.200179 | P112: 120668.15 | Q112: 150000 | R112: 20000 | S112: 435508.Laboratory - Scientific-Number of Students-Number | T112: Number | U112: 1 | V112: 220000 | W112: Chemicals and biologocal reagents for teaching; LN2 and CO2 gases; Consumables; Cloud based remote Biosignal recording consumables; NI myDAQ systems; Electrophoresis and visualization system | X112: 220000 | Y112: KU Regular operations | Z112: Recurring | AA112: =X112*0.9 -> 198000 | AB112: =X112*0.8 -> 176000 | AC112: =X112*0.7 -> 154000 | AD112: The 10% cut will affect the acquisition of the items from the providers. | AE112: The 20% cut will severely affect the acquisition of the items from the providers. Most probably we could not purchase the items. | AF112: The 30% cut will block the acquisition of the items from the providers. | AH112: 100000 | AI112: 100000 | AJ112: 20000 | AS112: 220000 | AT112: Develop the university innovation and entrepreneurship system
...

Sheet PVT 2023 DB-1 
A3: GL Account Combination | B3: Sum of 2021Actual | C3: Sum of 2022 Budget | D3: Sum of 2022 Estimates Full Year Actual | E3: Sum of 2023 Budget
A4: 847.8470110.1.420550.000000.847001.200179 | B4: 0 | C4: 30000 | D4: 30000 | E4: 100000
A5: 847.8470110.1.420570.000000.847001.200179 | B5: 0 | C5: 3684121 | D5: 3684121 | E5: 5000000
A6: 847.8470110.1.421000.000000.847001.200179 | B6: 0 | C6: 200000 | D6: 200000 | E6: 200000
A7: 847.8470110.1.425510.000000.847001.200179 | B7: -188793.94 | C7: 300000 | D7: 300000 | E7: 300000
A8: 847.8470110.1.425550.000000.847001.200179 | B8: 0 | C8: 300000 | D8: 300000 | E8: 300000
A9: 847.8470110.1.425900.000000.847001.200179 | B9: 1327.5 | C9: 10000 | D9: 10000 | E9: 50000
A10: 847.8470110.1.428090.000000.847001.200179 | B10: 15480.75 | C10: 1000000 | D10: 1000000 | E10: 1000000
A11: 847.8470110.1.428400.000000.847001.200179 | B11: 0 | C11: 50000 | D11: 50000 | E11: 50000
A12: 847.8470110.1.428640.000000.847001.200179 | B12: 0 | C12: 100000 | D12: 100000 | E12: 50000
A13: 847.8470120.1.420120.000000.847001.200179 | B13: 383814 | C13: 520000 | D13: 500000 | E13: 520000
A14: 847.8470120.1.426610.000000.847001.200179 | B14: 0 | C14: 56000 | D14: 55612 | E14: 24889
A15: 847.8470121.1.421000.000000.847001.200179 | E15: 150000
A16: 847.8470121.1.421700.000000.847001.200179 | E16: 150000
A17: 847.8470121.1.425900.000000.847001.200179 | E17: 15000
A18: 847.8470121.1.426610.000000.847001.200179 | E18: 150000
A19: 847.8470130.1.421000.000000.847001.200179 | B19: 690716 | C19: 720000 | E19: 540000
A20: 847.8470130.1.426610.000000.847001.200179 | B20: 0 | C20: 735000 | E20: 180000
A21: 847.8470130.1.428090.000000.847001.200179 | B21: 1100 | C21: 180000 | E21: 551250
A22: 847.8470140.1.425100.000000.847001.200179 | B22: 1900038 | C22: 4578464 | D22: 4578464 | E22: 14983000
A23: 847.8470140.1.425510.000000.847001.200179 | B23: 3922844.3 | C23: 5025358 | D23: 5025358 | E23: 6585400
A24: 847.8470140.1.425550.000000.847001.200179 | B24: 0 | C24: 791955 | D24: 791955 | E24: 2150328
A25: 847.8470140.1.425763.000000.847050.200179 | B25: 0 | C25: 400000 | D25: 400000 | E25: 400000
A26: 847.8470140.1.427100.000000.847001.200179 | B26: -820 | C26: 1157850 | D26: 1157850 | E26: 2500000
A27: 847.8470140.1.427200.000000.847001.200179 | B27: -7379 | C27: 750000 | D27: 750000 | E27: 750005
A28: 847.8470140.1.428640.000000.847001.200179 | B28: 0 | C28: 998000 | D28: 998000 | E28: 998000
A29: 847.8470140.1.435310.000000.847001.200179 | B29: 0 | C29: 10000 | D29: 10000 | E29: 10000
A30: 847.8470140.1.435519.000000.847001.200179 | B30: 0 | C30: 135000 | D30: 135000 | E30: 135000
A31: 847.8470140.1.492310.000000.847001.300180 | B31: 248690 | C31: 137589 | D31: 137589 | E31: 200000
A32: 847.8470150.1.420900.000000.847001.200179 | B32: 1350 | C32: 21000 | D32: 21000 | E32: 320000
A33: 847.8470150.1.427710.000000.847001.200179 | E33: 25000
A34: 847.8470160.1.425550.000000.847001.200179 | D34: 25000 | E34: 100000
A35: 847.8470160.1.425900.000000.847001.200179 | D35: 2200000 | E35: 1200000
A36: 847.8470160.1.428090.000000.847001.200179 | D36: 40000 | E36: 100000
A37: 847.8470160.1.428640.000000.847001.200179 | D37: 100000 | E37: 100000
A38: 847.8470220.1.420550.000000.847001.200179 | B38: 0 | C38: 60000 | D38: 60000 | E38: 420500
A39: 847.8470220.1.420570.000000.847001.200179 | B39: 0 | C39: 392387 | D39: 392387 | E39: 3000000
A40: 847.8470220.1.421700.000000.847001.200179 | B40: 0 | C40: 375000 | D40: 375000 | E40: 3450000
A41: 847.8470220.1.425510.000000.847001.200179 | B41: 0 | C41: 10000 | D41: 10000 | E41: 100000
A42: 847.8470220.1.425550.000000.847001.200179 | B42: 0 | C42: 25000 | D42: 25000 | E42: 100000
A43: 847.8470220.1.425740.000000.847001.200179 | B43: 0 | C43: 694710 | D43: 694710 | E43: 3600012
A44: 847.8470220.1.425900.000000.847001.200179 | B44: 0 | C44: 12000 | D44: 12000 | E44: 128004
A45: 847.8470220.1.426610.000000.847001.200179 | B45: 0 | C45: 50000 | D45: 50000 | E45: 45000
A46: 847.8470220.1.428090.000000.847001.200179 | B46: 0 | C46: 165500 | D46: 165500 | E46: 320000
A47: 847.8470220.1.428640.000000.847001.200179 | B47: 0 | C47: 20000 | D47: 20000 | E47: 2000000
A48: 847.8470220.1.432205.000000.847001.200179 | B48: 0 | C48: 10000 | D48: 10000 | E48: 60000
A49: 847.8470220.1.436120.000000.847001.200179 | E49: 6000
A50: 847.8470220.1.492316.000000.847001.300180 | B50: 160720 | C50: 0 | E50: 300000
A51: 847.8470230.1.420550.000000.847001.200179 | B51: 56949.06 | C51: 1020620 | D51: 1020620 | E51: 2009826
A52: 847.8470230.1.425100.000000.847001.200179 | B52: 0 | C52: 300000 | D52: 300000 | E52: 300000
A53: 847.8470230.1.425510.000000.847001.200179 | B53: 3706.11 | C53: 34000 | D53: 34000 | E53: 38400
A54: 847.8470230.1.425550.000000.847001.200179 | B54: 3326.03 | C54: 222000 | D54: 222000 | E54: 355200
A55: 847.8470230.1.425743.000000.847001.200179 | B55: 960000 | C55: 240000 | D55: 240000 | E55: 0
A56: 847.8470230.1.425744.000000.847001.200179 | B56: 0 | C56: 4816800 | D56: 4816800 | E56: 3700000
A57: 847.8470230.1.425745.000000.847001.200179 | B57: 1286175 | C57: 1971263 | D57: 1971263 | E57: 3104115
A58: 847.8470230.1.425749.000000.847001.200179 | B58: 84701166 | C58: 110824684 | D58: 110824684 | E58: 203750000
A59: 847.8470230.1.425761.000000.847001.200179 | B59: 0 | C59: 150000 | D59: 100000 | E59: 180000
A60: 847.8470230.1.425762.000000.847001.200179 | B60: 0 | C60: 150000 | D60: 150000 | E60: 180000
A61: 847.8470230.1.425900.000000.847001.200179 | B61: 0 | C61: 45648 | D61: 30000 | E61: 60078
A62: 847.8470230.1.426610.000000.847001.200179 | B62: 0 | C62: 10000 | D62: 10000 | E62: 10000
... A70: 847.8470305.1.425510.000000.847001.200179 | B70: -252 | C70: 20000 | D70: 20000 | E70: 20000
A71: 847.8470305.1.425720.000000.847001.200179 | B71: -3415.89 | C71: 0 | E71: 40000
A72: 847.8470305.1.425763.000000.847001.200179 | B72: 55389.96 | C72: 100000 | D72: 100000 | E72: 120000
A73: 847.8470305.1.425770.000000.847001.200179 | B73: 22014.5 | C73: 614499 | D73: 600000 | E73: 1000000
A74: 847.8470305.1.425900.000000.847001.200179 | B74: -131 | C74: 18000 | D74: 16000 | E74: 30000
A75: 847.8470305.1.426610.000000.847001.200179 | B75: 62198.28 | C75: 100000 | D75: 90000 | E75: 120000
A76: 847.8470305.1.428090.000000.847001.200179 | B76: 0 | C76: 35000 | D76: 30000 | E76: 90000
A77: 847.8470305.1.428640.000000.847001.200179 | B77: 0 | C77: 45000 | D77: 10000 | E77: 30000
A78: 847.8470305.1.432209.000000.847001.200179 | B78: 201150.01 | C78: 45292 | D78: 45000 | E78: 220000
A79: 847.8470305.1.432690.000000.847001.200179 | B79: 5000 | C79: 0 | E79: 0
A80: 847.8470305.1.435340.000000.847001.200179 | B80: -13614 | C80: 0 | E80: 0
A81: 847.8470305.1.435350.000000.847001.200179 | B81: 0 | C81: 260000 | D81: 260000 | E81: 270000
A82: 847.8470305.1.435508.000000.847001.200179 | B82: 35691.55 | C82: 100000 | D82: 100000 | E82: 120000
A83: 847.8470305.1.436600.000000.847001.200179 | B83: 0 | C83: 25000 | D83: 20000 | E83: 40000
A84: 847.8470310.1.420550.000000.847001.200179 | B84: 0 | C84: 20000 | D84: 20000 | E84: 20000
A85: 847.8470310.1.425510.000000.847001.200179 | B85: 0 | C85: 15000 | D85: 15000 | E85: 30000
A86: 847.8470310.1.425760.000000.847001.200179 | B86: 0 | C86: 150000 | D86: 150000 | E86: 150000
A87: 847.8470310.1.425763.000000.847001.200179 | B87: 113543.11 | C87: 350000 | D87: 350000 | E87: 360000
A88: 847.8470310.1.425770.000000.847001.200179 | B88: 0 | C88: 210000 | D88: 210000 | E88: 340000
A89: 847.8470310.1.425900.000000.847001.200179 | B89: 0 | C89: 8500 | D89: 8500 | E89: 8500
A90: 847.8470310.1.426610.000000.847001.200179 | B90: 0 | C90: 9114 | D90: 9114 | E90: 10000
A91: 847.8470310.1.428090.000000.847001.200179 | B91: 0 | C91: 40000 | D91: 40000 | E91: 40000
A92: 847.8470310.1.432209.000000.847001.200179 | B92: 0 | C92: 80000 | D92: 80000 | E92: 85000
... A128: 847.8470325.1.425760.000000.847001.200179 | B128: 0 | C128: 5000 | D128: 5000 | E128: 5000
A129: 847.8470325.1.425762.000000.847001.200179 | E129: 40000
A130: 847.8470325.1.425763.000000.847001.200179 | B130: 3020202.8 | C130: 370000 | D130: 370000 | E130: 60000
A131: 847.8470325.1.425770.000000.847001.200179 | B131: 0 | C131: 165000 | D131: 165000 | E131: 220000
A132: 847.8470325.1.426610.000000.847001.200179 | B132: 0 | C132: 34910 | D132: 34910 | E132: 45000
A133: 847.8470325.1.428090.000000.847001.200179 | B133: 0 | C133: 0 | E133: 20000
A134: 847.8470325.1.432209.000000.847001.200179 | B134: 0 | C134: 201550 | D134: 201550 | E134: 175000
A135: 847.8470325.1.435350.000000.847001.200179 | B135: 0 | C135: 80000 | D135: 80000 | E135: 80000
A136: 847.8470325.1.435508.000000.847001.200179 | B136: 35833.23 | C136: 92573 | D136: 92573 | E136: 95000
A137: 847.8470325.1.492316.000000.847001.300180 | B137: 190263 | C137: 611783 | D137: 611783 | E137: 1208362
A138: 847.8470330.1.420550.000000.847001.200179 | B138: 0 | C138: 3000 | D138: 3000 | E138: 3000
A139: 847.8470330.1.425510.000000.847001.200179 | B139: 0 | C139: 42000 | D139: 42000 | E139: 10000
A140: 847.8470330.1.425760.000000.847001.200179 | B140: 0 | C140: 72000 | D140: 72000 | E140: 75000
A141: 847.8470330.1.425763.000000.847001.200179 | B141: 216899.04 | C141: 405000 | D141: 405000 | E141: 435000
A142: 847.8470330.1.425770.000000.847001.200179 | B142: 12190.2 | C142: 650000 | D142: 650000 | E142: 1260000
A143: 847.8470330.1.425900.000000.847001.200179 | B143: 0 | C143: 16000 | D143: 16000 | E143: 30000
A144: 847.8470330.1.426610.000000.847001.200179 | B144: 122131.96 | C144: 720500 | D144: 720500 | E144: 710622
...

Sheet PVT 2024 DB-1
A3: Row Labels | B3: Sum of 2024 Budget
A4: 847.8470110.1.420550.000000.847001.200179 | B4: 100000
A5: 847.8470110.1.420570.000000.847001.200179 | B5: 5000000
A6: 847.8470110.1.421000.000000.847001.200179 | B6: 200000
A7: 847.8470110.1.425510.000000.847001.200179 | B7: 300000
A8: 847.8470110.1.425550.000000.847001.200179 | B8: 300000
A9: 847.8470110.1.425900.000000.847001.200179 | B9: 50000
A10: 847.8470110.1.428090.000000.847001.200179 | B10: 1000000
A11: 847.8470110.1.428400.000000.847001.200179 | B11: 50000
A12: 847.8470110.1.428640.000000.847001.200179 | B12: 50000
A13: 847.8470120.1.420120.000000.847001.200179 | B13: 514889
A14: 847.8470121.1.421000.000000.847001.200179 | B14: 165000
A15: 847.8470121.1.421700.000000.847001.200179 | B15: 165000
... A489: Grand Total | B489: 1.0389962e+09

Sheet PVT 2025 DB-1 
A3: Row Labels | B3: Sum of 2025 Budget
A4: 847.8470110.1.420550.000000.847001.200179 | B4: 100000
A5: 847.8470110.1.420570.000000.847001.200179 | B5: 5000000
A6: 847.8470110.1.421000.000000.847001.200179 | B6: 200000
A7: 847.8470110.1.425510.000000.847001.200179 | B7: 300000
A8: 847.8470110.1.425550.000000.847001.200179 | B8: 300000
A9: 847.8470110.1.425900.000000.847001.200179 | B9: 50000
A10: 847.8470110.1.428090.000000.847001.200179 | B10: 1000000
A11: 847.8470110.1.428400.000000.847001.200179 | B11: 50000
A12: 847.8470110.1.428640.000000.847001.200179 | B12: 50000
A13: 847.8470120.1.420120.000000.847001.200179 | B13: 490000
A14: 847.8470120.1.426610.000000.847001.200179 | B14: 24889
A15: 847.8470121.1.421000.000000.847001.200179 | B15: 181500
... A294: 847.8470530.1.421600.000000.847030.200179 | B294: 439000
A295: 847.8470530.1.421700.000000.847010.200179
A296: 847.8470530.1.425510.000000.847010.200179 | B296: 70000
A297: 847.8470530.1.425900.000000.847010.200179 | B297: 60000
A298: 847.8470530.1.426220.000000.847010.200179 | B298: 960437
A299: 847.8470530.1.426220.000000.847030.200179 | B299: 23714
A300: 847.8470530.1.426250.000000.847010.200179 | B300: 0
A301: 847.8470530.1.428090.000000.847001.200179 | B301: 300000
A302: 847.8470530.1.429900.000000.847010.200179 | B302: 220000
A303: 847.8470530.1.430110.000000.847010.200179 | B303: 233000
A304: 847.8470530.1.430120.000000.847020.200179 | B304: 18000000
A305: 847.8470530.1.430120.000000.847030.200179 | B305: 4725991
A306: 847.8470530.1.432120.000000.847010.200179 | B306: 13921121
A307: 847.8470530.1.432120.000000.847015.200179
A308: 847.8470530.1.432120.000000.847020.200179 | B308: 16435196
A309: 847.8470530.1.432120.000000.847030.200179 | B309: 1735252
A310: 847.8470530.1.432170.000000.847010.200179 | B310: 30000
