Workbook
Name Budget_2022: 'Main Page'!$B$9

Sheet Main Page
B6: KU Budget Template for Years 2023 to 2025
B8: Budget Menu
B9: Budget 2022
B10: Budget 2023
B11: Budget 2024
B12: Check List
B13: Drivers
B14: Account Code

Sheet Budget 2023
H1: Cost Center Description : | I1: =IFERROR(VLOOKUP(I2,'Cost Center'!$A:$B,2,FALSE),"")
H2: Cost Center Code : | P2: Return to Main Page | X2: Duplicated | Y2: Duplicated | AA2: Add Strategic Project
H3: Year | I3: 2023 | AV3: Updated 2023 | AW3: Updated 2023
H4: Account - Drop Box List | R4: Required | S4: Drop Box List | T4: Required | U4: Required | W4: Required | X4: Required | Y4: Required | Z4: Required | AA4: Required - Drop Box | AB4: Required - Drop Box | AF4: Required | AG4: Required | AH4: Required | AI4: Required | AV4: Drop Box List | AW4: Required | AX4: Required
A5: Account Group | B5: Content Expert | C5: Cost Center Code - Group | D5: Entity | E5: Cost Center Code | F5: Cost Center Description | G5: Budget Group | H5: Account Code | I5: Account Description | J5: Cost Center Code2 | K5: Future-1 Description | L5: Future-1 | M5: Future-2 Description | N5: Future-2 | O5: GL Account Combination | P5: 2021Actual | Q5: 2022 Budget | R5: 2022 Estimates full year Actual | S5: Budget Driver | T5: Measruing unit | U5: Quantity of measruing units | V5: Rate (expected) | W5: Itemised Details/Calculation method | X5: Quantity (expected) | Y5: Rate (expected)2 | Z5: 2023 Budget | AA5: Budget Activity Type | AB5: Expenditure Frequency | AC5: 2023 Budget Scenario 90% | AD5: 2023 Budget Scenario 80% | AE5: 2023 Budget Scenario 70% | AF5: 90% Budget Scenario Impact | AG5: 80% Budget Impact | AH5: 70% Budget Impact | AI5: Jan-23 | AJ5: Feb-23 | AK5: Mar-23 | AL5: Apr-23 | AM5: May-23 | AN5: Jun-23 | AO5: Jul-23 | AP5: Aug-23 | AQ5: Sep-23 | AR5: Oct-23 | AS5: Nov-23 | AT5: Dec-23 | AU5: Total | AV5: KU Strategy | AW5: Department operation Objective | AX5: Contract or Agreement or PO or budgetary Quotation - Uploaded in KU Driver
A6: =VLOOKUP(H6,'Accoount Code Combination'!$D:$L,8,FALSE) -> HR | B6: =VLOOKUP(Table1[[#This Row],[Account Code]],'Accoount Code Combination'!$D:$L,9,FALSE) -> Outsourcing | C6: =VLOOKUP(Table1[[#This Row],[Cost Center Code]],'Cost Center Group'!A:B,2,FALSE) -> President's Office | D6: 847 | E6: 8470110 | F6: KUST - Office of the President | G6: 1 | H6: 421100 | I6: =IFERROR(VLOOKUP(Table1[[#This Row],[Account Code]],'Accoount Code Combination'!$D:$H,2,FALSE),"") -> Manpower supply | J6: 8470110 | K6: COVID-19 Pandemic | L6: =IFERROR(VLOOKUP(Table1[[#This Row],[Future-1 Description]],'Other '!E1:$F10,2,FALSE),"") -> 847951 | N6: 200179 | P6: 29118.02 | Q6: 29119 | S6: Trips | T6: Number | U6: 50 | V6: 10000 | W6: %@1000 | Z6: =Table1[[#This Row],[Quantity of measruing units]]*Table1[[#This Row],[Rate (expected)]] -> 500000 | AC6: =Table1[[#This Row],[Quantity (expected)]]*Table1[[#This Row],[Rate (expected)2]]*0.9 -> 0 | AD6: =Table1[[#This Row],[Quantity (expected)]]*Table1[[#This Row],[Rate (expected)2]]*0.8 -> 0 | AE6: =Table1[[#This Row],[Quantity (expected)]]*Table1[[#This Row],[Rate (expected)2]]*0.7 -> 0 | AQ6: 0 | AR6: 0 | AS6: 0 | AU6: =SUM(Table1[[#This Row],[Jan-23]:[Dec-23]]) -> 0 | AV6: Develop the university innovation and entrepreneurship system | AY6: List : Yes/NO
A7: =VLOOKUP(H7,'Accoount Code Combination'!$D:$L,8,FALSE) -> Other support | B7: =VLOOKUP(Table1[[#This Row],[Account Code]],'Accoount Code Combination'!$D:$L,9,FALSE) -> Legal and professional fees | C7: =VLOOKUP(Table1[[#This Row],[Cost Center Code]],'Cost Center Group'!A:B,2,FALSE) -> Information Technology/ANKABUT | D7: 847 | E7: 8470810 | G7: 1 | H7: 420900 | I7: =VLOOKUP(Table1[[#This Row],[Account Code]],'Accoount Code Combination'!$D:$H,2,FALSE) -> Legal services | J7: 8470110 | K7: KUST- Masdar city campus | L7: =VLOOKUP(Table1[[#This Row],[Future-1 Description]],'Other '!E2:$F11,2,FALSE) -> 847030 | N7: 200179 | Z7: =Table1[[#This Row],[Quantity of measruing units]]*Table1[[#This Row],[Rate (expected)]] -> 0 | AC7: =Table1[[#This Row],[Quantity (expected)]]*Table1[[#This Row],[Rate (expected)2]]*0.9 -> 0 | AD7: =Table1[[#This Row],[Quantity (expected)]]*Table1[[#This Row],[Rate (expected)2]]*0.8 -> 0 | AE7: =Table1[[#This Row],[Quantity (expected)]]*Table1[[#This Row],[Rate (expected)2]]*0.7 -> 0 | AU7: =SUM(Table1[[#This Row],[Jan-23]:[Dec-23]]) -> 0
A8: =VLOOKUP(H8,'Accoount Code Combination'!$D:$L,8,FALSE) -> Academic | B8: =VLOOKUP(Table1[[#This Row],[Account Code]],'Accoount Code Combination'!$D:$L,9,FALSE) -> No Applicable | C8: =VLOOKUP(Table1[[#This Row],[Cost Center Code]],'Cost Center Group'!A:B,2,FALSE) -> President's Office | D8: 847 | E8: 8470110 | G8: 1 | H8: 425770 | I8: =VLOOKUP(Table1[[#This Row],[Account Code]],'Accoount Code Combination'!$D:$H,2,FALSE) -> Academic Missions - Combined expenses | J8: 8470110 | L8: =VLOOKUP(Table1[[#This Row],[Future-1 Description]],'Other '!E3:$F12,2,FALSE) -> #N/A | Z8: =Table1[[#This Row],[Quantity of measruing units]]*Table1[[#This Row],[Rate (expected)]] -> 0 | AC8: =Table1[[#This Row],[Quantity (expected)]]*Table1[[#This Row],[Rate (expected)2]]*0.9 -> 0 | AD8: =Table1[[#This Row],[Quantity (expected)]]*Table1[[#This Row],[Rate (expected)2]]*0.8 -> 0 | AE8: =Table1[[#This Row],[Quantity (expected)]]*Table1[[#This Row],[Rate (expected)2]]*0.7 -> 0 | AU8: =SUM(Table1[[#This Row],[Jan-23]:[Dec-23]]) -> 0
A9: =VLOOKUP(H9,'Accoount Code Combination'!$D:$L,8,FALSE) -> Other support | B9: =VLOOKUP(Table1[[#This Row],[Account Code]],'Accoount Code Combination'!$D:$L,9,FALSE) -> No Applicable | C9: =VLOOKUP(Table1[[#This Row],[Cost Center Code]],'Cost Center Group'!A:B,2,FALSE) -> President's Office | D9: 847 | E9: 8470110 | G9: 1 | H9: 425900 | I9: =VLOOKUP(Table1[[#This Row],[Account Code]],'Accoount Code Combination'!$D:$H,2,FALSE) -> Entertainment and hospitality | J9: 8470110 | K9: KUST - GRC Operations | L9: =VLOOKUP(Table1[[#This Row],[Future-1 Description]],'Other '!E4:$F13,2,FALSE) -> 847040 | Z9: =Table1[[#This Row],[Quantity of measruing units]]*Table1[[#This Row],[Rate (expected)]] -> 0 | AC9: =Table1[[#This Row],[Quantity (expected)]]*Table1[[#This Row],[Rate (expected)2]]*0.9 -> 0 | AD9: =Table1[[#This Row],[Quantity (expected)]]*Table1[[#This Row],[Rate (expected)2]]*0.8 -> 0 | AE9: =Table1[[#This Row],[Quantity (expected)]]*Table1[[#This Row],[Rate (expected)2]]*0.7 -> 0 | AU9: =SUM(Table1[[#This Row],[Jan-23]:[Dec-23]]) -> 0
A10: =VLOOKUP(H10,'Accoount Code Combination'!$D:$L,8,FALSE) -> Other support | B10: =VLOOKUP(Table1[[#This Row],[Account Code]],'Accoount Code Combination'!$D:$L,9,FALSE) -> Legal and professional fees | C10: =VLOOKUP(Table1[[#This Row],[Cost Center Code]],'Cost Center Group'!A:B,2,FALSE) -> President's Office | D10: 847 | E10: 8470110 | G10: 1 | H10: 420900 | I10: =VLOOKUP(Table1[[#This Row],[Account Code]],'Accoount Code Combination'!$D:$H,2,FALSE) -> Legal services | J10: 8470110 | K10: KUST - GRC Operations | L10: =VLOOKUP(Table1[[#This Row],[Future-1 Description]],'Other '!E5:$F14,2,FALSE) -> 847040 | Z10: =Table1[[#This Row],[Quantity of measruing units]]*Table1[[#This Row],[Rate (expected)]] -> 0 | AC10: =Table1[[#This Row],[Quantity (expected)]]*Table1[[#This Row],[Rate (expected)2]]*0.9 -> 0 | AD10: =Table1[[#This Row],[Quantity (expected)]]*Table1[[#This Row],[Rate (expected)2]]*0.8 -> 0 | AE10: =Table1[[#This Row],[Quantity (expected)]]*Table1[[#This Row],[Rate (expected)2]]*0.7 -> 0 | AU10: =SUM(Table1[[#This Row],[Jan-23]:[Dec-23]]) -> 0
A11: =VLOOKUP(H11,'Accoount Code Combination'!$D:$L,8,FALSE) -> #N/A | B11: =VLOOKUP(Table1[[#This Row],[Account Code]],'Accoount Code Combination'!$D:$L,9,FALSE) -> #N/A | C11: =VLOOKUP(Table1[[#This Row],[Cost Center Code]],'Cost Center Group'!A:B,2,FALSE) -> President's Office | D11: 847 | E11: 8470110 | G11: 1 | I11: =VLOOKUP(Table1[[#This Row],[Account Code]],'Accoount Code Combination'!$D:$H,2,FALSE) -> #N/A | J11: 8470110 | L11: =VLOOKUP(Table1[[#This Row],[Future-1 Description]],'Other '!E6:$F15,2,FALSE) -> #N/A | Z11: =Table1[[#This Row],[Quantity of measruing units]]*Table1[[#This Row],[Rate (expected)]] -> 0 | AC11: =Table1[[#This Row],[Quantity (expected)]]*Table1[[#This Row],[Rate (expected)2]]*0.9 -> 0 | AD11: =Table1[[#This Row],[Quantity (expected)]]*Table1[[#This Row],[Rate (expected)2]]*0.8 -> 0 | AE11: =Table1[[#This Row],[Quantity (expected)]]*Table1[[#This Row],[Rate (expected)2]]*0.7 -> 0 | AU11: =SUM(Table1[[#This Row],[Jan-23]:[Dec-23]]) -> 0
A12: =VLOOKUP(H12,'Accoount Code Combination'!$D:$L,8,FALSE) -> #N/A | B12: =VLOOKUP(Table1[[#This Row],[Account Code]],'Accoount Code Combination'!$D:$L,9,FALSE) -> #N/A | C12: =VLOOKUP(Table1[[#This Row],[Cost Center Code]],'Cost Center Group'!A:B,2,FALSE) -> President's Office | D12: 847 | E12: 8470110 | G12: 1 | I12: =VLOOKUP(Table1[[#This Row],[Account Code]],'Accoount Code Combination'!$D:$H,2,FALSE) -> #N/A | J12: 8470110 | L12: =VLOOKUP(Table1[[#This Row],[Future-1 Description]],'Other '!E7:$F16,2,FALSE) -> #N/A | Z12: =Table1[[#This Row],[Quantity of measruing units]]*Table1[[#This Row],[Rate (expected)]] -> 0 | AC12: =Table1[[#This Row],[Quantity (expected)]]*Table1[[#This Row],[Rate (expected)2]]*0.9 -> 0 | AD12: =Table1[[#This Row],[Quantity (expected)]]*Table1[[#This Row],[Rate (expected)2]]*0.8 -> 0 | AE12: =Table1[[#This Row],[Quantity (expected)]]*Table1[[#This Row],[Rate (expected)2]]*0.7 -> 0 | AU12: =SUM(Table1[[#This Row],[Jan-23]:[Dec-23]]) -> 0
A13: =VLOOKUP(H13,'Accoount Code Combination'!$D:$L,8,FALSE) -> #N/A | B13: =VLOOKUP(Table1[[#This Row],[Account Code]],'Accoount Code Combination'!$D:$L,9,FALSE) -> #N/A | C13: =VLOOKUP(Table1[[#This Row],[Cost Center Code]],'Cost Center Group'!A:B,2,FALSE) -> President's Office | D13: 847 | E13: 8470110 | G13: 1 | I13: =VLOOKUP(Table1[[#This Row],[Account Code]],'Accoount Code Combination'!$D:$H,2,FALSE) -> #N/A | J13: 8470110 | L13: =VLOOKUP(Table1[[#This Row],[Future-1 Description]],'Other '!E8:$F17,2,FALSE) -> #N/A | Z13: =Table1[[#This Row],[Quantity of measruing units]]*Table1[[#This Row],[Rate (expected)]] -> 0 | AC13: =Table1[[#This Row],[Quantity (expected)]]*Table1[[#This Row],[Rate (expected)2]]*0.9 -> 0 | AD13: =Table1[[#This Row],[Quantity (expected)]]*Table1[[#This Row],[Rate (expected)2]]*0.8 -> 0 | AE13: =Table1[[#This Row],[Quantity (expected)]]*Table1[[#This Row],[Rate (expected)2]]*0.7 -> 0 | AU13: =SUM(Table1[[#This Row],[Jan-23]:[Dec-23]]) -> 0
A14: =VLOOKUP(H14,'Accoount Code Combination'!$D:$L,8,FALSE) -> #N/A | B14: =VLOOKUP(Table1[[#This Row],[Account Code]],'Accoount Code Combination'!$D:$L,9,FALSE) -> #N/A | C14: =VLOOKUP(Table1[[#This Row],[Cost Center Code]],'Cost Center Group'!A:B,2,FALSE) -> President's Office | D14: 847 | E14: 8470110 | G14: 1 | I14: =VLOOKUP(Table1[[#This Row],[Account Code]],'Accoount Code Combination'!$D:$H,2,FALSE) -> #N/A | J14: 8470110 | L14: =VLOOKUP(Table1[[#This Row],[Future-1 Description]],'Other '!E2:$F11,2,FALSE) -> #N/A | Z14: =Table1[[#This Row],[Quantity of measruing units]]*Table1[[#This Row],[Rate (expected)]] -> 0 | AC14: =Table1[[#This Row],[Quantity (expected)]]*Table1[[#This Row],[Rate (expected)2]]*0.9 -> 0 | AD14: =Table1[[#This Row],[Quantity (expected)]]*Table1[[#This Row],[Rate (expected)2]]*0.8 -> 0 | AE14: =Table1[[#This Row],[Quantity (expected)]]*Table1[[#This Row],[Rate (expected)2]]*0.7 -> 0 | AU14: =SUM(Table1[[#This Row],[Jan-23]:[Dec-23]]) -> 0
A15: =VLOOKUP(H15,'Accoount Code Combination'!$D:$L,8,FALSE) -> Academic | B15: =VLOOKUP(Table1[[#This Row],[Account Code]],'Accoount Code Combination'!$D:$L,9,FALSE) -> No Applicable | C15: =VLOOKUP(Table1[[#This Row],[Cost Center Code]],'Cost Center Group'!A:B,2,FALSE) -> President's Office | D15: 847 | E15: 8470110 | F15: KUST - Office of the President | G15: 1 | H15: 420570 | I15: =IFERROR(VLOOKUP(Table1[[#This Row],[Account Code]],'Accoount Code Combination'!$D:$H,2,FALSE),"") -> Academic Collaborative Partnership Services | J15: 8470110 | L15: =IFERROR(VLOOKUP(Table1[[#This Row],[Future-1 Description]],'Other '!E3:$F12,2,FALSE),"") | P15: 0 | Q15: 1 | Z15: =Table1[[#This Row],[Quantity of measruing units]]*Table1[[#This Row],[Rate (expected)]] -> 0 | AC15: =Table1[[#This Row],[Quantity (expected)]]*Table1[[#This Row],[Rate (expected)2]]*0.9 -> 0 | AD15: =Table1[[#This Row],[Quantity (expected)]]*Table1[[#This Row],[Rate (expected)2]]*0.8 -> 0 | AE15: =Table1[[#This Row],[Quantity (expected)]]*Table1[[#This Row],[Rate (expected)2]]*0.7 -> 0 | AU15: =SUM(Table1[[#This Row],[Jan-23]:[Dec-23]]) -> 0
A16: =VLOOKUP(H16,'Accoount Code Combination'!$D:$L,8,FALSE) -> Other support | B16: =VLOOKUP(Table1[[#This Row],[Account Code]],'Accoount Code Combination'!$D:$L,9,FALSE) -> Legal and professional fees | C16: =VLOOKUP(Table1[[#This Row],[Cost Center Code]],'Cost Center Group'!A:B,2,FALSE) -> President's Office | D16: 847 | E16: 8470110 | F16: KUST - Office of the President | G16: 1 | H16: 420900 | I16: =IFERROR(VLOOKUP(Table1[[#This Row],[Account Code]],'Accoount Code Combination'!$D:$H,2,FALSE),"") -> Legal services | J16: 8470110 | L16: =IFERROR(VLOOKUP(Table1[[#This Row],[Future-1 Description]],'Other '!E4:$F13,2,FALSE),"") | P16: 1845 | Q16: 1501 | Z16: =Table1[[#This Row],[Quantity of measruing units]]*Table1[[#This Row],[Rate (expected)]] -> 0 | AC16: =Table1[[#This Row],[Quantity (expected)]]*Table1[[#This Row],[Rate (expected)2]]*0.9 -> 0 | AD16: =Table1[[#This Row],[Quantity (expected)]]*Table1[[#This Row],[Rate (expected)2]]*0.8 -> 0 | AE16: =Table1[[#This Row],[Quantity (expected)]]*Table1[[#This Row],[Rate (expected)2]]*0.7 -> 0 | AU16: =SUM(Table1[[#This Row],[Jan-23]:[Dec-23]]) -> 0
A17: =VLOOKUP(H17,'Accoount Code Combination'!$D:$L,8,FALSE) -> HR | B17: =VLOOKUP(Table1[[#This Row],[Account Code]],'Accoount Code Combination'!$D:$L,9,FALSE) -> Consultancy | C17: =VLOOKUP(Table1[[#This Row],[Cost Center Code]],'Cost Center Group'!A:B,2,FALSE) -> President's Office | D17: 847 | E17: 8470110 | F17: KUST - Office of the President | G17: 1 | H17: 421000 | I17: =IFERROR(VLOOKUP(Table1[[#This Row],[Account Code]],'Accoount Code Combination'!$D:$H,2,FALSE),"") -> Management consultancy | J17: 8470110 | L17: =IFERROR(VLOOKUP(Table1[[#This Row],[Future-1 Description]],'Other '!E5:$F14,2,FALSE),"") | P17: 0 | Q17: 1 | Z17: =Table1[[#This Row],[Quantity of measruing units]]*Table1[[#This Row],[Rate (expected)]] -> 0 | AC17: =Table1[[#This Row],[Quantity (expected)]]*Table1[[#This Row],[Rate (expected)2]]*0.9 -> 0 | AD17: =Table1[[#This Row],[Quantity (expected)]]*Table1[[#This Row],[Rate (expected)2]]*0.8 -> 0 | AE17: =Table1[[#This Row],[Quantity (expected)]]*Table1[[#This Row],[Rate (expected)2]]*0.7 -> 0 | AU17: =SUM(Table1[[#This Row],[Jan-23]:[Dec-23]]) -> 0
A18: =VLOOKUP(H18,'Accoount Code Combination'!$D:$L,8,FALSE) -> Academic | B18: =VLOOKUP(Table1[[#This Row],[Account Code]],'Accoount Code Combination'!$D:$L,9,FALSE) -> No Applicable | C18: =VLOOKUP(Table1[[#This Row],[Cost Center Code]],'Cost Center Group'!A:B,2,FALSE) -> President's Office | D18: 847 | E18: 8470110 | F18: KUST - Office of the President | G18: 1 | H18: 421700 | I18: =IFERROR(VLOOKUP(Table1[[#This Row],[Account Code]],'Accoount Code Combination'!$D:$H,2,FALSE),"") -> Standards certification (e.g. ISO) | J18: 8470110 | L18: =IFERROR(VLOOKUP(Table1[[#This Row],[Future-1 Description]],'Other '!E6:$F15,2,FALSE),"") | P18: 0 | Q18: 25000 | Z18: =Table1[[#This Row],[Quantity of measruing units]]*Table1[[#This Row],[Rate (expected)]] -> 0 | AC18: =Table1[[#This Row],[Quantity (expected)]]*Table1[[#This Row],[Rate (expected)2]]*0.9 -> 0 | AD18: =Table1[[#This Row],[Quantity (expected)]]*Table1[[#This Row],[Rate (expected)2]]*0.8 -> 0 | AE18: =Table1[[#This Row],[Quantity (expected)]]*Table1[[#This Row],[Rate (expected)2]]*0.7 -> 0 | AU18: =SUM(Table1[[#This Row],[Jan-23]:[Dec-23]]) -> 0
A19: =VLOOKUP(H19,'Accoount Code Combination'!$D:$L,8,FALSE) -> Communiction & Marketing | B19: =VLOOKUP(Table1[[#This Row],[Account Code]],'Accoount Code Combination'!$D:$L,9,FALSE) -> Advertising | C19: =VLOOKUP(Table1[[#This Row],[Cost Center Code]],'Cost Center Group'!A:B,2,FALSE) -> President's Office | D19: 847 | E19: 8470110 | F19: KUST - Office of the President | G19: 1 | H19: 425100 | I19: =IFERROR(VLOOKUP(Table1[[#This Row],[Account Code]],'Accoount Code Combination'!$D:$H,2,FALSE),"") -> Advertising | J19: 8470110 | L19: =IFERROR(VLOOKUP(Table1[[#This Row],[Future-1 Description]],'Other '!E7:$F16,2,FALSE),"") | P19: 0 | Q19: 0 | Z19: =Table1[[#This Row],[Quantity of measruing units]]*Table1[[#This Row],[Rate (expected)]] -> 0 | AC19: =Table1[[#This Row],[Quantity (expected)]]*Table1[[#This Row],[Rate (expected)2]]*0.9 -> 0 | AD19: =Table1[[#This Row],[Quantity (expected)]]*Table1[[#This Row],[Rate (expected)2]]*0.8 -> 0 | AE19: =Table1[[#This Row],[Quantity (expected)]]*Table1[[#This Row],[Rate (expected)2]]*0.7 -> 0 | AU19: =SUM(Table1[[#This Row],[Jan-23]:[Dec-23]]) -> 0
A20: =VLOOKUP(H20,'Accoount Code Combination'!$D:$L,8,FALSE) -> Communiction & Marketing | B20: =VLOOKUP(Table1[[#This Row],[Account Code]],'Accoount Code Combination'!$D:$L,9,FALSE) -> Events | C20: =VLOOKUP(Table1[[#This Row],[Cost Center Code]],'Cost Center Group'!A:B,2,FALSE) -> President's Office | D20: 847 | E20: 8470110 | F20: KUST - Office of the President | G20: 1 | H20: 425510 | I20: =IFERROR(VLOOKUP(Table1[[#This Row],[Account Code]],'Accoount Code Combination'!$D:$H,2,FALSE),"") -> Conferences, seminars and exhibitions and other events: - Local Events | J20: 8470110 | L20: =IFERROR(VLOOKUP(Table1[[#This Row],[Future-1 Description]],'Other '!E8:$F17,2,FALSE),"") | P20: 277368 | Q20: 0 | Z20: =Table1[[#This Row],[Quantity of measruing units]]*Table1[[#This Row],[Rate (expected)]] -> 0 | AC20: =Table1[[#This Row],[Quantity (expected)]]*Table1[[#This Row],[Rate (expected)2]]*0.9 -> 0 | AD20: =Table1[[#This Row],[Quantity (expected)]]*Table1[[#This Row],[Rate (expected)2]]*0.8 -> 0 | AE20: =Table1[[#This Row],[Quantity (expected)]]*Table1[[#This Row],[Rate (expected)2]]*0.7 -> 0 | AU20: =SUM(Table1[[#This Row],[Jan-23]:[Dec-23]]) -> 0
A21: =VLOOKUP(H21,'Accoount Code Combination'!$D:$L,8,FALSE) -> Communiction & Marketing | B21: =VLOOKUP(Table1[[#This Row],[Account Code]],'Accoount Code Combination'!$D:$L,9,FALSE) -> No Applicable | C21: =VLOOKUP(Table1[[#This Row],[Cost Center Code]],'Cost Center Group'!A:B,2,FALSE) -> President's Office | D21: 847 | E21: 8470110 | F21: KUST - Office of the President | G21: 1 | H21: 425550 | I21: =IFERROR(VLOOKUP(Table1[[#This Row],[Account Code]],'Accoount Code Combination'!$D:$H,2,FALSE),"") -> Conferences, seminars and exhibitions and other events: - Overseas event | J21: 8470110 | L21: =IFERROR(VLOOKUP(Table1[[#This Row],[Future-1 Description]],'Other '!E9:$F18,2,FALSE),"") | P21: 0 | Q21: 0 | Z21: =Table1[[#This Row],[Quantity of measruing units]]*Table1[[#This Row],[Rate (expected)]] -> 0 | AC21: =Table1[[#This Row],[Quantity (expected)]]*Table1[[#This Row],[Rate (expected)2]]*0.9 -> 0 | AD21: =Table1[[#This Row],[Quantity (expected)]]*Table1[[#This Row],[Rate (expected)2]]*0.8 -> 0 | AE21: =Table1[[#This Row],[Quantity (expected)]]*Table1[[#This Row],[Rate (expected)2]]*0.7 -> 0 | AU21: =SUM(Table1[[#This Row],[Jan-23]:[Dec-23]]) -> 0
A22: =VLOOKUP(H22,'Accoount Code Combination'!$D:$L,8,FALSE) -> Academic | B22: =VLOOKUP(Table1[[#This Row],[Account Code]],'Accoount Code Combination'!$D:$L,9,FALSE) -> No Applicable | C22: =VLOOKUP(Table1[[#This Row],[Cost Center Code]],'Cost Center Group'!A:B,2,FALSE) -> President's Office | D22: 847 | E22: 8470110 | F22: KUST - Office of the President | G22: 1 | H22: 425770 | I22: =IFERROR(VLOOKUP(Table1[[#This Row],[Account Code]],'Accoount Code Combination'!$D:$H,2,FALSE),"") -> Academic Missions - Combined expenses | J22: 8470110 | L22: =IFERROR(VLOOKUP(Table1[[#This Row],[Future-1 Description]],'Other '!E10:$F19,2,FALSE),"") | P22: -13420 | Q22: 0 | Z22: =Table1[[#This Row],[Quantity of measruing units]]*Table1[[#This Row],[Rate (expected)]] -> 0 | AC22: =Table1[[#This Row],[Quantity (expected)]]*Table1[[#This Row],[Rate (expected)2]]*0.9 -> 0 | AD22: =Table1[[#This Row],[Quantity (expected)]]*Table1[[#This Row],[Rate (expected)2]]*0.8 -> 0 | AE22: =Table1[[#This Row],[Quantity (expected)]]*Table1[[#This Row],[Rate (expected)2]]*0.7 -> 0 | AU22: =SUM(Table1[[#This Row],[Jan-23]:[Dec-23]]) -> 0
A23: =VLOOKUP(H23,'Accoount Code Combination'!$D:$L,8,FALSE) -> Other support | B23: =VLOOKUP(Table1[[#This Row],[Account Code]],'Accoount Code Combination'!$D:$L,9,FALSE) -> No Applicable | C23: =VLOOKUP(Table1[[#This Row],[Cost Center Code]],'Cost Center Group'!A:B,2,FALSE) -> President's Office | D23: 847 | E23: 8470110 | F23: KUST - Office of the President | G23: 1 | H23: 425900 | I23: =IFERROR(VLOOKUP(Table1[[#This Row],[Account Code]],'Accoount Code Combination'!$D:$H,2,FALSE),"") -> Entertainment and hospitality | J23: 8470110 | L23: =IFERROR(VLOOKUP(Table1[[#This Row],[Future-1 Description]],'Other '!E11:$F20,2,FALSE),"") | P23: 13355.7 | Q23: 10000 | Z23: =Table1[[#This Row],[Quantity of measruing units]]*Table1[[#This Row],[Rate (expected)]] -> 0 | AC23: =Table1[[#This Row],[Quantity (expected)]]*Table1[[#This Row],[Rate (expected)2]]*0.9 -> 0 | AD23: =Table1[[#This Row],[Quantity (expected)]]*Table1[[#This Row],[Rate (expected)2]]*0.8 -> 0 | AE23: =Table1[[#This Row],[Quantity (expected)]]*Table1[[#This Row],[Rate (expected)2]]*0.7 -> 0 | AU23: =SUM(Table1[[#This Row],[Jan-23]:[Dec-23]]) -> 0
A24: =VLOOKUP(H24,'Accoount Code Combination'!$D:$L,8,FALSE) -> IT | B24: =VLOOKUP(Table1[[#This Row],[Account Code]],'Accoount Code Combination'!$D:$L,9,FALSE) -> Software Operating | C24: =VLOOKUP(Table1[[#This Row],[Cost Center Code]],'Cost Center Group'!A:B,2,FALSE) -> President's Office | D24: 847 | E24: 8470110 | F24: KUST - Office of the President | G24: 1 | H24: 426610 | I24: =IFERROR(VLOOKUP(Table1[[#This Row],[Account Code]],'Accoount Code Combination'!$D:$H,2,FALSE),"") -> Computer software licenses | J24: 8470110 | L24: =IFERROR(VLOOKUP(Table1[[#This Row],[Future-1 Description]],'Other '!E12:$F21,2,FALSE),"") | P24: 42239.5 | Q24: 80204 | Z24: =Table1[[#This Row],[Quantity of measruing units]]*Table1[[#This Row],[Rate (expected)]] -> 0 | AC24: =Table1[[#This Row],[Quantity (expected)]]*Table1[[#This Row],[Rate (expected)2]]*0.9 -> 0 | AD24: =Table1[[#This Row],[Quantity (expected)]]*Table1[[#This Row],[Rate (expected)2]]*0.8 -> 0 | AE24: =Table1[[#This Row],[Quantity (expected)]]*Table1[[#This Row],[Rate (expected)2]]*0.7 -> 0 | AU24: =SUM(Table1[[#This Row],[Jan-23]:[Dec-23]]) -> 0
A25: =VLOOKUP(H25,'Accoount Code Combination'!$D:$L,8,FALSE) -> Academic | B25: =VLOOKUP(Table1[[#This Row],[Account Code]],'Accoount Code Combination'!$D:$L,9,FALSE) -> No Applicable | C25: =VLOOKUP(Table1[[#This Row],[Cost Center Code]],'Cost Center Group'!A:B,2,FALSE) -> President's Office | D25: 847 | E25: 8470110 | F25: KUST - Office of the President | G25: 1 | H25: 427710 | I25: =IFERROR(VLOOKUP(Table1[[#This Row],[Account Code]],'Accoount Code Combination'!$D:$H,2,FALSE),"") -> Subscriptions and membership fees: Trade organisations | J25: 8470110 | L25: =IFERROR(VLOOKUP(Table1[[#This Row],[Future-1 Description]],'Other '!E13:$F22,2,FALSE),"") | P25: 3882.17 | Q25: 1880 | Z25: =Table1[[#This Row],[Quantity of measruing units]]*Table1[[#This Row],[Rate (expected)]] -> 0 | AC25: =Table1[[#This Row],[Quantity (expected)]]*Table1[[#This Row],[Rate (expected)2]]*0.9 -> 0 | AD25: =Table1[[#This Row],[Quantity (expected)]]*Table1[[#This Row],[Rate (expected)2]]*0.8 -> 0 | AE25: =Table1[[#This Row],[Quantity (expected)]]*Table1[[#This Row],[Rate (expected)2]]*0.7 -> 0 | AU25: =SUM(Table1[[#This Row],[Jan-23]:[Dec-23]]) -> 0
A26: =VLOOKUP(H26,'Accoount Code Combination'!$D:$L,8,FALSE) -> Other support | B26: =VLOOKUP(Table1[[#This Row],[Account Code]],'Accoount Code Combination'!$D:$L,9,FALSE) -> No Applicable | C26: =VLOOKUP(Table1[[#This Row],[Cost Center Code]],'Cost Center Group'!A:B,2,FALSE) -> President's Office | D26: 847 | E26: 8470110 | F26: KUST - Office of the President | G26: 1 | H26: 427900 | I26: =IFERROR(VLOOKUP(Table1[[#This Row],[Account Code]],'Accoount Code Combination'!$D:$H,2,FALSE),"") -> Translation and interpretation service | J26: 8470110 | L26: =IFERROR(VLOOKUP(Table1[[#This Row],[Future-1 Description]],'Other '!E14:$F23,2,FALSE),"") | P26: 0 | Q26: 12585 | Z26: =Table1[[#This Row],[Quantity of measruing units]]*Table1[[#This Row],[Rate (expected)]] -> 0 | AC26: =Table1[[#This Row],[Quantity (expected)]]*Table1[[#This Row],[Rate (expected)2]]*0.9 -> 0 | AD26: =Table1[[#This Row],[Quantity (expected)]]*Table1[[#This Row],[Rate (expected)2]]*0.8 -> 0 | AE26: =Table1[[#This Row],[Quantity (expected)]]*Table1[[#This Row],[Rate (expected)2]]*0.7 -> 0 | AU26: =SUM(Table1[[#This Row],[Jan-23]:[Dec-23]]) -> 0
... A631: =VLOOKUP(H631,'Accoount Code Combination'!$D:$L,8,FALSE) -> 0 | B631: =VLOOKUP(Table1[[#This Row],[Account Code]],'Accoount Code Combination'!$D:$L,9,FALSE) -> Software Capital | C631: =VLOOKUP(Table1[[#This Row],[Cost Center Code]],'Cost Center Group'!A:B,2,FALSE) -> College of Medicine & Health Sciences | D631: 847 | E631: 8471305 | F631: KUST - Dean Of Medicine | G631: 1 | H631: 495140 | I631: =IFERROR(VLOOKUP(Table1[[#This Row],[Account Code]],'Accoount Code Combination'!$D:$H,2,FALSE),"") -> Copyrights, patents and licenses | J631: 8471305 | L631: =IFERROR(VLOOKUP(Table1[[#This Row],[Future-1 Description]],'Other '!E619:$F628,2,FALSE),"") | P631: 0 | Q631: 500000 | Z631: =Table1[[#This Row],[Quantity of measruing units]]*Table1[[#This Row],[Rate (expected)]] -> 0 | AC631: =Table1[[#This Row],[Quantity (expected)]]*Table1[[#This Row],[Rate (expected)2]]*0.9 -> 0 | AD631: =Table1[[#This Row],[Quantity (expected)]]*Table1[[#This Row],[Rate (expected)2]]*0.8 -> 0 | AE631: =Table1[[#This Row],[Quantity (expected)]]*Table1[[#This Row],[Rate (expected)2]]*0.7 -> 0 | AU631: =SUM(Table1[[#This Row],[Jan-23]:[Dec-23]]) -> 0
A632: =VLOOKUP(H632,'Accoount Code Combination'!$D:$L,8,FALSE) -> #N/A | B632: =VLOOKUP(Table1[[#This Row],[Account Code]],'Accoount Code Combination'!$D:$L,9,FALSE) -> #N/A | C632: =VLOOKUP(Table1[[#This Row],[Cost Center Code]],'Cost Center Group'!A:B,2,FALSE) -> #N/A | D632: 847 | G632: 1 | I632: =IFERROR(VLOOKUP(Table1[[#This Row],[Account Code]],'Accoount Code Combination'!$D:$H,2,FALSE),"") | L632: =IFERROR(VLOOKUP(Table1[[#This Row],[Future-1 Description]],'Other '!E620:$F629,2,FALSE),"") | Q632: 0 | Z632: =Table1[[#This Row],[Quantity of measruing units]]*Table1[[#This Row],[Rate (expected)]] -> 0 | AC632: =Table1[[#This Row],[Quantity (expected)]]*Table1[[#This Row],[Rate (expected)2]]*0.9 -> 0 | AD632: =Table1[[#This Row],[Quantity (expected)]]*Table1[[#This Row],[Rate (expected)2]]*0.8 -> 0 | AE632: =Table1[[#This Row],[Quantity (expected)]]*Table1[[#This Row],[Rate (expected)2]]*0.7 -> 0 | AU632: =SUM(Table1[[#This Row],[Jan-23]:[Dec-23]]) -> 0
A633: =VLOOKUP(H633,'Accoount Code Combination'!$D:$L,8,FALSE) -> #N/A | B633: =VLOOKUP(Table1[[#This Row],[Account Code]],'Accoount Code Combination'!$D:$L,9,FALSE) -> #N/A | C633: =VLOOKUP(Table1[[#This Row],[Cost Center Code]],'Cost Center Group'!A:B,2,FALSE) -> #N/A | D633: 847 | G633: 1 | I633: =IFERROR(VLOOKUP(Table1[[#This Row],[Account Code]],'Accoount Code Combination'!$D:$H,2,FALSE),"") | L633: =IFERROR(VLOOKUP(Table1[[#This Row],[Future-1 Description]],'Other '!E621:$F630,2,FALSE),"") | Z633: =Table1[[#This Row],[Quantity of measruing units]]*Table1[[#This Row],[Rate (expected)]] -> 0 | AC633: =Table1[[#This Row],[Quantity (expected)]]*Table1[[#This Row],[Rate (expected)2]]*0.9 -> 0 | AD633: =Table1[[#This Row],[Quantity (expected)]]*Table1[[#This Row],[Rate (expected)2]]*0.8 -> 0 | AE633: =Table1[[#This Row],[Quantity (expected)]]*Table1[[#This Row],[Rate (expected)2]]*0.7 -> 0 | AU633: =SUM(Table1[[#This Row],[Jan-23]:[Dec-23]]) -> 0
A634: =VLOOKUP(H634,'Accoount Code Combination'!$D:$L,8,FALSE) -> #N/A | B634: =VLOOKUP(Table1[[#This Row],[Account Code]],'Accoount Code Combination'!$D:$L,9,FALSE) -> #N/A | C634: =VLOOKUP(Table1[[#This Row],[Cost Center Code]],'Cost Center Group'!A:B,2,FALSE) -> #N/A | D634: 847 | G634: 1 | I634: =IFERROR(VLOOKUP(Table1[[#This Row],[Account Code]],'Accoount Code Combination'!$D:$H,2,FALSE),"") | L634: =IFERROR(VLOOKUP(Table1[[#This Row],[Future-1 Description]],'Other '!E622:$F631,2,FALSE),"") | Z634: =Table1[[#This Row],[Quantity of measruing units]]*Table1[[#This Row],[Rate (expected)]] -> 0 | AC634: =Table1[[#This Row],[Quantity (expected)]]*Table1[[#This Row],[Rate (expected)2]]*0.9 -> 0 | AD634: =Table1[[#This Row],[Quantity (expected)]]*Table1[[#This Row],[Rate (expected)2]]*0.8 -> 0 | AE634: =Table1[[#This Row],[Quantity (expected)]]*Table1[[#This Row],[Rate (expected)2]]*0.7 -> 0 | AU634: =SUM(Table1[[#This Row],[Jan-23]:[Dec-23]]) -> 0
P635: =SUM(Table1[2021Actual]) -> 5.2075457e+08 | Q635: =SUM(Table1[2022 Budget]) -> 508729156 | R635: =SUM(Table1[2022 Estimates full year Actual]) -> 0 | Z635: =SUM(Table1[[2023 Budget ]]) -> 500000 | AC635: =SUM(Table1[2023 Budget Scenario 90%]) -> 0 | AD635: =SUM(Table1[2023 Budget Scenario 80%]) -> 0 | AE635: =SUM(Table1[2023 Budget Scenario 70%]) -> 0 | AI635: =SUM(Table1[Jan-23]) -> 0 | AJ635: =SUM(Table1[Feb-23]) -> 0 | AK635: =SUM(Table1[Mar-23]) -> 0 | AL635: =SUM(Table1[Apr-23]) -> 0 | AM635: =SUM(Table1[May-23]) -> 0 | AN635: =SUM(Table1[Jun-23]) -> 0 | AO635: =SUM(Table1[Jul-23]) -> 0 | AP635: =SUM(Table1[Aug-23]) -> 0 | AQ635: =SUM(Table1[Sep-23]) -> 0 | AR635: =SUM(Table1[Oct-23]) -> 0 | AS635: =SUM(Table1[Nov-23]) -> 0 | AT635: =SUM(Table1[Dec-23]) -> 0 | AU635: =SUM(Table1[Total]) -> 0

Sheet xBudget 2024
F1: Cost Center Description : | G1: =IFERROR(VLOOKUP(G2,'Cost Center'!$A:$B,2,FALSE),"")
F2: Cost Center Code : | M2: Return to Main Page
F3: Year | G3: 2024
F4: Drop Box List | M4: Drop Box List | N4: Required | O4: Optional - Drop Box List | P4: Optional | Q4: Required | R4: Required | S4: Required | T4: Required | U4: Required - Drop Box List | V4: Required - Drop Box Lsit | W4: Drop Box List | X4: Drop Box List | Y4: Required
A5: Account Group | B5: Content Expert | C5: Cost Center Code - Group | D5: Cost Center Code | E5: Cost Center Description | F5: Account Code | G5: Account Description | H5: GL Account Combination | I5: Future-1 Description | J5: Future 1 | K5: Future-2 Description | L5: Future-2 | M5: Budget Driver Name - Primary | N5: Budget Driver Qty - Primary | O5: Budget Driver Name - Secondary | P5: Budget Driver Qty - Secondary | Q5: Itemised Details/Calculation method | R5: Quantity (expected) | S5: Rate (expected) | T5: 2023 Budget | U5: Budget Activity Type | V5: Expenditure Frequency | W5: KU Strategy | X5: Department operation Objective | Y5: Contract or Agreement or PO or budgetary Quotation - KU Driver
A6: =IFERROR(VLOOKUP(F6,'Accoount Code Combination'!$D:$L,8,FALSE),"") | B6: =IFERROR(VLOOKUP(Table15[[#This Row],[Account Code]],'Accoount Code Combination'!$D:$L,9,FALSE),"") | C6: =IFERROR(VLOOKUP(Table15[[#This Row],[Cost Center Code]],'Cost Center Group'!A:B,2,FALSE),"") | G6: =IFERROR(VLOOKUP(Table15[[#This Row],[Account Code]],'Accoount Code Combination'!$D:$H,2,FALSE),"") | J6: =IFERROR(VLOOKUP(Table15[[#This Row],[Future-1 Description]],'Other '!$E:$F,2,FALSE),"") | T6: =Table15[[#This Row],[Quantity (expected)]]*Table15[[#This Row],[Rate (expected)]] -> 0
A7: =IFERROR(VLOOKUP(F7,'Accoount Code Combination'!$D:$L,8,FALSE),"") | B7: =IFERROR(VLOOKUP(Table15[[#This Row],[Account Code]],'Accoount Code Combination'!$D:$L,9,FALSE),"") | C7: =IFERROR(VLOOKUP(Table15[[#This Row],[Cost Center Code]],'Cost Center Group'!A:B,2,FALSE),"") | G7: =IFERROR(VLOOKUP(Table15[[#This Row],[Account Code]],'Accoount Code Combination'!$D:$H,2,FALSE),"") | J7: =IFERROR(VLOOKUP(Table15[[#This Row],[Future-1 Description]],'Other '!$E:$F,2,FALSE),"") | T7: =Table15[[#This Row],[Quantity (expected)]]*Table15[[#This Row],[Rate (expected)]] -> 0
A8: =IFERROR(VLOOKUP(F8,'Accoount Code Combination'!$D:$L,8,FALSE),"") | B8: =IFERROR(VLOOKUP(Table15[[#This Row],[Account Code]],'Accoount Code Combination'!$D:$L,9,FALSE),"") | C8: =IFERROR(VLOOKUP(Table15[[#This Row],[Cost Center Code]],'Cost Center Group'!A:B,2,FALSE),"") | G8: =IFERROR(VLOOKUP(Table15[[#This Row],[Account Code]],'Accoount Code Combination'!$D:$H,2,FALSE),"") | J8: =IFERROR(VLOOKUP(Table15[[#This Row],[Future-1 Description]],'Other '!$E:$F,2,FALSE),"") | T8: =Table15[[#This Row],[Quantity (expected)]]*Table15[[#This Row],[Rate (expected)]] -> 0
A9: =IFERROR(VLOOKUP(F9,'Accoount Code Combination'!$D:$L,8,FALSE),"") | B9: =IFERROR(VLOOKUP(Table15[[#This Row],[Account Code]],'Accoount Code Combination'!$D:$L,9,FALSE),"") | C9: =IFERROR(VLOOKUP(Table15[[#This Row],[Cost Center Code]],'Cost Center Group'!A:B,2,FALSE),"") | G9: =IFERROR(VLOOKUP(Table15[[#This Row],[Account Code]],'Accoount Code Combination'!$D:$H,2,FALSE),"") | J9: =IFERROR(VLOOKUP(Table15[[#This Row],[Future-1 Description]],'Other '!$E:$F,2,FALSE),"") | T9: =Table15[[#This Row],[Quantity (expected)]]*Table15[[#This Row],[Rate (expected)]] -> 0
A10: =IFERROR(VLOOKUP(F10,'Accoount Code Combination'!$D:$L,8,FALSE),"") | B10: =IFERROR(VLOOKUP(Table15[[#This Row],[Account Code]],'Accoount Code Combination'!$D:$L,9,FALSE),"") | C10: =IFERROR(VLOOKUP(Table15[[#This Row],[Cost Center Code]],'Cost Center Group'!A:B,2,FALSE),"") | G10: =IFERROR(VLOOKUP(Table15[[#This Row],[Account Code]],'Accoount Code Combination'!$D:$H,2,FALSE),"") | J10: =IFERROR(VLOOKUP(Table15[[#This Row],[Future-1 Description]],'Other '!$E:$F,2,FALSE),"") | T10: =Table15[[#This Row],[Quantity (expected)]]*Table15[[#This Row],[Rate (expected)]] -> 0
A11: =IFERROR(VLOOKUP(F11,'Accoount Code Combination'!$D:$L,8,FALSE),"") | B11: =IFERROR(VLOOKUP(Table15[[#This Row],[Account Code]],'Accoount Code Combination'!$D:$L,9,FALSE),"") | C11: =IFERROR(VLOOKUP(Table15[[#This Row],[Cost Center Code]],'Cost Center Group'!A:B,2,FALSE),"") | G11: =IFERROR(VLOOKUP(Table15[[#This Row],[Account Code]],'Accoount Code Combination'!$D:$H,2,FALSE),"") | J11: =IFERROR(VLOOKUP(Table15[[#This Row],[Future-1 Description]],'Other '!$E:$F,2,FALSE),"") | T11: =Table15[[#This Row],[Quantity (expected)]]*Table15[[#This Row],[Rate (expected)]] -> 0
A12: =IFERROR(VLOOKUP(F12,'Accoount Code Combination'!$D:$L,8,FALSE),"") | B12: =IFERROR(VLOOKUP(Table15[[#This Row],[Account Code]],'Accoount Code Combination'!$D:$L,9,FALSE),"") | C12: =IFERROR(VLOOKUP(Table15[[#This Row],[Cost Center Code]],'Cost Center Group'!A:B,2,FALSE),"") | G12: =IFERROR(VLOOKUP(Table15[[#This Row],[Account Code]],'Accoount Code Combination'!$D:$H,2,FALSE),"") | J12: =IFERROR(VLOOKUP(Table15[[#This Row],[Future-1 Description]],'Other '!$E:$F,2,FALSE),"") | T12: =Table15[[#This Row],[Quantity (expected)]]*Table15[[#This Row],[Rate (expected)]] -> 0
A13: =IFERROR(VLOOKUP(F13,'Accoount Code Combination'!$D:$L,8,FALSE),"") | B13: =IFERROR(VLOOKUP(Table15[[#This Row],[Account Code]],'Accoount Code Combination'!$D:$L,9,FALSE),"") | C13: =IFERROR(VLOOKUP(Table15[[#This Row],[Cost Center Code]],'Cost Center Group'!A:B,2,FALSE),"") | G13: =IFERROR(VLOOKUP(Table15[[#This Row],[Account Code]],'Accoount Code Combination'!$D:$H,2,FALSE),"") | J13: =IFERROR(VLOOKUP(Table15[[#This Row],[Future-1 Description]],'Other '!$E:$F,2,FALSE),"") | T13: =Table15[[#This Row],[Quantity (expected)]]*Table15[[#This Row],[Rate (expected)]] -> 0
A14: =IFERROR(VLOOKUP(F14,'Accoount Code Combination'!$D:$L,8,FALSE),"") | B14: =IFERROR(VLOOKUP(Table15[[#This Row],[Account Code]],'Accoount Code Combination'!$D:$L,9,FALSE),"") | C14: =IFERROR(VLOOKUP(Table15[[#This Row],[Cost Center Code]],'Cost Center Group'!A:B,2,FALSE),"") | G14: =IFERROR(VLOOKUP(Table15[[#This Row],[Account Code]],'Accoount Code Combination'!$D:$H,2,FALSE),"") | J14: =IFERROR(VLOOKUP(Table15[[#This Row],[Future-1 Description]],'Other '!$E:$F,2,FALSE),"") | T14: =Table15[[#This Row],[Quantity (expected)]]*Table15[[#This Row],[Rate (expected)]] -> 0
A15: =IFERROR(VLOOKUP(F15,'Accoount Code Combination'!$D:$L,8,FALSE),"") | B15: =IFERROR(VLOOKUP(Table15[[#This Row],[Account Code]],'Accoount Code Combination'!$D:$L,9,FALSE),"") | C15: =IFERROR(VLOOKUP(Table15[[#This Row],[Cost Center Code]],'Cost Center Group'!A:B,2,FALSE),"") | G15: =IFERROR(VLOOKUP(Table15[[#This Row],[Account Code]],'Accoount Code Combination'!$D:$H,2,FALSE),"") | J15: =IFERROR(VLOOKUP(Table15[[#This Row],[Future-1 Description]],'Other '!$E:$F,2,FALSE),"") | T15: =Table15[[#This Row],[Quantity (expected)]]*Table15[[#This Row],[Rate (expected)]] -> 0
A16: =IFERROR(VLOOKUP(F16,'Accoount Code Combination'!$D:$L,8,FALSE),"") | B16: =IFERROR(VLOOKUP(Table15[[#This Row],[Account Code]],'Accoount Code Combination'!$D:$L,9,FALSE),"") | C16: =IFERROR(VLOOKUP(Table15[[#This Row],[Cost Center Code]],'Cost Center Group'!A:B,2,FALSE),"") | G16: =IFERROR(VLOOKUP(Table15[[#This Row],[Account Code]],'Accoount Code Combination'!$D:$H,2,FALSE),"") | J16: =IFERROR(VLOOKUP(Table15[[#This Row],[Future-1 Description]],'Other '!$E:$F,2,FALSE),"") | T16: =Table15[[#This Row],[Quantity (expected)]]*Table15[[#This Row],[Rate (expected)]] -> 0
A17: =IFERROR(VLOOKUP(F17,'Accoount Code Combination'!$D:$L,8,FALSE),"") | B17: =IFERROR(VLOOKUP(Table15[[#This Row],[Account Code]],'Accoount Code Combination'!$D:$L,9,FALSE),"") | C17: =IFERROR(VLOOKUP(Table15[[#This Row],[Cost Center Code]],'Cost Center Group'!A:B,2,FALSE),"") | G17: =IFERROR(VLOOKUP(Table15[[#This Row],[Account Code]],'Accoount Code Combination'!$D:$H,2,FALSE),"") | J17: =IFERROR(VLOOKUP(Table15[[#This Row],[Future-1 Description]],'Other '!$E:$F,2,FALSE),"") | T17: =Table15[[#This Row],[Quantity (expected)]]*Table15[[#This Row],[Rate (expected)]] -> 0
... A30: =IFERROR(VLOOKUP(F30,'Accoount Code Combination'!$D:$L,8,FALSE),"") | B30: =IFERROR(VLOOKUP(Table15[[#This Row],[Account Code]],'Accoount Code Combination'!$D:$L,9,FALSE),"") | C30: =IFERROR(VLOOKUP(Table15[[#This Row],[Cost Center Code]],'Cost Center Group'!A:B,2,FALSE),"") | G30: =IFERROR(VLOOKUP(Table15[[#This Row],[Account Code]],'Accoount Code Combination'!$D:$H,2,FALSE),"") | J30: =IFERROR(VLOOKUP(Table15[[#This Row],[Future-1 Description]],'Other '!$E:$F,2,FALSE),"") | T30: =Table15[[#This Row],[Quantity (expected)]]*Table15[[#This Row],[Rate (expected)]] -> 0
T31: =SUM(Table15[[2023 Budget ]]) -> 0

Sheet xBudget 2025
F1: Cost Center Description : | G1: =IFERROR(VLOOKUP(G2,'Cost Center'!$A:$B,2,FALSE),"")
F2: Cost Center Code : | M2: Return to Main Page
F3: Year | G3: 2025
F4: Drop Box List | M4: Drop Box List | N4: Required | O4: Optional - Drop Box | P4: Optional | Q4: Required | R4: Required | S4: Required | T4: Required | U4: Required - Drop Box | V4: Required - Drop Box | W4: Drop Box List | X4: Drop Box List | Y4: Required
A5: Account Group | B5: Content Expert | C5: Cost Center Code - Group | D5: Cost Center Code | E5: Cost Center Description | F5: Account Code | G5: Account Description | H5: GL Account Combination | I5: Future-1 Description | J5: Future 1 | K5: Future-2 Description | L5: Future-2 | M5: Budget Driver Name - Primary | N5: Budget Driver Qty - Primary | O5: Budget Driver Name - Secondary | P5: Budget Driver Qty - Secondary | Q5: Itemised Details/Calculation method | R5: Quantity (expected) | S5: Rate (expected) | T5: 2024 Budget | U5: Budget Activity Type | V5: Expenditure Frequency | W5: KU Strategy | X5: Department operation Objective | Y5: Contract or Agreement or PO or budgetary Quotation - KU Driver
A6: =IFERROR(VLOOKUP(F6,'Accoount Code Combination'!$D:$L,8,FALSE),"") | B6: =IFERROR(VLOOKUP(Table156[[#This Row],[Account Code]],'Accoount Code Combination'!$D:$L,9,FALSE),"") | C6: =IFERROR(VLOOKUP(Table156[[#This Row],[Cost Center Code]],'Cost Center Group'!A:B,2,FALSE),"") | G6: =IFERROR(VLOOKUP(Table156[[#This Row],[Account Code]],'Accoount Code Combination'!$D:$H,2,FALSE),"") | J6: =IFERROR(VLOOKUP(Table156[[#This Row],[Future-1 Description]],'Other '!$E:$F,2,FALSE),"") | T6: =Table156[[#This Row],[Quantity (expected)]]*Table156[[#This Row],[Rate (expected)]] -> 0
A7: =IFERROR(VLOOKUP(F7,'Accoount Code Combination'!$D:$L,8,FALSE),"") | B7: =IFERROR(VLOOKUP(Table156[[#This Row],[Account Code]],'Accoount Code Combination'!$D:$L,9,FALSE),"") | C7: =IFERROR(VLOOKUP(Table156[[#This Row],[Cost Center Code]],'Cost Center Group'!A:B,2,FALSE),"") | G7: =IFERROR(VLOOKUP(Table156[[#This Row],[Account Code]],'Accoount Code Combination'!$D:$H,2,FALSE),"") | J7: =IFERROR(VLOOKUP(Table156[[#This Row],[Future-1 Description]],'Other '!$E:$F,2,FALSE),"") | T7: =Table156[[#This Row],[Quantity (expected)]]*Table156[[#This Row],[Rate (expected)]] -> 0
A8: =IFERROR(VLOOKUP(F8,'Accoount Code Combination'!$D:$L,8,FALSE),"") | B8: =IFERROR(VLOOKUP(Table156[[#This Row],[Account Code]],'Accoount Code Combination'!$D:$L,9,FALSE),"") | C8: =IFERROR(VLOOKUP(Table156[[#This Row],[Cost Center Code]],'Cost Center Group'!A:B,2,FALSE),"") | G8: =IFERROR(VLOOKUP(Table156[[#This Row],[Account Code]],'Accoount Code Combination'!$D:$H,2,FALSE),"") | J8: =IFERROR(VLOOKUP(Table156[[#This Row],[Future-1 Description]],'Other '!$E:$F,2,FALSE),"") | T8: =Table156[[#This Row],[Quantity (expected)]]*Table156[[#This Row],[Rate (expected)]] -> 0
A9: =IFERROR(VLOOKUP(F9,'Accoount Code Combination'!$D:$L,8,FALSE),"") | B9: =IFERROR(VLOOKUP(Table156[[#This Row],[Account Code]],'Accoount Code Combination'!$D:$L,9,FALSE),"") | C9: =IFERROR(VLOOKUP(Table156[[#This Row],[Cost Center Code]],'Cost Center Group'!A:B,2,FALSE),"") | G9: =IFERROR(VLOOKUP(Table156[[#This Row],[Account Code]],'Accoount Code Combination'!$D:$H,2,FALSE),"") | J9: =IFERROR(VLOOKUP(Table156[[#This Row],[Future-1 Description]],'Other '!$E:$F,2,FALSE),"") | T9: =Table156[[#This Row],[Quantity (expected)]]*Table156[[#This Row],[Rate (expected)]] -> 0
A10: =IFERROR(VLOOKUP(F10,'Accoount Code Combination'!$D:$L,8,FALSE),"") | B10: =IFERROR(VLOOKUP(Table156[[#This Row],[Account Code]],'Accoount Code Combination'!$D:$L,9,FALSE),"") | C10: =IFERROR(VLOOKUP(Table156[[#This Row],[Cost Center Code]],'Cost Center Group'!A:B,2,FALSE),"") | G10: =IFERROR(VLOOKUP(Table156[[#This Row],[Account Code]],'Accoount Code Combination'!$D:$H,2,FALSE),"") | J10: =IFERROR(VLOOKUP(Table156[[#This Row],[Future-1 Description]],'Other '!$E:$F,2,FALSE),"") | T10: =Table156[[#This Row],[Quantity (expected)]]*Table156[[#This Row],[Rate (expected)]] -> 0
A11: =IFERROR(VLOOKUP(F11,'Accoount Code Combination'!$D:$L,8,FALSE),"") | B11: =IFERROR(VLOOKUP(Table156[[#This Row],[Account Code]],'Accoount Code Combination'!$D:$L,9,FALSE),"") | C11: =IFERROR(VLOOKUP(Table156[[#This Row],[Cost Center Code]],'Cost Center Group'!A:B,2,FALSE),"") | G11: =IFERROR(VLOOKUP(Table156[[#This Row],[Account Code]],'Accoount Code Combination'!$D:$H,2,FALSE),"") | J11: =IFERROR(VLOOKUP(Table156[[#This Row],[Future-1 Description]],'Other '!$E:$F,2,FALSE),"") | T11: =Table156[[#This Row],[Quantity (expected)]]*Table156[[#This Row],[Rate (expected)]] -> 0
A12: =IFERROR(VLOOKUP(F12,'Accoount Code Combination'!$D:$L,8,FALSE),"") | B12: =IFERROR(VLOOKUP(Table156[[#This Row],[Account Code]],'Accoount Code Combination'!$D:$L,9,FALSE),"") | C12: =IFERROR(VLOOKUP(Table156[[#This Row],[Cost Center Code]],'Cost Center Group'!A:B,2,FALSE),"") | G12: =IFERROR(VLOOKUP(Table156[[#This Row],[Account Code]],'Accoount Code Combination'!$D:$H,2,FALSE),"") | J12: =IFERROR(VLOOKUP(Table156[[#This Row],[Future-1 Description]],'Other '!$E:$F,2,FALSE),"") | T12: =Table156[[#This Row],[Quantity (expected)]]*Table156[[#This Row],[Rate (expected)]] -> 0
A13: =IFERROR(VLOOKUP(F13,'Accoount Code Combination'!$D:$L,8,FALSE),"") | B13: =IFERROR(VLOOKUP(Table156[[#This Row],[Account Code]],'Accoount Code Combination'!$D:$L,9,FALSE),"") | C13: =IFERROR(VLOOKUP(Table156[[#This Row],[Cost Center Code]],'Cost Center Group'!A:B,2,FALSE),"") | G13: =IFERROR(VLOOKUP(Table156[[#This Row],[Account Code]],'Accoount Code Combination'!$D:$H,2,FALSE),"") | J13: =IFERROR(VLOOKUP(Table156[[#This Row],[Future-1 Description]],'Other '!$E:$F,2,FALSE),"") | T13: =Table156[[#This Row],[Quantity (expected)]]*Table156[[#This Row],[Rate (expected)]] -> 0
A14: =IFERROR(VLOOKUP(F14,'Accoount Code Combination'!$D:$L,8,FALSE),"") | B14: =IFERROR(VLOOKUP(Table156[[#This Row],[Account Code]],'Accoount Code Combination'!$D:$L,9,FALSE),"") | C14: =IFERROR(VLOOKUP(Table156[[#This Row],[Cost Center Code]],'Cost Center Group'!A:B,2,FALSE),"") | G14: =IFERROR(VLOOKUP(Table156[[#This Row],[Account Code]],'Accoount Code Combination'!$D:$H,2,FALSE),"") | J14: =IFERROR(VLOOKUP(Table156[[#This Row],[Future-1 Description]],'Other '!$E:$F,2,FALSE),"") | T14: =Table156[[#This Row],[Quantity (expected)]]*Table156[[#This Row],[Rate (expected)]] -> 0
A15: =IFERROR(VLOOKUP(F15,'Accoount Code Combination'!$D:$L,8,FALSE),"") | B15: =IFERROR(VLOOKUP(Table156[[#This Row],[Account Code]],'Accoount Code Combination'!$D:$L,9,FALSE),"") | C15: =IFERROR(VLOOKUP(Table156[[#This Row],[Cost Center Code]],'Cost Center Group'!A:B,2,FALSE),"") | G15: =IFERROR(VLOOKUP(Table156[[#This Row],[Account Code]],'Accoount Code Combination'!$D:$H,2,FALSE),"") | J15: =IFERROR(VLOOKUP(Table156[[#This Row],[Future-1 Description]],'Other '!$E:$F,2,FALSE),"") | T15: =Table156[[#This Row],[Quantity (expected)]]*Table156[[#This Row],[Rate (expected)]] -> 0
A16: =IFERROR(VLOOKUP(F16,'Accoount Code Combination'!$D:$L,8,FALSE),"") | B16: =IFERROR(VLOOKUP(Table156[[#This Row],[Account Code]],'Accoount Code Combination'!$D:$L,9,FALSE),"") | C16: =IFERROR(VLOOKUP(Table156[[#This Row],[Cost Center Code]],'Cost Center Group'!A:B,2,FALSE),"") | G16: =IFERROR(VLOOKUP(Table156[[#This Row],[Account Code]],'Accoount Code Combination'!$D:$H,2,FALSE),"") | J16: =IFERROR(VLOOKUP(Table156[[#This Row],[Future-1 Description]],'Other '!$E:$F,2,FALSE),"") | T16: =Table156[[#This Row],[Quantity (expected)]]*Table156[[#This Row],[Rate (expected)]] -> 0
A17: =IFERROR(VLOOKUP(F17,'Accoount Code Combination'!$D:$L,8,FALSE),"") | B17: =IFERROR(VLOOKUP(Table156[[#This Row],[Account Code]],'Accoount Code Combination'!$D:$L,9,FALSE),"") | C17: =IFERROR(VLOOKUP(Table156[[#This Row],[Cost Center Code]],'Cost Center Group'!A:B,2,FALSE),"") | G17: =IFERROR(VLOOKUP(Table156[[#This Row],[Account Code]],'Accoount Code Combination'!$D:$H,2,FALSE),"") | J17: =IFERROR(VLOOKUP(Table156[[#This Row],[Future-1 Description]],'Other '!$E:$F,2,FALSE),"") | T17: =Table156[[#This Row],[Quantity (expected)]]*Table156[[#This Row],[Rate (expected)]] -> 0
... A38: =IFERROR(VLOOKUP(F38,'Accoount Code Combination'!$D:$L,8,FALSE),"") | B38: =IFERROR(VLOOKUP(Table156[[#This Row],[Account Code]],'Accoount Code Combination'!$D:$L,9,FALSE),"") | C38: =IFERROR(VLOOKUP(Table156[[#This Row],[Cost Center Code]],'Cost Center Group'!A:B,2,FALSE),"") | G38: =IFERROR(VLOOKUP(Table156[[#This Row],[Account Code]],'Accoount Code Combination'!$D:$H,2,FALSE),"") | J38: =IFERROR(VLOOKUP(Table156[[#This Row],[Future-1 Description]],'Other '!$E:$F,2,FALSE),"") | T38: =Table156[[#This Row],[Quantity (expected)]]*Table156[[#This Row],[Rate (expected)]] -> 0
T39: =SUM(Table156[[2024 Budget ]]) -> 0

Sheet Check List
B1: Return to Main Page
A3: Number | B3: Budget Compliance Description | C3: Feedback | D3: Date
A4: 1 | B4: Budget template received
A5: 2 | B5: Budget first submission
A6: 3 | B6: Budget Latest submission
A7: 4 | B7: Supporting Documents for each budget line upload in KU shared drive | E7: Insert the linked
A8: 5 | B8: Budget Itemized all lines entered
A9: 6 | B9: Entered full year Actual Expenditures for 2022
A10: 7 | B10: Entered budget scenarios impact for the 90% , 80% & 70%
A11: 8 | B11: Entered Itemized budget monthly Cash Flow for year 2023
A12: 9 | B12: Content expert’s confirmation | E12: Removed
A13: 10 | B13: IT – ADDA Template fill up and send to IT
A14: 11 | B14: FMS
A15: 12 | B15: Strategic Project | E15: Yes/No
A16: 13 | B16: Selected relevant budget driver/s
A17: 14 | B17: Entered KU Strategy linked with the budget objective
A18: 15 | B18: Enetred budget for the years 2024 - 2025

Sheet Drivers
A1: Return to Main Page
A3: Account | B3: Account Description | C3: Cost drivers (Measrable) | D3: Measruing unit | E3: Quantity of measruing units
A4: 425100 | B4: Advertising Services (General) | C4: Radio advertising cost | D4: Second
A5: 425100 | B5: Advertising Services (General) | C5: TV advertising cost | D5: Second
A6: 425100 | B6: Advertising Services (General) | C6: Advertising through newspapers and other print media | D6: cm2 - Word
A7: 425100 | B7: Advertising Services (General) | C7: Digital Marketing Campaigns | D7: count
A8: 425100 | B8: Advertising Services (General) | C8: Website Maintenance | D8: count
A9: 425100 | B9: Advertising Services (General) | C9: Animation Videos | D9: count
A10: 425100 | B10: Advertising Services (General) | C10: Search Engine Optimization (SEO) | D10: count
A11: 425100 | B11: Advertising Services (General) | C11: Video production | D11: second
A12: 425100 | B12: Advertising Services (General) | C12: Corporate Photoshoot | D12: count
A13: 425100 | B13: Advertising Services (General) | C13: International Publicity | D13: count
A14: 425100 | B14: Advertising Services (General) | C14: Branding | D14: count
A15: 425100 | B15: Advertising Services (General) | C15: Digital advertizing (Radio, TV, Social Media) | D15: count
A16: 425100 | B16: Advertising Services (General) | C16: The cost of advertising on billboards and malls | D16: cm2

Sheet Accoount Code Combination
A1: Cost Center Grouping | B1: Cost Center Code | C1: Cost Center Description | D1: Account Code | E1: Account Description | F1: Future1 | G1: Future1 Description | H1: Future2 Description | I1: Future2 | J1: GL Account Combination | K1: Account Group | L1: Content Expert
A2: President's Office | B2: 8470120 | C2: KUST - Audit & Compliance | D2: 420120 | E2: Internal Audit service | F2: 847001 | G2: KUST - General | H2: FA179-Opex Expense | I2: 200179 | J2: 847.8470120.1.420120.000000.847001.200179 | K2: Other support | L2: No Applicable
A3: President's Office | B3: 8470120 | C3: KUST - Audit & Compliance | D3: 420120 | E3: Internal Audit service | F3: 847001 | G3: KUST - General | H3: Un Specified | I3: 000000 | J3: 847.8470120.1.420120.000000.847001.000000 | K3: Other support | L3: No Applicable
A4: Finance & Business Development Office | B4: 8470620 | C4: KUST - Finance Operations | D4: 420130 | E4: External Audit service | F4: 847001 | G4: KUST - General | H4: FA179-Opex Expense | I4: 200179 | J4: 847.8470620.1.420130.000000.847001.200179 | K4: Other support | L4: No Applicable
A5: Finance & Business Development Office | B5: 8470620 | C5: KUST - Finance Operations | D5: 420130 | E5: External Audit service | F5: 847001 | G5: KUST - General | H5: Un Specified | I5: 000000 | J5: 847.8470620.1.420130.000000.847001.000000 | K5: Other support | L5: No Applicable
A6: Administration, Facilities and EHS Office | B6: 8470530 | C6: KUST - Facilities Management | D6: 420310 | E6: Cleaning: Business premises | F6: 847010 | G6: KUST - Main Campus | H6: FA179-Opex Expense | I6: 200179 | J6: 847.8470530.1.420310.000000.847010.200179 | K6: Facilities | L6: No Applicable
A7: Administration, Facilities and EHS Office | B7: 8470530 | C7: KUST - Facilities Management | D7: 420310 | E7: Cleaning: Business premises | F7: 847010 | G7: KUST - Main Campus | H7: Un Specified | I7: 000000 | J7: 847.8470530.1.420310.000000.847010.000000 | K7: Facilities | L7: No Applicable
A8: Administration, Facilities and EHS Office | B8: 8470530 | C8: KUST - Facilities Management | D8: 420310 | E8: Cleaning: Business premises | F8: 847020 | G8: KUST- Sas Al Nakhl Campus | H8: FA179-Opex Expense | I8: 200179 | J8: 847.8470530.1.420310.000000.847020.200179 | K8: Facilities | L8: No Applicable
A9: Administration, Facilities and EHS Office | B9: 8470530 | C9: KUST - Facilities Management | D9: 420310 | E9: Cleaning: Business premises | F9: 847020 | G9: KUST- Sas Al Nakhl Campus | H9: Un Specified | I9: 000000 | J9: 847.8470530.1.420310.000000.847020.000000 | K9: Facilities | L9: No Applicable
A10: Administration, Facilities and EHS Office | B10: 8470530 | C10: KUST - Facilities Management | D10: 420310 | E10: Cleaning: Business premises | F10: 847030 | G10: KUST- Masdar city campus | H10: FA179-Opex Expense | I10: 200179 | J10: 847.8470530.1.420310.000000.847030.200179 | K10: Facilities | L10: No Applicable
A11: Administration, Facilities and EHS Office | B11: 8470530 | C11: KUST - Facilities Management | D11: 420310 | E11: Cleaning: Business premises | F11: 847030 | G11: KUST- Masdar city campus | H11: Un Specified | I11: 000000 | J11: 847.8470530.1.420310.000000.847030.000000 | K11: Facilities | L11: No Applicable
A12: Academic and Student Services Office | B12: 8471210 | C12: KUST - SVP/ Academic & Student Services Office | D12: 420310 | E12: Cleaning: Business premises | F12: 847001 | G12: KUST - General | H12: Un Specified | I12: 000000 | J12: 847.8471210.1.420310.000000.847001.000000 | K12: Facilities | L12: No Applicable
A13: Academic and Student Services Office | B13: 8471260 | C13: KUST - Student Life | D13: 420310 | E13: Cleaning: Business premises | F13: 847001 | G13: KUST - General | H13: FA179-Opex Expense | I13: 200179 | J13: 847.8471260.1.420310.000000.847001.200179 | K13: Facilities | L13: No Applicable
... A97: Senior Vice President, Research Office | B97: 8471160 | C97: KUST - Research Laboratories | D97: 422100 | E97: Waste management service | F97: 847001 | G97: KUST - General | H97: Un Specified | I97: 000000 | J97: 847.8471160.1.422100.000000.847001.000000 | K97: Facilities | L97: No Applicable
A98: College of Medicine & Health Sciences | B98: 8471305 | C98: KUST - Dean Of Medicine | D98: 422900 | E98: Other specialised professional services, not mentioned elsewhere | F98: 847001 | G98: KUST - General | H98: FA179-Opex Expense | I98: 200179 | J98: 847.8471305.1.422900.000000.847001.200179 | K98: 0 | L98: No Applicable
A99: President's Office | B99: 8470130 | C99: KUST - Institutional Research & Planning | D99: 425100 | E99: Advertising | F99: 847001 | G99: KUST - General | H99: FA179-Opex Expense | I99: 200179 | J99: 847.8470130.1.425100.000000.847001.200179 | K99: Communiction & Marketing | L99: Advertising
A100: President's Office | B100: 8470140 | C100: KUST - Communication | D100: 425100 | E100: Advertising | F100: 847001 | G100: KUST - General | H100: FA179-Opex Expense | I100: 200179 | J100: 847.8470140.1.425100.000000.847001.200179 | K100: Communiction & Marketing | L100: Advertising
A101: President's Office | B101: 8470140 | C101: KUST - Communication | D101: 425100 | E101: Advertising | F101: 847001 | G101: KUST - General | H101: Un Specified | I101: 000000 | J101: 847.8470140.1.425100.000000.847001.000000 | K101: Communiction & Marketing | L101: Advertising
A102: Graduate Studies | B102: 8470230 | C102: KUST - Graduate Studies | D102: 425100 | E102: Advertising | F102: 847001 | G102: KUST - General | H102: FA179-Opex Expense | I102: 200179 | J102: 847.8470230.1.425100.000000.847001.200179 | K102: Communiction & Marketing | L102: Advertising
A103: College of Arts & Science | B103: 8470405 | C103: KUST - Dean Of Arts & Science | D103: 425100 | E103: Advertising | F103: 847001 | G103: KUST - General | H103: FA179-Opex Expense | I103: 200179 | J103: 847.8470405.1.425100.000000.847001.200179 | K103: Communiction & Marketing | L103: Advertising
A104: College of Arts & Science | B104: 8470405 | C104: KUST - Dean Of Arts & Science | D104: 425100 | E104: Advertising | F104: 847001 | G104: KUST - General | H104: Un Specified | I104: 000000 | J104: 847.8470405.1.425100.000000.847001.000000 | K104: Communiction & Marketing | L104: Advertising
A105: HR & Procurement Office | B105: 8470730 | C105: KUST - Human Resources | D105: 425100 | E105: Advertising | F105: 847001 | G105: KUST - General | H105: Un Specified | I105: 000000 | J105: 847.8470730.1.425100.000000.847001.000000 | K105: Communiction & Marketing | L105: Advertising
A106: College of Medicine & Health Sciences | B106: 8471305 | C106: KUST - Dean Of Medicine | D106: 425100 | E106: Advertising | F106: 847001 | G106: KUST - General | H106: FA179-Opex Expense | I106: 200179 | J106: 847.8471305.1.425100.000000.847001.200179 | K106: Communiction & Marketing | L106: Advertising
A107: Finance & Business Development Office | B107: 8470620 | C107: KUST - Finance Operations | D107: 425300 | E107: Banking service charges / Fees | F107: 847001 | G107: KUST - General | H107: FA179-Opex Expense | I107: 200179 | J107: 847.8470620.1.425300.000000.847001.200179 | K107: Finance | L107: No Applicable
A108: Finance & Business Development Office | B108: 8470620 | C108: KUST - Finance Operations | D108: 425300 | E108: Banking service charges / Fees | F108: 847001 | G108: KUST - General | H108: Un Specified | I108: 000000 | J108: 847.8470620.1.425300.000000.847001.000000 | K108: Finance | L108: No Applicable
A109: Finance & Business Development Office | B109: 8470620 | C109: KUST - Finance Operations | D109: 425350 | E109: Fees for processing e-payments | F109: 847001 | G109: KUST - General | H109: FA179-Opex Expense | I109: 200179 | J109: 847.8470620.1.425350.000000.847001.200179 | K109: Finance | L109: No Applicable
A110: Finance & Business Development Office | B110: 8470620 | C110: KUST - Finance Operations | D110: 425350 | E110: Fees for processing e-payments | F110: 847001 | G110: KUST - General | H110: Un Specified | I110: 000000 | J110: 847.8470620.1.425350.000000.847001.000000 | K110: Finance | L110: No Applicable
... A132: College of Arts & Science | B132: 8470405 | C132: KUST - Dean Of Arts & Science | D132: 425510 | E132: Conferences, seminars and exhibitions and other events: - Local Events | F132: 847001 | G132: KUST - General | H132: Un Specified | I132: 000000 | J132: 847.8470405.1.425510.000000.847001.000000 | K132: Communiction & Marketing | L132: Events
A133: #N/A | B133: 8470420 | C133: KUST - Computer Science | D133: 425510 | E133: Conferences, seminars and exhibitions and other events: - Local Events | F133: 847001 | G133: KUST - General | H133: FA179-Opex Expense | I133: 200179 | J133: 847.8470420.1.425510.000000.847001.200179 | K133: Communiction & Marketing | L133: Events
A134: #N/A | B134: 8470420 | C134: KUST - Computer Science | D134: 425510 | E134: Conferences, seminars and exhibitions and other events: - Local Events | F134: 847001 | G134: KUST - General | H134: Un Specified | I134: 000000 | J134: 847.8470420.1.425510.000000.847001.000000 | K134: Communiction & Marketing | L134: Events
A135: Administration, Facilities and EHS Office | B135: 8470520 | C135: KUST - Environment, Health & Safety | D135: 425510 | E135: Conferences, seminars and exhibitions and other events: - Local Events | F135: 847001 | G135: KUST - General | H135: FA179-Opex Expense | I135: 200179 | J135: 847.8470520.1.425510.000000.847001.200179 | K135: Communiction & Marketing | L135: Events
A136: Administration, Facilities and EHS Office | B136: 8470520 | C136: KUST - Environment, Health & Safety | D136: 425510 | E136: Conferences, seminars and exhibitions and other events: - Local Events | F136: 847001 | G136: KUST - General | H136: Un Specified | I136: 000000 | J136: 847.8470520.1.425510.000000.847001.000000 | K136: Communiction & Marketing | L136: Events
A137: Administration, Facilities and EHS Office | B137: 8470520 | C137: KUST - Environment, Health & Safety | D137: 425510 | E137: Conferences, seminars and exhibitions and other events: - Local Events | F137: 847951 | G137: COVID-19 Pandemic | H137: FA179-Opex Expense | I137: 200179 | J137: 847.8470520.1.425510.000000.847951.200179 | K137: Communiction & Marketing | L137: Events
A138: Administration, Facilities and EHS Office | B138: 8470530 | C138: KUST - Facilities Management | D138: 425510 | E138: Conferences, seminars and exhibitions and other events: - Local Events | F138: 847010 | G138: KUST - Main Campus | H138: FA179-Opex Expense | I138: 200179 | J138: 847.8470530.1.425510.000000.847010.200179 | K138: Communiction & Marketing | L138: Events
A139: Administration, Facilities and EHS Office | B139: 8470530 | C139: KUST - Facilities Management | D139: 425510 | E139: Conferences, seminars and exhibitions and other events: - Local Events | F139: 847010 | G139: KUST - Main Campus | H139: Un Specified | I139: 000000 | J139: 847.8470530.1.425510.000000.847010.000000 | K139: Communiction & Marketing | L139: Events
A140: Finance & Business Development Office | B140: 8470620 | C140: KUST - Finance Operations | D140: 425510 | E140: Conferences, seminars and exhibitions and other events: - Local Events | F140: 847001 | G140: KUST - General | H140: FA179-Opex Expense | I140: 200179 | J140: 847.8470620.1.425510.000000.847001.200179 | K140: Communiction & Marketing | L140: Events
A141: HR & Procurement Office | B141: 8470730 | C141: KUST - Human Resources | D141: 425510 | E141: Conferences, seminars and exhibitions and other events: - Local Events | F141: 847001 | G141: KUST - General | H141: FA179-Opex Expense | I141: 200179 | J141: 847.8470730.1.425510.000000.847001.200179 | K141: Communiction & Marketing | L141: Events
A142: HR & Procurement Office | B142: 8470730 | C142: KUST - Human Resources | D142: 425510 | E142: Conferences, seminars and exhibitions and other events: - Local Events | F142: 847001 | G142: KUST - General | H142: Un Specified | I142: 000000 | J142: 847.8470730.1.425510.000000.847001.000000 | K142: Communiction & Marketing | L142: Events
A143: Senior Vice President, Research Office | B143: 8471110 | C143: KUST - SVP/ Research & Development Office | D143: 425510 | E143: Conferences, seminars and exhibitions and other events: - Local Events | F143: 847001 | G143: KUST - General | H143: Un Specified | I143: 000000 | J143: 847.8471110.1.425510.000000.847001.000000 | K143: Communiction & Marketing | L143: Events
A144: Senior Vice President, Research Office | B144: 8471140 | C144: KUST - University Sponsored Research | D144: 425510 | E144: Conferences, seminars and exhibitions and other events: - Local Events | F144: 847001 | G144: KUST - General | H144: FA179-Opex Expense | I144: 200179 | J144: 847.8471140.1.425510.000000.847001.200179 | K144: Communiction & Marketing | L144: Events
A145: Senior Vice President, Research Office | B145: 8471140 | C145: KUST - University Sponsored Research | D145: 425510 | E145: Conferences, seminars and exhibitions and other events: - Local Events | F145: 847001 | G145: KUST - General | H145: Un Specified | I145: 000000 | J145: 847.8471140.1.425510.000000.847001.000000 | K145: Communiction & Marketing | L145: Events
A146: Senior Vice President, Research Office | B146: 8471150 | C146: KUST - Technology Management & Innovation | D146: 425510 | E146: Conferences, seminars and exhibitions and other events: - Local Events | F146: 847001 | G146: KUST - General | H146: Un Specified | I146: 000000 | J146: 847.8471150.1.425510.000000.847001.000000 | K146: Communiction & Marketing | L146: Events
... A172: College of Medicine & Health Sciences | B172: 8471305 | C172: KUST - Dean Of Medicine | D172: 425720 | E172: Education-Outsourced training service | F172: 847001 | G172: KUST - General | H172: Un Specified | I172: 000000 | J172: 847.8471305.1.425720.000000.847001.000000 | K172: Student | L172: No Applicable
A173: Graduate Studies | B173: 8470230 | C173: KUST - Graduate Studies | D173: 425740 | E173: Scholarships & other financial aid | F173: 847001 | G173: KUST - General | H173: Un Specified | I173: 000000 | J173: 847.8470230.1.425740.000000.847001.000000 | K173: 0 | L173: No Applicable
A174: Graduate Studies | B174: 8470230 | C174: KUST - Graduate Studies | D174: 425741 | E174: Student stipend | F174: 847001 | G174: KUST - General | H174: FA179-Opex Expense | I174: 200179 | J174: 847.8470230.1.425741.000000.847001.200179 | K174: Student | L174: No Applicable
A175: Graduate Studies | B175: 8470230 | C175: KUST - Graduate Studies | D175: 425741 | E175: Student stipend | F175: 847001 | G175: KUST - General | H175: Un Specified | I175: 000000 | J175: 847.8470230.1.425741.000000.847001.000000 | K175: Student | L175: No Applicable
A176: HR & Procurement Office | B176: 8470730 | C176: KUST - Human Resources | D176: 425741 | E176: Student stipend | F176: 847001 | G176: KUST - General | H176: Un Specified | I176: 000000 | J176: 847.8470730.1.425741.000000.847001.000000 | K176: Student | L176: No Applicable
A177: Academic and Student Services Office | B177: 8471210 | C177: KUST - SVP/ Academic & Student Services Office | D177: 425741 | E177: Student stipend | F177: 847001 | G177: KUST - General | H177: FA179-Opex Expense | I177: 200179 | J177: 847.8471210.1.425741.000000.847001.200179 | K177: Student | L177: No Applicable
A178: Academic and Student Services Office | B178: 8471220 | C178: KUST - Registrar | D178: 425741 | E178: Student stipend | F178: 847001 | G178: KUST - General | H178: FA179-Opex Expense | I178: 200179 | J178: 847.8471220.1.425741.000000.847001.200179 | K178: Student | L178: No Applicable
A179: Academic and Student Services Office | B179: 8471220 | C179: KUST - Registrar | D179: 425741 | E179: Student stipend | F179: 847001 | G179: KUST - General | H179: Un Specified | I179: 000000 | J179: 847.8471220.1.425741.000000.847001.000000 | K179: Student | L179: No Applicable
A180: College of Medicine & Health Sciences | B180: 8471305 | C180: KUST - Dean Of Medicine | D180: 425741 | E180: Student stipend | F180: 847001 | G180: KUST - General | H180: FA179-Opex Expense | I180: 200179 | J180: 847.8471305.1.425741.000000.847001.200179 | K180: Student | L180: No Applicable
A181: College of Medicine & Health Sciences | B181: 8471305 | C181: KUST - Dean Of Medicine | D181: 425741 | E181: Student stipend | F181: 847001 | G181: KUST - General | H181: Un Specified | I181: 000000 | J181: 847.8471305.1.425741.000000.847001.000000 | K181: Student | L181: No Applicable
A182: Graduate Studies | B182: 8470230 | C182: KUST - Graduate Studies | D182: 425742 | E182: Enrollment expenses | F182: 847001 | G182: KUST - General | H182: FA179-Opex Expense | I182: 200179 | J182: 847.8470230.1.425742.000000.847001.200179 | K182: Academic | L182: No Applicable
A183: Graduate Studies | B183: 8470230 | C183: KUST - Graduate Studies | D183: 425742 | E183: Enrollment expenses | F183: 847001 | G183: KUST - General | H183: Un Specified | I183: 000000 | J183: 847.8470230.1.425742.000000.847001.000000 | K183: Academic | L183: No Applicable
A184: Academic and Student Services Office | B184: 8471230 | C184: KUST - Student Enrollment | D184: 425742 | E184: Enrollment expenses | F184: 847001 | G184: KUST - General | H184: FA179-Opex Expense | I184: 200179 | J184: 847.8471230.1.425742.000000.847001.200179 | K184: Academic | L184: No Applicable
A185: Academic and Student Services Office | B185: 8471230 | C185: KUST - Student Enrollment | D185: 425742 | E185: Enrollment expenses | F185: 847001 | G185: KUST - General | H185: Un Specified | I185: 000000 | J185: 847.8471230.1.425742.000000.847001.000000 | K185: Academic | L185: No Applicable
... A282: College of Arts & Science | B282: 8470415 | C282: KUST - Chemistry | D282: 425770 | E282: Academic Missions - Combined expenses | F282: 847001 | G282: KUST - General | H282: Un Specified | I282: 000000 | J282: 847.8470415.1.425770.000000.847001.000000 | K282: Academic | L282: No Applicable
A283: #N/A | B283: 8470420 | C283: KUST - Computer Science | D283: 425770 | E283: Academic Missions - Combined expenses | F283: 847001 | G283: KUST - General | H283: FA179-Opex Expense | I283: 200179 | J283: 847.8470420.1.425770.000000.847001.200179 | K283: Academic | L283: No Applicable
A284: #N/A | B284: 8470420 | C284: KUST - Computer Science | D284: 425770 | E284: Academic Missions - Combined expenses | F284: 847001 | G284: KUST - General | H284: Un Specified | I284: 000000 | J284: 847.8470420.1.425770.000000.847001.000000 | K284: Academic | L284: No Applicable
A285: College of Arts & Science | B285: 8470425 | C285: KUST - Physics | D285: 425770 | E285: Academic Missions - Combined expenses | F285: 847001 | G285: KUST - General | H285: FA179-Opex Expense | I285: 200179 | J285: 847.8470425.1.425770.000000.847001.200179 | K285: Academic | L285: No Applicable
A286: College of Arts & Science | B286: 8470425 | C286: KUST - Physics | D286: 425770 | E286: Academic Missions - Combined expenses | F286: 847001 | G286: KUST - General | H286: Un Specified | I286: 000000 | J286: 847.8470425.1.425770.000000.847001.000000 | K286: Academic | L286: No Applicable
A287: College of Arts & Science | B287: 8470430 | C287: KUST - Preparatory Program | D287: 425770 | E287: Academic Missions - Combined expenses | F287: 847001 | G287: KUST - General | H287: FA179-Opex Expense | I287: 200179 | J287: 847.8470430.1.425770.000000.847001.200179 | K287: Academic | L287: No Applicable
A288: College of Arts & Science | B288: 8470430 | C288: KUST - Preparatory Program | D288: 425770 | E288: Academic Missions - Combined expenses | F288: 847001 | G288: KUST - General | H288: Un Specified | I288: 000000 | J288: 847.8470430.1.425770.000000.847001.000000 | K288: Academic | L288: No Applicable
A289: College of Arts & Science | B289: 8470435 | C289: KUST - Department of English | D289: 425770 | E289: Academic Missions - Combined expenses | F289: 847001 | G289: KUST - General | H289: FA179-Opex Expense | I289: 200179 | J289: 847.8470435.1.425770.000000.847001.200179 | K289: Academic | L289: No Applicable
A290: College of Arts & Science | B290: 8470435 | C290: KUST - Department of English | D290: 425770 | E290: Academic Missions - Combined expenses | F290: 847001 | G290: KUST - General | H290: Un Specified | I290: 000000 | J290: 847.8470435.1.425770.000000.847001.000000 | K290: Academic | L290: No Applicable
A291: College of Arts & Science | B291: 8470440 | C291: KUST - Humanities & Social Sciences | D291: 425770 | E291: Academic Missions - Combined expenses | F291: 847001 | G291: KUST - General | H291: FA179-Opex Expense | I291: 200179 | J291: 847.8470440.1.425770.000000.847001.200179 | K291: Academic | L291: No Applicable
A292: College of Arts & Science | B292: 8470440 | C292: KUST - Humanities & Social Sciences | D292: 425770 | E292: Academic Missions - Combined expenses | F292: 847001 | G292: KUST - General | H292: Un Specified | I292: 000000 | J292: 847.8470440.1.425770.000000.847001.000000 | K292: Academic | L292: No Applicable
A293: College of Arts & Science | B293: 8470445 | C293: KUST - Mathematics | D293: 425770 | E293: Academic Missions - Combined expenses | F293: 847001 | G293: KUST - General | H293: FA179-Opex Expense | I293: 200179 | J293: 847.8470445.1.425770.000000.847001.200179 | K293: Academic | L293: No Applicable
A294: College of Arts & Science | B294: 8470445 | C294: KUST - Mathematics | D294: 425770 | E294: Academic Missions - Combined expenses | F294: 847001 | G294: KUST - General | H294: Un Specified | I294: 000000 | J294: 847.8470445.1.425770.000000.847001.000000 | K294: Academic | L294: No Applicable
A295: College of Arts & Science | B295: 8470450 | C295: KUST - Earth Science | D295: 425770 | E295: Academic Missions - Combined expenses | F295: 847001 | G295: KUST - General | H295: FA179-Opex Expense | I295: 200179 | J295: 847.8470450.1.425770.000000.847001.200179 | K295: Academic | L295: No Applicable
A296: College of Arts & Science | B296: 8470450 | C296: KUST - Earth Science | D296: 425770 | E296: Academic Missions - Combined expenses | F296: 847001 | G296: KUST - General | H296: Un Specified | I296: 000000 | J296: 847.8470450.1.425770.000000.847001.000000 | K296: Academic | L296: No Applicable
... A368: Administration, Facilities and EHS Office | B368: 8470530 | C368: KUST - Facilities Management | D368: 426250 | E368: Insurance - Motor vehicles | F368: 847030 | G368: KUST- Masdar city campus | H368: Un Specified | I368: 000000 | J368: 847.8470530.1.426250.000000.847030.000000 | K368: Facilities | L368: No Applicable
A369: Administration, Facilities and EHS Office | B369: 8470530 | C369: KUST - Facilities Management | D369: 426290 | E369: Insurance - Other | F369: 847010 | G369: KUST - Main Campus | H369: Un Specified | I369: 000000 | J369: 847.8470530.1.426290.000000.847010.000000 | K369: 0 | L369: No Applicable
A370: HR & Procurement Office | B370: 8470730 | C370: KUST - Human Resources | D370: 426290 | E370: Insurance - Other | F370: 847001 | G370: KUST - General | H370: FA179-Opex Expense | I370: 200179 | J370: 847.8470730.1.426290.000000.847001.200179 | K370: 0 | L370: No Applicable
A371: President's Office | B371: 8470110 | C371: KUST - Office of the President | D371: 426610 | E371: Computer software licenses | F371: 847001 | G371: KUST - General | H371: FA179-Opex Expense | I371: 200179 | J371: 847.8470110.1.426610.000000.847001.200179 | K371: IT | L371: Software Operating
A372: President's Office | B372: 8470110 | C372: KUST - Office of the President | D372: 426610 | E372: Computer software licenses | F372: 847001 | G372: KUST - General | H372: Un Specified | I372: 000000 | J372: 847.8470110.1.426610.000000.847001.000000 | K372: IT | L372: Software Operating
A373: President's Office | B373: 8470140 | C373: KUST - Communication | D373: 426610 | E373: Computer software licenses | F373: 847001 | G373: KUST - General | H373: Un Specified | I373: 000000 | J373: 847.8470140.1.426610.000000.847001.000000 | K373: IT | L373: Software Operating
A374: Graduate Studies | B374: 8470230 | C374: KUST - Graduate Studies | D374: 426610 | E374: Computer software licenses | F374: 847001 | G374: KUST - General | H374: Un Specified | I374: 000000 | J374: 847.8470230.1.426610.000000.847001.000000 | K374: IT | L374: Software Operating
A375: College of Engineering | B375: 8470305 | C375: KUST - Dean Of Engineering | D375: 426610 | E375: Computer software licenses | F375: 847001 | G375: KUST - General | H375: FA179-Opex Expense | I375: 200179 | J375: 847.8470305.1.426610.000000.847001.200179 | K375: IT | L375: Software Operating
A376: College of Engineering | B376: 8470305 | C376: KUST - Dean Of Engineering | D376: 426610 | E376: Computer software licenses | F376: 847001 | G376: KUST - General | H376: Un Specified | I376: 000000 | J376: 847.8470305.1.426610.000000.847001.000000 | K376: IT | L376: Software Operating
A377: College of Engineering | B377: 8470310 | C377: KUST - Aerospace Engineering | D377: 426610 | E377: Computer software licenses | F377: 847001 | G377: KUST - General | H377: FA179-Opex Expense | I377: 200179 | J377: 847.8470310.1.426610.000000.847001.200179 | K377: IT | L377: Software Operating
A378: College of Engineering | B378: 8470310 | C378: KUST - Aerospace Engineering | D378: 426610 | E378: Computer software licenses | F378: 847001 | G378: KUST - General | H378: Un Specified | I378: 000000 | J378: 847.8470310.1.426610.000000.847001.000000 | K378: IT | L378: Software Operating
A379: College of Engineering | B379: 8470315 | C379: KUST - Biomedical Engineering | D379: 426610 | E379: Computer software licenses | F379: 847001 | G379: KUST - General | H379: FA179-Opex Expense | I379: 200179 | J379: 847.8470315.1.426610.000000.847001.200179 | K379: IT | L379: Software Operating
A380: College of Engineering | B380: 8470320 | C380: KUST - Chemical Engineering | D380: 426610 | E380: Computer software licenses | F380: 847001 | G380: KUST - General | H380: FA179-Opex Expense | I380: 200179 | J380: 847.8470320.1.426610.000000.847001.200179 | K380: IT | L380: Software Operating
A381: College of Engineering | B381: 8470325 | C381: KUST - Civil Engineering | D381: 426610 | E381: Computer software licenses | F381: 847001 | G381: KUST - General | H381: FA179-Opex Expense | I381: 200179 | J381: 847.8470325.1.426610.000000.847001.200179 | K381: IT | L381: Software Operating
A382: College of Engineering | B382: 8470330 | C382: KUST - Electrical & Computer Engineering | D382: 426610 | E382: Computer software licenses | F382: 847001 | G382: KUST - General | H382: FA179-Opex Expense | I382: 200179 | J382: 847.8470330.1.426610.000000.847001.200179 | K382: IT | L382: Software Operating
... A415: College of Medicine & Health Sciences | B415: 8471305 | C415: KUST - Dean Of Medicine | D415: 426610 | E415: Computer software licenses | F415: 847001 | G415: KUST - General | H415: FA179-Opex Expense | I415: 200179 | J415: 847.8471305.1.426610.000000.847001.200179 | K415: IT | L415: Software Operating
A416: #N/A | B416: 8477110 | C416: ADRIC operations | D416: 426610 | E416: Computer software licenses | F416: 847078 | G416: Research Software renewal | H416: Un Specified | I416: 000000 | J416: 847.8477110.1.426610.000000.847078.000000 | K416: IT | L416: Software Operating
A417: Academic and Student Services Office | B417: 8471210 | C417: KUST - SVP/ Academic & Student Services Office | D417: 426751 | E417: Local Medical treatment expenses including preventive testing | F417: 847001 | G417: KUST - General | H417: Un Specified | I417: 000000 | J417: 847.8471210.1.426751.000000.847001.000000 | K417: 0 | L417: No Applicable
A418: Administration, Facilities and EHS Office | B418: 8470530 | C418: KUST - Facilities Management | D418: 426800 | E418: Motor vehicle registration and inspection charges | F418: 847010 | G418: KUST - Main Campus | H418: FA179-Opex Expense | I418: 200179 | J418: 847.8470530.1.426800.000000.847010.200179 | K418: Facilities | L418: No Applicable
A419: Administration, Facilities and EHS Office | B419: 8470530 | C419: KUST - Facilities Management | D419: 426800 | E419: Motor vehicle registration and inspection charges | F419: 847010 | G419: KUST - Main Campus | H419: Un Specified | I419: 000000 | J419: 847.8470530.1.426800.000000.847010.000000 | K419: Facilities | L419: No Applicable
A420: Administration, Facilities and EHS Office | B420: 8470530 | C420: KUST - Facilities Management | D420: 426800 | E420: Motor vehicle registration and inspection charges | F420: 847020 | G420: KUST- Sas Al Nakhl Campus | H420: FA179-Opex Expense | I420: 200179 | J420: 847.8470530.1.426800.000000.847020.200179 | K420: Facilities | L420: No Applicable
A421: Administration, Facilities and EHS Office | B421: 8470530 | C421: KUST - Facilities Management | D421: 426800 | E421: Motor vehicle registration and inspection charges | F421: 847020 | G421: KUST- Sas Al Nakhl Campus | H421: Un Specified | I421: 000000 | J421: 847.8470530.1.426800.000000.847020.000000 | K421: Facilities | L421: No Applicable
A422: Administration, Facilities and EHS Office | B422: 8470530 | C422: KUST - Facilities Management | D422: 426900 | E422: Postal, courier and other document delivery expenses | F422: 847010 | G422: KUST - Main Campus | H422: FA179-Opex Expense | I422: 200179 | J422: 847.8470530.1.426900.000000.847010.200179 | K422: HR | L422: No Applicable
A423: Administration, Facilities and EHS Office | B423: 8470530 | C423: KUST - Facilities Management | D423: 426900 | E423: Postal, courier and other document delivery expenses | F423: 847020 | G423: KUST- Sas Al Nakhl Campus | H423: Un Specified | I423: 000000 | J423: 847.8470530.1.426900.000000.847020.000000 | K423: HR | L423: No Applicable
A424: HR & Procurement Office | B424: 8470720 | C424: KUST - Procurement | D424: 426900 | E424: Postal, courier and other document delivery expenses | F424: 847001 | G424: KUST - General | H424: FA179-Opex Expense | I424: 200179 | J424: 847.8470720.1.426900.000000.847001.200179 | K424: HR | L424: No Applicable
A425: HR & Procurement Office | B425: 8470720 | C425: KUST - Procurement | D425: 426900 | E425: Postal, courier and other document delivery expenses | F425: 847001 | G425: KUST - General | H425: Un Specified | I425: 000000 | J425: 847.8470720.1.426900.000000.847001.000000 | K425: HR | L425: No Applicable
A426: Senior Vice President, Research Office | B426: 8471130 | C426: KUST - Research Service | D426: 426900 | E426: Postal, courier and other document delivery expenses | F426: 847001 | G426: KUST - General | H426: Un Specified | I426: 000000 | J426: 847.8471130.1.426900.000000.847001.000000 | K426: HR | L426: No Applicable
A427: Academic and Student Services Office | B427: 8471220 | C427: KUST - Registrar | D427: 426900 | E427: Postal, courier and other document delivery expenses | F427: 847001 | G427: KUST - General | H427: FA179-Opex Expense | I427: 200179 | J427: 847.8471220.1.426900.000000.847001.200179 | K427: HR | L427: No Applicable
A428: President's Office | B428: 8470140 | C428: KUST - Communication | D428: 427100 | E428: Public relations | F428: 847001 | G428: KUST - General | H428: FA179-Opex Expense | I428: 200179 | J428: 847.8470140.1.427100.000000.847001.200179 | K428: Communiction & Marketing | L428: Communications
...

Sheet Account Code
B1: Return to Main Page
A3: Account Code | B3: Account Description
A4: 435508 | B4: Laboratory - Scientific
A5: 420550 | B5: Academic Advisory Service
A6: 420900 | B6: Legal services
A7: 421000 | B7: Management consultancy
A8: 425510 | B8: Conferences, seminars and exhibitions and other events: - Local Events
A9: 425770 | B9: Academic Missions - Combined expenses
A10: 425900 | B10: Entertainment and hospitality
A11: 426610 | B11: Computer software licenses
A12: 427710 | B12: Subscriptions and membership fees: Trade organisations
A13: 427900 | B13: Translation and interpretation service
A14: 428090 | B14: Business Travel - Combined expenses
A15: 428400 | B15: Sponsorship expenses/contributions
... A90: 426100 | B90: Freight and shipping costs, not included elsewhere under purchase costs

Sheet Cost Center
A1: Cost Center Code | B1: Cost Center Description | C1: Cost Center Code
A2: 8470110 | B2: KUST - Office of the President | C2: 8470110
A3: 8470120 | B3: KUST - Audit & Compliance | C3: 8470120
A4: 8470130 | B4: KUST - Institutional Research & Planning | C4: 8470130
A5: 8470140 | B5: KUST - Communication | C5: 8470140
A6: 8470150 | B6: KUST - General Counsel | C6: 8470150
A7: 8470210 | B7: KUST - Khalifa University of Science & Technology - General Administration | C7: 8470210
A8: 8470220 | B8: KUST - Office of the Provost | C8: 8470220
A9: 8470230 | B9: KUST - Graduate Studies | C9: 8470230
A10: 8470305 | B10: KUST - Dean Of Engineering | C10: 8470305
A11: 8470310 | B11: KUST - Aerospace Engineering | C11: 8470310
A12: 8470315 | B12: KUST - Biomedical Engineering | C12: 8470315
A13: 8470320 | B13: KUST - Chemical Engineering | C13: 8470320
... A61: 8471121 | B61: KUST - Petroleum Institute | C61: 8471121

Sheet Strategic Objectives 2023
B2: Khalifa University Strategic Objectives and Targets 2023
B5: # | C5: Objectives | D5: Key Performance Indicators | E5: Target 2022 | F5: Owner
B6: 1 | C6: Widen access to students with outstanding academic potential | D6: Total students enrolment | E6: 4703 | F6: Senior VP Academic and Student Services | G6: 8471200 - 8471299
B7: 2 | C7: Align academic programs with the local and global labor market needs | D7: % of new established programs aligned to the global and local market needs starting from 2021 | E7: 1 | F7: Provost | G7: 8470300 - 8470499 & 8470230 , 8471305
B8: 3 | C8: Develop a new learning outcomes assessment framework at the course, programs, and institutional levels | D8: % of assessed programs learning outcomes | E8: 1 | F8: EVP/Director IRP | G8: 8470100 -8470199
B9: 4 | C9: Develop holistic internship programs | D9: Number of experiential learning programs a student should attend before graduating | E9: 2 | F9: Senior VP Academic and Student Services | G9: 8471200 - 8471299
B10: 5 | C10: Develop a career guidance system | D10: % of graduating students who are engaged in institutionalized career guidance sessions | E10: 1 | F10: Senior VP Academic and Student Services | G10: 8471200 - 8471299
B11: 6 | C11: Develop the university innovation and entrepreneurship system | D11: Innovation and entrepreneurship ecosystem | E11: Complete | F11: Provost | G11: 8470300 - 8470499 & 8470230 , 8471305
B12: 7 | C12: Develop a life-long culture of community service beyond the classroom | D12: Number of community services activities | E12: 30 | F12: Senior VP Academic and Student Services | G12: 8471200 - 8471299
B13: 8 | C13: Establish a mobility program for students, faculty, researchers and staff | D13: % of the students participate in exchange programs annually | E13: 0.05 | F13: Senior VP Academic and Student Services | G13: 8471200 - 8471299
B14: 9 | C14: Establish a mobility program for students, faculty, researchers and staff | D14: % of the Faculty participate in exchange programs annually | E14: 0.05 | F14: Provost | G14: 8470300 - 8470499 & 8470230 , 8471305
B15: 10 | C15: Establish a mobility program for students, faculty, researchers and staff | D15: % of the staff participate in exchange programs annually | E15: 0.05 | F15: EVP/Chief of Staff | G15: 8470100 -8470199
B16: 11 | C16: Align the postgraduates programs with the research strategy | D16: % of aligned postgraduate programs and research strategy | E16: 1 | F16: Provost | G16: 8470300 - 8470499 & 8470230 , 8471305
B17: 12 | C17: Develop a comprehensive competitive internal research funding program | D17: % of faculty received internal research funds | E17: 0.25 | F17: Senior VP Research and Development | G17: 8471100 - 8471199
B18: 13 | C18: Diversify and increase external research funds | D18: % of the external research expenditure from total expenditure on research | E18: 0.6 | F18: Senior VP Research and Development/VP Finance | G18: 8471100 - 8471199
B19: 14 | C19: Strengthen research ethical culture framework across the university | D19: % of the university staff attended training programs on research ethics | E19: 1 | F19: Senior VP Research and Development | G19: 8471100 - 8471199
B20: 15 | C20: Review and revise as needed the research strategic plan | D20: Implementing the updated research strategic plan | E20: Complete | F20: Senior VP Research and Development | G20: 8471100 - 8471199
B21: 16 | C21: Attract and organize international conferences and summits | D21: Number of conferences/summits per year | E21: 8 | F21: Provost | G21: 8470300 - 8470499 & 8470230 , 8471305
B22: 17 | C22: Increase number of postgraduate students | D22: % of postgraduate students from the total student enrolment | E22: 0.3 | F22: Provost | G22: 8470300 - 8470499 & 8470230 , 8471305
B23: 18 | C23: Develop a multidimensional program to attract and retain diverse outstanding students | D23: % international students | E23: 0.3 | F23: Senior VP Academic and Student Services | G23: 8471200 - 8471299
B24: 19 | C24: Recruit and retain high caliber faculty, researchers and staff | D24: % of the newly recruited faculty with h-5index >= 4 | E24: 0.8 | F24: Provost | G24: 8470300 - 8470499 & 8470230 , 8471305
B25: 20 | C25: Realize a sustainable , healthy and safe campus environment for all community members | D25: % compatibility with the national standards** | E25: 1 | F25: SVP Support Services | G25: 8470500 -8470999
B26: 21 | C26: Enhance the communication plan and outreach activities | D26: Update and enhance the Communication and marketing plan | E26: Complete | F26: EVP/Director Marketing and Comm | G26: 8470100 -8470199
B27: 22 | C27: Increase publications in journals with high impact factor | D27: Average number of publications indexed in Scopus per faculty | E27: 4 | F27: Provost | G27: 8470300 - 8470499 & 8470230 , 8471305
B28: 23 | C28: Increase filed and issued patents in USPTO and PCT | D28: Number of annual registered patents | E28: 40 | F28: Senior VP Research and Development | G28: 8471200 - 8471299
B29: 24 | C29: Build partnerships with local and international universities | D29: Number of new strategic partnerships with international universities/per year | E29: 8 | F29: EVP/Chief of Staff | G29: 8470100 -8470199
B30: 25 | C30: Develop competitive fellowship programs for students | D30: % of sponsored students by external entities | E30: 0.15 | F30: Dean of Postgraduate School | G30: 8470300
B31: 26 | C31: Establish and manage start-up companies | D31: Total number of start-up companies that have spun out of KU projects/research | E31: 20 | F31: Senior VP Research and Development | G31: 8471100 - 8471199
B32: 27 | C32: Create diversified financial resources for self sustaining university | D32: % of the university revenue from external funding sources from total revenue | E32: 0.1 | F32: Senior VP Research and Development/VP Finance | G32: 8471100 - 8471199
B33: 28 | C33: Design and implement professional development programs for researchers, faculty, and staff to contribute to the university strategic plan | D33: % of the university human capital who received documented and structured training | E33: 1 | F33: SVP support services/VP HR and Procurement Al Kathiri/Provost | G33: 8470720 - 730
B34: 29 | C34: Ensure the university sustainability | D34: % of employed nationals out of the total number of employees | E34: 0.35 | F34: SVP support services/VP HR and Procurement | G34: 8470720 - 730
B35: 30 | C35: Utilize state-of-the-art technologies and facilities in an optimal and efficient manner | D35: % utilization rate of the university facilities | E35: 1 | F35: SVP Support Services/CEO Ankabut and VP facilities | G35: 8470810
B36: 31 | C36: Promote a working culture of excellence and accountability | D36: Process excellence framework | E36: Complete | F36: VP Finance | G36: 8470620-630
B37: 32 | C37: Provide reliable, accurate and timely reports to different stakeholders | D37: Holistic university information system | E37: Complete | F37: EVP/Director IRP and CEO Ankabut | G37: 8470100 -8470199 / 8470810
B38: 33 | C38: Develop and implement of performance management system across the university | D38: Automated performance management system | E38: Complete | F38: EVP/Director IRP and CEO Ankabut | G38: 8470100 -8470199 / 8470810

Sheet Supporting Document

Sheet Other 
A1: Budget Type | B1: Expenditure Frequency | D1: Future1 | E1: Future1 Description | F1: Future1
A2: Strategic New Initiative | B2: Recurring | D2: 847001 | E2: KUST - General | F2: 847001
A3: Regular operations | B3: Non-recurring | D3: 847010 | E3: KUST - Main Campus | F3: 847010
D4: 847020 | E4: KUST- Sas Al Nakhl Campus | F4: 847020
D5: 847030 | E5: KUST- Masdar city campus | F5: 847030
D6: 847951 | E6: COVID-19 Pandemic | F6: 847951
D7: 847015 | E7: Student Related Costs | F7: 847015
D8: 847040 | E8: KUST - GRC Operations | F8: 847040
D9: 847078 | E9: Research Software renewal | F9: 847078

Sheet Cost Center Group
A1: Cost Center | B1: Cost Center Code - Group | C1: Cost Center Description
A2: 8470405 | B2: College of Arts & Science | C2: KUST - Dean Of Arts & Science
A3: 8470410 | B3: College of Arts & Science | C3: KUST - Institute of International & Civil Security
A4: 8470415 | B4: College of Arts & Science | C4: KUST - Chemistry
A5: 8470425 | B5: College of Arts & Science | C5: KUST - Physics
A6: 8470430 | B6: College of Arts & Science | C6: KUST - Preparatory Program
A7: 8470435 | B7: College of Arts & Science | C7: KUST - Department of English
A8: 8470440 | B8: College of Arts & Science | C8: KUST - Humanities & Social Sciences
A9: 8470445 | B9: College of Arts & Science | C9: KUST - Mathematics
A10: 8470450 | B10: College of Arts & Science | C10: KUST - Earth Science
A11: 8470530 | B11: Administration, Facilities and EHS Office | C11: KUST - Facilities Management
A12: 8470520 | B12: Administration, Facilities and EHS Office | C12: KUST - Environment, Health & Safety
A13: 8470540 | B13: Administration, Facilities and EHS Office | C13: KUST - Administration
... A57: 8471122 | B57: Senior Vice President, Research Office | C57: kust- Masdar Institute
