Workbook

Sheet Sheet5
A1: Future2 Description | B1: FA180-Capex Expense
A3: Row Labels | B3: 2021 Revised Budget | C3: 2021 Actual Amount | D3: 2021 PR | E3: 2021 PO | F3: 2020 Revis.ed Budget | G3: 2020 Actual Amount
A4: KUST - Aerospace Engineering | B4: 759151 | C4: 4619 | D4: 637243.48 | E4: 98213 | F4: 434000 | G4: 433999
A5: KUST - Ankabut office | B5: 4272296 | C5: -379409 | D5: 3948857 | E5: 94598 | F5: 5949149 | G5: 5927842.4
A6: KUST - Biomedical Engineering | B6: 109201 | D6: 0 | E6: 108878.38 | F6: 187000 | G6: 187000
A7: KUST - Center for Teaching & Learning | F7: 0 | G7: 0
A8: KUST - Chemical Engineering | F8: 0 | G8: 0
A9: KUST - Chemistry | B9: 781895 | C9: 13000 | D9: 760900 | E9: 0 | F9: 0 | G9: 0
A10: KUST - Civil Engineering | B10: 224144 | C10: 125060 | D10: 46550 | E10: 39743 | F10: 1585072 | G10: 1525688
A11: KUST - Communication | B11: 200000 | C11: 192455 | D11: 0 | E11: 0 | F11: 0 | G11: 0
A12: KUST - Dean Of Arts & Science
A13: KUST - Dean Of Engineering | F13: 2550 | G13: 2550.19
A14: KUST - Dean Of Medicine | B14: 27422265 | C14: 4474163.7 | D14: 3427896 | E14: 9410471.6 | F14: 19467391 | G14: 17595457
A15: KUST - Department of English | F15: 0 | G15: 0
A16: KUST - Earth Science | F16: 0 | G16: 0
A17: KUST - Electrical & Computer Engineering | B17: 233948 | D17: 232000 | F17: 585250 | G17: 585058.63
A18: KUST - Environment, Health & Safety | F18: 502000 | G18: 501601.43
A19: KUST - Executive Vice President Office | F19: 0 | G19: 0
A20: KUST - Facilities Management | B20: 25061676 | C20: 2067526.2 | D20: 22185794 | E20: 652506 | F20: 34240670 | G20: 34247975
A21: KUST - Finance Operations
A22: KUST - Graduate Studies
A23: KUST - Human Resources | B23: 110494 | C23: 18149.5 | D23: 0 | E23: 0 | F23: 29334 | G23: 29334.5
A24: KUST - Humanities & Social Sciences
A25: KUST - Industrial & Systems Engineering | B25: 80120 | D25: 49000 | F25: 283271 | G25: 283271
A26: KUST - Libraries
A27: KUST - Mathematics
A28: KUST - Mechanical Engineering | B28: 269248 | D28: 193435 | E28: 69443 | F28: 829817 | G28: 822867.91
A29: KUST - Nuclear Engineering | B29: 139983 | D29: 62441 | E29: 77504.46 | F29: 86000 | G29: 0
A30: KUST - Office of the President | F30: 2981521 | G30: 39940.11
A31: KUST - Office of the Provost | B31: 160720 | C31: 10720 | E31: 150000 | F31: 1641944 | G31: 1481224
A32: KUST - Petroleum Engineering | B32: 772173 | D32: 763616.7 | F32: 585128 | G32: 584893
A33: KUST - Physics | B33: 2912920 | C33: 26928 | D33: 1990500 | E33: 868629.7 | F33: 0 | G33: 0
A34: KUST - Preparatory Program | F34: 0 | G34: 0
A35: KUST - Research Computing | B35: 6795858 | C35: 9510 | D35: 6628812.2 | E35: 0 | F35: 5546000 | G35: 5545455
A36: KUST - Research Laboratories | B36: 15882373 | C36: 402222.34 | D36: 14314209 | E36: 764750.27 | F36: 10813606 | G36: 9475691.4
A37: KUST - Research Service | B37: 0 | F37: 3338153 | G37: 3312663.8
A38: KUST - Student Enrollment
A39: KUST - Student Life | F39: 1964000 | G39: 1963930
A40: KUST - SVP/ Academic & Student Services Office
A41: KUST - SVP/ Research & Development Office | F41: 2998678 | G41: 0
A42: KUST - University Sponsored Research | B42: 1606304 | C42: 593236.71 | D42: 456508.59 | E42: 0 | F42: 0 | G42: 0
A43: KUST - Biology
A44: KUST - Computer Science
A45: Grand Total | B45: 87794769 | C45: 7558181.5 | D45: 55697762 | E45: 12334737 | F45: 94050534 | G45: 84546442

Sheet Pivot CH1 & Ch2 & Ch3
N2: TO DOF
A3: Future2 Description | B3: Cost Center Code - Group | C3: 2018 Actual | D3: 2019 Actual | E3: 2020 Actual | F3: 2021 R. Budget | G3: 2021 Actual | H3: 2021 PR | I3: 2021 PO | J3: 2022 Budget | K3: 2022 Budget Scenario 90% | L3: 2022 Budget Scenario 80% | M3: 2022 Budget Scenario 70% | N3: 2022 Budget Finance Recommendation | O3: 2023 Budget | P3: 2023 Budget Finance Recommendation | Q3: 2024 Budget | R3: 2024 Budget Finance Recommendation
A4: FA178-Manpower Expense | B4: Manpower | C4: 666857437 | D4: 734104574 | E4: 541385100 | F4: 583465683 | G4: 3.1287481e+08 | H4: 577263.62 | I4: 120262.4 | J4: 624050000 | K4: 561645000 | L4: 499240000 | M4: 436835000 | N4: 614050000 | O4: 624050000 | P4: 624050000 | Q4: 624050000 | R4: 624050000 | S4: =GETPIVOTDATA(" 2022 Budget Finance Recommendation",$A$3,"Cost Center Code - Group","Manpower","Future2 Description","FA178-Manpower Expense")/GETPIVOTDATA(" 2021 R. Budget",$A$3,"Cost Center Code - Group","Manpower","Future2 Description","FA178-Manpower Expense") -> 1.0524184 | T4: =GETPIVOTDATA(" 2022 Budget Finance Recommendation",$A$3,"Cost Center Code - Group","Manpower","Future2 Description","FA178-Manpower Expense")-GETPIVOTDATA(" 2021 R. Budget",$A$3,"Cost Center Code - Group","Manpower","Future2 Description","FA178-Manpower Expense") -> 30584317
A5: FA179-Opex Expense | C5: 4.1157745e+08 | D5: 4.5345466e+08 | E5: 4.3620813e+08 | F5: 398910380 | G5: 1.2931363e+08 | H5: 53383699 | I5: 31493207 | J5: 7.9647721e+08 | K5: 7.0897699e+08 | L5: 6.3020177e+08 | M5: 5.5142654e+08 | N5: 6.708027e+08 | O5: 8.7845816e+08 | P5: 7.3663227e+08 | Q5: 9.1822665e+08 | R5: 8.0277819e+08 | S5: =GETPIVOTDATA(" 2022 Budget Finance Recommendation",$A$3,"Future2 Description","FA179-Opex Expense")/GETPIVOTDATA(" 2021 R. Budget",$A$3,"Future2 Description","FA179-Opex Expense") -> 1.6815875 | T5: =GETPIVOTDATA(" 2022 Budget Finance Recommendation",$A$3,"Future2 Description","FA179-Opex Expense")-GETPIVOTDATA(" 2021 R. Budget",$A$3,"Future2 Description","FA179-Opex Expense") -> 2.7189232e+08
A6: FA180-Capex Expense | C6: 50440080 | D6: 1.5695179e+08 | E6: 84546442 | F6: 87794769 | G6: 7558181.5 | H6: 55697762 | I6: 12334737 | J6: 4.395527e+08 | K6: 3.9330243e+08 | L6: 3.4960216e+08 | M6: 3.0590189e+08 | N6: 1.2478174e+08 | O6: 1.7446565e+08 | P6: 92930733 | Q6: 82288069 | R6: 96961077 | S6: =GETPIVOTDATA(" 2022 Budget Finance Recommendation",$A$3,"Future2 Description","FA180-Capex Expense")/GETPIVOTDATA(" 2021 R. Budget",$A$3,"Future2 Description","FA180-Capex Expense") -> 1.421289 | T6: =GETPIVOTDATA(" 2022 Budget Finance Recommendation",$A$3,"Future2 Description","FA180-Capex Expense")-GETPIVOTDATA(" 2021 R. Budget",$A$3,"Future2 Description","FA180-Capex Expense") -> 36986974
A7: Grand Total | C7: 1.128875e+09 | D7: 1.344511e+09 | E7: 1.0621397e+09 | F7: 1070170832 | G7: 4.4974662e+08 | H7: 1.0965872e+08 | I7: 43948207 | J7: 1.8600799e+09 | K7: 1.6639244e+09 | L7: 1.4790439e+09 | M7: 1.2941634e+09 | N7: 1.4096344e+09 | O7: 1.6769738e+09 | P7: 1.453613e+09 | Q7: 1.6245647e+09 | R7: 1.5237893e+09
F10: 45000000 | J10: CMHS | N10: -45000000
F11: 80000000 | J11: UG | N11: -80000000
F12: =GETPIVOTDATA(" 2021 R. Budget",$A$3)+F10+F11 -> 1195170832 | J12: PG | N12: -40000000
J13: Balance | N13: =GETPIVOTDATA(" 2022 Budget Finance Recommendation",$A$3)+N11+N10+N12 -> 1.2446344e+09
N16: =GETPIVOTDATA(" 2022 Budget Finance Recommendation",$A$3)/F12 -> 1.1794418
A19: Budget Chapters | B19: 2018 Actual | C19: 2019 Actual | D19: 2020 Actual | E19: 2021 R. Budget | F19: 2022 Budget | G19: 2023 Budget | H19: 2024 Budget
A20: CH1-Manpower | B20: 666857437 | C20: 734104574 | D20: 541385100 | E20: 583465683 | F20: 624050000 | G20: 624050000 | H20: 624050000
A21: CH2-Opex | B21: 4.1157745e+08 | C21: 4.5345466e+08 | D21: 4.3620813e+08 | E21: 398910380 | F21: 7.9647721e+08 | G21: 8.7845816e+08 | H21: 9.1822665e+08
A22: CH3-Capex | B22: 50440080 | C22: 1.5695179e+08 | D22: 84546442 | E22: 87794769 | F22: 4.395527e+08 | G22: 1.7446565e+08 | H22: 82288069
A23: Grand Total | B23: =SUM(B20:B22) -> 1.128875e+09 | C23: =SUM(C20:C22) -> 1.344511e+09 | D23: =SUM(D20:D22) -> 1.0621397e+09 | E23: =SUM(E20:E22) -> 1070170832 | F23: =SUM(F20:F22) -> 1.8600799e+09 | G23: =SUM(G20:G22) -> 1.6769738e+09 | H23: =SUM(H20:H22) -> 1.6245647e+09
A29: Budget Chapters | B29: 2021 R. Budget | C29: 2021 Actual | D29: 2021 PR | E29: 2021 PO | F29: 2021 Fund Available
A30: CH1-Manpower | B30: 583465683 | C30: 3.1287481e+08 | D30: 577263.62 | E30: 120262.4 | F30: =B30-C30-D30-E30 -> 2.6989335e+08
A31: CH2-Opex | B31: 398910380 | C31: 1.2931363e+08 | D31: 53383699 | E31: 31493207 | F31: =B31-C31-D31-E31 -> 1.8471984e+08
A32: CH3-Capex | B32: 87794769 | C32: 7558181.5 | D32: 55697762 | E32: 12334737 | F32: =B32-C32-D32-E32 -> 12204088
A33: Grand Total | B33: =SUM(B30:B32) -> 1070170832 | C33: =SUM(C30:C32) -> 4.4974662e+08 | D33: =SUM(D30:D32) -> 1.0965872e+08 | E33: =SUM(E30:E32) -> 43948207 | F33: =SUM(F30:F32) -> 4.6681728e+08
A40: Budget Chapters | B40: 2021 R. Budget | C40: 2022 Budget | D40: 2022 Budget Finance Recommendation | E40: 2023 Budget | F40: 2023 Budget Finance Recommendation | G40: 2024 Budget | H40: 2024 Budget Finance Recommendation
A41: CH1-Manpower | B41: 583465683 | C41: 624050000 | D41: 614050000 | E41: 624050000 | F41: 624050000 | G41: 624050000 | H41: 624050000
A42: CH2-Opex | B42: 398910380 | C42: 7.9647721e+08 | D42: 6.708027e+08 | E42: 8.7845816e+08 | F42: 7.3663227e+08 | G42: 9.1822665e+08 | H42: 8.0277819e+08
A43: CH3-Capex | B43: 87794769 | C43: 4.395527e+08 | D43: 1.2478174e+08 | E43: 1.7446565e+08 | F43: 92930733 | G43: 82288069 | H43: 96961077
A44: Grand Total | B44: =SUM(B41:B43) -> 1070170832 | C44: =SUM(C41:C43) -> 1.8600799e+09 | D44: =SUM(D41:D43) -> 1.4096344e+09 | E44: =SUM(E41:E43) -> 1.6769738e+09 | F44: =SUM(F41:F43) -> 1.453613e+09 | G44: =SUM(G41:G43) -> 1.6245647e+09 | H44: =SUM(H41:H43) -> 1.5237893e+09

Sheet CH1
A1: Chapter Summary
A3: Ledger Name | B3: Chapter Name | C3: 2021 Annual Budget | D3: 2021 Revised Budget | E3: 2021 Actual Amount | F3: 2021 PR | G3: 2021 PO | H3: 2021 Fund Available
A4: KUST Ledger | B4: 1 Personnel Costs | C4: 563874000 | D4: 583465683 | E4: 3.1287481e+08 | F4: 577263.62 | G4: 120262.4 | H4: 2.6989335e+08
B5: 2 Other Operating Costs | C5: 418640000 | D5: 398910380 | E5: 1.3203661e+08 | F5: 52994194 | G5: 29519382 | H5: 1.8436019e+08
B6: 3 Capital Payments | C6: 87207000 | D6: 87794769 | E6: 7708181.5 | F6: 55329862 | G6: 12538999 | H6: 12217726
A7: Grand Total | C7: 1069721000 | D7: 1070170832 | E7: 4.526196e+08 | F7: 1.0890132e+08 | G7: 42178644 | H7: 4.6647127e+08

Sheet Pivot Ch2
A1: Future2 Description | B1: FA179-Opex Expense
A3: Cost Center Code - Group | B3: 2018 Actual | C3: 2019 Actual | D3: 2020 Actual | E3: 2021 R. Budget | F3: 2021 Actual | G3: 2021 PR | H3: 2021 PO | I3: 2022 Budget | J3: 2022 Budget Scenario 90% | K3: 2022 Budget Scenario 80% | L3: 2022 Budget Scenario 70% | M3: 2022 Budget Finance Recommendation | N3: 2023 Budget | O3: 2023 Budget Finance Recommendation | P3: 2024 Budget | Q3: 2024 Budget Finance Recommendation
A4: Senior Vice President, Research Office | B4: 50355414 | C4: 86138314 | D4: 1.1373651e+08 | E4: 118471878 | F4: 43791752 | G4: 13759031 | H4: 9087279.5 | I4: 2.135858e+08 | J4: 1.9222722e+08 | K4: 1.7086864e+08 | L4: 1.4951006e+08 | M4: 1.5050129e+08 | N4: 1.8720002e+08 | O4: 1.3676079e+08 | P4: 1.5396619e+08 | Q4: 1.406961e+08
A5: Graduate Studies | B5: 59904650 | C5: 69759619 | D5: 65711376 | E5: 104483969 | F5: 40905424 | H5: 0 | I5: 178231406 | J5: 1.6040827e+08 | K5: 1.4258512e+08 | L5: 1.2476198e+08 | M5: 150618667 | N5: 219371651 | O5: 167591982 | P5: 2.4392202e+08 | Q5: 186410819
A6: Academic and Student Services Office | B6: 1.8012185e+08 | C6: 1.0242806e+08 | D6: 80592865 | E6: 38514134 | F6: 14455242 | G6: 2557216 | H6: 6173087.8 | I6: 1.4416226e+08 | J6: 1.2974603e+08 | K6: 1.1532981e+08 | L6: 1.0091358e+08 | M6: 1.1760326e+08 | N6: 1.7668398e+08 | O6: 1.4600298e+08 | P6: 1.9877588e+08 | Q6: 1.6365788e+08
A7: College of Medicine & Health Sciences | B7: 3391925.2 | C7: 6964244.4 | D7: 13219211 | E7: 17266074 | F7: 7938865.9 | G7: 1512517.1 | H7: 251075.5 | I7: 87599982 | J7: 77759983 | K7: 69119985 | L7: 60479987 | M7: 85436717 | N7: 1.0541561e+08 | O7: 1.0274461e+08 | P7: 1.2350534e+08 | Q7: 1.2021116e+08
A8: Administration, Facilities and EHS Office | B8: 67137093 | C8: 79045704 | D8: 67113228 | E8: 70236116 | F8: 13384126 | G8: 23785047 | H8: 9787477 | I8: 68823639 | J8: 61941275 | K8: 55058911 | L8: 48176548 | M8: 68823639 | N8: 78028823 | O8: 78028823 | P8: 78307016 | Q8: 78307016
A9: President's Office | B9: 13723360 | C9: 42423014 | D9: 28084938 | E9: 7179350 | F9: 2150653 | G9: 3029213.9 | H9: 601972.5 | I9: 33353835 | J9: 30018451 | K9: 26683068 | L9: 23347684 | M9: 31353835 | N9: 33744388 | O9: 33044388 | P9: 35616380 | Q9: 34116380
A10: Information Technology/ANKABUT | B10: 25090427 | C10: 36724659 | D10: 57480385 | E10: 33281345 | F10: 4265401.8 | G10: 7625202.4 | H10: 4804417.4 | I10: 32355401 | J10: 29119861 | K10: 25884321 | L10: 22648781 | M10: 32355401 | N10: 37434321 | O10: 37434321 | P10: 40279229 | Q10: 40279229
A11: College of Arts & Science | B11: 2320570.8 | C11: 3165328.2 | D11: 1656685.5 | E11: 2461725 | F11: 255636.46 | G11: 46754.46 | H11: 247334.44 | I11: 14070890 | J11: 11520801 | K11: 10240712 | L11: 8960623 | M11: 12880240 | N11: 16817192 | O11: 14291642 | P11: 15601592 | Q11: 13941592
A12: College of Engineering | B12: 6242088.2 | C12: 7538445.4 | D12: 5920790.6 | E12: 4632949 | F12: 1331639.2 | G12: 747237.29 | H12: 500008.16 | I12: 13353788 | J12: 12018409 | K12: 10683030 | L12: 9347651.6 | M12: 13353788 | N12: 13592078 | O12: 13592078 | P12: 17352406 | Q12: 17352406
A13: Provost | I13: 6255000 | M13: 3190650 | N13: 6255000 | O13: 3225550 | P13: 6255000 | Q13: 3160000
A14: HR & Procurement Office | B14: 2324810.4 | C14: 18766991 | D14: 1529905.5 | E14: 1206264 | F14: 402070.04 | G14: 196800.53 | H14: 40555 | I14: 3018400 | J14: 2716560 | K14: 2414720 | L14: 2112880 | M14: 3018400 | N14: 2904000 | O14: 2904000 | P14: 2904000 | Q14: 2904000
A15: Finance & Business Development Office | B15: 965265.4 | C15: 500280.96 | D15: 1162237.7 | E15: 984076 | F15: 397042 | G15: 31680 | I15: 1164440 | J15: 1047996 | K15: 931552 | L15: 815108 | M15: 1164440 | N15: 432480 | O15: 432480 | P15: 442180 | Q15: 442180
A16: Continuing Education | B16: 0 | C16: 0 | D16: 0 | E16: 192500 | F16: 35781.5 | G16: 93000 | I16: 502370 | J16: 452133 | K16: 401896 | L16: 351659 | M16: 502370 | N16: 578620 | O16: 578620 | P16: 1299424 | Q16: 1299424
A17: Grand Total | B17: 4.1157745e+08 | C17: 4.5345466e+08 | D17: 4.3620813e+08 | E17: 398910380 | F17: 1.2931363e+08 | G17: 53383699 | H17: 31493207 | I17: 7.9647721e+08 | J17: 7.0897699e+08 | K17: 6.3020177e+08 | L17: 5.5142654e+08 | M17: 6.708027e+08 | N17: 8.7845816e+08 | O17: 7.3663227e+08 | P17: 9.1822665e+08 | Q17: 8.0277819e+08

Sheet Pivot Ch2 Account
A1: Future2 Description | B1: FA179-Opex Expense
A3: Row Labels | B3: 2018 Actual | C3: 2019 Actual | D3: 2020 Actual | E3: 2021 R. Budget | F3: 2021 Actual | G3: 2021 PR | H3: 2021 PO | I3: 2022 Budget | J3: 2022 Budget Scenario 90% | K3: 2022 Budget Scenario 80% | L3: 2022 Budget Scenario 70% | M3: 2022 Budget Finance Recommendation | N3: 2023 Budget | O3: 2023 Budget Finance Recommendation | P3: 2024 Budget | Q3: 2024 Budget Finance Recommendation
A4: Postgraduate Student Salaries | B4: 0 | C4: 0 | D4: 26246724 | E4: 112772759 | F4: 45891287 | I4: 203710434 | J4: 1.8333939e+08 | K4: 1.6296835e+08 | L4: 1.425973e+08 | M4: 176097695 | N4: 259296044 | O4: 207516375 | P4: 2.9734536e+08 | Q4: 239834163
A5: Scientific | B5: 39989703 | C5: 64438059 | D5: 93594271 | E5: 95910011 | F5: 39988888 | G5: 4008035.6 | H5: 3655194.6 | I5: 1.7960203e+08 | J5: 1.6164183e+08 | K5: 1.4368162e+08 | L5: 1.2572142e+08 | M5: 1.1651752e+08 | N5: 1.5741575e+08 | O5: 1.0697652e+08 | P5: 1.2024661e+08 | Q5: 1.0697652e+08
A6: Student stipend | B6: 94937565 | C6: 1.0947368e+08 | D6: 72208398 | I6: 106236000 | J6: 95612400 | K6: 84988800 | L6: 74365200 | M6: 79677000 | N6: 123039000 | O6: 92358000 | P6: 140802750 | Q6: 105684750
A7: Academic Collaborative Partnership Services | B7: 167121.5 | C7: 120474.4 | D7: 105415.14 | E7: 409202 | F7: 4040.3 | I7: 40162080 | J7: 34345872 | K7: 30529664 | L7: 26713456 | M7: 37225230 | N7: 39162080 | O7: 37560130 | P7: 39162080 | Q7: 36694580
A8: Bldg maintenance-Business premises | B8: 26063815 | C8: 31663888 | D8: 30543870 | E8: 26125691 | F8: 1420463.6 | G8: 19352824 | H8: 2594008.2 | I8: 24034389 | J8: 21630950 | K8: 19227511 | L8: 16824072 | M8: 24034389 | N8: 32832695 | O8: 32832695 | P8: 33088495 | Q8: 33088495
A9: Computer software licenses | B9: 8039197.1 | C9: 10369252 | D9: 10814022 | E9: 15353817 | F9: 1775371.7 | G9: 8556263.3 | H9: 2802726.4 | I9: 19077946 | J9: 17035151 | K9: 15142357 | L9: 13249562 | M9: 19027946 | N9: 20762835 | O9: 20712835 | P9: 22165121 | Q9: 22115121
A10: Laboratory equipment | B10: 5482693.5 | C10: 14016405 | D10: 13658821 | E10: 15553556 | F10: 2475706.4 | G10: 7209968.4 | H10: 5192617.8 | I10: 18551535 | J10: 16426381 | K10: 14601228 | L10: 12776074 | M10: 18551535 | N10: 19754055 | O10: 19754055 | P10: 21000545 | Q10: 21000545
A11: Library books | B11: 536647.68 | C11: 14570173 | D11: 11597337 | E11: 12976004 | F11: 7530590 | G11: 1585181.6 | H11: 3170562.5 | I11: 17362029 | J11: 15625826 | K11: 13889623 | L11: 12153420 | M11: 17362029 | N11: 19074757 | O11: 19074757 | P11: 20959938 | Q11: 20959938
A12: Electricity consumption charges | B12: 32233264 | C12: 28477238 | D12: 24742245 | E12: 16047749 | F12: 5972680.9 | I12: 15465717 | J12: 13919145 | K12: 12372574 | L12: 10826002 | M12: 15465717 | N12: 15465717 | O12: 15465717 | P12: 15465717 | Q12: 15465717
A13: Manpower supply | B13: 8402324.3 | C13: 5295365.6 | D13: 27841721 | E13: 9124106 | F13: 1184032.6 | G13: 460004 | H13: 3431819.2 | I13: 14743480 | J13: 12189132 | K13: 10834784 | L13: 9480435.9 | M13: 13543480 | N13: 15733740 | O13: 14293740 | P13: 16842912 | Q13: 15114912
A14: IT Systems & Support expenses | B14: 5695281.6 | C14: 851424.58 | D14: 1444211.6 | E14: 2100000 | F14: 300000 | G14: 798441 | I14: 13996443 | J14: 12596799 | K14: 11197154 | L14: 9797510.1 | M14: 13967178 | N14: 16414809 | O14: 16414809 | P14: 19710778 | Q14: 19710778
A15: Laboratory - Scientific | B15: 5667447.1 | C15: 7342951.6 | D15: 2473540 | E15: 2420637 | F15: 1409865.5 | G15: 555102.68 | H15: 266424.85 | I15: 11929794 | J15: 10129315 | K15: 9003835.4 | L15: 7878356 | M15: 10739144 | N15: 9032195 | O15: 6506645 | P15: 7238224 | Q15: 5578224
A16: Student Transport | B16: 7066550.8 | C16: 9622796 | D16: 3208631.9 | E16: 6886815 | F16: -22192.57 | G16: 1 | H16: 329381.77 | I16: 10315850 | J16: 9284265 | K16: 8252680 | L16: 7221095 | M16: 10315850 | N16: 10243400 | O16: 10243400 | P16: 10255900 | Q16: 10255900
A17: Conferences, seminars and exhibitions and other events: - Local Events | B17: 9149933.7 | C17: 22006418 | D17: 4201523.9 | E17: 3408789 | F17: 1358731.1 | G17: 1439000 | H17: 257157.5 | I17: 9824821 | J17: 8824338.9 | K17: 7843856.8 | L17: 6863374.7 | M17: 9814821 | N17: 10282383 | O17: 10272383 | P17: 12239237 | Q17: 12229237
A18: Security service | B18: 7859664.9 | C18: 9750717.3 | D18: 9751370 | E18: 7496200 | F18: 1254059.8 | G18: 3366683.3 | H18: 2462249.8 | I18: 9388680 | J18: 8449812 | K18: 7510944 | L18: 6572076 | M18: 9388680 | N18: 9388680 | O18: 9388680 | P18: 9388680 | Q18: 9388680
A19: Cleaning Services: Business premises | B19: 11085217 | C19: 10507188 | D19: 11146117 | E19: 8284070 | F19: 2995204.4 | G19: 5.8207661e-11 | H19: 3285674.5 | I19: 8921787.4 | J19: 8029608.6 | K19: 7137429.9 | L19: 6245251.1 | M19: 8921787.4 | N19: 8921787.3 | O19: 8921787.3 | P19: 8921787.4 | Q19: 8921787.4
A20: Advertising Services (General) | B20: 581045.24 | C20: 5913007.8 | D20: 2482845.9 | E20: 3537655 | F20: 620757.53 | G20: 1894366 | H20: 0 | I20: 7070992.4 | J20: 6363893.2 | K20: 5656793.9 | L20: 4949694.7 | M20: 7070992.4 | N20: 7927000 | O20: 7927000 | P20: 8403333 | Q20: 8403333
A21: Student Internship | B21: 363847.16 | C21: 766232.81 | D21: 263497.54 | E21: 59066 | I21: 6572388.9 | J21: 5915150 | K21: 5257911.1 | L21: 4600672.2 | M21: 6572388.9 | N21: 6900008.3 | O21: 6900008.3 | P21: 7242383.8 | Q21: 7242383.8
A22: Academic Missions - Combined expenses | B22: 2296576.1 | C22: 2740427.7 | D22: 815412.15 | E22: 1459712 | F22: 53465.38 | I22: 6430000 | J22: 5715000 | K22: 5080000 | L22: 4445000 | M22: 6430000 | N22: 6511000 | O22: 6511000 | P22: 6783040 | Q22: 6783040
A23: Student medical insurance | B23: 4336.82 | C23: 0 | D23: 0 | E23: 1 | I23: 4816800 | J23: 4335120 | K23: 3853440 | L23: 3371760 | M23: 4816800 | N23: 5724000 | O23: 5724000 | P23: 6107400 | Q23: 6107400
A24: Water consumption charges | B24: 0 | C24: 1657218.5 | D24: 5368341.6 | E24: 4858034 | F24: 1435559.7 | I24: 4691229 | J24: 4222106.1 | K24: 3752983.2 | L24: 3283860.3 | M24: 4691229 | N24: 4691229 | O24: 4691229 | P24: 4691229 | Q24: 4691229
A25: Education-Outsourced training service | B25: 55955.5 | C25: 963988.45 | D25: 1520699.7 | E25: 2508953 | F25: 577646.56 | G25: 1460393.3 | H25: 3500 | I25: 4592470 | J25: 4133223 | K25: 3673976 | L25: 3214729 | M25: 4592470 | N25: 4340820 | O25: 4340820 | P25: 4415224 | Q25: 4415224
A26: Legal services | B26: 1429997.3 | C26: 2439034.1 | D26: 2695109.5 | E26: 3219289 | F26: 339046.71 | G26: 729456.63 | H26: 36638.18 | I26: 3872238 | J26: 3485014.2 | K26: 3097790.4 | L26: 2710566.6 | M26: 3872238 | N26: 4646385 | O26: 4646385 | P26: 5575362 | Q26: 5575362
A27: Business Travel - Combined expenses | B27: 2147895.3 | C27: 2766837.1 | D27: 216176.96 | E27: 104982 | F27: 17390 | I27: 3631093 | J27: 3105083.7 | K27: 2760074.4 | L27: 2415065.1 | M27: 3565593 | N27: 3619093 | O27: 3553593 | P27: 3828093 | Q27: 3762593
A28: Scholarships & other financial aid | B28: 180843.83 | C28: 0 | D28: 0 | I28: 3000000 | J28: 0 | K28: 0 | L28: 0 | M28: 1500000 | N28: 3000000 | O28: 1500000 | P28: 3000000 | Q28: 1500000
A29: Conferences, seminars and exhibitions and other events: - Overseas event | B29: 6178.69 | C29: 485784.96 | D29: 79093.7 | E29: 90276 | F29: 4515.02 | I29: 2768957 | J29: 2447061.3 | K29: 2175165.6 | L29: 1903269.9 | M29: 2743957 | N29: 2948942 | O29: 2923942 | P29: 3128962 | Q29: 3103962
A30: Academic Publications | B30: 68297.76 | C30: 158851.65 | D30: 436584.61 | E30: 421029 | F30: 130190.17 | G30: 20564 | I30: 2655819.9 | J30: 2318237.9 | K30: 2060655.9 | L30: 1803073.9 | M30: 2655819.9 | N30: 2954459.9 | O30: 2954459.9 | P30: 3238699.9 | Q30: 3238699.9
A31: Student relocation & travel exps | B31: 753383.32 | C31: 2811698.8 | D31: 1730271.6 | E31: 1403064 | F31: 632845 | I31: 2629904 | J31: 2366913.6 | K31: 2103923.2 | L31: 1840932.8 | M31: 2629904 | N31: 3371287 | O31: 3371287 | P31: 3555424 | Q31: 3555424
A32: Data Transmission charges | B32: 2321014.7 | C32: 5668930.6 | D32: 6668930.9 | E32: 3829088 | F32: 2105954.1 | I32: 2618028 | J32: 2356225.2 | K32: 2094422.4 | L32: 1832619.6 | M32: 2618028 | N32: 2018028 | O32: 2018028 | P32: 2018028 | Q32: 2018028
A33: Printing and publishing | B33: 2535 | C33: 334407.04 | D33: 220432.79 | E33: 170455 | F33: 119433.03 | H33: 0 | I33: 2511000 | J33: 2259900 | K33: 2008800 | L33: 1757700 | M33: 2511000 | N33: 1270000 | O33: 1270000 | P33: 1370000 | Q33: 1370000
A34: Public relations | B34: 947316.9 | C34: 1380274.2 | D34: 129310 | E34: 137342 | F34: -820 | I34: 2500000 | J34: 2250000 | K34: 2000000 | L34: 1750000 | M34: 2500000 | N34: 2500000 | O34: 2500000 | P34: 2500000 | Q34: 2500000
A35: Computers and peripherals | B35: 4511639.1 | C35: 17212941 | D35: 16808255 | E35: 14018221 | F35: 781991.19 | G35: 523039.62 | H35: 3370975.3 | I35: 2455000 | J35: 2191500 | K35: 1948000 | L35: 1704500 | M35: 1511000 | N35: 2929000 | O35: 1688000 | P35: 3226180 | Q35: 1650000
A36: Standards Certification Services (e.g. ISO) | B36: 658540.72 | C36: 725941.01 | D36: 1198953 | E36: 972421 | F36: 148176.88 | I36: 2443004 | J36: 1523703.6 | K36: 1354403.2 | L36: 1185102.8 | M36: 2068004 | N36: 1625000 | O36: 1250000 | P36: 5082997 | Q36: 4707997
A37: Student Field trips | B37: 826094.05 | C37: 783042.21 | D37: 537386.89 | E37: 460997 | F37: 18869.47 | H37: 0 | I37: 2370500 | J37: 2133450 | K37: 1896400 | L37: 1659350 | M37: 2370500 | N37: 2695500 | O37: 2695500 | P37: 3020500 | Q37: 3020500
A38: Enrollment expenses | B38: 740812.13 | C38: 5729189.4 | D38: 1588063.2 | E38: 2152196 | F38: 273993.74 | G38: 163301 | H38: 125500 | I38: 2180000 | J38: 1962000 | K38: 1744000 | L38: 1526000 | M38: 2180000 | N38: 2590000 | O38: 2590000 | P38: 3090000 | Q38: 3090000
A39: Student Project Expenses | B39: 693103.86 | C39: 748513.72 | D39: 1440754.9 | E39: 888872 | F39: 527092.53 | G39: 0 | H39: 0 | I39: 2102590 | J39: 1892331 | K39: 1682072 | L39: 1471813 | M39: 2102590 | N39: 2663340 | O39: 2663340 | P39: 2485190 | Q39: 2485190
A40: Events - Awards, prizes & gifts | B40: 19662 | C40: 18555.73 | D40: 2489.15 | E40: 81313 | F40: 7777.99 | I40: 2068000 | J40: 1820700 | K40: 1618400 | L40: 1416100 | M40: 2048000 | N40: 2068000 | O40: 2048000 | P40: 2073400 | Q40: 2053400
A41: Academic Advisory Service | B41: 184630.62 | C41: 491712.84 | D41: 149237.89 | E41: 109861 | F41: 27566.75 | I41: 1821620 | J41: 1531458 | K41: 1361296 | L41: 1191134 | M41: 1761620 | N41: 2887677.5 | O41: 2827677.5 | P41: 3940580 | Q41: 3880580
A42: Management consultancy | B42: 1068485.7 | C42: 2404225.5 | D42: 460065.57 | E42: 134501 | F42: 134500 | H42: 0 | I42: 1491000 | J42: 1341900 | K42: 1192800 | L42: 1043700 | M42: 1491000 | N42: 1555412.5 | O42: 1555412.5 | P42: 1424412.5 | Q42: 1424412.5
A43: Student activities & field trip expenses | B43: 79226.8 | C43: 865669.37 | D43: 27430.98 | E43: 105021 | F43: 20948 | G43: 75000 | I43: 1457500 | J43: 1302750 | K43: 1158000 | L43: 1013250 | M43: 1457500 | N43: 1539500 | O43: 1539500 | P43: 1556700 | Q43: 1556700
A44: Entertainment and hospitality | B44: 195592.98 | C44: 460268.13 | D44: 108086.61 | E44: 114696 | F44: 16760.67 | I44: 1442064 | J44: 1262757.6 | K44: 1122451.2 | L44: 982144.8 | M44: 1430064 | N44: 1534917.5 | O44: 1522917.5 | P44: 2202585 | Q44: 2190585
A45: Printing supplies | B45: 44078 | C45: 514889.34 | D45: 378771.38 | E45: 786147 | F45: 203248.23 | G45: 14400 | H45: 22000 | I45: 1388277 | J45: 1244949.3 | K45: 1106621.6 | L45: 968293.9 | M45: 1388277 | N45: 1467329.5 | O45: 1467329.5 | P45: 1588354.5 | Q45: 1588354.5
A46: Text books and library books | B46: 6078537.1 | C46: 7588849.4 | D46: 11550829 | E46: 11664518 | F46: 5474781.4 | G46: 1 | H46: -0.22 | I46: 1356418 | J46: 1220776.2 | K46: 1085134.4 | L46: 949492.59 | M46: 1356418 | N46: 13233154 | O46: 13233154 | P46: 14800295 | Q46: 14800295
A47: Rental - Equipment | B47: 282588.69 | C47: 1433354.3 | D47: 1425417.5 | E47: 2582500 | F47: 420366.67 | G47: 724916.67 | H47: 0 | I47: 1021317 | J47: 919185.3 | K47: 817053.6 | L47: 714921.9 | M47: 1021317 | N47: 1822350 | O47: 1822350 | P47: 2134080 | Q47: 2134080
A48: Rental - Motor vehicles | B48: 312660.04 | C48: 505734.43 | D48: 399619.75 | F48: -98627.08 | H48: 0 | I48: 967680 | J48: 870912 | K48: 774144 | L48: 677376 | M48: 967680 | N48: 967680 | O48: 967680 | P48: 967680 | Q48: 967680
A49: Health,safety&environment awareness | B49: 843918.88 | C49: 1118577.1 | D49: 676060.8 | E49: 943129 | F49: 147007.29 | G49: 159181.48 | H49: 102367.1 | I49: 890000 | J49: 801000 | K49: 712000 | L49: 623000 | M49: 890000 | N49: 957000 | O49: 957000 | P49: 974850 | Q49: 974850
A50: Skill assessment service | B50: 15300 | C50: 4184.5 | D50: -16200 | E50: 25000 | F50: 25000 | H50: 0 | I50: 887068.76 | J50: 798361.88 | K50: 709655.01 | L50: 620948.13 | M50: 887068.76 | N50: 48641.36 | O50: 48641.36 | P50: 48641.36 | Q50: 48641.36
A51: Catering supplies: Offices | B51: 2431401.2 | C51: 1394068.1 | D51: 538849.67 | E51: 850801 | F51: 117109.31 | G51: 2190.53 | H51: 595 | I51: 840000 | J51: 756000 | K51: 672000 | L51: 588000 | M51: 840000 | N51: 900000 | O51: 900000 | P51: 900000 | Q51: 900000
A52: Telephone and telefax charges | B52: 1009600.7 | C52: 1745978.6 | D52: 2669705.2 | E52: 1078281 | F52: 158783.61 | I52: 810000 | J52: 729000 | K52: 648000 | L52: 567000 | M52: 810000 | N52: 1101000 | O52: 1101000 | P52: 932000 | Q52: 932000
A53: Bldg decoration & minor improvements | B53: 180758.79 | C53: 272887.78 | D53: 83624.49 | E53: 28558 | F53: 27198 | H53: 0 | I53: 730000 | J53: 657000 | K53: 584000 | L53: 511000 | M53: 730000 | N53: 430000 | O53: 430000 | P53: 330000 | Q53: 330000
A54: Subscriptions and membership fees: Trade organisations | B54: 683051.72 | C54: 78811.91 | D54: 146610.84 | E54: 211949 | F54: 155275.62 | I54: 651128.6 | J54: 586015.74 | K54: 520902.88 | L54: 455790.02 | M54: 651128.6 | N54: 903389.3 | O54: 903389.3 | P54: 996602.9 | Q54: 996602.9
A55: Internal Audit service | B55: 787666.24 | C55: 304115.92 | D55: -493500 | E55: 400000 | G55: 15847.9 | H55: 383815 | I55: 500000 | J55: 450000 | K55: 400000 | L55: 350000 | M55: 500000 | N55: 520000 | O55: 520000 | P55: 490000 | Q55: 490000
A56: Fuel, oil and lubricants: Motor vehicles | B56: 78118.69 | C56: 44689.32 | D56: -10915.63 | E56: 3000 | I56: 336000 | J56: 302400 | K56: 268800 | L56: 235200 | M56: 336000 | N56: 336000 | O56: 336000 | P56: 336000 | Q56: 336000
A57: Other specialised professional services, not mentioned elsewhere | B57: 0 | C57: 0 | D57: 15988.5 | E57: 61934 | F57: 36070.33 | I57: 310500 | J57: 279450 | K57: 248400 | L57: 217350 | M57: 310500 | N57: 0 | O57: 0 | P57: 0 | Q57: 0
A58: External Audit service | B58: 109500 | C58: 135000 | D58: 543500 | E58: 319725 | F58: 83515 | I58: 295000 | J58: 265500 | K58: 236000 | L58: 206500 | M58: 295000 | N58: 295000 | O58: 295000 | P58: 295000 | Q58: 295000
A59: Stationery | B59: 623797.58 | C59: 334460.45 | D59: 121728.63 | E59: 129848 | F59: 12466.5 | G59: 6659 | H59: 0 | I59: 281125 | J59: 253012.5 | K59: 224900 | L59: 196787.5 | M59: 281125 | N59: 619800 | O59: 619800 | P59: 297100 | Q59: 297100
A60: Training/Teaching equipment and other educational aid | B60: 188257.22 | C60: 17937.24 | D60: 12367.03 | E60: 31123 | F60: 11697.81 | G60: 16520 | H60: 0 | I60: 272140 | J60: 244926 | K60: 217712 | L60: 190498 | M60: 272140 | N60: 203500 | O60: 203500 | P60: 205900 | Q60: 205900
A61: Graduation rewards | B61: 3500875 | C61: 7340000 | D61: 2010000 | E61: 720000 | F61: 720000 | I61: 240000 | J61: 216000 | K61: 192000 | L61: 168000 | M61: 240000 | N61: 0 | O61: 0 | P61: 0 | Q61: 0
A62: Student Accommodation | B62: 95364264 | C62: 1057127.6 | D62: 667536.03 | E62: 213000 | I62: 225000 | J62: 202500 | K62: 180000 | L62: 157500 | M62: 225000 | N62: 225000 | O62: 225000 | P62: 225000 | Q62: 225000
A63: Photography - Consumable materials /Tools | B63: 0 | C63: 5300 | D63: 56182.5 | E63: 220297 | F63: 500 | G63: 0 | I63: 155000 | J63: 139500 | K63: 124000 | L63: 108500 | M63: 155000 | N63: 476250 | O63: 476250 | P63: 693312 | Q63: 693312
A64: Motor vehicles (non-military) | B64: 38746.36 | C64: 63841.42 | D64: 43876.11 | E64: 38320 | F64: 13160 | I64: 140000 | J64: 126000 | K64: 112000 | L64: 98000 | M64: 140000 | N64: 140000 | O64: 140000 | P64: 140000 | Q64: 140000
A65: Freight and shipping costs, not included elsewhere under purchase costs | B65: 0 | C65: 0 | D65: 62.59 | E65: 30000 | I65: 110000 | J65: 99000 | K65: 88000 | L65: 77000 | M65: 110000 | N65: 117000 | O65: 117000 | P65: 125250 | Q65: 125250
A66: Other services, not specifically mentioned elsewhere | B66: 0 | C66: 0 | D66: 13750 | E66: 146807 | F66: 76000 | I66: 99510 | J66: 89559 | K66: 79608 | L66: 69657 | M66: 99510 | N66: 149510 | O66: 149510 | P66: 149510 | Q66: 149510
A67: Newspapers, magazines, journals, etc | B67: 10968484 | C67: 991302.43 | D67: -107430.42 | E67: 60227 | F67: -8404.76 | I67: 95228.7 | J67: 85705.83 | K67: 76182.96 | L67: 66660.09 | M67: 95228.7 | N67: 200228.7 | O67: 200228.7 | P67: 205478.7 | Q67: 205478.7
A68: Fees for processing e-payments | B68: 53105.47 | C68: 76670.31 | D68: 71796.92 | E68: 87500 | F68: 25814.92 | I68: 90000 | J68: 81000 | K68: 72000 | L68: 63000 | M68: 90000 | N68: 96000 | O68: 96000 | P68: 102000 | Q68: 102000
A69: Postal, courier and other document delivery expenses | B69: 53037.89 | C69: 148058.47 | D69: 31540.97 | E69: 84670 | F69: 2183.8 | G69: 1 | I69: 72000 | J69: 64800 | K69: 57600 | L69: 50400 | M69: 72000 | N69: 85450 | O69: 85450 | P69: 88800 | Q69: 88800
A70: Sponsorship expenses/contributions | B70: 1800000 | C70: 11807880 | D70: 25108675 | E70: 1 | I70: 50000 | J70: 45000 | K70: 40000 | L70: 35000 | M70: 50000 | N70: 50000 | O70: 50000 | P70: 50000 | Q70: 50000
A71: School consumables, not specifically mentioned elsewhere | B71: 4158.7 | C71: 968 | D71: 1745.52 | E71: 1001 | F71: 924.33 | I71: 47000 | J71: 42300 | K71: 37600 | L71: 32900 | M71: 47000 | N71: 47000 | O71: 47000 | P71: 47000 | Q71: 47000
A72: Medical equipment | B72: 0 | C72: 0 | D72: 0 | E72: 0 | I72: 35000 | J72: 31500 | K72: 28000 | L72: 24500 | M72: 35000 | N72: 1606152.2 | O72: 1606152.2 | P72: 2135941.9 | Q72: 2135941.9
A73: Residential Furniture and fixtures | B73: 0 | C73: 20034 | D73: 19422 | E73: 5000 | F73: 0 | I73: 26000 | J73: 23400 | K73: 20800 | L73: 18200 | M73: 26000 | N73: 26000 | O73: 26000 | P73: 26000 | Q73: 26000
A74: Translation and interpretation service | B74: 15295 | C74: 0 | D74: 0 | E74: 27585 | I74: 15000 | J74: 13500 | K74: 12000 | L74: 10500 | M74: 15000 | N74: 15000 | O74: 15000 | P74: 15000 | Q74: 15000
A75: Waste management service | B75: 144093.95 | C75: 198501.1 | D75: 3122.05 | E75: 209066 | F75: 100000 | G75: 0 | H75: 0 | I75: 12000 | J75: 10800 | K75: 9600 | L75: 8400 | M75: 12000 | N75: 74400 | O75: 74400 | P75: 117000 | Q75: 117000
A76: Motor vehicle registration and inspection charges | B76: 10847.7 | C76: 13863.52 | D76: 6771.21 | E76: 20000 | F76: 6080 | I76: 10000 | J76: 9000 | K76: 8000 | L76: 7000 | M76: 10000 | N76: 10000 | O76: 10000 | P76: 10000 | Q76: 10000
A77: Banking service charges / Fees | B77: 41098.23 | C77: 20258.04 | D77: 2000.5 | E77: 3511 | F77: 573.08 | I77: 3600 | J77: 3240 | K77: 2880 | L77: 2520 | M77: 3600 | N77: 4800 | O77: 4800 | P77: 6000 | Q77: 6000
A78: Local Medical treatment expenses including preventive testing
A79: Academic and Student Services Office | B79: 115000 | C79: 0
A80: Local Medical treatment expenses including preventive testing Total | B80: 115000 | C80: 0
A81: Landscaping and other horticulture
A82: Administration, Facilities and EHS Office | B82: 813073.06 | C82: 1365379.1
A83: Landscaping and other horticulture Total | B83: 813073.06 | C83: 1365379.1
A84: Insurance - Cash and fidelity | B84: 3422.15 | C84: 5078.77 | D84: 3156.73 | E84: 6221 | F84: 452 | I84: 0 | J84: 0 | K84: 0 | L84: 0 | M84: 0 | N84: 0 | O84: 0 | P84: 0 | Q84: 0
A85: Insurance - Motor vehicles | B85: 22123 | C85: 30109.81 | D85: 17753.17 | E85: 50000 | I85: 0 | J85: 0 | K85: 0 | L85: 0 | M85: 0 | N85: 0 | O85: 0 | P85: 0 | Q85: 0
A86: Consolidated cost of outsourced employees | B86: 0 | C86: 0 | I86: 0 | J86: 0 | K86: 0 | L86: 0 | M86: 0 | N86: 0 | O86: 0 | P86: 0 | Q86: 0
A87: Plant, machinery and heavy equipment, not mentioned elsewhere | B87: 139868.43 | C87: 6925.2 | D87: -2820 | E87: 5000 | F87: 5000 | H87: 0 | I87: 0 | J87: 0 | K87: 0 | L87: 0 | M87: 0 | N87: 0 | O87: 0 | P87: 0 | Q87: 0
A88: Insurance - Other | B88: 28000 | C88: 15608924
A89: Laboratory - Veterinary | B89: 0 | C89: 0 | D89: 0 | E89: 0 | I89: 0 | J89: 0 | K89: 0 | L89: 0 | M89: 0 | N89: 0 | O89: 0 | P89: 0 | Q89: 0
A90: Insurance - Fire and allied perils | B90: 2279287.2 | C90: 2825181.3 | D90: 1692882.5 | E90: 1732850 | F90: 65067.15 | I90: 0 | J90: 0 | K90: 0 | L90: 0 | M90: 0 | N90: 0 | O90: 0 | P90: 0 | Q90: 0
A91: Road signs | B91: 0 | C91: 71100 | D91: 0 | E91: 246360 | G91: 246356 | I91: 0 | J91: 0 | K91: 0 | L91: 0 | M91: 0 | N91: 0 | O91: 0 | P91: 0 | Q91: 0
A92: Rental - Buildings, other than staff residences | B92: 0 | C92: 271839.82 | D92: 0 | E92: 180000 | I92: 0 | J92: 0 | K92: 0 | L92: 0 | M92: 0 | N92: 0 | O92: 0 | P92: 0 | Q92: 0
A93: Grand Total | B93: 4.1157745e+08 | C93: 4.5345466e+08 | D93: 4.3620813e+08 | E93: 398910380 | F93: 1.2931363e+08 | G93: 53383699 | H93: 31493207 | I93: 7.9647721e+08 | J93: 7.0897699e+08 | K93: 6.3020177e+08 | L93: 5.5142654e+08 | M93: 6.708027e+08 | N93: 8.7845816e+08 | O93: 7.3663227e+08 | P93: 9.1822665e+08 | Q93: 8.0277819e+08

Sheet Pivot Ch3
A1: Future2 Description | B1: FA180-Capex Expense
A3: Cost Center Code - Group | B3: 2018 Actual | C3: 2019 Actual | D3: 2020 Actual | E3: 2021 R. Budget | F3: 2021 Actual | G3: 2021 PR | H3: 2021 PO | I3: 2022 Budget | J3: 2022 Budget Scenario 90% | K3: 2022 Budget Scenario 80% | L3: 2022 Budget Scenario 70% | M3: 2022 Budget Finance Recommendation | N3: 2023 Budget | O3: 2023 Budget Finance Recommendation | P3: 2024 Budget | Q3: 2024 Budget Finance Recommendation
A4: Senior Vice President, Research Office | B4: 16088011 | C4: 24817595 | D4: 18333810 | E4: 24284535 | F4: 1004969.1 | G4: 21399529 | H4: 764750.27 | I4: 2.782088e+08 | J4: 2.5038792e+08 | K4: 2.2256704e+08 | L4: 1.9474616e+08 | M4: 25102366 | N4: 83859445 | O4: 24489459 | P4: 18786312 | Q4: 22489459
A5: Administration, Facilities and EHS Office | B5: 14268377 | C5: 43165437 | D5: 34749576 | E5: 25061676 | F5: 2067526.2 | G5: 22185794 | H5: 652506 | I5: 1.0023933e+08 | J5: 90215397 | K5: 80191464 | L5: 70167531 | M5: 48116815 | N5: 53402634 | O5: 32762500 | P5: 22264265 | Q5: 34354925
A6: College of Medicine & Health Sciences | B6: 2152795 | C6: 61124462 | D6: 17595457 | E6: 27422265 | F6: 4474163.7 | G6: 3427896 | H6: 9410471.6 | I6: 34786123 | J6: 31307511 | K6: 27828898 | L6: 24350286 | M6: 25444123 | N6: 18823354 | O6: 17498554 | P6: 22502422 | Q6: 21581622
A7: College of Engineering | B7: 12466383 | C7: 9982516.4 | D7: 4425327.8 | E7: 2587968 | F7: 129679 | G7: 1984286.2 | H7: 393781.84 | I7: 9343216 | J7: 8408894.4 | K7: 7474572.8 | L7: 6540251.2 | M7: 9343216 | N7: 6053819 | O7: 6053819 | P7: 6590561 | Q7: 6590561
A8: College of Arts & Science | B8: 1500024.6 | C8: 2059737.4 | D8: 0 | E8: 3694815 | F8: 39928 | G8: 2751400 | H8: 868629.7 | I8: 7896973.8 | J8: 4812276.4 | K8: 4277579 | L8: 3742881.7 | M8: 7896973.8 | N8: 5123150.2 | O8: 5123150.2 | P8: 5523260 | Q8: 5523260
A9: Information Technology/ANKABUT | B9: 1848159.8 | C9: 521238.5 | D9: 5927842.4 | E9: 4272296 | F9: -379409 | G9: 3948857 | H9: 94598 | I9: 5011250 | J9: 4510125 | K9: 4009000 | L9: 3507875 | M9: 5011250 | N9: 4432250 | O9: 4432250 | P9: 3850250 | Q9: 3850250
A10: Graduate Studies | B10: 0 | C10: 0 | I10: 2007000 | J10: 1806300 | K10: 1605600 | L10: 1404900 | M10: 2007000 | N10: 711000 | O10: 711000 | P10: 711000 | Q10: 711000
A11: HR & Procurement Office | B11: 0 | C11: 0 | D11: 29334.5 | E11: 110494 | F11: 18149.5 | G11: 0 | H11: 0 | I11: 1650000 | J11: 1485000 | K11: 1320000 | L11: 1155000 | M11: 1650000 | N11: 1650000 | O11: 1650000 | P11: 1650000 | Q11: 1650000
A12: KUST - Office of the Provost | B12: 0 | C12: 2004424.2 | D12: 1481224 | E12: 160720 | F12: 10720 | H12: 150000 | I12: 200000 | J12: 180000 | K12: 160000 | L12: 140000 | M12: 0 | N12: 200000 | O12: 0 | P12: 200000 | Q12: 0
A13: President's Office | B13: 1408395.4 | C13: 4151760.4 | D13: 39940.11 | E13: 200000 | F13: 192455 | G13: 0 | H13: 0 | I13: 200000 | J13: 180000 | K13: 160000 | L13: 140000 | M13: 200000 | N13: 200000 | O13: 200000 | P13: 200000 | Q13: 200000
A14: Academic and Student Services Office | B14: 583733.8 | C14: 9124622.2 | D14: 1963930 | I14: 10000 | J14: 9000 | K14: 8000 | L14: 7000 | M14: 10000 | N14: 10000 | O14: 10000 | P14: 10000 | Q14: 10000
A15: Finance & Business Development Office | B15: 124200 | C15: 0
A16: Grand Total | B16: 50440080 | C16: 1.5695179e+08 | D16: 84546442 | E16: 87794769 | F16: 7558181.5 | G16: 55697762 | H16: 12334737 | I16: 4.395527e+08 | J16: 3.9330243e+08 | K16: 3.4960216e+08 | L16: 3.0590189e+08 | M16: 1.2478174e+08 | N16: 1.7446565e+08 | O16: 92930733 | P16: 82288069 | Q16: 96961077

Sheet Pivot Ch3 Account
A1: Future2 Description | B1: FA180-Capex Expense
A3: Account Description | B3: Cost Center Code - Group | C3: 2018 Actual | D3: 2019 Actual | E3: 2020 Actual | F3: 2021 R. Budget | G3: 2021 Actual | H3: 2021 PR | I3: 2021 PO | J3: 2022 Budget | K3: 2022 Budget Scenario 90% | L3: 2022 Budget Scenario 80% | M3: 2022 Budget Scenario 70% | N3: 2022 Budget Finance Recommendation | O3: 2023 Budget | P3: 2023 Budget Finance Recommendation | Q3: 2024 Budget | R3: 2024 Budget Finance Recommendation
A4: Laboratory equipment | B4: Senior Vice President, Research Office | C4: 16088011 | D4: 24396868 | E4: 18053325 | F4: 18484535 | G4: 995459.05 | H4: 15764203 | I4: 764750.27 | J4: 2.7710644e+08 | K4: 2.4939579e+08 | L4: 2.2168515e+08 | M4: 1.9397451e+08 | N4: 24000000 | O4: 83369986 | P4: 24000000 | Q4: 18296852 | R4: 22000000
B5: College of Medicine & Health Sciences | C5: 2152795 | D5: 57068649 | E5: 15725666 | F5: 21361628 | G5: 4313893.7 | H5: 704656.02 | I5: 7405657.1 | J5: 25108588 | K5: 22597729 | L5: 20086870 | M5: 17576012 | N5: 25108588 | O5: 17127086 | P5: 17127086 | Q5: 21380746 | R5: 21380746
B6: College of Engineering | C6: 12344498 | D6: 9583252.2 | E6: 3600118.5 | F6: 2587968 | G6: 129679 | H6: 1984286.2 | I6: 393781.84 | J6: 9319817 | K6: 8387835.3 | L6: 7455853.6 | M6: 6523871.9 | N6: 9319817 | O6: 6053819 | P6: 6053819 | Q6: 6590561 | R6: 6590561
B7: College of Arts & Science | C7: 1500024.6 | D7: 2035058.2 | E7: 0 | F7: 3694815 | G7: 39928 | H7: 2751400 | I7: 868629.7 | J7: 7493317 | K7: 4448985.3 | L7: 3954653.6 | M7: 3460321.9 | N7: 7493317 | O7: 4371150.2 | P7: 4371150.2 | Q7: 4243260 | R7: 4243260
B8: Administration, Facilities and EHS Office | C8: 579460 | D8: 235407 | E8: 501601.43 | F8: 245879 | H8: 140700 | J8: 250000 | K8: 225000 | L8: 200000 | M8: 175000 | N8: 250000 | O8: 262500 | P8: 262500 | Q8: 275625 | R8: 275625
B9: KUST - Office of the Provost | C9: 0 | D9: 2004424.2 | E9: 1481224 | F9: 160720 | G9: 10720 | I9: 150000 | J9: 200000 | K9: 180000 | L9: 160000 | M9: 140000 | N9: 0 | O9: 200000 | P9: 0 | Q9: 200000 | R9: 0
B10: Academic and Student Services Office | C10: 583733.8 | D10: 0 | E10: 0 | J10: 10000 | K10: 9000 | L10: 8000 | M10: 7000 | N10: 10000 | O10: 10000 | P10: 10000 | Q10: 10000 | R10: 10000
B11: President's Office | C11: 1408395.4 | D11: 4151760.4 | E11: 39940.11 | J11: 0 | K11: 0 | L11: 0 | M11: 0 | N11: 0 | O11: 0 | P11: 0 | Q11: 0 | R11: 0
B12: Information Technology/ANKABUT | C12: 733356 | D12: 0 | E12: -380451 | G12: -388859 | J12: 0 | K12: 0 | L12: 0 | M12: 0 | N12: 0 | O12: 0 | P12: 0 | Q12: 0 | R12: 0
B13: Finance & Business Development Office | C13: 78000 | D13: 0
A14: Laboratory equipment Total | C14: 35468274 | D14: 99475419 | E14: 39021424 | F14: 46535545 | G14: 5100820.8 | H14: 21345245 | I14: 9582818.9 | J14: 3.1948816e+08 | K14: 2.8524434e+08 | L14: 2.5355053e+08 | M14: 2.2185671e+08 | N14: 66181722 | O14: 1.1139454e+08 | P14: 51824555 | Q14: 50997044 | R14: 54500192
A15: Capital expense - Buildings | B15: Administration, Facilities and EHS Office | C15: 13472136 | D15: 39380218 | E15: 27682854 | F15: 22388565 | G15: 1910376.8 | H15: 19776918 | I15: 652506 | J15: 97989330 | K15: 88190397 | L15: 78391464 | M15: 68592531 | N15: 45866815 | O15: 50640134 | P15: 30000000 | Q15: 20988640 | R15: 33079300
B16: Senior Vice President, Research Office | C16: 0 | D16: 0 | E16: 0 | F16: 5600000 | H16: 5600000 | J16: 0 | K16: 0 | L16: 0 | M16: 0 | N16: 0 | O16: 0 | P16: 0 | Q16: 0 | R16: 0
B17: College of Medicine & Health Sciences | C17: 0 | D17: 0 | E17: 1143379 | J17: 0 | K17: 0 | L17: 0 | M17: 0 | N17: 0 | O17: 0 | P17: 0 | Q17: 0 | R17: 0
B18: Academic and Student Services Office | C18: 0 | D18: 0 | E18: 995000 | J18: 0 | K18: 0 | L18: 0 | M18: 0 | N18: 0 | O18: 0 | P18: 0 | Q18: 0 | R18: 0
B19: College of Engineering | C19: 0 | D19: 391826 | E19: 817887 | J19: 0 | K19: 0 | L19: 0 | M19: 0 | N19: 0 | O19: 0 | P19: 0 | Q19: 0 | R19: 0
A20: Capital expense - Buildings Total | C20: 13472136 | D20: 39772044 | E20: 30639120 | F20: 27988565 | G20: 1910376.8 | H20: 25376918 | I20: 652506 | J20: 97989330 | K20: 88190397 | L20: 78391464 | M20: 68592531 | N20: 45866815 | O20: 50640134 | P20: 30000000 | Q20: 20988640 | R20: 33079300
A21: Hardware & peripherals | C21: 630336.13 | D21: 1299505.9 | E21: 6642773.4 | F21: 8592933 | G21: 360785 | H21: 5866329 | I21: 1776727.5 | J21: 16080942 | K21: 14472848 | L21: 12864753 | M21: 11256659 | N21: 6738941.8 | O21: 6624268.5 | P21: 5299468.5 | Q21: 6182288.5 | R21: 5261488.5
A22: Furniture & Fixtures - Offices | C22: 216781 | D22: 15951980 | E22: 7658852.1 | F22: 3026175 | G22: 149900 | H22: 2243075 | I22: 322685 | J22: 3678500 | K22: 3310650 | L22: 2942800 | M22: 2574950 | N22: 3678500 | O22: 4170000 | P22: 4170000 | Q22: 2670000 | R22: 2670000
A23: Computer software | C23: 0 | D23: 0 | E23: 0 | F23: 990000 | H23: 835194.2 | J23: 2042365.7 | K23: 1838129.1 | L23: 1633892.6 | M23: 1429656 | N23: 2042365.7 | O23: 1339459.3 | P23: 1339459.3 | Q23: 1289459.3 | R23: 1289459.3
A24: Copyrights, patents and licenses | C24: 652553.14 | D24: 452844.8 | E24: 584272.75 | F24: 661551 | G24: 36299 | H24: 31000 | I24: 0 | J24: 273399 | K24: 246059.1 | L24: 218719.2 | M24: 191379.3 | N24: 273399 | O24: 297250 | P24: 297250 | Q24: 160637.5 | R24: 160637.5
A25: Grand Total | C25: 50440080 | D25: 1.5695179e+08 | E25: 84546442 | F25: 87794769 | G25: 7558181.5 | H25: 55697762 | I25: 12334737 | J25: 4.395527e+08 | K25: 3.9330243e+08 | L25: 3.4960216e+08 | M25: 3.0590189e+08 | N25: 1.2478174e+08 | O25: 1.7446565e+08 | P25: 92930733 | Q25: 82288069 | R25: 96961077

Sheet UG and PG
B1: 2021-2022 | C1: 2022-2023 | D1: 2023-2024 | E1: 2024-2025 | F1: 2025-2026 | G1: 2026-2027
A2: Continuing Students - UG | B2: 2620 | C2: 3080 | D2: 3696 | E2: 4261 | F2: 4780 | G2: 5248
A3: Continuing Students - PG | B3: 582 | C3: 858 | D3: 1100 | E3: 1250 | F3: 1500 | G3: 1750
A4: Intake - UG | B4: 800 | C4: 858 | D4: 859 | E4: 860 | F4: 861 | G4: 861
A5: Intake - PG | B5: 400 | C5: 400 | D5: 400 | E5: 400 | F5: 400 | G5: 400
A6: Total UG | B6: =SUM(B2,B4) -> 3420 | C6: =SUM(C2,C4) -> 3938 | D6: =SUM(D2,D4) -> 4555 | E6: =SUM(E2,E4) -> 5121 | F6: =SUM(F2,F4) -> 5641 | G6: =SUM(G2,G4) -> 6109
A7: Total PG | B7: 982 | C7: 1258 | D7: =SUM(D3,D5) -> 1500 | E7: =SUM(E3,E5) -> 1650 | F7: =SUM(F3,F5) -> 1900 | G7: =SUM(G3,G5) -> 2150
A8: Grand Total | B8: =SUM(B6:B7) -> 4402 | C8: =SUM(C6:C7) -> 5196 | D8: =SUM(D6:D7) -> 6055 | E8: =SUM(E6:E7) -> 6771 | F8: =SUM(F6:F7) -> 7541 | G8: =SUM(G6:G7) -> 8259

Sheet Cons. Ch2 & Ch3
A1: Cost Center Code - Group | B1: Cost Center Code | C1: Cost Center Description | D1: Account Code | E1: Account Description | F1: GL Account Combination | G1: 2021 Annual Budget | H1: 2021 Revised Budget | I1: 2021 Actual Amount | J1: 2021 PR | K1: 2021 PO | L1: 2021 Fund Available | M1: Future1 | N1: Future1 Description | O1: Future2 | P1: Future2 Description | Q1: 2020 Revis.ed Budget | R1: 2020 Actual Amount | S1: 2022 Budget | T1: 2022 Budget Scenario 90% | U1: 2022 Budget Scenario 80% | V1: 2022 Budget Scenario 70% | W1: 2023 Budget | X1: 2024 Budget | Y1: 2022 Budget Finance Recommendation | Z1: 2023 Budget Finance Recommendation | AA1: 2024 Budget Finance Recommendation | AB1: 2018 Actual Amount | AC1: 2019 Actual Amount | AD1: Diff 2022 | AF1: Diff 2023 | AH1: Diff 2024
A2: President's Office | B2: 8470110 | C2: KUST - Office of the President | D2: 420550 | E2: Academic Advisory Service | F2: 847.8470110.1.420550.000000.847001.200179 | G2: 29119 | H2: 29119 | L2: 29119 | M2: 847001 | N2: KUST - General | O2: 200179 | P2: FA179-Opex Expense | Q2: 29118.09 | R2: 29118.02 | S2: 30000 | T2: =S2*0.9 -> 27000 | U2: =S2*0.8 -> 24000 | V2: =S2*0.7 -> 21000 | W2: 30000 | X2: 30000 | Y2: 30000 | Z2: 30000 | AA2: 30000 | AB2: 2811.43 | AC2: 0 | AD2: =S2-Y2 -> 0 | AF2: =W2-Z2 -> 0 | AH2: =X2-AA2 -> 0
A3: Manpower | B3: Ch1 | C3: Manpower | D3: Ch1 | E3: #N/A | G3: 563874000 | H3: 583465683 | I3: 3.1287481e+08 | J3: 577263.62 | K3: 120262.4 | L3: 2.6989335e+08 | M3: 847001 | N3: KUST - General | O3: 100178 | P3: FA178-Manpower Expense | Q3: 551795870 | R3: 541385100 | S3: 624050000 | T3: =S3*0.9 -> 561645000 | U3: =S3*0.8 -> 499240000 | V3: =S3*0.7 -> 436835000 | W3: 624050000 | X3: 624050000 | Y3: 614050000 | Z3: 624050000 | AA3: 624050000 | AB3: 666857437 | AC3: 734104574 | AD3: =S3-Y3 -> 10000000 | AF3: =W3-Z3 -> 0 | AH3: =X3-AA3 -> 0
A4: President's Office | B4: 8470110 | C4: KUST - Office of the President | D4: 420570 | E4: Academic Collaborative Partnership Services | F4: 847.8470110.1.420570.000000.847001.200179 | G4: 1 | H4: 1 | L4: 1 | M4: 847001 | N4: KUST - General | O4: 200179 | P4: FA179-Opex Expense | Q4: 0.94 | R4: 0 | S4: 10000000 | T4: =S4*0.9 -> 9000000 | U4: =S4*0.8 -> 8000000 | V4: =S4*0.7 -> 7000000 | W4: 10000000 | X4: 10000000 | Y4: 8000000 | Z4: =10000000-700000 -> 9300000 | AA4: =10000000-1500000 -> 8500000 | AB4: 0 | AC4: 0 | AD4: =S4-Y4 -> 2000000 | AE4: ok | AF4: =W4-Z4 -> 700000 | AG4: ok | AH4: =X4-AA4 -> 1500000 | AI4: ok
A5: President's Office | B5: 8470110 | C5: KUST - Office of the President | D5: 420900 | E5: Legal services | F5: 847.8470110.1.420900.000000.847001.200179 | G5: 1501 | H5: 1501 | L5: 1501 | M5: 847001 | N5: KUST - General | O5: 200179 | P5: FA179-Opex Expense | Q5: 1900.4 | R5: 1845 | S5: 1500 | T5: =S5*0.9 -> 1350 | U5: =S5*0.8 -> 1200 | V5: =S5*0.7 -> 1050 | W5: 1500 | X5: 1500 | Y5: 1500 | Z5: 1500 | AA5: 1500 | AB5: 12303.86 | AC5: 2400 | AD5: =S5-Y5 -> 0 | AF5: =W5-Z5 -> 0 | AH5: =X5-AA5 -> 0
A6: President's Office | B6: 8470110 | C6: KUST - Office of the President | D6: 421000 | E6: Management consultancy | F6: 847.8470110.1.421000.000000.847001.200179 | G6: 1 | H6: 1 | L6: 1 | M6: 847001 | N6: KUST - General | O6: 200179 | P6: FA179-Opex Expense | Q6: 0.65 | R6: 0 | S6: 200000 | T6: =S6*0.9 -> 180000 | U6: =S6*0.8 -> 160000 | V6: =S6*0.7 -> 140000 | W6: 200000 | X6: 200000 | Y6: 200000 | Z6: 200000 | AA6: 200000 | AB6: 229317.15 | AC6: 204012.83 | AD6: =S6-Y6 -> 0 | AF6: =W6-Z6 -> 0 | AH6: =X6-AA6 -> 0
A7: President's Office | B7: 8470110 | C7: KUST - Office of the President | D7: 421700 | E7: Standards Certification Services (e.g. ISO) | F7: 847.8470110.1.421700.000000.847001.200179 | G7: 25000 | H7: 25000 | L7: 25000 | M7: 847001 | N7: KUST - General | O7: 200179 | P7: FA179-Opex Expense | Q7: 1.21 | R7: 0 | S7: 25000 | T7: =S7*0.9 -> 22500 | U7: =S7*0.8 -> 20000 | V7: =S7*0.7 -> 17500 | W7: 25000 | X7: 25000 | Y7: 25000 | Z7: 25000 | AA7: 25000 | AB7: 0 | AC7: 0 | AD7: =S7-Y7 -> 0 | AF7: =W7-Z7 -> 0 | AH7: =X7-AA7 -> 0
A8: President's Office | B8: 8470110 | C8: KUST - Office of the President | D8: 425510 | E8: Conferences, seminars and exhibitions and other events: - Local Events | F8: 847.8470110.1.425510.000000.847001.200179 | I8: -190000 | L8: 190000 | M8: 847001 | N8: KUST - General | O8: 200179 | P8: FA179-Opex Expense | Q8: 277367.71 | R8: 277368 | S8: 300000 | T8: =S8*0.9 -> 270000 | U8: =S8*0.8 -> 240000 | V8: =S8*0.7 -> 210000 | W8: 300000 | X8: 300000 | Y8: 300000 | Z8: 300000 | AA8: 300000 | AB8: 96210.44 | AC8: 10546039 | AD8: =S8-Y8 -> 0 | AF8: =W8-Z8 -> 0 | AH8: =X8-AA8 -> 0
A9: President's Office | B9: 8470110 | C9: KUST - Office of the President | D9: 425900 | E9: Entertainment and hospitality | F9: 847.8470110.1.425900.000000.847001.200179 | G9: 10000 | H9: 10000 | I9: -90 | L9: 10090 | M9: 847001 | N9: KUST - General | O9: 200179 | P9: FA179-Opex Expense | Q9: 13356.81 | R9: 13355.7 | S9: 10000 | T9: =S9*0.9 -> 9000 | U9: =S9*0.8 -> 8000 | V9: =S9*0.7 -> 7000 | W9: 10000 | X9: 10000 | Y9: 10000 | Z9: 10000 | AA9: 10000 | AB9: 57571.93 | AC9: 146141.49 | AD9: =S9-Y9 -> 0 | AF9: =W9-Z9 -> 0 | AH9: =X9-AA9 -> 0
A10: President's Office | B10: 8470110 | C10: KUST - Office of the President | D10: 426610 | E10: Computer software licenses | F10: 847.8470110.1.426610.000000.847001.200179 | G10: 80204 | H10: 80204 | I10: 42239.5 | L10: 37964.5 | M10: 847001 | N10: KUST - General | O10: 200179 | P10: FA179-Opex Expense | Q10: 42240.57 | R10: 42239.5 | S10: 518387.5 | T10: =S10*0.9 -> 466548.75 | U10: =S10*0.8 -> 414710 | V10: =S10*0.7 -> 362871.25 | W10: 518387.5 | X10: 518387.5 | Y10: 518387.5 | Z10: 518387.5 | AA10: 518387.5 | AB10: 29255.45 | AC10: 42239.5 | AD10: =S10-Y10 -> 0 | AF10: =W10-Z10 -> 0 | AH10: =X10-AA10 -> 0
A11: President's Office | B11: 8470110 | C11: KUST - Office of the President | D11: 427710 | E11: Subscriptions and membership fees: Trade organisations | F11: 847.8470110.1.427710.000000.847001.200179 | G11: 1880 | H11: 1880 | L11: 1880 | M11: 847001 | N11: KUST - General | O11: 200179 | P11: FA179-Opex Expense | Q11: 3883 | R11: 3882.17 | S11: 0 | T11: =S11*0.9 -> 0 | U11: =S11*0.8 -> 0 | V11: =S11*0.7 -> 0 | W11: 0 | X11: 0 | Y11: 0 | Z11: 0 | AA11: 0 | AB11: 0 | AC11: 0 | AD11: =S11-Y11 -> 0 | AF11: =W11-Z11 -> 0 | AH11: =X11-AA11 -> 0
A12: President's Office | B12: 8470110 | C12: KUST - Office of the President | D12: 427900 | E12: Translation and interpretation service | F12: 847.8470110.1.427900.000000.847001.200179 | G12: 12585 | H12: 12585 | L12: 12585 | M12: 847001 | N12: KUST - General | O12: 200179 | P12: FA179-Opex Expense | Q12: 0.82 | R12: 0 | S12: 0 | T12: =S12*0.9 -> 0 | U12: =S12*0.8 -> 0 | V12: =S12*0.7 -> 0 | W12: 0 | X12: 0 | Y12: 0 | Z12: 0 | AA12: 0 | AB12: 310 | AC12: 0 | AD12: =S12-Y12 -> 0 | AF12: =W12-Z12 -> 0 | AH12: =X12-AA12 -> 0
A13: President's Office | B13: 8470110 | C13: KUST - Office of the President | D13: 428090 | E13: Business Travel - Combined expenses | F13: 847.8470110.1.428090.000000.847001.200179 | G13: 64381 | H13: 64381 | I13: 17390 | L13: 46991 | M13: 847001 | N13: KUST - General | O13: 200179 | P13: FA179-Opex Expense | Q13: 104380.21 | R13: 64375.44 | S13: 1000000 | T13: =S13*0.9 -> 900000 | U13: =S13*0.8 -> 800000 | V13: =S13*0.7 -> 700000 | W13: 1000000 | X13: 1000000 | Y13: 1000000 | Z13: 1000000 | AA13: 1000000 | AB13: 918073.73 | AC13: 1236161 | AD13: =S13-Y13 -> 0 | AF13: =W13-Z13 -> 0 | AH13: =X13-AA13 -> 0
A14: President's Office | B14: 8470110 | C14: KUST - Office of the President | D14: 428640 | E14: Events - Awards, prizes & gifts | F14: 847.8470110.1.428640.000000.847001.200179 | G14: 1 | H14: 1 | L14: 1 | M14: 847001 | N14: KUST - General | O14: 200179 | P14: FA179-Opex Expense | Q14: 0.62 | R14: 0 | S14: 100000 | T14: =S14*0.9 -> 90000 | U14: =S14*0.8 -> 80000 | V14: =S14*0.7 -> 70000 | W14: 100000 | X14: 100000 | Y14: 100000 | Z14: 100000 | AA14: 100000 | AB14: 0 | AC14: 0 | AD14: =S14-Y14 -> 0 | AF14: =W14-Z14 -> 0 | AH14: =X14-AA14 -> 0
A15: President's Office | B15: 8470110 | C15: KUST - Office of the President | D15: 435410 | E15: Catering supplies: Offices | F15: 847.8470110.1.435410.000000.847001.200179 | G15: 1 | H15: 1 | L15: 1 | M15: 847001 | N15: KUST - General | O15: 200179 | P15: FA179-Opex Expense | Q15: 0.96 | R15: 0 | S15: 0 | T15: =S15*0.9 -> 0 | U15: =S15*0.8 -> 0 | V15: =S15*0.7 -> 0 | W15: 0 | X15: 0 | Y15: 0 | Z15: 0 | AA15: 0 | AB15: 1242.04 | AC15: 0 | AD15: =S15-Y15 -> 0 | AF15: =W15-Z15 -> 0 | AH15: =X15-AA15 -> 0
A16: President's Office | B16: 8470110 | C16: KUST - Office of the President | D16: 435519 | E16: Photography - Consumable materials /Tools | F16: 847.8470110.1.435519.000000.847001.200179 | G16: 2000 | H16: 2000 | L16: 2000 | M16: 847001 | N16: KUST - General | O16: 200179 | P16: FA179-Opex Expense | Q16: 0.94 | R16: 0 | S16: 0 | T16: =S16*0.9 -> 0 | U16: =S16*0.8 -> 0 | V16: =S16*0.7 -> 0 | W16: 0 | X16: 0 | Y16: 0 | Z16: 0 | AA16: 0 | AB16: 0 | AC16: 0 | AD16: =S16-Y16 -> 0 | AF16: =W16-Z16 -> 0 | AH16: =X16-AA16 -> 0
A17: President's Office | B17: 8470110 | C17: KUST - Office of the President | D17: 436110 | E17: Printing supplies | F17: 847.8470110.1.436110.000000.847001.200179 | G17: 4195 | H17: 4195 | L17: 4195 | M17: 847001 | N17: KUST - General | O17: 200179 | P17: FA179-Opex Expense | Q17: 0.94 | R17: 0 | S17: 0 | T17: =S17*0.9 -> 0 | U17: =S17*0.8 -> 0 | V17: =S17*0.7 -> 0 | W17: 0 | X17: 0 | Y17: 0 | Z17: 0 | AA17: 0 | AB17: 0 | AC17: 0 | AD17: =S17-Y17 -> 0 | AF17: =W17-Z17 -> 0 | AH17: =X17-AA17 -> 0
A18: President's Office | B18: 8470120 | C18: KUST - Audit & Compliance | D18: 420120 | E18: Internal Audit service | F18: 847.8470120.1.420120.000000.847001.200179 | G18: 400000 | H18: 400000 | J18: 15847.9 | K18: 383815 | L18: 337.1 | M18: 847001 | N18: KUST - General | O18: 200179 | P18: FA179-Opex Expense | Q18: -477000 | R18: -493500 | S18: 500000 | T18: =S18*0.9 -> 450000 | U18: =S18*0.8 -> 400000 | V18: =S18*0.7 -> 350000 | W18: 520000 | X18: 490000 | Y18: 500000 | Z18: 520000 | AA18: 490000 | AB18: 787666.24 | AC18: 304115.92 | AD18: =S18-Y18 -> 0 | AF18: =W18-Z18 -> 0 | AH18: =X18-AA18 -> 0
A19: President's Office | B19: 8470130 | C19: KUST - Institutional Research & Planning | D19: 421000 | E19: Management consultancy | F19: 847.8470130.1.421000.000000.847001.200179 | G19: 276300 | H19: 134500 | I19: 134500 | K19: 0 | L19: 0 | M19: 847001 | N19: KUST - General | O19: 200179 | P19: FA179-Opex Expense | Q19: 162970 | R19: 28465.75 | S19: 720000 | T19: =S19*0.9 -> 648000 | U19: =S19*0.8 -> 576000 | V19: =S19*0.7 -> 504000 | W19: 720000 | X19: 720000 | Y19: 720000 | Z19: 720000 | AA19: 720000 | AB19: 0 | AC19: 0 | AD19: =S19-Y19 -> 0 | AF19: =W19-Z19 -> 0 | AH19: =X19-AA19 -> 0
A20: President's Office | B20: 8470130 | C20: KUST - Institutional Research & Planning | D20: 425510 | E20: Conferences, seminars and exhibitions and other events: - Local Events | F20: 847.8470130.1.425510.000000.847001.200179 | G20: 2200 | H20: 2200 | L20: 2200 | M20: 847001 | N20: KUST - General | O20: 200179 | P20: FA179-Opex Expense | Q20: 2200 | R20: 2200 | S20: 0 | T20: =S20*0.9 -> 0 | U20: =S20*0.8 -> 0 | V20: =S20*0.7 -> 0 | W20: 0 | X20: 0 | Y20: 0 | Z20: 0 | AA20: 0 | AB20: 0 | AC20: 920160 | AD20: =S20-Y20 -> 0 | AF20: =W20-Z20 -> 0 | AH20: =X20-AA20 -> 0
A21: President's Office | B21: 8470130 | C21: KUST - Institutional Research & Planning | D21: 427710 | E21: Subscriptions and membership fees: Trade organisations | F21: 847.8470130.1.427710.000000.847001.200179 | G21: 125000 | H21: 129650 | I21: 129634.5 | L21: 15.5 | M21: 847001 | N21: KUST - General | O21: 200179 | P21: FA179-Opex Expense | Q21: 0 | R21: 0 | S21: 0 | T21: =S21*0.9 -> 0 | U21: =S21*0.8 -> 0 | V21: =S21*0.7 -> 0 | W21: 0 | X21: 0 | Y21: 0 | Z21: 0 | AA21: 0 | AB21: 0 | AC21: 0 | AD21: =S21-Y21 -> 0 | AF21: =W21-Z21 -> 0 | AH21: =X21-AA21 -> 0
A22: President's Office | B22: 8470140 | C22: KUST - Communication | D22: 425100 | E22: Advertising Services (General) | F22: 847.8470140.1.425100.000000.847001.200179 | G22: 2320934 | H22: 3070934 | I22: 620757.53 | J22: 1801366 | K22: 0 | L22: 648810.47 | M22: 847001 | N22: KUST - General | O22: 200179 | P22: FA179-Opex Expense | Q22: 2558303.5 | R22: 2353626.8 | S22: 6450992.4 | T22: =S22*0.9 -> 5805893.2 | U22: =S22*0.8 -> 5160793.9 | V22: =S22*0.7 -> 4515694.7 | W22: 7284500 | X22: 7745833 | Y22: 6450992.4 | Z22: 7284500 | AA22: 7745833 | AB22: 559823.4 | AC22: 5116143.8 | AD22: =S22-Y22 -> 0 | AF22: =W22-Z22 -> 0 | AH22: =X22-AA22 -> 0
A23: President's Office | B23: 8470140 | C23: KUST - Communication | D23: 425510 | E23: Conferences, seminars and exhibitions and other events: - Local Events | F23: 847.8470140.1.425510.000000.847001.200179 | G23: 3500000 | H23: 2850000 | I23: 1418079.7 | J23: 1212000 | K23: 218157.5 | L23: 1762.78 | M23: 847001 | N23: KUST - General | O23: 200179 | P23: FA179-Opex Expense | Q23: 2911261.6 | R23: 2727959.1 | S23: 7048000 | T23: =S23*0.9 -> 6343200 | U23: =S23*0.8 -> 5638400 | V23: =S23*0.7 -> 4933600 | W23: 6585060 | X23: 8025300 | Y23: 7048000 | Z23: 6585060 | AA23: 8025300 | AB23: 8248780 | AC23: 9740819.5 | AD23: =S23-Y23 -> 0 | AF23: =W23-Z23 -> 0 | AH23: =X23-AA23 -> 0
A24: President's Office | B24: 8470140 | C24: KUST - Communication | D24: 425550 | E24: Conferences, seminars and exhibitions and other events: - Overseas event | F24: 847.8470140.1.425550.000000.847001.200179 | G24: 1 | H24: 1 | L24: 1 | M24: 847001 | N24: KUST - General | O24: 200179 | P24: FA179-Opex Expense | Q24: 0.88 | R24: 0 | S24: 791955 | T24: =S24*0.9 -> 712759.5 | U24: =S24*0.8 -> 633564 | V24: =S24*0.7 -> 554368.5 | W24: 791940 | X24: 791960 | Y24: 791955 | Z24: 791940 | AA24: 791960 | AB24: 0 | AC24: 73716.59 | AD24: =S24-Y24 -> 0 | AF24: =W24-Z24 -> 0 | AH24: =X24-AA24 -> 0
A25: President's Office | B25: 8470140 | C25: KUST - Communication | D25: 427100 | E25: Public relations | F25: 847.8470140.1.427100.000000.847001.200179 | G25: 137341 | H25: 137341 | I25: -820 | L25: 138161 | M25: 847001 | N25: KUST - General | O25: 200179 | P25: FA179-Opex Expense | Q25: 135840.03 | R25: 129310 | S25: 2500000 | T25: =S25*0.9 -> 2250000 | U25: =S25*0.8 -> 2000000 | V25: =S25*0.7 -> 1750000 | W25: 2500000 | X25: 2500000 | Y25: 2500000 | Z25: 2500000 | AA25: 2500000 | AB25: 934828.56 | AC25: 1380274.2 | AD25: =S25-Y25 -> 0 | AF25: =W25-Z25 -> 0 | AH25: =X25-AA25 -> 0
A26: President's Office | B26: 8470140 | C26: KUST - Communication | D26: 427200 | E26: Printing and publishing | F26: 847.8470140.1.427200.000000.847001.200179 | G26: 1962 | H26: 1962 | I26: -21038.22 | K26: 0 | L26: 23000.22 | M26: 847001 | N26: KUST - General | O26: 200179 | P26: FA179-Opex Expense | Q26: 132195.98 | R26: 125002.84 | S26: 750000 | T26: =S26*0.9 -> 675000 | U26: =S26*0.8 -> 600000 | V26: =S26*0.7 -> 525000 | W26: 750000 | X26: 750000 | Y26: 750000 | Z26: 750000 | AA26: 750000 | AB26: 0 | AC26: 332618.73 | AD26: =S26-Y26 -> 0 | AF26: =W26-Z26 -> 0 | AH26: =X26-AA26 -> 0
A27: President's Office | B27: 8470140 | C27: KUST - Communication | D27: 435310 | E27: Newspapers, magazines, journals, etc | F27: 847.8470140.1.435310.000000.847001.200179 | G27: 10000 | H27: 10000 | L27: 10000 | M27: 847001 | N27: KUST - General | O27: 200179 | P27: FA179-Opex Expense | Q27: 13569 | R27: 13568.1 | S27: 10000 | T27: =S27*0.9 -> 9000 | U27: =S27*0.8 -> 8000 | V27: =S27*0.7 -> 7000 | W27: 10000 | X27: 10000 | Y27: 10000 | Z27: 10000 | AA27: 10000 | AB27: 2158 | AC27: 17260.1 | AD27: =S27-Y27 -> 0 | AF27: =W27-Z27 -> 0 | AH27: =X27-AA27 -> 0
A28: President's Office | B28: 8470140 | C28: KUST - Communication | D28: 435519 | E28: Photography - Consumable materials /Tools | F28: 847.8470140.1.435519.000000.847001.200179 | G28: 193297 | H28: 193297 | J28: 0 | L28: 193297 | M28: 847001 | N28: KUST - General | O28: 200179 | P28: FA179-Opex Expense | Q28: 77323.96 | R28: 53870 | S28: 135000 | T28: =S28*0.9 -> 121500 | U28: =S28*0.8 -> 108000 | V28: =S28*0.7 -> 94500 | W28: 135000 | X28: 135000 | Y28: 135000 | Z28: 135000 | AA28: 135000 | AB28: 0 | AC28: 0 | AD28: =S28-Y28 -> 0 | AF28: =W28-Z28 -> 0 | AH28: =X28-AA28 -> 0
A29: President's Office | B29: 8470150 | C29: KUST - General Counsel | D29: 420900 | E29: Legal services | F29: 847.8470150.1.420900.000000.847001.200179 | G29: 18595 | H29: 18595 | L29: 18595 | M29: 847001 | N29: KUST - General | O29: 200179 | P29: FA179-Opex Expense | Q29: 18595 | R29: 16996.14 | S29: 0 | T29: =S29*0.9 -> 0 | U29: =S29*0.8 -> 0 | V29: =S29*0.7 -> 0 | W29: 0 | X29: 0 | Y29: 0 | Z29: 0 | AA29: 0 | AB29: 0 | AC29: 0 | AD29: =S29-Y29 -> 0 | AF29: =W29-Z29 -> 0 | AH29: =X29-AA29 -> 0
A30: President's Office | B30: 8470150 | C30: KUST - General Counsel | D30: 425900 | E30: Entertainment and hospitality | F30: 847.8470150.1.425900.000000.847001.200179 | G30: 1 | H30: 1 | L30: 1 | M30: 847001 | N30: KUST - General | O30: 200179 | P30: FA179-Opex Expense | Q30: 0.17 | R30: 0 | S30: 0 | T30: =S30*0.9 -> 0 | U30: =S30*0.8 -> 0 | V30: =S30*0.7 -> 0 | W30: 0 | X30: 0 | Y30: 0 | Z30: 0 | AA30: 0 | AB30: 0 | AC30: 0 | AD30: =S30-Y30 -> 0 | AF30: =W30-Z30 -> 0 | AH30: =X30-AA30 -> 0
A31: Graduate Studies | B31: 8470230 | C31: KUST - Graduate Studies | D31: 420550 | E31: Academic Advisory Service | F31: 847.8470230.1.420550.000000.847001.200179 | G31: 80740 | H31: 80740 | I31: 27566.75 | L31: 53173.25 | M31: 847001 | N31: KUST - General | O31: 200179 | P31: FA179-Opex Expense | Q31: 79821 | R31: 79119.87 | S31: 1020620 | T31: =S31*0.9 -> 918558 | U31: =S31*0.8 -> 816496 | V31: =S31*0.7 -> 714434 | W31: 2057477.5 | X31: 3110580 | Y31: 1020620 | Z31: 2057477.5 | AA31: 3110580 | AB31: 154511.25 | AC31: 346385.92 | AD31: =S31-Y31 -> 0 | AF31: =W31-Z31 -> 0 | AH31: =X31-AA31 -> 0
A32: Graduate Studies | B32: 8470230 | C32: KUST - Graduate Studies | D32: 425100 | E32: Advertising Services (General) | F32: 847.8470230.1.425100.000000.847001.200179 | G32: 240000 | H32: 240000 | L32: 240000 | M32: 847001 | N32: KUST - General | O32: 200179 | P32: FA179-Opex Expense | Q32: 0 | R32: 0 | S32: 300000 | T32: =S32*0.9 -> 270000 | U32: =S32*0.8 -> 240000 | V32: =S32*0.7 -> 210000 | W32: 300000 | X32: 300000 | Y32: 300000 | Z32: 300000 | AA32: 300000 | AB32: 0 | AC32: 251555 | AD32: =S32-Y32 -> 0 | AF32: =W32-Z32 -> 0 | AH32: =X32-AA32 -> 0
A33: Graduate Studies | B33: 8470230 | C33: KUST - Graduate Studies | D33: 425510 | E33: Conferences, seminars and exhibitions and other events: - Local Events | F33: 847.8470230.1.425510.000000.847001.200179 | G33: 10000 | H33: 10000 | I33: -6134.47 | K33: 0 | L33: 16134.47 | M33: 847001 | N33: KUST - General | O33: 200179 | P33: FA179-Opex Expense | Q33: 17919 | R33: 17919 | S33: 34000 | T33: =S33*0.9 -> 30600 | U33: =S33*0.8 -> 27200 | V33: =S33*0.7 -> 23800 | W33: 34000 | X33: 34000 | Y33: 34000 | Z33: 34000 | AA33: 34000 | AB33: 0 | AC33: 46160.94 | AD33: =S33-Y33 -> 0 | AF33: =W33-Z33 -> 0 | AH33: =X33-AA33 -> 0
A34: Graduate Studies | B34: 8470230 | C34: KUST - Graduate Studies | D34: 425550 | E34: Conferences, seminars and exhibitions and other events: - Overseas event | F34: 847.8470230.1.425550.000000.847001.200179 | G34: 16500 | H34: 16500 | I34: 3326.03 | L34: 13173.97 | M34: 847001 | N34: KUST - General | O34: 200179 | P34: FA179-Opex Expense | Q34: 25218 | R34: 25200.26 | S34: 222000 | T34: =S34*0.9 -> 199800 | U34: =S34*0.8 -> 177600 | V34: =S34*0.7 -> 155400 | W34: 222000 | X34: 222000 | Y34: 222000 | Z34: 222000 | AA34: 222000 | AB34: 6178.69 | AC34: 347020.06 | AD34: =S34-Y34 -> 0 | AF34: =W34-Z34 -> 0 | AH34: =X34-AA34 -> 0
A35: Graduate Studies | B35: 8470230 | C35: KUST - Graduate Studies | D35: 425743 | E35: Graduation rewards | F35: 847.8470230.1.425743.000000.847001.200179 | G35: 720000 | H35: 720000 | I35: 720000 | L35: 0 | M35: 847001 | N35: KUST - General | O35: 200179 | P35: FA179-Opex Expense | Q35: 2010000 | R35: 2010000 | S35: 240000 | T35: =S35*0.9 -> 216000 | U35: =S35*0.8 -> 192000 | V35: =S35*0.7 -> 168000 | W35: 0 | X35: 0 | Y35: 240000 | Z35: 0 | AA35: 0 | AB35: 3500875 | AC35: 7340000 | AD35: =S35-Y35 -> 0 | AF35: =W35-Z35 -> 0 | AH35: =X35-AA35 -> 0
A36: Graduate Studies | B36: 8470230 | C36: KUST - Graduate Studies | D36: 425744 | E36: Student medical insurance | F36: 847.8470230.1.425744.000000.847001.200179 | G36: 1 | H36: 1 | L36: 1 | M36: 847001 | N36: KUST - General | O36: 200179 | P36: FA179-Opex Expense | Q36: 1 | R36: 0 | S36: 4816800 | T36: =S36*0.9 -> 4335120 | U36: =S36*0.8 -> 3853440 | V36: =S36*0.7 -> 3371760 | W36: 5724000 | X36: 6107400 | Y36: 4816800 | Z36: 5724000 | AA36: 6107400 | AB36: 4336.82 | AC36: 0 | AD36: =S36-Y36 -> 0 | AF36: =W36-Z36 -> 0 | AH36: =X36-AA36 -> 0
A37: Graduate Studies | B37: 8470230 | C37: KUST - Graduate Studies | D37: 425745 | E37: Student relocation & travel exps | F37: 847.8470230.1.425745.000000.847001.200179 | G37: 1403064 | H37: 1403064 | I37: 632845 | L37: 770219 | M37: 847001 | N37: KUST - General | O37: 200179 | P37: FA179-Opex Expense | Q37: 1899907 | R37: 1706509.4 | S37: 2629904 | T37: =S37*0.9 -> 2366913.6 | U37: =S37*0.8 -> 2103923.2 | V37: =S37*0.7 -> 1840932.8 | W37: 3371287 | X37: 3555424 | Y37: 2629904 | Z37: 3371287 | AA37: 3555424 | AB37: 561661.9 | AC37: 2585908.8 | AD37: =S37-Y37 -> 0 | AF37: =W37-Z37 -> 0 | AH37: =X37-AA37 -> 0
A38: Graduate Studies | B38: 8470230 | C38: KUST - Graduate Studies | D38: 425749 | E38: Postgraduate Student Salaries | F38: 847.8470230.1.425749.000000.847001.200179 | G38: 101999705 | H38: 101999705 | I38: 39527820 | L38: 62471885 | M38: 847001 | N38: KUST - General | O38: 200179 | P38: FA179-Opex Expense | Q38: 22420122 | R38: 22420057 | S38: 168430434 | T38: =S38*0.9 -> 1.5158739e+08 | U38: =S38*0.8 -> 1.3474435e+08 | V38: =S38*0.7 -> 1.179013e+08 | W38: 207120284 | X38: 2.3004481e+08 | Y38: 140817695 | Z38: 155340615 | AA38: 172533615 | AB38: 0 | AC38: 0 | AD38: =S38-Y38 -> 27612739 | AE38: ok | AF38: =W38-Z38 -> 51779669 | AG38: ok | AH38: =X38-AA38 -> 57511197 | AI38: ok
A39: Graduate Studies | B39: 8470230 | C39: KUST - Graduate Studies | D39: 426610 | E39: Computer software licenses | F39: 847.8470230.1.426610.000000.847001.200179 | G39: 8959 | H39: 8959 | L39: 8959 | M39: 847001 | N39: KUST - General | O39: 200179 | P39: FA179-Opex Expense | Q39: 1 | R39: 0 | S39: 10000 | T39: =S39*0.9 -> 9000 | U39: =S39*0.8 -> 8000 | V39: =S39*0.7 -> 7000 | W39: 10000 | X39: 10000 | Y39: 10000 | Z39: 10000 | AA39: 10000 | AB39: 31437.25 | AC39: 0 | AD39: =S39-Y39 -> 0 | AF39: =W39-Z39 -> 0 | AH39: =X39-AA39 -> 0
A40: Graduate Studies | B40: 8470230 | C40: KUST - Graduate Studies | D40: 436110 | E40: Printing supplies | F40: 847.8470230.1.436110.000000.847001.200179 | G40: 5000 | H40: 5000 | L40: 5000 | M40: 847001 | N40: KUST - General | O40: 200179 | P40: FA179-Opex Expense | Q40: 42101 | R40: 42100 | S40: 5000 | T40: =S40*0.9 -> 4500 | U40: =S40*0.8 -> 4000 | V40: =S40*0.7 -> 3500 | W40: 5000 | X40: 5000 | Y40: 5000 | Z40: 5000 | AA40: 5000 | AB40: 1650 | AC40: 1400 | AD40: =S40-Y40 -> 0 | AF40: =W40-Z40 -> 0 | AH40: =X40-AA40 -> 0
A41: College of Engineering | B41: 8470305 | C41: KUST - Dean Of Engineering | D41: 420550 | E41: Academic Advisory Service | F41: 847.8470305.1.420550.000000.847001.200179 | G41: 1 | H41: 1 | L41: 1 | M41: 847001 | N41: KUST - General | O41: 200179 | P41: FA179-Opex Expense | Q41: 0.43 | R41: 0 | S41: 10000 | T41: =S41*0.9 -> 9000 | U41: =S41*0.8 -> 8000 | V41: =S41*0.7 -> 7000 | W41: 10000 | X41: 10000 | Y41: 10000 | Z41: 10000 | AA41: 10000 | AB41: 0 | AC41: 0 | AD41: =S41-Y41 -> 0 | AF41: =W41-Z41 -> 0 | AH41: =X41-AA41 -> 0
A42: College of Engineering | B42: 8470305 | C42: KUST - Dean Of Engineering | D42: 420570 | E42: Academic Collaborative Partnership Services | F42: 847.8470305.1.420570.000000.847001.200179 | G42: 0 | H42: 9200 | I42: 4591.25 | L42: 4608.75 | M42: 847001 | N42: KUST - General | O42: 200179 | P42: FA179-Opex Expense | Q42: 4592 | R42: 4591.25 | S42: 10000 | T42: =S42*0.9 -> 9000 | U42: =S42*0.8 -> 8000 | V42: =S42*0.7 -> 7000 | W42: 10000 | X42: 10000 | Y42: 10000 | Z42: 10000 | AA42: 10000 | AB42: 4591.25 | AC42: 4591.25 | AD42: =S42-Y42 -> 0 | AF42: =W42-Z42 -> 0 | AH42: =X42-AA42 -> 0
A43: College of Engineering | B43: 8470305 | C43: KUST - Dean Of Engineering | D43: 421700 | E43: Standards Certification Services (e.g. ISO) | F43: 847.8470305.1.421700.000000.847001.200179 | G43: 400000 | H43: 390800 | L43: 390800 | M43: 847001 | N43: KUST - General | O43: 200179 | P43: FA179-Opex Expense | Q43: 597851.4 | R43: 597850.89 | S43: 506004 | T43: =S43*0.9 -> 455403.6 | U43: =S43*0.8 -> 404803.2 | V43: =S43*0.7 -> 354202.8 | W43: 210000 | X43: 3659997 | Y43: 506004 | Z43: 210000 | AA43: 3659997 | AB43: 375778.65 | AC43: 391361.36 | AD43: =S43-Y43 -> 0 | AF43: =W43-Z43 -> 0 | AH43: =X43-AA43 -> 0
A44: College of Engineering | B44: 8470305 | C44: KUST - Dean Of Engineering | D44: 425510 | E44: Conferences, seminars and exhibitions and other events: - Local Events | F44: 847.8470305.1.425510.000000.847001.200179 | G44: 10000 | H44: 10000 | I44: -252 | L44: 10252 | M44: 847001 | N44: KUST - General | O44: 200179 | P44: FA179-Opex Expense | Q44: 10444.08 | R44: 10444 | S44: 20000 | T44: =S44*0.9 -> 18000 | U44: =S44*0.8 -> 16000 | V44: =S44*0.7 -> 14000 | W44: 20000 | X44: 20000 | Y44: 20000 | Z44: 20000 | AA44: 20000 | AB44: 26029.52 | AC44: 38554.15 | AD44: =S44-Y44 -> 0 | AF44: =W44-Z44 -> 0 | AH44: =X44-AA44 -> 0
A45: College of Engineering | B45: 8470305 | C45: KUST - Dean Of Engineering | D45: 425720 | E45: Education-Outsourced training service | F45: 847.8470305.1.425720.000000.847001.200179 | I45: -3415.89 | L45: 3415.89 | M45: 847001 | N45: KUST - General | O45: 200179 | P45: FA179-Opex Expense | Q45: 0 | R45: 0 | S45: 0 | T45: =S45*0.9 -> 0 | U45: =S45*0.8 -> 0 | V45: =S45*0.7 -> 0 | W45: 0 | X45: 0 | Y45: 0 | Z45: 0 | AA45: 0 | AB45: 0 | AC45: 29384 | AD45: =S45-Y45 -> 0 | AF45: =W45-Z45 -> 0 | AH45: =X45-AA45 -> 0
A46: College of Engineering | B46: 8470305 | C46: KUST - Dean Of Engineering | D46: 425763 | E46: Student Project Expenses | F46: 847.8470305.1.425763.000000.847001.200179 | G46: 30000 | H46: 100000 | L46: 100000 | M46: 847001 | N46: KUST - General | O46: 200179 | P46: FA179-Opex Expense | Q46: 617772.08 | R46: 617637.56 | S46: 100000 | T46: =S46*0.9 -> 90000 | U46: =S46*0.8 -> 80000 | V46: =S46*0.7 -> 70000 | W46: 110000 | X46: 120000 | Y46: 100000 | Z46: 110000 | AA46: 120000 | AB46: 23850 | AC46: 19184.07 | AD46: =S46-Y46 -> 0 | AF46: =W46-Z46 -> 0 | AH46: =X46-AA46 -> 0
A47: College of Engineering | B47: 8470305 | C47: KUST - Dean Of Engineering | D47: 425770 | E47: Academic Missions - Combined expenses | F47: 847.8470305.1.425770.000000.847001.200179 | G47: 30000 | H47: 20000 | L47: 20000 | M47: 847001 | N47: KUST - General | O47: 200179 | P47: FA179-Opex Expense | Q47: 7219.24 | R47: 7218.55 | S47: 750000 | T47: =S47*0.9 -> 675000 | U47: =S47*0.8 -> 600000 | V47: =S47*0.7 -> 525000 | W47: 795000 | X47: 795000 | Y47: 750000 | Z47: 795000 | AA47: 795000 | AB47: 956.54 | AC47: 96239.15 | AD47: =S47-Y47 -> 0 | AF47: =W47-Z47 -> 0 | AH47: =X47-AA47 -> 0
A48: College of Engineering | B48: 8470305 | C48: KUST - Dean Of Engineering | D48: 425900 | E48: Entertainment and hospitality | F48: 847.8470305.1.425900.000000.847001.200179 | I48: -131 | L48: 131 | M48: 847001 | N48: KUST - General | O48: 200179 | P48: FA179-Opex Expense | Q48: -10520.45 | R48: -10521 | S48: 18000 | T48: =S48*0.9 -> 16200 | U48: =S48*0.8 -> 14400 | V48: =S48*0.7 -> 12600 | W48: 18000 | X48: 18000 | Y48: 18000 | Z48: 18000 | AA48: 18000 | AB48: 6238 | AC48: 19368.86 | AD48: =S48-Y48 -> 0 | AF48: =W48-Z48 -> 0 | AH48: =X48-AA48 -> 0
A49: College of Engineering | B49: 8470305 | C49: KUST - Dean Of Engineering | D49: 426610 | E49: Computer software licenses | F49: 847.8470305.1.426610.000000.847001.200179 | G49: 224793 | H49: 224793 | I49: 32671.59 | J49: 28400.54 | L49: 163720.87 | M49: 847001 | N49: KUST - General | O49: 200179 | P49: FA179-Opex Expense | Q49: 236658.87 | R49: 236658.04 | S49: 100000 | T49: =S49*0.9 -> 90000 | U49: =S49*0.8 -> 80000 | V49: =S49*0.7 -> 70000 | W49: 105000 | X49: 110000 | Y49: 100000 | Z49: 105000 | AA49: 110000 | AB49: 161847.46 | AC49: 185612.89 | AD49: =S49-Y49 -> 0 | AF49: =W49-Z49 -> 0 | AH49: =X49-AA49 -> 0
A50: College of Engineering | B50: 8470305 | C50: KUST - Dean Of Engineering | D50: 428640 | E50: Events - Awards, prizes & gifts | F50: 847.8470305.1.428640.000000.847001.200179 | G50: 1 | H50: 1 | L50: 1 | M50: 847001 | N50: KUST - General | O50: 200179 | P50: FA179-Opex Expense | Q50: -3636.61 | R50: -3637.45 | S50: 45000 | T50: =S50*0.9 -> 40500 | U50: =S50*0.8 -> 36000 | V50: =S50*0.7 -> 31500 | W50: 45000 | X50: 45000 | Y50: 45000 | Z50: 45000 | AA50: 45000 | AB50: 0 | AC50: 11200 | AD50: =S50-Y50 -> 0 | AF50: =W50-Z50 -> 0 | AH50: =X50-AA50 -> 0
A51: College of Engineering | B51: 8470305 | C51: KUST - Dean Of Engineering | D51: 432209 | E51: Laboratory equipment | F51: 847.8470305.1.432209.000000.847001.200179 | G51: 250000 | H51: 250000 | I51: 101101 | J51: 0 | K51: 145565.85 | L51: 3333.15 | M51: 847001 | N51: KUST - General | O51: 200179 | P51: FA179-Opex Expense | Q51: 1194799.8 | R51: 786038.6 | S51: 0 | T51: =S51*0.9 -> 0 | U51: =S51*0.8 -> 0 | V51: =S51*0.7 -> 0 | W51: 0 | X51: 0 | Y51: 0 | Z51: 0 | AA51: 0 | AB51: 107597.52 | AC51: 979023.51 | AD51: =S51-Y51 -> 0 | AF51: =W51-Z51 -> 0 | AH51: =X51-AA51 -> 0
A52: College of Engineering | B52: 8470305 | C52: KUST - Dean Of Engineering | D52: 432690 | E52: Plant, machinery and heavy equipment, not mentioned elsewhere | F52: 847.8470305.1.432690.000000.847001.200179 | G52: 0 | H52: 5000 | I52: 5000 | K52: 0 | L52: 0 | M52: 847001 | N52: KUST - General | O52: 200179 | P52: FA179-Opex Expense | Q52: 0 | R52: -2820 | S52: 0 | T52: =S52*0.9 -> 0 | U52: =S52*0.8 -> 0 | V52: =S52*0.7 -> 0 | W52: 0 | X52: 0 | Y52: 0 | Z52: 0 | AA52: 0 | AB52: 139268.43 | AC52: 6925.2 | AD52: =S52-Y52 -> 0 | AF52: =W52-Z52 -> 0 | AH52: =X52-AA52 -> 0
A53: College of Engineering | B53: 8470305 | C53: KUST - Dean Of Engineering | D53: 435350 | E53: Academic Publications | F53: 847.8470305.1.435350.000000.847001.200179 | G53: 22529 | H53: 22529 | L53: 22529 | M53: 847001 | N53: KUST - General | O53: 200179 | P53: FA179-Opex Expense | Q53: 2390.16 | R53: 2389 | S53: 260000 | T53: =S53*0.9 -> 234000 | U53: =S53*0.8 -> 208000 | V53: =S53*0.7 -> 182000 | W53: 260000 | X53: 260000 | Y53: 260000 | Z53: 260000 | AA53: 260000 | AB53: 0 | AC53: 0 | AD53: =S53-Y53 -> 0 | AF53: =W53-Z53 -> 0 | AH53: =X53-AA53 -> 0
A54: College of Engineering | B54: 8470305 | C54: KUST - Dean Of Engineering | D54: 435508 | E54: Laboratory - Scientific | F54: 847.8470305.1.435508.000000.847001.200179 | G54: 51790 | H54: 51790 | I54: 51790 | K54: 0 | L54: 0 | M54: 847001 | N54: KUST - General | O54: 200179 | P54: FA179-Opex Expense | Q54: 61268.13 | R54: 22871.83 | S54: 100000 | T54: =S54*0.9 -> 90000 | U54: =S54*0.8 -> 80000 | V54: =S54*0.7 -> 70000 | W54: 100000 | X54: 100000 | Y54: 100000 | Z54: 100000 | AA54: 100000 | AB54: 0 | AC54: 148738.8 | AD54: =S54-Y54 -> 0 | AF54: =W54-Z54 -> 0 | AH54: =X54-AA54 -> 0
A55: College of Engineering | B55: 8470305 | C55: KUST - Dean Of Engineering | D55: 435530 | E55: School consumables, not specifically mentioned elsewhere | F55: 847.8470305.1.435530.000000.847001.200179 | G55: 0 | H55: 0 | L55: 0 | M55: 847001 | N55: KUST - General | O55: 200179 | P55: FA179-Opex Expense | Q55: 1 | R55: 0 | S55: 0 | T55: =S55*0.9 -> 0 | U55: =S55*0.8 -> 0 | V55: =S55*0.7 -> 0 | W55: 0 | X55: 0 | Y55: 0 | Z55: 0 | AA55: 0 | AB55: 0 | AC55: 0 | AD55: =S55-Y55 -> 0 | AF55: =W55-Z55 -> 0 | AH55: =X55-AA55 -> 0
A56: College of Engineering | B56: 8470305 | C56: KUST - Dean Of Engineering | D56: 436110 | E56: Printing supplies | F56: 847.8470305.1.436110.000000.847001.200179 | G56: 0 | H56: 0 | L56: 0 | M56: 847001 | N56: KUST - General | O56: 200179 | P56: FA179-Opex Expense | Q56: 0.69 | R56: 0 | S56: 0 | T56: =S56*0.9 -> 0 | U56: =S56*0.8 -> 0 | V56: =S56*0.7 -> 0 | W56: 0 | X56: 0 | Y56: 0 | Z56: 0 | AA56: 0 | AB56: 0 | AC56: 0 | AD56: =S56-Y56 -> 0 | AF56: =W56-Z56 -> 0 | AH56: =X56-AA56 -> 0
A57: College of Engineering | B57: 8470310 | C57: KUST - Aerospace Engineering | D57: 425763 | E57: Student Project Expenses | F57: 847.8470310.1.425763.000000.847001.200179 | G57: 85000 | H57: 119000 | I57: 118694.51 | L57: 305.49 | M57: 847001 | N57: KUST - General | O57: 200179 | P57: FA179-Opex Expense | Q57: 62470 | R57: 62464.48 | S57: 350000 | T57: =S57*0.9 -> 315000 | U57: =S57*0.8 -> 280000 | V57: =S57*0.7 -> 245000 | W57: 375000 | X57: 375000 | Y57: 350000 | Z57: 375000 | AA57: 375000 | AB57: 86062 | AC57: 155850.68 | AD57: =S57-Y57 -> 0 | AF57: =W57-Z57 -> 0 | AH57: =X57-AA57 -> 0
A58: College of Engineering | B58: 8470310 | C58: KUST - Aerospace Engineering | D58: 425770 | E58: Academic Missions - Combined expenses | F58: 847.8470310.1.425770.000000.847001.200179 | G58: 65000 | H58: 490 | L58: 490 | M58: 847001 | N58: KUST - General | O58: 200179 | P58: FA179-Opex Expense | Q58: 2891 | R58: 2890 | S58: 210000 | T58: =S58*0.9 -> 189000 | U58: =S58*0.8 -> 168000 | V58: =S58*0.7 -> 147000 | W58: 240000 | X58: 270000 | Y58: 210000 | Z58: 240000 | AA58: 270000 | AB58: 64495.38 | AC58: 50028.33 | AD58: =S58-Y58 -> 0 | AF58: =W58-Z58 -> 0 | AH58: =X58-AA58 -> 0
A59: College of Engineering | B59: 8470310 | C59: KUST - Aerospace Engineering | D59: 430120 | E59: Rental - Buildings, other than staff residences | F59: 847.8470310.1.430120.000000.847001.200179 | G59: 180000 | H59: 180000 | L59: 180000 | M59: 847001 | N59: KUST - General | O59: 200179 | P59: FA179-Opex Expense | Q59: 0 | R59: 0 | S59: 0 | T59: =S59*0.9 -> 0 | U59: =S59*0.8 -> 0 | V59: =S59*0.7 -> 0 | W59: 0 | X59: 0 | Y59: 0 | Z59: 0 | AA59: 0 | AB59: 0 | AC59: 271839.82 | AD59: =S59-Y59 -> 0 | AF59: =W59-Z59 -> 0 | AH59: =X59-AA59 -> 0
A60: College of Engineering | B60: 8470310 | C60: KUST - Aerospace Engineering | D60: 435350 | E60: Academic Publications | F60: 847.8470310.1.435350.000000.847001.200179 | G60: 2000 | H60: 52000 | L60: 52000 | M60: 847001 | N60: KUST - General | O60: 200179 | P60: FA179-Opex Expense | Q60: 1 | R60: 0 | S60: 182000 | T60: =S60*0.9 -> 163800 | U60: =S60*0.8 -> 145600 | V60: =S60*0.7 -> 127400 | W60: 208000 | X60: 234000 | Y60: 182000 | Z60: 208000 | AA60: 234000 | AB60: 0 | AC60: 3242.5 | AD60: =S60-Y60 -> 0 | AF60: =W60-Z60 -> 0 | AH60: =X60-AA60 -> 0
A61: College of Engineering | B61: 8470310 | C61: KUST - Aerospace Engineering | D61: 435508 | E61: Laboratory - Scientific | F61: 847.8470310.1.435508.000000.847001.200179 | G61: 50000 | H61: 50000 | J61: 49622.03 | L61: 377.97 | M61: 847001 | N61: KUST - General | O61: 200179 | P61: FA179-Opex Expense | Q61: 119612 | R61: 119603.75 | S61: 80000 | T61: =S61*0.9 -> 72000 | U61: =S61*0.8 -> 64000 | V61: =S61*0.7 -> 56000 | W61: 80000 | X61: 80000 | Y61: 80000 | Z61: 80000 | AA61: 80000 | AB61: 6751.4 | AC61: 61346.5 | AD61: =S61-Y61 -> 0 | AF61: =W61-Z61 -> 0 | AH61: =X61-AA61 -> 0
A62: College of Engineering | B62: 8470310 | C62: KUST - Aerospace Engineering | D62: 436600 | E62: Training/Teaching equipment and other educational aid | F62: 847.8470310.1.436600.000000.847001.200179 | G62: 0 | H62: 510 | I62: 505.12 | L62: 4.88 | M62: 847001 | N62: KUST - General | O62: 200179 | P62: FA179-Opex Expense | Q62: 0 | R62: 0 | S62: 5000 | T62: =S62*0.9 -> 4500 | U62: =S62*0.8 -> 4000 | V62: =S62*0.7 -> 3500 | W62: 5000 | X62: 5000 | Y62: 5000 | Z62: 5000 | AA62: 5000 | AB62: 2000 | AC62: 0 | AD62: =S62-Y62 -> 0 | AF62: =W62-Z62 -> 0 | AH62: =X62-AA62 -> 0
A63: College of Engineering | B63: 8470315 | C63: KUST - Biomedical Engineering | D63: 425510 | E63: Conferences, seminars and exhibitions and other events: - Local Events | F63: 847.8470315.1.425510.000000.847001.200179 | G63: 1502 | H63: 1502 | L63: 1502 | M63: 847001 | N63: KUST - General | O63: 200179 | P63: FA179-Opex Expense | Q63: 1502 | R63: 1502 | S63: 4000 | T63: =S63*0.9 -> 3600 | U63: =S63*0.8 -> 3200 | V63: =S63*0.7 -> 2800 | W63: 4000 | X63: 4000 | Y63: 4000 | Z63: 4000 | AA63: 4000 | AB63: 0 | AC63: 5000 | AD63: =S63-Y63 -> 0 | AF63: =W63-Z63 -> 0 | AH63: =X63-AA63 -> 0
A64: College of Engineering | B64: 8470315 | C64: KUST - Biomedical Engineering | D64: 425760 | E64: Student activities & field trip expenses | F64: 847.8470315.1.425760.000000.847001.200179 | G64: 875 | H64: 875 | L64: 875 | M64: 847001 | N64: KUST - General | O64: 200179 | P64: FA179-Opex Expense | Q64: 875 | R64: 875 | S64: 20000 | T64: =S64*0.9 -> 18000 | U64: =S64*0.8 -> 16000 | V64: =S64*0.7 -> 14000 | W64: 20000 | X64: 20000 | Y64: 20000 | Z64: 20000 | AA64: 20000 | AB64: 0 | AC64: 0 | AD64: =S64-Y64 -> 0 | AF64: =W64-Z64 -> 0 | AH64: =X64-AA64 -> 0
A65: College of Engineering | B65: 8470315 | C65: KUST - Biomedical Engineering | D65: 425763 | E65: Student Project Expenses | F65: 847.8470315.1.425763.000000.847001.200179 | G65: 59000 | H65: 59000 | I65: 51781.09 | L65: 7218.91 | M65: 847001 | N65: KUST - General | O65: 200179 | P65: FA179-Opex Expense | Q65: 56358 | R65: 54242.58 | S65: 180000 | T65: =S65*0.9 -> 162000 | U65: =S65*0.8 -> 144000 | V65: =S65*0.7 -> 126000 | W65: 204000 | X65: 240000 | Y65: 180000 | Z65: 204000 | AA65: 240000 | AB65: 35370.65 | AC65: 18774.11 | AD65: =S65-Y65 -> 0 | AF65: =W65-Z65 -> 0 | AH65: =X65-AA65 -> 0
A66: College of Engineering | B66: 8470315 | C66: KUST - Biomedical Engineering | D66: 425770 | E66: Academic Missions - Combined expenses | F66: 847.8470315.1.425770.000000.847001.200179 | G66: 47557 | H66: 22557 | L66: 22557 | M66: 847001 | N66: KUST - General | O66: 200179 | P66: FA179-Opex Expense | Q66: 30571 | R66: 30570.03 | S66: 180000 | T66: =S66*0.9 -> 162000 | U66: =S66*0.8 -> 144000 | V66: =S66*0.7 -> 126000 | W66: 195000 | X66: 240000 | Y66: 180000 | Z66: 195000 | AA66: 240000 | AB66: 94481.76 | AC66: 64039.18 | AD66: =S66-Y66 -> 0 | AF66: =W66-Z66 -> 0 | AH66: =X66-AA66 -> 0
A67: College of Engineering | B67: 8470315 | C67: KUST - Biomedical Engineering | D67: 425900 | E67: Entertainment and hospitality | F67: 847.8470315.1.425900.000000.847001.200179 | G67: 1024 | H67: 1024 | L67: 1024 | M67: 847001 | N67: KUST - General | O67: 200179 | P67: FA179-Opex Expense | Q67: 1024 | R67: 1023.75 | S67: 10000 | T67: =S67*0.9 -> 9000 | U67: =S67*0.8 -> 8000 | V67: =S67*0.7 -> 7000 | W67: 16000 | X67: 19000 | Y67: 10000 | Z67: 16000 | AA67: 19000 | AB67: 420 | AC67: 9582.35 | AD67: =S67-Y67 -> 0 | AF67: =W67-Z67 -> 0 | AH67: =X67-AA67 -> 0
A68: College of Engineering | B68: 8470315 | C68: KUST - Biomedical Engineering | D68: 426610 | E68: Computer software licenses | F68: 847.8470315.1.426610.000000.847001.200179 | G68: 9738 | H68: 9738 | I68: 3816.25 | L68: 5921.75 | M68: 847001 | N68: KUST - General | O68: 200179 | P68: FA179-Opex Expense | Q68: 8706 | R68: 8705.01 | S68: 99576 | T68: =S68*0.9 -> 89618.4 | U68: =S68*0.8 -> 79660.8 | V68: =S68*0.7 -> 69703.2 | W68: 104554 | X68: 109782 | Y68: 99576 | Z68: 104554 | AA68: 109782 | AB68: 0 | AC68: 0 | AD68: =S68-Y68 -> 0 | AF68: =W68-Z68 -> 0 | AH68: =X68-AA68 -> 0
A69: College of Engineering | B69: 8470315 | C69: KUST - Biomedical Engineering | D69: 432209 | E69: Laboratory equipment | F69: 847.8470315.1.432209.000000.847001.200179 | G69: 6195 | H69: 6195 | I69: 5900 | L69: 295 | M69: 847001 | N69: KUST - General | O69: 200179 | P69: FA179-Opex Expense | Q69: 0 | R69: 0 | S69: 90250 | T69: =S69*0.9 -> 81225 | U69: =S69*0.8 -> 72200 | V69: =S69*0.7 -> 63175 | W69: 90250 | X69: 90250 | Y69: 90250 | Z69: 90250 | AA69: 90250 | AB69: 0 | AC69: 64961 | AD69: =S69-Y69 -> 0 | AF69: =W69-Z69 -> 0 | AH69: =X69-AA69 -> 0
A70: College of Engineering | B70: 8470315 | C70: KUST - Biomedical Engineering | D70: 435350 | E70: Academic Publications | F70: 847.8470315.1.435350.000000.847001.200179 | G70: 16000 | H70: 16000 | L70: 16000 | M70: 847001 | N70: KUST - General | O70: 200179 | P70: FA179-Opex Expense | Q70: 1 | R70: 0 | S70: 38400 | T70: =S70*0.9 -> 34560 | U70: =S70*0.8 -> 30720 | V70: =S70*0.7 -> 26880 | W70: 41600 | X70: 51200 | Y70: 38400 | Z70: 41600 | AA70: 51200 | AB70: 5967.8 | AC70: 0 | AD70: =S70-Y70 -> 0 | AF70: =W70-Z70 -> 0 | AH70: =X70-AA70 -> 0
A71: College of Engineering | B71: 8470315 | C71: KUST - Biomedical Engineering | D71: 435508 | E71: Laboratory - Scientific | F71: 847.8470315.1.435508.000000.847001.200179 | G71: 80000 | H71: 105000 | I71: 83654.93 | J71: 0 | K71: -4.7748472e-12 | L71: 21345.07 | M71: 847001 | N71: KUST - General | O71: 200179 | P71: FA179-Opex Expense | Q71: 194155 | R71: 186107.21 | S71: 150000 | T71: =S71*0.9 -> 135000 | U71: =S71*0.8 -> 120000 | V71: =S71*0.7 -> 105000 | W71: 150000 | X71: 150000 | Y71: 150000 | Z71: 150000 | AA71: 150000 | AB71: 182675.47 | AC71: 271760.63 | AD71: =S71-Y71 -> 0 | AF71: =W71-Z71 -> 0 | AH71: =X71-AA71 -> 0
A72: College of Engineering | B72: 8470315 | C72: KUST - Biomedical Engineering | D72: 435508 | E72: Laboratory - Scientific | F72: 847.8470315.1.435508.000000.847951.200179 | G72: 17444 | H72: 17444 | L72: 17444 | M72: 847951 | N72: COVID-19 Pandemic | O72: 200179 | P72: FA179-Opex Expense | Q72: 0 | R72: 0 | S72: 0 | T72: =S72*0.9 -> 0 | U72: =S72*0.8 -> 0 | V72: =S72*0.7 -> 0 | W72: 0 | X72: 0 | Y72: 0 | Z72: 0 | AA72: 0 | AB72: 0 | AC72: 0 | AD72: =S72-Y72 -> 0 | AF72: =W72-Z72 -> 0 | AH72: =X72-AA72 -> 0
A73: College of Engineering | B73: 8470315 | C73: KUST - Biomedical Engineering | D73: 436110 | E73: Printing supplies | F73: 847.8470315.1.436110.000000.847001.200179 | G73: 500 | H73: 500 | L73: 500 | M73: 847001 | N73: KUST - General | O73: 200179 | P73: FA179-Opex Expense | Q73: 1 | R73: 0 | S73: 2000 | T73: =S73*0.9 -> 1800 | U73: =S73*0.8 -> 1600 | V73: =S73*0.7 -> 1400 | W73: 2000 | X73: 2000 | Y73: 2000 | Z73: 2000 | AA73: 2000 | AB73: 0 | AC73: 0 | AD73: =S73-Y73 -> 0 | AF73: =W73-Z73 -> 0 | AH73: =X73-AA73 -> 0
A74: College of Engineering | B74: 8470320 | C74: KUST - Chemical Engineering | D74: 425763 | E74: Student Project Expenses | F74: 847.8470320.1.425763.000000.847001.200179 | G74: 20000 | H74: 20000 | I74: 20000 | L74: 0 | M74: 847001 | N74: KUST - General | O74: 200179 | P74: FA179-Opex Expense | Q74: 95179 | R74: 95178.15 | S74: 100000 | T74: =S74*0.9 -> 90000 | U74: =S74*0.8 -> 80000 | V74: =S74*0.7 -> 70000 | W74: 100000 | X74: 100000 | Y74: 100000 | Z74: 100000 | AA74: 100000 | AB74: 0 | AC74: 0 | AD74: =S74-Y74 -> 0 | AF74: =W74-Z74 -> 0 | AH74: =X74-AA74 -> 0
A75: College of Engineering | B75: 8470320 | C75: KUST - Chemical Engineering | D75: 425770 | E75: Academic Missions - Combined expenses | F75: 847.8470320.1.425770.000000.847001.200179 | G75: 50000 | H75: 12750 | L75: 12750 | M75: 847001 | N75: KUST - General | O75: 200179 | P75: FA179-Opex Expense | Q75: 5990 | R75: 1493.55 | S75: 450000 | T75: =S75*0.9 -> 405000 | U75: =S75*0.8 -> 360000 | V75: =S75*0.7 -> 315000 | W75: 450000 | X75: 450000 | Y75: 450000 | Z75: 450000 | AA75: 450000 | AB75: 181371.74 | AC75: 198877.13 | AD75: =S75-Y75 -> 0 | AF75: =W75-Z75 -> 0 | AH75: =X75-AA75 -> 0
A76: College of Engineering | B76: 8470320 | C76: KUST - Chemical Engineering | D76: 426610 | E76: Computer software licenses | F76: 847.8470320.1.426610.000000.847001.200179 | G76: 18985 | H76: 51585 | I76: 26945.13 | J76: 0 | K76: 5387.08 | L76: 19252.79 | M76: 847001 | N76: KUST - General | O76: 200179 | P76: FA179-Opex Expense | Q76: 8100 | R76: 8098.97 | S76: 75000 | T76: =S76*0.9 -> 67500 | U76: =S76*0.8 -> 60000 | V76: =S76*0.7 -> 52500 | W76: 113705.9 | X76: 118919.4 | Y76: 75000 | Z76: 113705.9 | AA76: 118919.4 | AB76: 0 | AC76: 18937.99 | AD76: =S76-Y76 -> 0 | AF76: =W76-Z76 -> 0 | AH76: =X76-AA76 -> 0
A77: College of Engineering | B77: 8470320 | C77: KUST - Chemical Engineering | D77: 435350 | E77: Academic Publications | F77: 847.8470320.1.435350.000000.847001.200179 | G77: 25000 | H77: 25000 | L77: 25000 | M77: 847001 | N77: KUST - General | O77: 200179 | P77: FA179-Opex Expense | Q77: 1 | R77: 0 | S77: 50000 | T77: =S77*0.9 -> 45000 | U77: =S77*0.8 -> 40000 | V77: =S77*0.7 -> 35000 | W77: 50000 | X77: 50000 | Y77: 50000 | Z77: 50000 | AA77: 50000 | AB77: 2420.25 | AC77: 6173.61 | AD77: =S77-Y77 -> 0 | AF77: =W77-Z77 -> 0 | AH77: =X77-AA77 -> 0
A78: College of Engineering | B78: 8470320 | C78: KUST - Chemical Engineering | D78: 435508 | E78: Laboratory - Scientific | F78: 847.8470320.1.435508.000000.847001.200179 | G78: 100000 | H78: 100000 | I78: 91628 | K78: 0 | L78: 8372 | M78: 847001 | N78: KUST - General | O78: 200179 | P78: FA179-Opex Expense | Q78: 233493 | R78: 161058.6 | S78: 200000 | T78: =S78*0.9 -> 180000 | U78: =S78*0.8 -> 160000 | V78: =S78*0.7 -> 140000 | W78: 170000 | X78: 160000 | Y78: 200000 | Z78: 170000 | AA78: 160000 | AB78: 477.22 | AC78: 191336.14 | AD78: =S78-Y78 -> 0 | AF78: =W78-Z78 -> 0 | AH78: =X78-AA78 -> 0
A79: College of Engineering | B79: 8470325 | C79: KUST - Civil Engineering | D79: 425763 | E79: Student Project Expenses | F79: 847.8470325.1.425763.000000.847001.200179 | G79: 0 | H79: 35000 | I79: 30075.49 | L79: 4924.51 | M79: 847001 | N79: KUST - General | O79: 200179 | P79: FA179-Opex Expense | Q79: 89793 | R79: 89791.52 | S79: 120000 | T79: =S79*0.9 -> 108000 | U79: =S79*0.8 -> 96000 | V79: =S79*0.7 -> 84000 | W79: 135000 | X79: 135000 | Y79: 120000 | Z79: 135000 | AA79: 135000 | AB79: 56435.68 | AC79: 15676.77 | AD79: =S79-Y79 -> 0 | AF79: =W79-Z79 -> 0 | AH79: =X79-AA79 -> 0
A80: College of Engineering | B80: 8470325 | C80: KUST - Civil Engineering | D80: 426610 | E80: Computer software licenses | F80: 847.8470325.1.426610.000000.847001.200179 | G80: 23000 | H80: 0 | L80: 0 | M80: 847001 | N80: KUST - General | O80: 200179 | P80: FA179-Opex Expense | Q80: 28273 | R80: 28271.54 | S80: 34910 | T80: =S80*0.9 -> 31419 | U80: =S80*0.8 -> 27928 | V80: =S80*0.7 -> 24437 | W80: 14606 | X80: 15336 | Y80: 34910 | Z80: 14606 | AA80: 15336 | AB80: 0 | AC80: 16473.41 | AD80: =S80-Y80 -> 0 | AF80: =W80-Z80 -> 0 | AH80: =X80-AA80 -> 0
A81: College of Engineering | B81: 8470325 | C81: KUST - Civil Engineering | D81: 435508 | E81: Laboratory - Scientific | F81: 847.8470325.1.435508.000000.847001.200179 | G81: 11350 | H81: 34350 | I81: 32675.81 | J81: 0 | K81: 0 | L81: 1674.19 | M81: 847001 | N81: KUST - General | O81: 200179 | P81: FA179-Opex Expense | Q81: 53916 | R81: 54573.2 | S81: 92573 | T81: =S81*0.9 -> 83315.7 | U81: =S81*0.8 -> 74058.4 | V81: =S81*0.7 -> 64801.1 | W81: 91319 | X81: 87744 | Y81: 92573 | Z81: 91319 | AA81: 87744 | AB81: 4631.9 | AC81: 165658.56 | AD81: =S81-Y81 -> 0 | AF81: =W81-Z81 -> 0 | AH81: =X81-AA81 -> 0
A82: College of Engineering | B82: 8470325 | C82: KUST - Civil Engineering | D82: 435509 | E82: Laboratory - Veterinary | F82: 847.8470325.1.435509.000000.847001.200179 | G82: 0 | H82: 0 | L82: 0 | M82: 847001 | N82: KUST - General | O82: 200179 | P82: FA179-Opex Expense | Q82: 0 | R82: 0 | S82: 0 | T82: =S82*0.9 -> 0 | U82: =S82*0.8 -> 0 | V82: =S82*0.7 -> 0 | W82: 0 | X82: 0 | Y82: 0 | Z82: 0 | AA82: 0 | AB82: 0 | AC82: 0 | AD82: =S82-Y82 -> 0 | AF82: =W82-Z82 -> 0 | AH82: =X82-AA82 -> 0
A83: College of Engineering | B83: 8470325 | C83: KUST - Civil Engineering | D83: 436110 | E83: Printing supplies | F83: 847.8470325.1.436110.000000.847001.200179 | G83: 0 | H83: 0 | L83: 0 | M83: 847001 | N83: KUST - General | O83: 200179 | P83: FA179-Opex Expense | Q83: 1 | R83: 0 | S83: 0 | T83: =S83*0.9 -> 0 | U83: =S83*0.8 -> 0 | V83: =S83*0.7 -> 0 | W83: 0 | X83: 0 | Y83: 0 | Z83: 0 | AA83: 0 | AB83: 0 | AC83: 367.5 | AD83: =S83-Y83 -> 0 | AF83: =W83-Z83 -> 0 | AH83: =X83-AA83 -> 0
A84: College of Engineering | B84: 8470330 | C84: KUST - Electrical & Computer Engineering | D84: 425763 | E84: Student Project Expenses | F84: 847.8470330.1.425763.000000.847001.200179 | G84: 180000 | H84: 180000 | I84: 110008.23 | L84: 69991.77 | M84: 847001 | N84: KUST - General | O84: 200179 | P84: FA179-Opex Expense | Q84: 218974 | R84: 217038 | S84: 405000 | T84: =S84*0.9 -> 364500 | U84: =S84*0.8 -> 324000 | V84: =S84*0.7 -> 283500 | W84: 405000 | X84: 405000 | Y84: 405000 | Z84: 405000 | AA84: 405000 | AB84: 172977.87 | AC84: 190324.35 | AD84: =S84-Y84 -> 0 | AF84: =W84-Z84 -> 0 | AH84: =X84-AA84 -> 0
A85: College of Engineering | B85: 8470330 | C85: KUST - Electrical & Computer Engineering | D85: 425770 | E85: Academic Missions - Combined expenses | F85: 847.8470330.1.425770.000000.847001.200179 | G85: 105000 | H85: 50000 | I85: 2000 | L85: 48000 | M85: 847001 | N85: KUST - General | O85: 200179 | P85: FA179-Opex Expense | Q85: 89907 | R85: 89564.48 | S85: 900000 | T85: =S85*0.9 -> 810000 | U85: =S85*0.8 -> 720000 | V85: =S85*0.7 -> 630000 | W85: 900000 | X85: 900000 | Y85: 900000 | Z85: 900000 | AA85: 900000 | AB85: 314018.66 | AC85: 338379.41 | AD85: =S85-Y85 -> 0 | AF85: =W85-Z85 -> 0 | AH85: =X85-AA85 -> 0
A86: College of Engineering | B86: 8470330 | C86: KUST - Electrical & Computer Engineering | D86: 426610 | E86: Computer software licenses | F86: 847.8470330.1.426610.000000.847001.200179 | G86: 312530 | H86: 296003 | I86: 63834.1 | J86: 57357.57 | K86: 58297.86 | L86: 116513.47 | M86: 847001 | N86: KUST - General | O86: 200179 | P86: FA179-Opex Expense | Q86: 283205 | R86: 224906.03 | S86: 720500 | T86: =S86*0.9 -> 648450 | U86: =S86*0.8 -> 576400 | V86: =S86*0.7 -> 504350 | W86: 798000 | X86: 798000 | Y86: 720500 | Z86: 798000 | AA86: 798000 | AB86: 0 | AC86: 0 | AD86: =S86-Y86 -> 0 | AF86: =W86-Z86 -> 0 | AH86: =X86-AA86 -> 0
A87: College of Engineering | B87: 8470330 | C87: KUST - Electrical & Computer Engineering | D87: 428640 | E87: Events - Awards, prizes & gifts | F87: 847.8470330.1.428640.000000.847001.200179 | G87: 0 | H87: 5000 | I87: 4487.99 | L87: 512.01 | M87: 847001 | N87: KUST - General | O87: 200179 | P87: FA179-Opex Expense | Q87: 0 | R87: 0 | S87: 302000 | T87: =S87*0.9 -> 271800 | U87: =S87*0.8 -> 241600 | V87: =S87*0.7 -> 211400 | W87: 302000 | X87: 302000 | Y87: 302000 | Z87: 302000 | AA87: 302000 | AB87: 0 | AC87: 0 | AD87: =S87-Y87 -> 0 | AF87: =W87-Z87 -> 0 | AH87: =X87-AA87 -> 0
A88: College of Engineering | B88: 8470330 | C88: KUST - Electrical & Computer Engineering | D88: 435350 | E88: Academic Publications | F88: 847.8470330.1.435350.000000.847001.200179 | G88: 5615 | H88: 55615 | I88: 29166.1 | L88: 26448.9 | M88: 847001 | N88: KUST - General | O88: 200179 | P88: FA179-Opex Expense | Q88: 270283 | R88: 269679.27 | S88: 420000 | T88: =S88*0.9 -> 378000 | U88: =S88*0.8 -> 336000 | V88: =S88*0.7 -> 294000 | W88: 441000 | X88: 441000 | Y88: 420000 | Z88: 441000 | AA88: 441000 | AB88: 30231.99 | AC88: 98310.48 | AD88: =S88-Y88 -> 0 | AF88: =W88-Z88 -> 0 | AH88: =X88-AA88 -> 0
A89: College of Engineering | B89: 8470330 | C89: KUST - Electrical & Computer Engineering | D89: 435508 | E89: Laboratory - Scientific | F89: 847.8470330.1.435508.000000.847001.200179 | G89: 32000 | H89: 32000 | I89: 31543.88 | K89: 0 | L89: 456.12 | M89: 847001 | N89: KUST - General | O89: 200179 | P89: FA179-Opex Expense | Q89: 20546 | R89: 19879.82 | S89: 20000 | T89: =S89*0.9 -> 18000 | U89: =S89*0.8 -> 16000 | V89: =S89*0.7 -> 14000 | W89: 20000 | X89: 20000 | Y89: 20000 | Z89: 20000 | AA89: 20000 | AB89: 21905.39 | AC89: 13925.94 | AD89: =S89-Y89 -> 0 | AF89: =W89-Z89 -> 0 | AH89: =X89-AA89 -> 0
A90: College of Engineering | B90: 8470330 | C90: KUST - Electrical & Computer Engineering | D90: 436600 | E90: Training/Teaching equipment and other educational aid | F90: 847.8470330.1.436600.000000.847001.200179 | G90: 0 | H90: 16527 | J90: 16520 | L90: 7 | M90: 847001 | N90: KUST - General | O90: 200179 | P90: FA179-Opex Expense | Q90: 0 | R90: 0 | S90: 60000 | T90: =S90*0.9 -> 54000 | U90: =S90*0.8 -> 48000 | V90: =S90*0.7 -> 42000 | W90: 16000 | X90: 16000 | Y90: 60000 | Z90: 16000 | AA90: 16000 | AB90: 7910.22 | AC90: 0 | AD90: =S90-Y90 -> 0 | AF90: =W90-Z90 -> 0 | AH90: =X90-AA90 -> 0
A91: College of Engineering | B91: 8470335 | C91: KUST - Industrial & Systems Engineering | D91: 425763 | E91: Student Project Expenses | F91: 847.8470335.1.425763.000000.847001.200179 | G91: 25000 | H91: 25000 | I91: 25000 | L91: 0 | M91: 847001 | N91: KUST - General | O91: 200179 | P91: FA179-Opex Expense | Q91: 40127 | R91: 40125.89 | S91: 50000 | T91: =S91*0.9 -> 45000 | U91: =S91*0.8 -> 40000 | V91: =S91*0.7 -> 35000 | W91: 60000 | X91: 70000 | Y91: 50000 | Z91: 60000 | AA91: 70000 | AB91: 0 | AC91: 23595.32 | AD91: =S91-Y91 -> 0 | AF91: =W91-Z91 -> 0 | AH91: =X91-AA91 -> 0
A92: College of Engineering | B92: 8470335 | C92: KUST - Industrial & Systems Engineering | D92: 425770 | E92: Academic Missions - Combined expenses | F92: 847.8470335.1.425770.000000.847001.200179 | G92: 75000 | H92: 75000 | I92: -3762.15 | L92: 78762.15 | M92: 847001 | N92: KUST - General | O92: 200179 | P92: FA179-Opex Expense | Q92: 54556 | R92: 54554.56 | S92: 270000 | T92: =S92*0.9 -> 243000 | U92: =S92*0.8 -> 216000 | V92: =S92*0.7 -> 189000 | W92: 300000 | X92: 315000 | Y92: 270000 | Z92: 300000 | AA92: 315000 | AB92: 115188.88 | AC92: 124462.87 | AD92: =S92-Y92 -> 0 | AF92: =W92-Z92 -> 0 | AH92: =X92-AA92 -> 0
A93: College of Engineering | B93: 8470335 | C93: KUST - Industrial & Systems Engineering | D93: 426610 | E93: Computer software licenses | F93: 847.8470335.1.426610.000000.847001.200179 | G93: 149370 | H93: 149370 | I93: 40542.84 | J93: 77260.02 | K93: 22440.77 | L93: 9126.37 | M93: 847001 | N93: KUST - General | O93: 200179 | P93: FA179-Opex Expense | Q93: 137795 | R93: 124805.06 | S93: 150257 | T93: =S93*0.9 -> 135231.3 | U93: =S93*0.8 -> 120205.6 | V93: =S93*0.7 -> 105179.9 | W93: 161319.6 | X93: 161319.6 | Y93: 150257 | Z93: 161319.6 | AA93: 161319.6 | AB93: 31519.03 | AC93: 111804.23 | AD93: =S93-Y93 -> 0 | AF93: =W93-Z93 -> 0 | AH93: =X93-AA93 -> 0
A94: College of Engineering | B94: 8470335 | C94: KUST - Industrial & Systems Engineering | D94: 435350 | E94: Academic Publications | F94: 847.8470335.1.435350.000000.847001.200179 | G94: 51520 | H94: 51520 | I94: 22479.86 | L94: 29040.14 | M94: 847001 | N94: KUST - General | O94: 200179 | P94: FA179-Opex Expense | Q94: 38005 | R94: 38004.2 | S94: 51520 | T94: =S94*0.9 -> 46368 | U94: =S94*0.8 -> 41216 | V94: =S94*0.7 -> 36064 | W94: 57960 | X94: 64400 | Y94: 51520 | Z94: 57960 | AA94: 64400 | AB94: 0 | AC94: 5625.53 | AD94: =S94-Y94 -> 0 | AF94: =W94-Z94 -> 0 | AH94: =X94-AA94 -> 0
A95: College of Engineering | B95: 8470335 | C95: KUST - Industrial & Systems Engineering | D95: 435508 | E95: Laboratory - Scientific | F95: 847.8470335.1.435508.000000.847001.200179 | G95: 60000 | H95: 60000 | I95: 37764.01 | J95: 0 | K95: 13424 | L95: 8811.99 | M95: 847001 | N95: KUST - General | O95: 200179 | P95: FA179-Opex Expense | Q95: 112268 | R95: 99043.8 | S95: 139000 | T95: =S95*0.9 -> 125100 | U95: =S95*0.8 -> 111200 | V95: =S95*0.7 -> 97300 | W95: 80000 | X95: 88000 | Y95: 139000 | Z95: 80000 | AA95: 88000 | AB95: 2430.08 | AC95: 156426.09 | AD95: =S95-Y95 -> 0 | AF95: =W95-Z95 -> 0 | AH95: =X95-AA95 -> 0
A96: College of Engineering | B96: 8470335 | C96: KUST - Industrial & Systems Engineering | D96: 436110 | E96: Printing supplies | F96: 847.8470335.1.436110.000000.847001.200179 | G96: 0 | H96: 0 | L96: 0 | M96: 847001 | N96: KUST - General | O96: 200179 | P96: FA179-Opex Expense | Q96: 3779 | R96: 3777.8 | S96: 4000 | T96: =S96*0.9 -> 3600 | U96: =S96*0.8 -> 3200 | V96: =S96*0.7 -> 2800 | W96: 800 | X96: 800 | Y96: 4000 | Z96: 800 | AA96: 800 | AB96: 0 | AC96: 3577 | AD96: =S96-Y96 -> 0 | AF96: =W96-Z96 -> 0 | AH96: =X96-AA96 -> 0
A97: College of Engineering | B97: 8470335 | C97: KUST - Industrial & Systems Engineering | D97: 436600 | E97: Training/Teaching equipment and other educational aid | F97: 847.8470335.1.436600.000000.847001.200179 | G97: 13858 | H97: 13858 | I97: 11192.69 | J97: 0 | K97: 0 | L97: 2665.31 | M97: 847001 | N97: KUST - General | O97: 200179 | P97: FA179-Opex Expense | Q97: 12141 | R97: 12140.5 | S97: 12000 | T97: =S97*0.9 -> 10800 | U97: =S97*0.8 -> 9600 | V97: =S97*0.7 -> 8400 | W97: 12000 | X97: 14400 | Y97: 12000 | Z97: 12000 | AA97: 14400 | AB97: 2000 | AC97: 0 | AD97: =S97-Y97 -> 0 | AF97: =W97-Z97 -> 0 | AH97: =X97-AA97 -> 0
A98: College of Engineering | B98: 8470340 | C98: KUST - Mechanical Engineering | D98: 425763 | E98: Student Project Expenses | F98: 847.8470340.1.425763.000000.847001.200179 | G98: 300000 | H98: 300000 | I98: 148453.21 | L98: 151546.79 | M98: 847001 | N98: KUST - General | O98: 200179 | P98: FA179-Opex Expense | Q98: 225404 | R98: 225403.24 | S98: 480000 | T98: =S98*0.9 -> 432000 | U98: =S98*0.8 -> 384000 | V98: =S98*0.7 -> 336000 | W98: 480000 | X98: 480000 | Y98: 480000 | Z98: 480000 | AA98: 480000 | AB98: 317803.44 | AC98: 208320.92 | AD98: =S98-Y98 -> 0 | AF98: =W98-Z98 -> 0 | AH98: =X98-AA98 -> 0
A99: College of Engineering | B99: 8470340 | C99: KUST - Mechanical Engineering | D99: 425770 | E99: Academic Missions - Combined expenses | F99: 847.8470340.1.425770.000000.847001.200179 | G99: 52050 | H99: 52050 | I99: 13078.03 | L99: 38971.97 | M99: 847001 | N99: KUST - General | O99: 200179 | P99: FA179-Opex Expense | Q99: 54308 | R99: 54007.37 | S99: 630000 | T99: =S99*0.9 -> 567000 | U99: =S99*0.8 -> 504000 | V99: =S99*0.7 -> 441000 | W99: 555000 | X99: 600000 | Y99: 630000 | Z99: 555000 | AA99: 600000 | AB99: 315890.03 | AC99: 276102.03 | AD99: =S99-Y99 -> 0 | AF99: =W99-Z99 -> 0 | AH99: =X99-AA99 -> 0
A100: College of Engineering | B100: 8470340 | C100: KUST - Mechanical Engineering | D100: 426610 | E100: Computer software licenses | F100: 847.8470340.1.426610.000000.847001.200179 | G100: 209338 | H100: 209338 | I100: 29192.5 | J100: 91633.4 | K100: 41872.2 | L100: 46639.9 | M100: 847001 | N100: KUST - General | O100: 200179 | P100: FA179-Opex Expense | Q100: 173962 | R100: 173961.31 | S100: 210000 | T100: =S100*0.9 -> 189000 | U100: =S100*0.8 -> 168000 | V100: =S100*0.7 -> 147000 | W100: 230000 | X100: 220000 | Y100: 210000 | Z100: 230000 | AA100: 220000 | AB100: 126016.66 | AC100: 93817.55 | AD100: =S100-Y100 -> 0 | AF100: =W100-Z100 -> 0 | AH100: =X100-AA100 -> 0
...

Sheet Dof 2022 Items Support
A1: Cost Center Code | B1: Cost Center Description | C1: Account Code | D1: Account Description | E1: GL Account Code Combination | F1: Future-1 Description | G1: Future-1 | H1: Future-2 Description | I1: Future-2 | J1: Itemised Details/Calculation method | K1: Quantity (expected) | L1: Rate (expected) | M1: 2022 Budget
A2: 8470110 | B2: KUST - Office of the President | C2: 420570 | D2: Academic Collaborative Partnership Services | E2: =CONCATENATE(847,".",A2,".",1,".",C2,".","000000",".",G2,".",I2) -> 847.8470110.1.420570.000000.847001.200179 | F2: KUST - General | G2: 847001 | H2: FA179-Opex Expense | I2: 200179 | J2: For payments made to collaborating institutions, as part of partnership agreements. This would include a potential affilation partnership for the greaduate school of busineess | K2: 1 | L2: 10000000 | M2: 8000000
A3: 8470230 | B3: KUST - Graduate Studies | C3: 425749 | D3: Postgraduate Student Salaries | E3: =CONCATENATE(847,".",A3,".",1,".",C3,".","000000",".",G3,".",I3) -> 847.8470230.1.425749.000000.847001.200179 | F3: KUST - General | G3: 847001 | H3: FA179-Opex Expense | I3: 200179 | J3: Students Stipend | K3: 1151 | L3: 146334 | M3: 140817695
A4: 8470305 | B4: KUST - Dean Of Engineering | C4: 420550 | D4: Academic Advisory Service | E4: =CONCATENATE(847,".",A4,".",1,".",C4,".","000000",".",G4,".",I4) -> 847.8470305.1.420550.000000.847001.200179 | F4: KUST - General | G4: 847001 | H4: FA179-Opex Expense | I4: 200179 | J4: advisory meeting | K4: 1 | L4: 10000 | M4: 10000
A5: 8470305 | B5: KUST - Dean Of Engineering | C5: 420570 | D5: Academic Collaborative Partnership Services | E5: =CONCATENATE(847,".",A5,".",1,".",C5,".","000000",".",G5,".",I5) -> 847.8470305.1.420570.000000.847001.200179 | F5: KUST - General | G5: 847001 | H5: FA179-Opex Expense | I5: 200179 | J5: local industry partnerships | K5: 1 | L5: 10000 | M5: 10000
A6: 8470305 | B6: KUST - Dean Of Engineering | C6: 421700 | D6: Standards certification (e.g. ISO) | E6: =CONCATENATE(847,".",A6,".",1,".",C6,".","000000",".",G6,".",I6) -> 847.8470305.1.421700.000000.847001.200179 | F6: KUST - General | G6: 847001 | H6: FA179-Opex Expense | I6: 200179 | J6: 3 programs CAA Accreditation 150K each; 9 UG programs ABET acreditation yearly | K6: 12 | L6: 42167 | M6: 506004
A7: 8470305 | B7: KUST - Dean Of Engineering | C7: 425510 | D7: Conferences, seminars and exhibitions and other events: - Local Events | E7: =CONCATENATE(847,".",A7,".",1,".",C7,".","000000",".",G7,".",I7) -> 847.8470305.1.425510.000000.847001.200179 | F7: KUST - General | G7: 847001 | H7: FA179-Opex Expense | I7: 200179 | J7: support for local events | K7: 2 | L7: 10000 | M7: 20000
A8: 8470305 | B8: KUST - Dean Of Engineering | C8: 425762 | D8: Student Internship | E8: =CONCATENATE(847,".",A8,".",1,".",C8,".","000000",".",G8,".",I8) -> 847.8470305.1.425762.000000.847001.200179 | F8: KUST - General | G8: 847001 | H8: FA179-Opex Expense | I8: 200179 | M8: 0
A9: 8470305 | B9: KUST - Dean Of Engineering | C9: 425763 | D9: Student Project Expenses | E9: =CONCATENATE(847,".",A9,".",1,".",C9,".","000000",".",G9,".",I9) -> 847.8470305.1.425763.000000.847001.200179 | F9: KUST - General | G9: 847001 | H9: FA179-Opex Expense | I9: 200179 | J9: support for 10% of senior engineering UG student 2K each for projects | K9: 50 | L9: 2000 | M9: 100000
A10: 8470305 | B10: KUST - Dean Of Engineering | C10: 425770 | D10: Academic Missions - Combined expenses | E10: =CONCATENATE(847,".",A10,".",1,".",C10,".","000000",".",G10,".",I10) -> 847.8470305.1.425770.000000.847001.200179 | F10: KUST - General | G10: 847001 | H10: FA179-Opex Expense | I10: 200179 | J10: one conference for 25% of faculty | K10: 50 | L10: 15000 | M10: 750000
A11: 8470305 | B11: KUST - Dean Of Engineering | C11: 425900 | D11: Entertainment and hospitality | E11: =CONCATENATE(847,".",A11,".",1,".",C11,".","000000",".",G11,".",I11) -> 847.8470305.1.425900.000000.847001.200179 | F11: KUST - General | G11: 847001 | H11: FA179-Opex Expense | I11: 200179 | J11: 1 Chair retreats and 2 faculty meeting | K11: 3 | L11: 6000 | M11: 18000
A12: 8470305 | B12: KUST - Dean Of Engineering | C12: 426610 | D12: Computer software licenses | E12: =CONCATENATE(847,".",A12,".",1,".",C12,".","000000",".",G12,".",I12) -> 847.8470305.1.426610.000000.847001.200179 | F12: KUST - General | G12: 847001 | H12: FA179-Opex Expense | I12: 200179 | J12: software for multi-departments | K12: 1 | L12: 100000 | M12: 100000
A13: 8470305 | B13: KUST - Dean Of Engineering | C13: 428090 | D13: Business Travel - Combined expenses | E13: =CONCATENATE(847,".",A13,".",1,".",C13,".","000000",".",G13,".",I13) -> 847.8470305.1.428090.000000.847001.200179 | F13: KUST - General | G13: 847001 | H13: FA179-Opex Expense | I13: 200179 | J13: one business trip for deans | K13: 1 | L13: 35000 | M13: 35000
A14: 8470305 | B14: KUST - Dean Of Engineering | C14: 428400 | D14: Sponsorship expenses/contributions | E14: =CONCATENATE(847,".",A14,".",1,".",C14,".","000000",".",G14,".",I14) -> 847.8470305.1.428400.000000.847001.200179 | F14: KUST - General | G14: 847001 | H14: FA179-Opex Expense | I14: 200179 | M14: 0
A15: 8470305 | B15: KUST - Dean Of Engineering | C15: 428640 | D15: Events - Awards, prizes & gifts | E15: =CONCATENATE(847,".",A15,".",1,".",C15,".","000000",".",G15,".",I15) -> 847.8470305.1.428640.000000.847001.200179 | F15: KUST - General | G15: 847001 | H15: FA179-Opex Expense | I15: 200179 | J15: 3 awards events; 2 UG Dean's list, 1 Gr best Thesis | K15: 3 | L15: 15000 | M15: 45000
A16: 8470305 | B16: KUST - Dean Of Engineering | C16: 430330 | D16: Rental - Motor vehicles | E16: =CONCATENATE(847,".",A16,".",1,".",C16,".","000000",".",G16,".",I16) -> 847.8470305.1.430330.000000.847001.200179 | F16: KUST - General | G16: 847001 | H16: FA179-Opex Expense | I16: 200179 | M16: 0
A17: 8470305 | B17: KUST - Dean Of Engineering | C17: 432209 | D17: Laboratory equipment | E17: =CONCATENATE(847,".",A17,".",1,".",C17,".","000000",".",G17,".",I17) -> 847.8470305.1.432209.000000.847001.200179 | F17: KUST - General | G17: 847001 | H17: FA179-Opex Expense | I17: 200179 | M17: 0
A18: 8470305 | B18: KUST - Dean Of Engineering | C18: 432690 | D18: Plant, machinery and heavy equipment, not mentioned elsewhere | E18: =CONCATENATE(847,".",A18,".",1,".",C18,".","000000",".",G18,".",I18) -> 847.8470305.1.432690.000000.847001.200179 | F18: KUST - General | G18: 847001 | H18: FA179-Opex Expense | I18: 200179 | M18: 0
A19: 8470305 | B19: KUST - Dean Of Engineering | C19: 435350 | D19: Academic Publications | E19: =CONCATENATE(847,".",A19,".",1,".",C19,".","000000",".",G19,".",I19) -> 847.8470305.1.435350.000000.847001.200179 | F19: KUST - General | G19: 847001 | H19: FA179-Opex Expense | I19: 200179 | J19: support for open access publications - IEEE (180K) and others per publication (10pub x 8k) | K19: 1 | L19: 260000 | M19: 260000
A20: 8470305 | B20: KUST - Dean Of Engineering | C20: 435508 | D20: Laboratory - Scientific | E20: =CONCATENATE(847,".",A20,".",1,".",C20,".","000000",".",G20,".",I20) -> 847.8470305.1.435508.000000.847001.200179 | F20: KUST - General | G20: 847001 | H20: FA179-Opex Expense | I20: 200179 | J20: lab supplies for college shared facilities | K20: 1 | L20: 100000 | M20: 100000
A21: 8470305 | B21: KUST - Dean Of Engineering | C21: 435530 | D21: School consumables, not specifically mentioned elsewhere | E21: =CONCATENATE(847,".",A21,".",1,".",C21,".","000000",".",G21,".",I21) -> 847.8470305.1.435530.000000.847001.200179 | F21: KUST - General | G21: 847001 | H21: FA179-Opex Expense | I21: 200179 | M21: 0
A22: 8470305 | B22: KUST - Dean Of Engineering | C22: 436110 | D22: Printing supplies | E22: =CONCATENATE(847,".",A22,".",1,".",C22,".","000000",".",G22,".",I22) -> 847.8470305.1.436110.000000.847001.200179 | F22: KUST - General | G22: 847001 | H22: FA179-Opex Expense | I22: 200179 | M22: 0
A23: 8470305 | B23: KUST - Dean Of Engineering | C23: 436600 | D23: Training/Teaching equipment and other educational aid | E23: =CONCATENATE(847,".",A23,".",1,".",C23,".","000000",".",G23,".",I23) -> 847.8470305.1.436600.000000.847001.200179 | F23: KUST - General | G23: 847001 | H23: FA179-Opex Expense | I23: 200179 | J23: local technical training (for 5 staff, 5K per staff) | K23: 5 | L23: 5000 | M23: 25000
A24: 8470305 | B24: KUST - Dean Of Engineering | C24: 492316 | D24: Laboratory equipment | E24: =CONCATENATE(847,".",A24,".",1,".",C24,".","000000",".",G24,".",I24) -> 847.8470305.1.492316.000000.847001.300180 | F24: KUST - General | G24: 847001 | H24: FA180-Capex Expense | I24: 300180 | M24: 0
A25: 8470310 | B25: KUST - Aerospace Engineering | C25: 420550 | D25: Academic Advisory Service | E25: =CONCATENATE(847,".",A25,".",1,".",C25,".","000000",".",G25,".",I25) -> 847.8470310.1.420550.000000.847001.200179 | F25: KUST - General | G25: 847001 | H25: FA179-Opex Expense | I25: 200179 | J25: 2 Board meetings of about 10 members. AED 10k per meeting. | K25: 2 | L25: 10000 | M25: 20000
A26: 8470310 | B26: KUST - Aerospace Engineering | C26: 425510 | D26: Conferences, seminars and exhibitions and other events: - Local Events | E26: =CONCATENATE(847,".",A26,".",1,".",C26,".","000000",".",G26,".",I26) -> 847.8470310.1.425510.000000.847001.200179 | F26: KUST - General | G26: 847001 | H26: FA179-Opex Expense | I26: 200179 | K26: 3 | L26: 5000 | M26: 15000
A27: 8470310 | B27: KUST - Aerospace Engineering | C27: 425760 | D27: Student activities & field trip expenses | E27: =CONCATENATE(847,".",A27,".",1,".",C27,".","000000",".",G27,".",I27) -> 847.8470310.1.425760.000000.847001.200179 | F27: KUST - General | G27: 847001 | H27: FA179-Opex Expense | I27: 200179 | J27: Students travel to the US for Design Build Fly competetion | K27: 15 | L27: 10000 | M27: 150000
A28: 8470310 | B28: KUST - Aerospace Engineering | C28: 425763 | D28: Student Project Expenses | E28: =CONCATENATE(847,".",A28,".",1,".",C28,".","000000",".",G28,".",I28) -> 847.8470310.1.425763.000000.847001.200179 | F28: KUST - General | G28: 847001 | H28: FA179-Opex Expense | I28: 200179 | J28: Senior design projects for 70 students | K28: 70 | L28: 5000 | M28: 350000
A29: 8470310 | B29: KUST - Aerospace Engineering | C29: 425770 | D29: Academic Missions - Combined expenses | E29: =CONCATENATE(847,".",A29,".",1,".",C29,".","000000",".",G29,".",I29) -> 847.8470310.1.425770.000000.847001.200179 | F29: KUST - General | G29: 847001 | H29: FA179-Opex Expense | I29: 200179 | J29: International conference travel and registration fee | K29: 14 | L29: 15000 | M29: 210000
A30: 8470310 | B30: KUST - Aerospace Engineering | C30: 425900 | D30: Entertainment and hospitality | E30: =CONCATENATE(847,".",A30,".",1,".",C30,".","000000",".",G30,".",I30) -> 847.8470310.1.425900.000000.847001.200179 | F30: KUST - General | G30: 847001 | H30: FA179-Opex Expense | I30: 200179 | J30: 12 Faculty Meeting (one per month) + 5 visits by professional organizations to the department. | K30: 17 | L30: 500 | M30: 8500
A31: 8470310 | B31: KUST - Aerospace Engineering | C31: 426610 | D31: Computer software licenses | E31: =CONCATENATE(847,".",A31,".",1,".",C31,".","000000",".",G31,".",I31) -> 847.8470310.1.426610.000000.847001.200179 | F31: KUST - General | G31: 847001 | H31: FA179-Opex Expense | I31: 200179 | J31: Software renewal as per the CoE list | K31: 1 | L31: 9114 | M31: 9114
A32: 8470310 | B32: KUST - Aerospace Engineering | C32: 428090 | D32: Business Travel - Combined expenses | E32: =CONCATENATE(847,".",A32,".",1,".",C32,".","000000",".",G32,".",I32) -> 847.8470310.1.428090.000000.847001.200179 | F32: KUST - General | G32: 847001 | H32: FA179-Opex Expense | I32: 200179 | J32: 2 business trips by the Chair or a faculty to international universities or organizations to promote the department and KU. | K32: 2 | L32: 20000 | M32: 40000
A33: 8470310 | B33: KUST - Aerospace Engineering | C33: 430120 | D33: Rental - Buildings, other than staff residences | E33: =CONCATENATE(847,".",A33,".",1,".",C33,".","000000",".",G33,".",I33) -> 847.8470310.1.430120.000000.847001.200179 | F33: KUST - General | G33: 847001 | H33: FA179-Opex Expense | I33: 200179 | M33: 0
A34: 8470310 | B34: KUST - Aerospace Engineering | C34: 432209 | D34: Laboratory equipment | E34: =CONCATENATE(847,".",A34,".",1,".",C34,".","000000",".",G34,".",I34) -> 847.8470310.1.432209.000000.847001.200179 | F34: KUST - General | G34: 847001 | H34: FA179-Opex Expense | I34: 200179 | J34: Aerospace Lab Maintenance | K34: 1 | L34: 80000 | M34: 80000
A35: 8470310 | B35: KUST - Aerospace Engineering | C35: 435350 | D35: Academic Publications | E35: =CONCATENATE(847,".",A35,".",1,".",C35,".","000000",".",G35,".",I35) -> 847.8470310.1.435350.000000.847001.200179 | F35: KUST - General | G35: 847001 | H35: FA179-Opex Expense | I35: 200179 | J35: Publications in open access Q1 journals $3500 per paper | K35: 14 | L35: 13000 | M35: 182000
A36: 8470310 | B36: KUST - Aerospace Engineering | C36: 435508 | D36: Laboratory - Scientific | E36: =CONCATENATE(847,".",A36,".",1,".",C36,".","000000",".",G36,".",I36) -> 847.8470310.1.435508.000000.847001.200179 | F36: KUST - General | G36: 847001 | H36: FA179-Opex Expense | I36: 200179 | J36: Lab consumables | K36: 1 | L36: 80000 | M36: 80000
A37: 8470310 | B37: KUST - Aerospace Engineering | C37: 436110 | D37: Printing supplies | E37: =CONCATENATE(847,".",A37,".",1,".",C37,".","000000",".",G37,".",I37) -> 847.8470310.1.436110.000000.847001.200179 | F37: KUST - General | G37: 847001 | H37: FA179-Opex Expense | I37: 200179 | J37: Printing services to the department (brochures, posters, handouts, etc) | K37: 8 | L37: 500 | M37: 4000
A38: 8470310 | B38: KUST - Aerospace Engineering | C38: 436600 | D38: Training/Teaching equipment and other educational aid | E38: =CONCATENATE(847,".",A38,".",1,".",C38,".","000000",".",G38,".",I38) -> 847.8470310.1.436600.000000.847001.200179 | F38: KUST - General | G38: 847001 | H38: FA179-Opex Expense | I38: 200179 | J38: Training/Teaching equipment and other educational aid | K38: 5 | L38: 1000 | M38: 5000
A39: 8470310 | B39: KUST - Aerospace Engineering | C39: 492316 | D39: Laboratory equipment | E39: =CONCATENATE(847,".",A39,".",1,".",C39,".","000000",".",G39,".",I39) -> 847.8470310.1.492316.000000.847001.300180 | F39: KUST - General | G39: 847001 | H39: FA180-Capex Expense | I39: 300180 | J39: Work stations for new faculty and lab upgrade | K39: 10 | L39: 12776 | M39: 127760
A40: 8470310 | B40: KUST - Aerospace Engineering | C40: 492316 | D40: Laboratory equipment | E40: =CONCATENATE(847,".",A40,".",1,".",C40,".","000000",".",G40,".",I40) -> 847.8470310.1.492316.000000.847001.300180 | F40: KUST - General | G40: 847001 | H40: FA180-Capex Expense | I40: 300180 | J40: Aircraft Design Lab, flight simulator | K40: 1 | L40: 1091000 | M40: 1091000
A41: 8470310 | B41: KUST - Aerospace Engineering | C41: 492316 | D41: Laboratory equipment | E41: =CONCATENATE(847,".",A41,".",1,".",C41,".","000000",".",G41,".",I41) -> 847.8470310.1.492316.000000.847001.300180 | F41: KUST - General | G41: 847001 | H41: FA180-Capex Expense | I41: 300180 | J41: Catia software for Aero 215 Introduction to Aerospace Engineering (100 seats) | K41: 1 | L41: 91145 | M41: 91145
A42: 8470310 | B42: KUST - Aerospace Engineering | C42: 492316 | D42: Laboratory equipment | E42: =CONCATENATE(847,".",A42,".",1,".",C42,".","000000",".",G42,".",I42) -> 847.8470310.1.492316.000000.847001.300180 | F42: KUST - General | G42: 847001 | H42: FA180-Capex Expense | I42: 300180 | J42: Gravitation constant measuring equipment for space lab aero 465 | K42: 1 | L42: 38115 | M42: 38115
A43: 8470310 | B43: KUST - Aerospace Engineering | C43: 492316 | D43: Laboratory equipment | E43: =CONCATENATE(847,".",A43,".",1,".",C43,".","000000",".",G43,".",I43) -> 847.8470310.1.492316.000000.847001.300180 | F43: KUST - General | G43: 847001 | H43: FA180-Capex Expense | I43: 300180 | J43: National Instruments' software needed for controlling stepper motors that will be used in student projects. | K43: 1 | L43: 14330 | M43: 14330
A44: 8470315 | B44: KUST - Biomedical Engineering | C44: 420550 | D44: Academic Advisory Service | E44: =CONCATENATE(847,".",A44,".",1,".",C44,".","000000",".",G44,".",I44) -> 847.8470315.1.420550.000000.847001.200179 | F44: KUST - General | G44: 847001 | H44: FA179-Opex Expense | I44: 200179 | J44: Advisory board meeting expenses (2hrs per meeting, 1 meeting per year) | K44: 1 | L44: 1000 | M44: 1000
A45: 8470315 | B45: KUST - Biomedical Engineering | C45: 425510 | D45: Conferences, seminars and exhibitions and other events: - Local Events | E45: =CONCATENATE(847,".",A45,".",1,".",C45,".","000000",".",G45,".",I45) -> 847.8470315.1.425510.000000.847001.200179 | F45: KUST - General | G45: 847001 | H45: FA179-Opex Expense | I45: 200179 | J45: INTERACTION series: 7 seminars per year; Students' exhibitions (3 per year) | K45: 10 | L45: 400 | M45: 4000
... A108: 8470325 | B108: KUST - Civil Engineering | C108: 425770 | D108: Academic Missions - Combined expenses | E108: =CONCATENATE(847,".",A108,".",1,".",C108,".","000000",".",G108,".",I108) -> 847.8470325.1.425770.000000.847001.200179 | F108: KUST - General | G108: 847001 | H108: FA179-Opex Expense | I108: 200179 | J108: AED 15000 per Faculty to address the registration, travel & living costs of 1 international Conference per year | K108: 11 | L108: 15000 | M108: 165000
A109: 8470325 | B109: KUST - Civil Engineering | C109: 425900 | D109: Entertainment and hospitality | E109: =CONCATENATE(847,".",A109,".",1,".",C109,".","000000",".",G109,".",I109) -> 847.8470325.1.425900.000000.847001.200179 | F109: KUST - General | G109: 847001 | H109: FA179-Opex Expense | I109: 200179 | M109: 0
A110: 8470325 | B110: KUST - Civil Engineering | C110: 426610 | D110: Computer software licenses | E110: =CONCATENATE(847,".",A110,".",1,".",C110,".","000000",".",G110,".",I110) -> 847.8470325.1.426610.000000.847001.200179 | F110: KUST - General | G110: 847001 | H110: FA179-Opex Expense | I110: 200179 | J110: Costs vary per license. Details in the form: ADDA IT Form v2. A total cost for licenses renewal is shown in columns W and X | K110: 1 | L110: 34910 | M110: 34910
A111: 8470325 | B111: KUST - Civil Engineering | C111: 428090 | D111: Business Travel - Combined expenses | E111: =CONCATENATE(847,".",A111,".",1,".",C111,".","000000",".",G111,".",I111) -> 847.8470325.1.428090.000000.847001.200179 | F111: KUST - General | G111: 847001 | H111: FA179-Opex Expense | I111: 200179 | J111: Senior Faculty participation in Board & Executive Council meetings of International Organizations and Q1 Journals | K111: 2 | L111: 15000 | M111: 30000
A112: 8470325 | B112: KUST - Civil Engineering | C112: 432209 | D112: Laboratory equipment | E112: =CONCATENATE(847,".",A112,".",1,".",C112,".","000000",".",G112,".",I112) -> 847.8470325.1.432209.000000.847001.200179 | F112: KUST - General | G112: 847001 | H112: FA179-Opex Expense | I112: 200179 | J112: Expenses for the yearly maintenance of CIVE labs equipment utilized for teaching purposes. Quotes from individual suppliers are included in the folder Maintenance Quotations | K112: 1 | L112: 171550 | M112: 171550
A113: 8470325 | B113: KUST - Civil Engineering | C113: 435350 | D113: Academic Publications | E113: =CONCATENATE(847,".",A113,".",1,".",C113,".","000000",".",G113,".",I113) -> 847.8470325.1.435350.000000.847001.200179 | F113: KUST - General | G113: 847001 | H113: FA179-Opex Expense | I113: 200179 | J113: Open Access Q1 Journal submissions | K113: 8 | L113: 10000 | M113: 80000
A114: 8470325 | B114: KUST - Civil Engineering | C114: 435508 | D114: Laboratory - Scientific | E114: =CONCATENATE(847,".",A114,".",1,".",C114,".","000000",".",G114,".",I114) -> 847.8470325.1.435508.000000.847001.200179 | F114: KUST - General | G114: 847001 | H114: FA179-Opex Expense | I114: 200179 | J114: Consumables for the operation of the CIVE instructional labs. Quotes from individual suppliers are listed per item in the Excel sheet "CIVE OPEX Lab Scientific list" in the folder "CIVE OPEX Quotations" | K114: 1 | L114: 92573 | M114: 92573
A115: 8470325 | B115: KUST - Civil Engineering | C115: 436110 | D115: Printing supplies | E115: =CONCATENATE(847,".",A115,".",1,".",C115,".","000000",".",G115,".",I115) -> 847.8470325.1.436110.000000.847001.200179 | F115: KUST - General | G115: 847001 | H115: FA179-Opex Expense | I115: 200179 | M115: 0
A116: 8470325 | B116: KUST - Civil Engineering | C116: 436600 | D116: Training/Teaching equipment and other educational aid | E116: =CONCATENATE(847,".",A116,".",1,".",C116,".","000000",".",G116,".",I116) -> 847.8470325.1.436600.000000.847001.200179 | F116: KUST - General | G116: 847001 | H116: FA179-Opex Expense | I116: 200179 | M116: 0
A117: 8470325 | B117: KUST - Civil Engineering | C117: 492200 | D117: Capital expense - Buildings | E117: =CONCATENATE(847,".",A117,".",1,".",C117,".","000000",".",G117,".",I117) -> 847.8470325.1.492200.000000.847001.200179 | F117: KUST - General | G117: 847001 | H117: FA179-Opex Expense | I117: 200179 | M117: 0
A118: 8470325 | B118: KUST - Civil Engineering | C118: 492316 | D118: Laboratory equipment | E118: =CONCATENATE(847,".",A118,".",1,".",C118,".","000000",".",G118,".",I118) -> 847.8470325.1.492316.000000.847001.300180 | F118: KUST - General | G118: 847001 | H118: FA180-Capex Expense | I118: 300180 | J118: Atomic Absorption Spectrophotometer | K118: 1 | L118: 272160 | M118: 272160
A119: 8470325 | B119: KUST - Civil Engineering | C119: 492316 | D119: Laboratory equipment | E119: =CONCATENATE(847,".",A119,".",1,".",C119,".","000000",".",G119,".",I119) -> 847.8470325.1.492316.000000.847001.300180 | F119: KUST - General | G119: 847001 | H119: FA180-Capex Expense | I119: 300180 | J119: Washing Machine with Disinfector for Lab Glassware | K119: 1 | L119: 24150 | M119: 24150
A120: 8470325 | B120: KUST - Civil Engineering | C120: 492316 | D120: Laboratory equipment | E120: =CONCATENATE(847,".",A120,".",1,".",C120,".","000000",".",G120,".",I120) -> 847.8470325.1.492316.000000.847001.300180 | F120: KUST - General | G120: 847001 | H120: FA180-Capex Expense | I120: 300180 | J120: Pavemix, Automatic Asphalt Mixer, 32 liters | K120: 1 | L120: 98400 | M120: 98400
A121: 8470325 | B121: KUST - Civil Engineering | C121: 492316 | D121: Laboratory equipment | E121: =CONCATENATE(847,".",A121,".",1,".",C121,".","000000",".",G121,".",I121) -> 847.8470325.1.492316.000000.847001.300180 | F121: KUST - General | G121: 847001 | H121: FA180-Capex Expense | I121: 300180 | J121: Mechanical shaker for 8" and 12" diameter sieves | K121: 1 | L121: 20700 | M121: 20700
A122: 8470325 | B122: KUST - Civil Engineering | C122: 492316 | D122: Laboratory equipment | E122: =CONCATENATE(847,".",A122,".",1,".",C122,".","000000",".",G122,".",I122) -> 847.8470325.1.492316.000000.847001.300180 | F122: KUST - General | G122: 847001 | H122: FA180-Capex Expense | I122: 300180 | J122: Sieves Set of 8" and 12" diameter | K122: 2 | L122: 6200 | M122: 12400
A123: 8470325 | B123: KUST - Civil Engineering | C123: 492316 | D123: Laboratory equipment | E123: =CONCATENATE(847,".",A123,".",1,".",C123,".","000000",".",G123,".",I123) -> 847.8470325.1.492316.000000.847001.300180 | F123: KUST - General | G123: 847001 | H123: FA180-Capex Expense | I123: 300180 | J123: Fall Cone Test Apparatus | K123: 4 | L123: 4950 | M123: 19800
A124: 8470325 | B124: KUST - Civil Engineering | C124: 492316 | D124: Laboratory equipment | E124: =CONCATENATE(847,".",A124,".",1,".",C124,".","000000",".",G124,".",I124) -> 847.8470325.1.492316.000000.847001.300180 | F124: KUST - General | G124: 847001 | H124: FA180-Capex Expense | I124: 300180 | J124: ELE Compression Machine Missing Loading Parts | K124: 1 | L124: 80000 | M124: 80000
A125: 8470325 | B125: KUST - Civil Engineering | C125: 492316 | D125: Laboratory equipment | E125: =CONCATENATE(847,".",A125,".",1,".",C125,".","000000",".",G125,".",I125) -> 847.8470325.1.492316.000000.847001.300180 | F125: KUST - General | G125: 847001 | H125: FA180-Capex Expense | I125: 300180 | J125: Consolidometer device | K125: 2 | L125: 28529 | M125: 57058
A126: 8470325 | B126: KUST - Civil Engineering | C126: 492316 | D126: Laboratory equipment | E126: =CONCATENATE(847,".",A126,".",1,".",C126,".","000000",".",G126,".",I126) -> 847.8470325.1.492316.000000.847001.300180 | F126: KUST - General | G126: 847001 | H126: FA180-Capex Expense | I126: 300180 | J126: Balance | K126: 1 | L126: 7770 | M126: 7770
A127: 8470325 | B127: KUST - Civil Engineering | C127: 492316 | D127: Laboratory equipment | E127: =CONCATENATE(847,".",A127,".",1,".",C127,".","000000",".",G127,".",I127) -> 847.8470325.1.492316.000000.847001.300180 | F127: KUST - General | G127: 847001 | H127: FA180-Capex Expense | I127: 300180 | J127: Data Logger for MTS | K127: 1 | L127: 149050 | M127: 149050
A128: 8470325 | B128: KUST - Civil Engineering | C128: 492316 | D128: Laboratory equipment | E128: =CONCATENATE(847,".",A128,".",1,".",C128,".","000000",".",G128,".",I128) -> 847.8470325.1.492316.000000.847001.300180 | F128: KUST - General | G128: 847001 | H128: FA180-Capex Expense | I128: 300180 | J128: Desktop computers | K128: 30 | L128: 3460 | M128: 103800
A129: 8470325 | B129: KUST - Civil Engineering | C129: 492316 | D129: Laboratory equipment | E129: =CONCATENATE(847,".",A129,".",1,".",C129,".","000000",".",G129,".",I129) -> 847.8470325.1.492316.000000.847001.300180 | F129: KUST - General | G129: 847001 | H129: FA180-Capex Expense | I129: 300180 | J129: PTV Traffic Simulation Bundle | K129: 1 | L129: 44000 | M129: 44000
A130: 8470330 | B130: KUST - Electrical & Computer Engineering | C130: 420550 | D130: Academic Advisory Service | E130: =CONCATENATE(847,".",A130,".",1,".",C130,".","000000",".",G130,".",I130) -> 847.8470330.1.420550.000000.847001.200179 | F130: KUST - General | G130: 847001 | H130: FA179-Opex Expense | I130: 200179 | J130: One meeting of the DAB of the deprtment. Hospitality for 7 members and 5 KU faculty. | K130: 1 | L130: 3000 | M130: 3000
A131: 8470330 | B131: KUST - Electrical & Computer Engineering | C131: 421700 | D131: Standards certification (e.g. ISO) | E131: =CONCATENATE(847,".",A131,".",1,".",C131,".","000000",".",G131,".",I131) -> 847.8470330.1.421700.000000.847001.200179 | F131: KUST - General | G131: 847001 | H131: FA179-Opex Expense | I131: 200179 | M131: 0
A132: 8470330 | B132: KUST - Electrical & Computer Engineering | C132: 425510 | D132: Conferences, seminars and exhibitions and other events: - Local Events | E132: =CONCATENATE(847,".",A132,".",1,".",C132,".","000000",".",G132,".",I132) -> 847.8470330.1.425510.000000.847001.200179 | F132: KUST - General | G132: 847001 | H132: FA179-Opex Expense | I132: 200179 | J132: Workshop on “ Electric vehicles”. October/November 2022. Organizers: Dr. Balanthi Beig and Dr. Khaled Al Jaafari . Cost calculation details: International expert travel: AED 20,000. Accommodation for 5 days: AED 9000. Food/stationary/banners: AED 5000. Total : 34000 . Participants: 30. Workshop on High Voltage: AED 8000 | K132: 2 | L132: 21000 | M132: 42000
A133: 8470330 | B133: KUST - Electrical & Computer Engineering | C133: 425760 | D133: Student activities & field trip expenses | E133: =CONCATENATE(847,".",A133,".",1,".",C133,".","000000",".",G133,".",I133) -> 847.8470330.1.425760.000000.847001.200179 | F133: KUST - General | G133: 847001 | H133: FA179-Opex Expense | I133: 200179 | J133: 8 field trips trips @ AED 2000/trip . Also IEEE KU students activities (AED 10000) include common design project, engineering design project, industrial project, and community service project plus the IEEE KU student chapter running costs, including inviting speakers and organizing workshops. Also Competitions, like KPC (AED 5000), GPC (AED 15000), and International overseas ones (AED 25000) | K133: 10 | L133: 7200 | M133: 72000
A134: 8470330 | B134: KUST - Electrical & Computer Engineering | C134: 425761 | D134: Student Field trips | E134: =CONCATENATE(847,".",A134,".",1,".",C134,".","000000",".",G134,".",I134) -> 847.8470330.1.425761.000000.847001.200179 | F134: KUST - General | G134: 847001 | H134: FA179-Opex Expense | I134: 200179 | M134: 0
A135: 8470330 | B135: KUST - Electrical & Computer Engineering | C135: 425763 | D135: Student Project Expenses | E135: =CONCATENATE(847,".",A135,".",1,".",C135,".","000000",".",G135,".",I135) -> 847.8470330.1.425763.000000.847001.200179 | F135: KUST - General | G135: 847001 | H135: FA179-Opex Expense | I135: 200179 | J135: # of students * 3000 /student | K135: 135 | L135: 3000 | M135: 405000
A136: 8470330 | B136: KUST - Electrical & Computer Engineering | C136: 425770 | D136: Academic Missions - Combined expenses | E136: =CONCATENATE(847,".",A136,".",1,".",C136,".","000000",".",G136,".",I136) -> 847.8470330.1.425770.000000.847001.200179 | F136: KUST - General | G136: 847001 | H136: FA179-Opex Expense | I136: 200179 | J136: 15k/Faculty FTE | K136: 60 | L136: 15000 | M136: 900000
A137: 8470330 | B137: KUST - Electrical & Computer Engineering | C137: 425900 | D137: Entertainment and hospitality | E137: =CONCATENATE(847,".",A137,".",1,".",C137,".","000000",".",G137,".",I137) -> 847.8470330.1.425900.000000.847001.200179 | F137: KUST - General | G137: 847001 | H137: FA179-Opex Expense | I137: 200179 | J137: Department meetings' hospitality. average # of department participants @ AED 25/faculty/meeting. Also for one speaker from local industry per sementer @ 1000 /speaker. | K137: 8 | L137: 2000 | M137: 16000
A138: 8470330 | B138: KUST - Electrical & Computer Engineering | C138: 426610 | D138: Computer software licenses | E138: =CONCATENATE(847,".",A138,".",1,".",C138,".","000000",".",G138,".",I138) -> 847.8470330.1.426610.000000.847001.200179 | F138: KUST - General | G138: 847001 | H138: FA179-Opex Expense | I138: 200179 | J138: average cost of SW licenses* # of licenses: Altium Designer 1.848 PLECS Combo Academic Concurrent License 2.218 LogixPro 500 2.705 PSCAD Educational 10.458 ETAP - Educational Licenses 14.172 Rockwell Automation Toolkit - Studio 5000 18.201 GAMS (General Algebraic Modeling System) 61.329 National Instruments Circuit Design Multisim 141.750 LabView Academic Site License Teaching 103.789 Synopsys 150.696 Cadence 212.520 TOTAL 719.685 | K138: 11 | L138: 65500 | M138: 720500
A139: 8470330 | B139: KUST - Electrical & Computer Engineering | C139: 428090 | D139: Business Travel - Combined expenses | E139: =CONCATENATE(847,".",A139,".",1,".",C139,".","000000",".",G139,".",I139) -> 847.8470330.1.428090.000000.847001.200179 | F139: KUST - General | G139: 847001 | H139: FA179-Opex Expense | I139: 200179 | M139: 0
A140: 8470330 | B140: KUST - Electrical & Computer Engineering | C140: 428640 | D140: Events - Awards, prizes & gifts | E140: =CONCATENATE(847,".",A140,".",1,".",C140,".","000000",".",G140,".",I140) -> 847.8470330.1.428640.000000.847001.200179 | F140: KUST - General | G140: 847001 | H140: FA179-Opex Expense | I140: 200179 | J140: Honored faculty * gift cost Also (Dr Arif's project: Smart Mobile Application Annual Contest 2022/2023/2024: Total Cost: ~300K Awards: 3 teams to win 75K, 50K, 25K (Total 150K) Travel support can be given AED 1.5K-3K per person (depending on region) to shortlisted teams based on receipt of tickets and accommodation (twin or triple rooms) up to 15 shortlisted teams can be supported 1-2 from each country (total cost of ~115K). Accommodation: twin-triple room (1 night per team) Max of AED 1K per team. Total Cost: 15 K. Cost of publications and event preparation: AED 10K. Catering 150 attendees: 10K | K140: 2 | L140: 151000 | M140: 302000
A141: 8470330 | B141: KUST - Electrical & Computer Engineering | C141: 432209 | D141: Laboratory equipment | E141: =CONCATENATE(847,".",A141,".",1,".",C141,".","000000",".",G141,".",I141) -> 847.8470330.1.432209.000000.847001.200179 | F141: KUST - General | G141: 847001 | H141: FA179-Opex Expense | I141: 200179 | J141: Maintenance/calibration for the RF Measurement lab 1. 6 Test Cables @ 3400 = 20400, See attachment "Nishar. OPEX 1 RF Test Cables - old.pdf" and for RF Parts (Amplifiers, Mixers, Filters, cables, adapters) @ 47000, see attachment "Nishar. OPEX 2 RF Parts.pdf". Total 67400. | K141: 2 | L141: 33700 | M141: 67400
A142: 8470330 | B142: KUST - Electrical & Computer Engineering | C142: 435340 | D142: Text books and library books | E142: =CONCATENATE(847,".",A142,".",1,".",C142,".","000000",".",G142,".",I142) -> 847.8470330.1.435340.000000.847001.200179 | F142: KUST - General | G142: 847001 | H142: FA179-Opex Expense | I142: 200179 | M142: 0
A143: 8470330 | B143: KUST - Electrical & Computer Engineering | C143: 435350 | D143: Academic Publications | E143: =CONCATENATE(847,".",A143,".",1,".",C143,".","000000",".",G143,".",I143) -> 847.8470330.1.435350.000000.847001.200179 | F143: KUST - General | G143: 847001 | H143: FA179-Opex Expense | I143: 200179 | J143: one paper or page charges / faculty | K143: 60 | L143: 7000 | M143: 420000
A144: 8470330 | B144: KUST - Electrical & Computer Engineering | C144: 435508 | D144: Laboratory - Scientific | E144: =CONCATENATE(847,".",A144,".",1,".",C144,".","000000",".",G144,".",I144) -> 847.8470330.1.435508.000000.847001.200179 | F144: KUST - General | G144: 847001 | H144: FA179-Opex Expense | I144: 200179 | J144: Lab Consumables | K144: 20 | L144: 1000 | M144: 20000
A145: 8470330 | B145: KUST - Electrical & Computer Engineering | C145: 436110 | D145: Printing supplies | E145: =CONCATENATE(847,".",A145,".",1,".",C145,".","000000",".",G145,".",I145) -> 847.8470330.1.436110.000000.847001.200179 | F145: KUST - General | G145: 847001 | H145: FA179-Opex Expense | I145: 200179 | M145: 0
A146: 8470330 | B146: KUST - Electrical & Computer Engineering | C146: 436600 | D146: Training/Teaching equipment and other educational aid | E146: =CONCATENATE(847,".",A146,".",1,".",C146,".","000000",".",G146,".",I146) -> 847.8470330.1.436600.000000.847001.200179 | F146: KUST - General | G146: 847001 | H146: FA179-Opex Expense | I146: 200179 | J146: 2 servers @ 8000 each, =16000. RPi 4 with on-board 8 GB memory, casing with fan + heatsink, 5V 3.5 A power adapter. 5 RaspPi @ 600 each, = 3000. 6 Android Phones (for programming) @ 600 each = 3600. 2 licenses of VMware Workstation 16 Pro for Academic Use @ 600 each, = 1200. 5 NVIDIA Jetson Nano Developer Kit (include - microSD card (64GB UHS-1) & Micro-USB power supply) @ 500 each, = 2500. 2 Raspberry Pi Cluster 6 Layer Rack for Raspberry Pi 4 or RPi3 @ 75 each = 150. 10 RASPBERRY PI 4 COMPUTER MODEL B 8GB @300 each = 3000. Total cost: 33k. 11 items @ 3k per item | K146: 20 | L146: 3000 | M146: 60000
A147: 8470330 | B147: KUST - Electrical & Computer Engineering | C147: 492316 | D147: Laboratory equipment | E147: =CONCATENATE(847,".",A147,".",1,".",C147,".","000000",".",G147,".",I147) -> 847.8470330.1.492316.000000.847001.300180 | F147: KUST - General | G147: 847001 | H147: FA180-Capex Expense | I147: 300180 | J147: CAPEX equipment. See quotations for the 4 items @ an average price of AED 166000 and a total of AED 664,000 in the attachments: Nofel. Tensorbook Official Quote.pdf Nazarudeen. Quote_All-in-one PC.pdf Nishar. 3 Quote_Lab Computers_RF LAB.pdf Sajid. GeForce-GPU.pdf | K147: 4 | L147: 166000 | M147: 664000
A148: 8470335 | B148: KUST - Industrial & Systems Engineering | C148: 420550 | D148: Academic Advisory Service | E148: =CONCATENATE(847,".",A148,".",1,".",C148,".","000000",".",G148,".",I148) -> 847.8470335.1.420550.000000.847001.200179 | F148: KUST - General | G148: 847001 | H148: FA179-Opex Expense | I148: 200179 | J148: Academic advisor board meetings | K148: 2 | L148: 5000 | M148: 10000
A149: 8470335 | B149: KUST - Industrial & Systems Engineering | C149: 425510 | D149: Conferences, seminars and exhibitions and other events: - Local Events | E149: =CONCATENATE(847,".",A149,".",1,".",C149,".","000000",".",G149,".",I149) -> 847.8470335.1.425510.000000.847001.200179 | F149: KUST - General | G149: 847001 | H149: FA179-Opex Expense | I149: 200179 | J149: Students to regiser into local conferences and intl competitions | K149: 10 | L149: 2000 | M149: 20000
A150: 8470335 | B150: KUST - Industrial & Systems Engineering | C150: 425760 | D150: Student activities & field trip expenses | E150: =CONCATENATE(847,".",A150,".",1,".",C150,".","000000",".",G150,".",I150) -> 847.8470335.1.425760.000000.847001.200179 | F150: KUST - General | G150: 847001 | H150: FA179-Opex Expense | I150: 200179 | J150: Students trips to local industry | K150: 4 | L150: 2500 | M150: 10000
A151: 8470335 | B151: KUST - Industrial & Systems Engineering | C151: 425763 | D151: Student Project Expenses | E151: =CONCATENATE(847,".",A151,".",1,".",C151,".","000000",".",G151,".",I151) -> 847.8470335.1.425763.000000.847001.200179 | F151: KUST - General | G151: 847001 | H151: FA179-Opex Expense | I151: 200179 | J151: 2000 Dhs per student for SDP project | K151: 25 | L151: 2000 | M151: 50000
A152: 8470335 | B152: KUST - Industrial & Systems Engineering | C152: 425770 | D152: Academic Missions - Combined expenses | E152: =CONCATENATE(847,".",A152,".",1,".",C152,".","000000",".",G152,".",I152) -> 847.8470335.1.425770.000000.847001.200179 | F152: KUST - General | G152: 847001 | H152: FA179-Opex Expense | I152: 200179 | J152: Faculty travel to conferences 15000 dhs per trip | K152: 18 | L152: 15000 | M152: 270000
A153: 8470335 | B153: KUST - Industrial & Systems Engineering | C153: 425900 | D153: Entertainment and hospitality | E153: =CONCATENATE(847,".",A153,".",1,".",C153,".","000000",".",G153,".",I153) -> 847.8470335.1.425900.000000.847001.200179 | F153: KUST - General | G153: 847001 | H153: FA179-Opex Expense | I153: 200179 | J153: Department academic meetings and retreats and student orientations | K153: 4 | L153: 5000 | M153: 20000
A154: 8470335 | B154: KUST - Industrial & Systems Engineering | C154: 426610 | D154: Computer software licenses | E154: =CONCATENATE(847,".",A154,".",1,".",C154,".","000000",".",G154,".",I154) -> 847.8470335.1.426610.000000.847001.200179 | F154: KUST - General | G154: 847001 | H154: FA179-Opex Expense | I154: 200179 | J154: Per IT softwar licenses fo ISYE department teaching 25 licenses renewals | K154: 25 | L154: 5974.8 | M154: 150257
A155: 8470335 | B155: KUST - Industrial & Systems Engineering | C155: 428090 | D155: Business Travel - Combined expenses | E155: =CONCATENATE(847,".",A155,".",1,".",C155,".","000000",".",G155,".",I155) -> 847.8470335.1.428090.000000.847001.200179 | F155: KUST - General | G155: 847001 | H155: FA179-Opex Expense | I155: 200179 | J155: University missions, e.g. conference bidding | K155: 1 | L155: 40000 | M155: 40000
A156: 8470335 | B156: KUST - Industrial & Systems Engineering | C156: 435350 | D156: Academic Publications | E156: =CONCATENATE(847,".",A156,".",1,".",C156,".","000000",".",G156,".",I156) -> 847.8470335.1.435350.000000.847001.200179 | F156: KUST - General | G156: 847001 | H156: FA179-Opex Expense | I156: 200179 | J156: 8 open access Q1 papers | K156: 8 | L156: 6440 | M156: 51520
A157: 8470335 | B157: KUST - Industrial & Systems Engineering | C157: 435508 | D157: Laboratory - Scientific | E157: =CONCATENATE(847,".",A157,".",1,".",C157,".","000000",".",G157,".",I157) -> 847.8470335.1.435508.000000.847001.200179 | F157: KUST - General | G157: 847001 | H157: FA179-Opex Expense | I157: 200179 | J157: Upgrade for exiting I-motion and EEG head set/ECG shimmer/ Neuro Electrics Enobio 8 units | K157: 1 | L157: 54000 | M157: 54000
... A173: 8470340 | B173: KUST - Mechanical Engineering | C173: 426610 | D173: Computer software licenses | E173: =CONCATENATE(847,".",A173,".",1,".",C173,".","000000",".",G173,".",I173) -> 847.8470340.1.426610.000000.847001.200179 | F173: KUST - General | G173: 847001 | H173: FA179-Opex Expense | I173: 200179 | J173: Please, see itemized list of software that is used for educational purposes in the deprtment. Annual renewal of software, split in two semesters. | K173: 1 | L173: 210000 | M173: 210000
A174: 8470340 | B174: KUST - Mechanical Engineering | C174: 428090 | D174: Business Travel - Combined expenses | E174: =CONCATENATE(847,".",A174,".",1,".",C174,".","000000",".",G174,".",I174) -> 847.8470340.1.428090.000000.847001.200179 | F174: KUST - General | G174: 847001 | H174: FA179-Opex Expense | I174: 200179 | M174: 0
A175: 8470340 | B175: KUST - Mechanical Engineering | C175: 432209 | D175: Laboratory equipment | E175: =CONCATENATE(847,".",A175,".",1,".",C175,".","000000",".",G175,".",I175) -> 847.8470340.1.432209.000000.847001.200179 | F175: KUST - General | G175: 847001 | H175: FA179-Opex Expense | I175: 200179 | J175: One maintenance contract for the instructional equipment of the deprtment. | K175: 1 | L175: 80000 | M175: 80000
A176: 8470340 | B176: KUST - Mechanical Engineering | C176: 435350 | D176: Academic Publications | E176: =CONCATENATE(847,".",A176,".",1,".",C176,".","000000",".",G176,".",I176) -> 847.8470340.1.435350.000000.847001.200179 | F176: KUST - General | G176: 847001 | H176: FA179-Opex Expense | I176: 200179 | J176: One open-access publication for each faculty member in a Q1 journal. 42 faculty members x 8000 AED per publication. | K176: 42 | L176: 8000 | M176: 336000
A177: 8470340 | B177: KUST - Mechanical Engineering | C177: 435508 | D177: Laboratory - Scientific | E177: =CONCATENATE(847,".",A177,".",1,".",C177,".","000000",".",G177,".",I177) -> 847.8470340.1.435508.000000.847001.200179 | F177: KUST - General | G177: 847001 | H177: FA179-Opex Expense | I177: 200179 | J177: Consumables for educational laboratories and the machine shop that include raw materials for machining, electric and electronic hardware, chemicals, gases, as well as tools and hardware. Itemized estmates: Workshop consumables (Main and SAN): 6500 AED, Solids, Heat Transfer and Fluids labs: 1000 AED, Material Testing lab: 5000 AED, 3D Printing labs: 6000 AED, Mechatronics lab: 1000 AED, Spare Parts for all labs: 2500 AED | K177: 12 | L177: 22000 | M177: 264000
...

Sheet Opex 2021
A1: Cost Center Code | B1: Cost Center Description | C1: Account Code | D1: Account Description | E1: GL Account Combination | F1: Annual Budget | G1: Revised Budget | H1: Actual Amount | I1: PR | J1: PO | K1: Fund Available | L1: Future1 | M1: Future1 Description | N1: Future2 | O1: Future2 Description | P1: 2020 Revis.ed Budget | Q1: 2020 Actual Amount
A2: 8470110 | B2: KUST - Office of the President | C2: 420550 | D2: Academic Advisory Service | E2: 847.8470110.1.420550.000000.847001.200179 | F2: 29119 | G2: 29119 | K2: 29119 | L2: 847001 | M2: KUST - General | N2: 200179 | O2: FA179-Opex Expense | P2: =IFERROR(VLOOKUP('Opex 2021'!E:E,'Opex 2020'!E:H,3,FALSE),0) -> 29118.09 | Q2: =IFERROR(VLOOKUP('Opex 2021'!E:E,'Opex 2020'!E:H,4,FALSE),0) -> 29118.02
A3: 8470110 | B3: KUST - Office of the President | C3: 420570 | D3: Academic Collaborative Partnership Services | E3: 847.8470110.1.420570.000000.847001.200179 | F3: 1 | G3: 1 | K3: 1 | L3: 847001 | M3: KUST - General | N3: 200179 | O3: FA179-Opex Expense | P3: =IFERROR(VLOOKUP('Opex 2021'!E:E,'Opex 2020'!E:H,3,FALSE),0) -> 0.94 | Q3: =IFERROR(VLOOKUP('Opex 2021'!E:E,'Opex 2020'!E:H,4,FALSE),0) -> 0
A4: 8470110 | B4: KUST - Office of the President | C4: 420900 | D4: Legal services | E4: 847.8470110.1.420900.000000.847001.200179 | F4: 1501 | G4: 1501 | K4: 1501 | L4: 847001 | M4: KUST - General | N4: 200179 | O4: FA179-Opex Expense | P4: =IFERROR(VLOOKUP('Opex 2021'!E:E,'Opex 2020'!E:H,3,FALSE),0) -> 1900.4 | Q4: =IFERROR(VLOOKUP('Opex 2021'!E:E,'Opex 2020'!E:H,4,FALSE),0) -> 1845
A5: 8470110 | B5: KUST - Office of the President | C5: 421000 | D5: Management consultancy | E5: 847.8470110.1.421000.000000.847001.200179 | F5: 1 | G5: 1 | K5: 1 | L5: 847001 | M5: KUST - General | N5: 200179 | O5: FA179-Opex Expense | P5: =IFERROR(VLOOKUP('Opex 2021'!E:E,'Opex 2020'!E:H,3,FALSE),0) -> 0.65 | Q5: =IFERROR(VLOOKUP('Opex 2021'!E:E,'Opex 2020'!E:H,4,FALSE),0) -> 0
A6: 8470110 | B6: KUST - Office of the President | C6: 421700 | D6: Standards Certification Services (e.g. ISO) | E6: 847.8470110.1.421700.000000.847001.200179 | F6: 25000 | G6: 25000 | K6: 25000 | L6: 847001 | M6: KUST - General | N6: 200179 | O6: FA179-Opex Expense | P6: =IFERROR(VLOOKUP('Opex 2021'!E:E,'Opex 2020'!E:H,3,FALSE),0) -> 1.21 | Q6: =IFERROR(VLOOKUP('Opex 2021'!E:E,'Opex 2020'!E:H,4,FALSE),0) -> 0
A7: 8470110 | B7: KUST - Office of the President | C7: 425510 | D7: Conferences, seminars and exhibitions and other events: - Local Events | E7: 847.8470110.1.425510.000000.847001.200179 | H7: -190000 | K7: 190000 | L7: 847001 | M7: KUST - General | N7: 200179 | O7: FA179-Opex Expense | P7: =IFERROR(VLOOKUP('Opex 2021'!E:E,'Opex 2020'!E:H,3,FALSE),0) -> 277367.71 | Q7: =IFERROR(VLOOKUP('Opex 2021'!E:E,'Opex 2020'!E:H,4,FALSE),0) -> 277368
A8: 8470110 | B8: KUST - Office of the President | C8: 425900 | D8: Entertainment and hospitality | E8: 847.8470110.1.425900.000000.847001.200179 | F8: 10000 | G8: 10000 | H8: -90 | K8: 10090 | L8: 847001 | M8: KUST - General | N8: 200179 | O8: FA179-Opex Expense | P8: =IFERROR(VLOOKUP('Opex 2021'!E:E,'Opex 2020'!E:H,3,FALSE),0) -> 13356.81 | Q8: =IFERROR(VLOOKUP('Opex 2021'!E:E,'Opex 2020'!E:H,4,FALSE),0) -> 13355.7
A9: 8470110 | B9: KUST - Office of the President | C9: 426610 | D9: Computer software licenses | E9: 847.8470110.1.426610.000000.847001.200179 | F9: 80204 | G9: 80204 | H9: 42239.5 | K9: 37964.5 | L9: 847001 | M9: KUST - General | N9: 200179 | O9: FA179-Opex Expense | P9: =IFERROR(VLOOKUP('Opex 2021'!E:E,'Opex 2020'!E:H,3,FALSE),0) -> 42240.57 | Q9: =IFERROR(VLOOKUP('Opex 2021'!E:E,'Opex 2020'!E:H,4,FALSE),0) -> 42239.5
A10: 8470110 | B10: KUST - Office of the President | C10: 427710 | D10: Subscriptions and membership fees: Trade organisations | E10: 847.8470110.1.427710.000000.847001.200179 | F10: 1880 | G10: 1880 | K10: 1880 | L10: 847001 | M10: KUST - General | N10: 200179 | O10: FA179-Opex Expense | P10: =IFERROR(VLOOKUP('Opex 2021'!E:E,'Opex 2020'!E:H,3,FALSE),0) -> 3883 | Q10: =IFERROR(VLOOKUP('Opex 2021'!E:E,'Opex 2020'!E:H,4,FALSE),0) -> 3882.17
A11: 8470110 | B11: KUST - Office of the President | C11: 427900 | D11: Translation and interpretation service | E11: 847.8470110.1.427900.000000.847001.200179 | F11: 12585 | G11: 12585 | K11: 12585 | L11: 847001 | M11: KUST - General | N11: 200179 | O11: FA179-Opex Expense | P11: =IFERROR(VLOOKUP('Opex 2021'!E:E,'Opex 2020'!E:H,3,FALSE),0) -> 0.82 | Q11: =IFERROR(VLOOKUP('Opex 2021'!E:E,'Opex 2020'!E:H,4,FALSE),0) -> 0
A12: 8470110 | B12: KUST - Office of the President | C12: 428090 | D12: Business Travel - Combined expenses | E12: 847.8470110.1.428090.000000.847001.200179 | F12: 64381 | G12: 64381 | H12: 17390 | K12: 46991 | L12: 847001 | M12: KUST - General | N12: 200179 | O12: FA179-Opex Expense | P12: =IFERROR(VLOOKUP('Opex 2021'!E:E,'Opex 2020'!E:H,3,FALSE),0) -> 104380.21 | Q12: =IFERROR(VLOOKUP('Opex 2021'!E:E,'Opex 2020'!E:H,4,FALSE),0) -> 64375.44
A13: 8470110 | B13: KUST - Office of the President | C13: 428640 | D13: Events - Awards, prizes & gifts | E13: 847.8470110.1.428640.000000.847001.200179 | F13: 1 | G13: 1 | K13: 1 | L13: 847001 | M13: KUST - General | N13: 200179 | O13: FA179-Opex Expense | P13: =IFERROR(VLOOKUP('Opex 2021'!E:E,'Opex 2020'!E:H,3,FALSE),0) -> 0.62 | Q13: =IFERROR(VLOOKUP('Opex 2021'!E:E,'Opex 2020'!E:H,4,FALSE),0) -> 0
A14: 8470110 | B14: KUST - Office of the President | C14: 435410 | D14: Catering supplies: Offices | E14: 847.8470110.1.435410.000000.847001.200179 | F14: 1 | G14: 1 | K14: 1 | L14: 847001 | M14: KUST - General | N14: 200179 | O14: FA179-Opex Expense | P14: =IFERROR(VLOOKUP('Opex 2021'!E:E,'Opex 2020'!E:H,3,FALSE),0) -> 0.96 | Q14: =IFERROR(VLOOKUP('Opex 2021'!E:E,'Opex 2020'!E:H,4,FALSE),0) -> 0
A15: 8470110 | B15: KUST - Office of the President | C15: 435519 | D15: Photography - Consumable materials /Tools | E15: 847.8470110.1.435519.000000.847001.200179 | F15: 2000 | G15: 2000 | K15: 2000 | L15: 847001 | M15: KUST - General | N15: 200179 | O15: FA179-Opex Expense | P15: =IFERROR(VLOOKUP('Opex 2021'!E:E,'Opex 2020'!E:H,3,FALSE),0) -> 0.94 | Q15: =IFERROR(VLOOKUP('Opex 2021'!E:E,'Opex 2020'!E:H,4,FALSE),0) -> 0
A16: 8470110 | B16: KUST - Office of the President | C16: 436110 | D16: Printing supplies | E16: 847.8470110.1.436110.000000.847001.200179 | F16: 4195 | G16: 4195 | K16: 4195 | L16: 847001 | M16: KUST - General | N16: 200179 | O16: FA179-Opex Expense | P16: =IFERROR(VLOOKUP('Opex 2021'!E:E,'Opex 2020'!E:H,3,FALSE),0) -> 0.94 | Q16: =IFERROR(VLOOKUP('Opex 2021'!E:E,'Opex 2020'!E:H,4,FALSE),0) -> 0
A17: 8470120 | B17: KUST - Audit & Compliance | C17: 420120 | D17: Internal Audit service | E17: 847.8470120.1.420120.000000.847001.200179 | F17: 400000 | G17: 400000 | I17: 15847.9 | J17: 383815 | K17: 337.1 | L17: 847001 | M17: KUST - General | N17: 200179 | O17: FA179-Opex Expense | P17: =IFERROR(VLOOKUP('Opex 2021'!E:E,'Opex 2020'!E:H,3,FALSE),0) -> -477000 | Q17: =IFERROR(VLOOKUP('Opex 2021'!E:E,'Opex 2020'!E:H,4,FALSE),0) -> -493500
A18: 8470130 | B18: KUST - Institutional Research & Planning | C18: 421000 | D18: Management consultancy | E18: 847.8470130.1.421000.000000.847001.200179 | F18: 276300 | G18: 134500 | H18: 134500 | J18: 0 | K18: 0 | L18: 847001 | M18: KUST - General | N18: 200179 | O18: FA179-Opex Expense | P18: =IFERROR(VLOOKUP('Opex 2021'!E:E,'Opex 2020'!E:H,3,FALSE),0) -> 162970 | Q18: =IFERROR(VLOOKUP('Opex 2021'!E:E,'Opex 2020'!E:H,4,FALSE),0) -> 28465.75
A19: 8470130 | B19: KUST - Institutional Research & Planning | C19: 425510 | D19: Conferences, seminars and exhibitions and other events: - Local Events | E19: 847.8470130.1.425510.000000.847001.200179 | F19: 2200 | G19: 2200 | K19: 2200 | L19: 847001 | M19: KUST - General | N19: 200179 | O19: FA179-Opex Expense | P19: =IFERROR(VLOOKUP('Opex 2021'!E:E,'Opex 2020'!E:H,3,FALSE),0) -> 2200 | Q19: =IFERROR(VLOOKUP('Opex 2021'!E:E,'Opex 2020'!E:H,4,FALSE),0) -> 2200
A20: 8470130 | B20: KUST - Institutional Research & Planning | C20: 427710 | D20: Subscriptions and membership fees: Trade organisations | E20: 847.8470130.1.427710.000000.847001.200179 | F20: 125000 | G20: 129650 | H20: 129634.5 | K20: 15.5 | L20: 847001 | M20: KUST - General | N20: 200179 | O20: FA179-Opex Expense | P20: =IFERROR(VLOOKUP('Opex 2021'!E:E,'Opex 2020'!E:H,3,FALSE),0) -> 0 | Q20: =IFERROR(VLOOKUP('Opex 2021'!E:E,'Opex 2020'!E:H,4,FALSE),0) -> 0
A21: 8470140 | B21: KUST - Communication | C21: 425100 | D21: Advertising Services (General) | E21: 847.8470140.1.425100.000000.847001.200179 | F21: 2320934 | G21: 3070934 | H21: 620757.53 | I21: 1801366 | J21: 0 | K21: 648810.47 | L21: 847001 | M21: KUST - General | N21: 200179 | O21: FA179-Opex Expense | P21: =IFERROR(VLOOKUP('Opex 2021'!E:E,'Opex 2020'!E:H,3,FALSE),0) -> 2558303.5 | Q21: =IFERROR(VLOOKUP('Opex 2021'!E:E,'Opex 2020'!E:H,4,FALSE),0) -> 2353626.8
A22: 8470140 | B22: KUST - Communication | C22: 425510 | D22: Conferences, seminars and exhibitions and other events: - Local Events | E22: 847.8470140.1.425510.000000.847001.200179 | F22: 3500000 | G22: 2850000 | H22: 1418079.7 | I22: 1212000 | J22: 218157.5 | K22: 1762.78 | L22: 847001 | M22: KUST - General | N22: 200179 | O22: FA179-Opex Expense | P22: =IFERROR(VLOOKUP('Opex 2021'!E:E,'Opex 2020'!E:H,3,FALSE),0) -> 2911261.6 | Q22: =IFERROR(VLOOKUP('Opex 2021'!E:E,'Opex 2020'!E:H,4,FALSE),0) -> 2727959.1
A23: 8470140 | B23: KUST - Communication | C23: 425550 | D23: Conferences, seminars and exhibitions and other events: - Overseas event | E23: 847.8470140.1.425550.000000.847001.200179 | F23: 1 | G23: 1 | K23: 1 | L23: 847001 | M23: KUST - General | N23: 200179 | O23: FA179-Opex Expense | P23: =IFERROR(VLOOKUP('Opex 2021'!E:E,'Opex 2020'!E:H,3,FALSE),0) -> 0.88 | Q23: =IFERROR(VLOOKUP('Opex 2021'!E:E,'Opex 2020'!E:H,4,FALSE),0) -> 0
A24: 8470140 | B24: KUST - Communication | C24: 427100 | D24: Public relations | E24: 847.8470140.1.427100.000000.847001.200179 | F24: 137341 | G24: 137341 | H24: -820 | K24: 138161 | L24: 847001 | M24: KUST - General | N24: 200179 | O24: FA179-Opex Expense | P24: =IFERROR(VLOOKUP('Opex 2021'!E:E,'Opex 2020'!E:H,3,FALSE),0) -> 135840.03 | Q24: =IFERROR(VLOOKUP('Opex 2021'!E:E,'Opex 2020'!E:H,4,FALSE),0) -> 129310
A25: 8470140 | B25: KUST - Communication | C25: 427200 | D25: Printing and publishing | E25: 847.8470140.1.427200.000000.847001.200179 | F25: 1962 | G25: 1962 | H25: -21038.22 | J25: 0 | K25: 23000.22 | L25: 847001 | M25: KUST - General | N25: 200179 | O25: FA179-Opex Expense | P25: =IFERROR(VLOOKUP('Opex 2021'!E:E,'Opex 2020'!E:H,3,FALSE),0) -> 132195.98 | Q25: =IFERROR(VLOOKUP('Opex 2021'!E:E,'Opex 2020'!E:H,4,FALSE),0) -> 125002.84
A26: 8470140 | B26: KUST - Communication | C26: 435310 | D26: Newspapers, magazines, journals, etc | E26: 847.8470140.1.435310.000000.847001.200179 | F26: 10000 | G26: 10000 | K26: 10000 | L26: 847001 | M26: KUST - General | N26: 200179 | O26: FA179-Opex Expense | P26: =IFERROR(VLOOKUP('Opex 2021'!E:E,'Opex 2020'!E:H,3,FALSE),0) -> 13569 | Q26: =IFERROR(VLOOKUP('Opex 2021'!E:E,'Opex 2020'!E:H,4,FALSE),0) -> 13568.1
A27: 8470140 | B27: KUST - Communication | C27: 435519 | D27: Photography - Consumable materials /Tools | E27: 847.8470140.1.435519.000000.847001.200179 | F27: 193297 | G27: 193297 | I27: 0 | K27: 193297 | L27: 847001 | M27: KUST - General | N27: 200179 | O27: FA179-Opex Expense | P27: =IFERROR(VLOOKUP('Opex 2021'!E:E,'Opex 2020'!E:H,3,FALSE),0) -> 77323.96 | Q27: =IFERROR(VLOOKUP('Opex 2021'!E:E,'Opex 2020'!E:H,4,FALSE),0) -> 53870
A28: 8470150 | B28: KUST - General Counsel | C28: 420900 | D28: Legal services | E28: 847.8470150.1.420900.000000.847001.200179 | F28: 18595 | G28: 18595 | K28: 18595 | L28: 847001 | M28: KUST - General | N28: 200179 | O28: FA179-Opex Expense | P28: =IFERROR(VLOOKUP('Opex 2021'!E:E,'Opex 2020'!E:H,3,FALSE),0) -> 18595 | Q28: =IFERROR(VLOOKUP('Opex 2021'!E:E,'Opex 2020'!E:H,4,FALSE),0) -> 16996.14
A29: 8470150 | B29: KUST - General Counsel | C29: 425900 | D29: Entertainment and hospitality | E29: 847.8470150.1.425900.000000.847001.200179 | F29: 1 | G29: 1 | K29: 1 | L29: 847001 | M29: KUST - General | N29: 200179 | O29: FA179-Opex Expense | P29: =IFERROR(VLOOKUP('Opex 2021'!E:E,'Opex 2020'!E:H,3,FALSE),0) -> 0.17 | Q29: =IFERROR(VLOOKUP('Opex 2021'!E:E,'Opex 2020'!E:H,4,FALSE),0) -> 0
A30: 8470230 | B30: KUST - Graduate Studies | C30: 420550 | D30: Academic Advisory Service | E30: 847.8470230.1.420550.000000.847001.200179 | F30: 80740 | G30: 80740 | H30: 27566.75 | K30: 53173.25 | L30: 847001 | M30: KUST - General | N30: 200179 | O30: FA179-Opex Expense | P30: =IFERROR(VLOOKUP('Opex 2021'!E:E,'Opex 2020'!E:H,3,FALSE),0) -> 79821 | Q30: =IFERROR(VLOOKUP('Opex 2021'!E:E,'Opex 2020'!E:H,4,FALSE),0) -> 79119.87
A31: 8470230 | B31: KUST - Graduate Studies | C31: 425100 | D31: Advertising Services (General) | E31: 847.8470230.1.425100.000000.847001.200179 | F31: 240000 | G31: 240000 | K31: 240000 | L31: 847001 | M31: KUST - General | N31: 200179 | O31: FA179-Opex Expense | P31: =IFERROR(VLOOKUP('Opex 2021'!E:E,'Opex 2020'!E:H,3,FALSE),0) -> 0 | Q31: =IFERROR(VLOOKUP('Opex 2021'!E:E,'Opex 2020'!E:H,4,FALSE),0) -> 0
A32: 8470230 | B32: KUST - Graduate Studies | C32: 425510 | D32: Conferences, seminars and exhibitions and other events: - Local Events | E32: 847.8470230.1.425510.000000.847001.200179 | F32: 10000 | G32: 10000 | H32: -6134.47 | J32: 0 | K32: 16134.47 | L32: 847001 | M32: KUST - General | N32: 200179 | O32: FA179-Opex Expense | P32: =IFERROR(VLOOKUP('Opex 2021'!E:E,'Opex 2020'!E:H,3,FALSE),0) -> 17919 | Q32: =IFERROR(VLOOKUP('Opex 2021'!E:E,'Opex 2020'!E:H,4,FALSE),0) -> 17919
A33: 8470230 | B33: KUST - Graduate Studies | C33: 425550 | D33: Conferences, seminars and exhibitions and other events: - Overseas event | E33: 847.8470230.1.425550.000000.847001.200179 | F33: 16500 | G33: 16500 | H33: 3326.03 | K33: 13173.97 | L33: 847001 | M33: KUST - General | N33: 200179 | O33: FA179-Opex Expense | P33: =IFERROR(VLOOKUP('Opex 2021'!E:E,'Opex 2020'!E:H,3,FALSE),0) -> 25218 | Q33: =IFERROR(VLOOKUP('Opex 2021'!E:E,'Opex 2020'!E:H,4,FALSE),0) -> 25200.26
A34: 8470230 | B34: KUST - Graduate Studies | C34: 425743 | D34: Graduation rewards | E34: 847.8470230.1.425743.000000.847001.200179 | F34: 720000 | G34: 720000 | H34: 720000 | K34: 0 | L34: 847001 | M34: KUST - General | N34: 200179 | O34: FA179-Opex Expense | P34: =IFERROR(VLOOKUP('Opex 2021'!E:E,'Opex 2020'!E:H,3,FALSE),0) -> 2010000 | Q34: =IFERROR(VLOOKUP('Opex 2021'!E:E,'Opex 2020'!E:H,4,FALSE),0) -> 2010000
A35: 8470230 | B35: KUST - Graduate Studies | C35: 425744 | D35: Student medical insurance | E35: 847.8470230.1.425744.000000.847001.200179 | F35: 1 | G35: 1 | K35: 1 | L35: 847001 | M35: KUST - General | N35: 200179 | O35: FA179-Opex Expense | P35: =IFERROR(VLOOKUP('Opex 2021'!E:E,'Opex 2020'!E:H,3,FALSE),0) -> 1 | Q35: =IFERROR(VLOOKUP('Opex 2021'!E:E,'Opex 2020'!E:H,4,FALSE),0) -> 0
A36: 8470230 | B36: KUST - Graduate Studies | C36: 425745 | D36: Student relocation & travel exps | E36: 847.8470230.1.425745.000000.847001.200179 | F36: 1403064 | G36: 1403064 | H36: 632845 | K36: 770219 | L36: 847001 | M36: KUST - General | N36: 200179 | O36: FA179-Opex Expense | P36: =IFERROR(VLOOKUP('Opex 2021'!E:E,'Opex 2020'!E:H,3,FALSE),0) -> 1899907 | Q36: =IFERROR(VLOOKUP('Opex 2021'!E:E,'Opex 2020'!E:H,4,FALSE),0) -> 1706509.4
A37: 8470230 | B37: KUST - Graduate Studies | C37: 425749 | D37: Postgraduate Student Salaries | E37: 847.8470230.1.425749.000000.847001.200179 | F37: 101999705 | G37: 101999705 | H37: 39527820 | K37: 62471885 | L37: 847001 | M37: KUST - General | N37: 200179 | O37: FA179-Opex Expense | P37: =IFERROR(VLOOKUP('Opex 2021'!E:E,'Opex 2020'!E:H,3,FALSE),0) -> 22420122 | Q37: =IFERROR(VLOOKUP('Opex 2021'!E:E,'Opex 2020'!E:H,4,FALSE),0) -> 22420057
A38: 8470230 | B38: KUST - Graduate Studies | C38: 426610 | D38: Computer software licenses | E38: 847.8470230.1.426610.000000.847001.200179 | F38: 8959 | G38: 8959 | K38: 8959 | L38: 847001 | M38: KUST - General | N38: 200179 | O38: FA179-Opex Expense | P38: =IFERROR(VLOOKUP('Opex 2021'!E:E,'Opex 2020'!E:H,3,FALSE),0) -> 1 | Q38: =IFERROR(VLOOKUP('Opex 2021'!E:E,'Opex 2020'!E:H,4,FALSE),0) -> 0
A39: 8470230 | B39: KUST - Graduate Studies | C39: 436110 | D39: Printing supplies | E39: 847.8470230.1.436110.000000.847001.200179 | F39: 5000 | G39: 5000 | K39: 5000 | L39: 847001 | M39: KUST - General | N39: 200179 | O39: FA179-Opex Expense | P39: =IFERROR(VLOOKUP('Opex 2021'!E:E,'Opex 2020'!E:H,3,FALSE),0) -> 42101 | Q39: =IFERROR(VLOOKUP('Opex 2021'!E:E,'Opex 2020'!E:H,4,FALSE),0) -> 42100
A40: 8470305 | B40: KUST - Dean Of Engineering | C40: 420550 | D40: Academic Advisory Service | E40: 847.8470305.1.420550.000000.847001.200179 | F40: 1 | G40: 1 | K40: 1 | L40: 847001 | M40: KUST - General | N40: 200179 | O40: FA179-Opex Expense | P40: =IFERROR(VLOOKUP('Opex 2021'!E:E,'Opex 2020'!E:H,3,FALSE),0) -> 0.43 | Q40: =IFERROR(VLOOKUP('Opex 2021'!E:E,'Opex 2020'!E:H,4,FALSE),0) -> 0
A41: 8470305 | B41: KUST - Dean Of Engineering | C41: 420570 | D41: Academic Collaborative Partnership Services | E41: 847.8470305.1.420570.000000.847001.200179 | F41: 0 | G41: 9200 | H41: 4591.25 | K41: 4608.75 | L41: 847001 | M41: KUST - General | N41: 200179 | O41: FA179-Opex Expense | P41: =IFERROR(VLOOKUP('Opex 2021'!E:E,'Opex 2020'!E:H,3,FALSE),0) -> 4592 | Q41: =IFERROR(VLOOKUP('Opex 2021'!E:E,'Opex 2020'!E:H,4,FALSE),0) -> 4591.25
A42: 8470305 | B42: KUST - Dean Of Engineering | C42: 421700 | D42: Standards Certification Services (e.g. ISO) | E42: 847.8470305.1.421700.000000.847001.200179 | F42: 400000 | G42: 390800 | K42: 390800 | L42: 847001 | M42: KUST - General | N42: 200179 | O42: FA179-Opex Expense | P42: =IFERROR(VLOOKUP('Opex 2021'!E:E,'Opex 2020'!E:H,3,FALSE),0) -> 597851.4 | Q42: =IFERROR(VLOOKUP('Opex 2021'!E:E,'Opex 2020'!E:H,4,FALSE),0) -> 597850.89
A43: 8470305 | B43: KUST - Dean Of Engineering | C43: 425510 | D43: Conferences, seminars and exhibitions and other events: - Local Events | E43: 847.8470305.1.425510.000000.847001.200179 | F43: 10000 | G43: 10000 | H43: -252 | K43: 10252 | L43: 847001 | M43: KUST - General | N43: 200179 | O43: FA179-Opex Expense | P43: =IFERROR(VLOOKUP('Opex 2021'!E:E,'Opex 2020'!E:H,3,FALSE),0) -> 10444.08 | Q43: =IFERROR(VLOOKUP('Opex 2021'!E:E,'Opex 2020'!E:H,4,FALSE),0) -> 10444
A44: 8470305 | B44: KUST - Dean Of Engineering | C44: 425720 | D44: Education-Outsourced training service | E44: 847.8470305.1.425720.000000.847001.200179 | H44: -3415.89 | K44: 3415.89 | L44: 847001 | M44: KUST - General | N44: 200179 | O44: FA179-Opex Expense | P44: =IFERROR(VLOOKUP('Opex 2021'!E:E,'Opex 2020'!E:H,3,FALSE),0) -> 0 | Q44: =IFERROR(VLOOKUP('Opex 2021'!E:E,'Opex 2020'!E:H,4,FALSE),0) -> 0
A45: 8470305 | B45: KUST - Dean Of Engineering | C45: 425763 | D45: Student Project Expenses | E45: 847.8470305.1.425763.000000.847001.200179 | F45: 30000 | G45: 100000 | K45: 100000 | L45: 847001 | M45: KUST - General | N45: 200179 | O45: FA179-Opex Expense | P45: =IFERROR(VLOOKUP('Opex 2021'!E:E,'Opex 2020'!E:H,3,FALSE),0) -> 617772.08 | Q45: =IFERROR(VLOOKUP('Opex 2021'!E:E,'Opex 2020'!E:H,4,FALSE),0) -> 617637.56
A46: 8470305 | B46: KUST - Dean Of Engineering | C46: 425770 | D46: Academic Missions - Combined expenses | E46: 847.8470305.1.425770.000000.847001.200179 | F46: 30000 | G46: 20000 | K46: 20000 | L46: 847001 | M46: KUST - General | N46: 200179 | O46: FA179-Opex Expense | P46: =IFERROR(VLOOKUP('Opex 2021'!E:E,'Opex 2020'!E:H,3,FALSE),0) -> 7219.24 | Q46: =IFERROR(VLOOKUP('Opex 2021'!E:E,'Opex 2020'!E:H,4,FALSE),0) -> 7218.55
A47: 8470305 | B47: KUST - Dean Of Engineering | C47: 425900 | D47: Entertainment and hospitality | E47: 847.8470305.1.425900.000000.847001.200179 | H47: -131 | K47: 131 | L47: 847001 | M47: KUST - General | N47: 200179 | O47: FA179-Opex Expense | P47: =IFERROR(VLOOKUP('Opex 2021'!E:E,'Opex 2020'!E:H,3,FALSE),0) -> -10520.45 | Q47: =IFERROR(VLOOKUP('Opex 2021'!E:E,'Opex 2020'!E:H,4,FALSE),0) -> -10521
A48: 8470305 | B48: KUST - Dean Of Engineering | C48: 426610 | D48: Computer software licenses | E48: 847.8470305.1.426610.000000.847001.200179 | F48: 224793 | G48: 224793 | H48: 32671.59 | I48: 28400.54 | K48: 163720.87 | L48: 847001 | M48: KUST - General | N48: 200179 | O48: FA179-Opex Expense | P48: =IFERROR(VLOOKUP('Opex 2021'!E:E,'Opex 2020'!E:H,3,FALSE),0) -> 236658.87 | Q48: =IFERROR(VLOOKUP('Opex 2021'!E:E,'Opex 2020'!E:H,4,FALSE),0) -> 236658.04
A49: 8470305 | B49: KUST - Dean Of Engineering | C49: 428640 | D49: Events - Awards, prizes & gifts | E49: 847.8470305.1.428640.000000.847001.200179 | F49: 1 | G49: 1 | K49: 1 | L49: 847001 | M49: KUST - General | N49: 200179 | O49: FA179-Opex Expense | P49: =IFERROR(VLOOKUP('Opex 2021'!E:E,'Opex 2020'!E:H,3,FALSE),0) -> -3636.61 | Q49: =IFERROR(VLOOKUP('Opex 2021'!E:E,'Opex 2020'!E:H,4,FALSE),0) -> -3637.45
A50: 8470305 | B50: KUST - Dean Of Engineering | C50: 432209 | D50: Laboratory equipment | E50: 847.8470305.1.432209.000000.847001.200179 | F50: 250000 | G50: 250000 | H50: 101101 | I50: 0 | J50: 145565.85 | K50: 3333.15 | L50: 847001 | M50: KUST - General | N50: 200179 | O50: FA179-Opex Expense | P50: =IFERROR(VLOOKUP('Opex 2021'!E:E,'Opex 2020'!E:H,3,FALSE),0) -> 1194799.8 | Q50: =IFERROR(VLOOKUP('Opex 2021'!E:E,'Opex 2020'!E:H,4,FALSE),0) -> 786038.6
A51: 8470305 | B51: KUST - Dean Of Engineering | C51: 432690 | D51: Plant, machinery and heavy equipment, not mentioned elsewhere | E51: 847.8470305.1.432690.000000.847001.200179 | F51: 0 | G51: 5000 | H51: 5000 | J51: 0 | K51: 0 | L51: 847001 | M51: KUST - General | N51: 200179 | O51: FA179-Opex Expense | P51: =IFERROR(VLOOKUP('Opex 2021'!E:E,'Opex 2020'!E:H,3,FALSE),0) -> 0 | Q51: =IFERROR(VLOOKUP('Opex 2021'!E:E,'Opex 2020'!E:H,4,FALSE),0) -> -2820
A52: 8470305 | B52: KUST - Dean Of Engineering | C52: 435350 | D52: Academic Publications | E52: 847.8470305.1.435350.000000.847001.200179 | F52: 22529 | G52: 22529 | K52: 22529 | L52: 847001 | M52: KUST - General | N52: 200179 | O52: FA179-Opex Expense | P52: =IFERROR(VLOOKUP('Opex 2021'!E:E,'Opex 2020'!E:H,3,FALSE),0) -> 2390.16 | Q52: =IFERROR(VLOOKUP('Opex 2021'!E:E,'Opex 2020'!E:H,4,FALSE),0) -> 2389
A53: 8470305 | B53: KUST - Dean Of Engineering | C53: 435508 | D53: Laboratory - Scientific | E53: 847.8470305.1.435508.000000.847001.200179 | F53: 51790 | G53: 51790 | H53: 51790 | J53: 0 | K53: 0 | L53: 847001 | M53: KUST - General | N53: 200179 | O53: FA179-Opex Expense | P53: =IFERROR(VLOOKUP('Opex 2021'!E:E,'Opex 2020'!E:H,3,FALSE),0) -> 61268.13 | Q53: =IFERROR(VLOOKUP('Opex 2021'!E:E,'Opex 2020'!E:H,4,FALSE),0) -> 22871.83
A54: 8470305 | B54: KUST - Dean Of Engineering | C54: 435530 | D54: School consumables, not specifically mentioned elsewhere | E54: 847.8470305.1.435530.000000.847001.200179 | F54: 0 | G54: 0 | K54: 0 | L54: 847001 | M54: KUST - General | N54: 200179 | O54: FA179-Opex Expense | P54: =IFERROR(VLOOKUP('Opex 2021'!E:E,'Opex 2020'!E:H,3,FALSE),0) -> 1 | Q54: =IFERROR(VLOOKUP('Opex 2021'!E:E,'Opex 2020'!E:H,4,FALSE),0) -> 0
A55: 8470305 | B55: KUST - Dean Of Engineering | C55: 436110 | D55: Printing supplies | E55: 847.8470305.1.436110.000000.847001.200179 | F55: 0 | G55: 0 | K55: 0 | L55: 847001 | M55: KUST - General | N55: 200179 | O55: FA179-Opex Expense | P55: =IFERROR(VLOOKUP('Opex 2021'!E:E,'Opex 2020'!E:H,3,FALSE),0) -> 0.69 | Q55: =IFERROR(VLOOKUP('Opex 2021'!E:E,'Opex 2020'!E:H,4,FALSE),0) -> 0
A56: 8470310 | B56: KUST - Aerospace Engineering | C56: 425763 | D56: Student Project Expenses | E56: 847.8470310.1.425763.000000.847001.200179 | F56: 85000 | G56: 119000 | H56: 118694.51 | K56: 305.49 | L56: 847001 | M56: KUST - General | N56: 200179 | O56: FA179-Opex Expense | P56: =IFERROR(VLOOKUP('Opex 2021'!E:E,'Opex 2020'!E:H,3,FALSE),0) -> 62470 | Q56: =IFERROR(VLOOKUP('Opex 2021'!E:E,'Opex 2020'!E:H,4,FALSE),0) -> 62464.48
A57: 8470310 | B57: KUST - Aerospace Engineering | C57: 425770 | D57: Academic Missions - Combined expenses | E57: 847.8470310.1.425770.000000.847001.200179 | F57: 65000 | G57: 490 | K57: 490 | L57: 847001 | M57: KUST - General | N57: 200179 | O57: FA179-Opex Expense | P57: =IFERROR(VLOOKUP('Opex 2021'!E:E,'Opex 2020'!E:H,3,FALSE),0) -> 2891 | Q57: =IFERROR(VLOOKUP('Opex 2021'!E:E,'Opex 2020'!E:H,4,FALSE),0) -> 2890
A58: 8470310 | B58: KUST - Aerospace Engineering | C58: 430120 | D58: Rental - Buildings, other than staff residences | E58: 847.8470310.1.430120.000000.847001.200179 | F58: 180000 | G58: 180000 | K58: 180000 | L58: 847001 | M58: KUST - General | N58: 200179 | O58: FA179-Opex Expense | P58: =IFERROR(VLOOKUP('Opex 2021'!E:E,'Opex 2020'!E:H,3,FALSE),0) -> 0 | Q58: =IFERROR(VLOOKUP('Opex 2021'!E:E,'Opex 2020'!E:H,4,FALSE),0) -> 0
A59: 8470310 | B59: KUST - Aerospace Engineering | C59: 435350 | D59: Academic Publications | E59: 847.8470310.1.435350.000000.847001.200179 | F59: 2000 | G59: 52000 | K59: 52000 | L59: 847001 | M59: KUST - General | N59: 200179 | O59: FA179-Opex Expense | P59: =IFERROR(VLOOKUP('Opex 2021'!E:E,'Opex 2020'!E:H,3,FALSE),0) -> 1 | Q59: =IFERROR(VLOOKUP('Opex 2021'!E:E,'Opex 2020'!E:H,4,FALSE),0) -> 0
A60: 8470310 | B60: KUST - Aerospace Engineering | C60: 435508 | D60: Laboratory - Scientific | E60: 847.8470310.1.435508.000000.847001.200179 | F60: 50000 | G60: 50000 | I60: 49622.03 | K60: 377.97 | L60: 847001 | M60: KUST - General | N60: 200179 | O60: FA179-Opex Expense | P60: =IFERROR(VLOOKUP('Opex 2021'!E:E,'Opex 2020'!E:H,3,FALSE),0) -> 119612 | Q60: =IFERROR(VLOOKUP('Opex 2021'!E:E,'Opex 2020'!E:H,4,FALSE),0) -> 119603.75
A61: 8470310 | B61: KUST - Aerospace Engineering | C61: 436600 | D61: Training/Teaching equipment and other educational aid | E61: 847.8470310.1.436600.000000.847001.200179 | F61: 0 | G61: 510 | H61: 505.12 | K61: 4.88 | L61: 847001 | M61: KUST - General | N61: 200179 | O61: FA179-Opex Expense | P61: =IFERROR(VLOOKUP('Opex 2021'!E:E,'Opex 2020'!E:H,3,FALSE),0) -> 0 | Q61: =IFERROR(VLOOKUP('Opex 2021'!E:E,'Opex 2020'!E:H,4,FALSE),0) -> 0
A62: 8470315 | B62: KUST - Biomedical Engineering | C62: 425510 | D62: Conferences, seminars and exhibitions and other events: - Local Events | E62: 847.8470315.1.425510.000000.847001.200179 | F62: 1502 | G62: 1502 | K62: 1502 | L62: 847001 | M62: KUST - General | N62: 200179 | O62: FA179-Opex Expense | P62: =IFERROR(VLOOKUP('Opex 2021'!E:E,'Opex 2020'!E:H,3,FALSE),0) -> 1502 | Q62: =IFERROR(VLOOKUP('Opex 2021'!E:E,'Opex 2020'!E:H,4,FALSE),0) -> 1502
A63: 8470315 | B63: KUST - Biomedical Engineering | C63: 425760 | D63: Student activities & field trip expenses | E63: 847.8470315.1.425760.000000.847001.200179 | F63: 875 | G63: 875 | K63: 875 | L63: 847001 | M63: KUST - General | N63: 200179 | O63: FA179-Opex Expense | P63: =IFERROR(VLOOKUP('Opex 2021'!E:E,'Opex 2020'!E:H,3,FALSE),0) -> 875 | Q63: =IFERROR(VLOOKUP('Opex 2021'!E:E,'Opex 2020'!E:H,4,FALSE),0) -> 875
A64: 8470315 | B64: KUST - Biomedical Engineering | C64: 425763 | D64: Student Project Expenses | E64: 847.8470315.1.425763.000000.847001.200179 | F64: 59000 | G64: 59000 | H64: 51781.09 | K64: 7218.91 | L64: 847001 | M64: KUST - General | N64: 200179 | O64: FA179-Opex Expense | P64: =IFERROR(VLOOKUP('Opex 2021'!E:E,'Opex 2020'!E:H,3,FALSE),0) -> 56358 | Q64: =IFERROR(VLOOKUP('Opex 2021'!E:E,'Opex 2020'!E:H,4,FALSE),0) -> 54242.58
A65: 8470315 | B65: KUST - Biomedical Engineering | C65: 425770 | D65: Academic Missions - Combined expenses | E65: 847.8470315.1.425770.000000.847001.200179 | F65: 47557 | G65: 22557 | K65: 22557 | L65: 847001 | M65: KUST - General | N65: 200179 | O65: FA179-Opex Expense | P65: =IFERROR(VLOOKUP('Opex 2021'!E:E,'Opex 2020'!E:H,3,FALSE),0) -> 30571 | Q65: =IFERROR(VLOOKUP('Opex 2021'!E:E,'Opex 2020'!E:H,4,FALSE),0) -> 30570.03
A66: 8470315 | B66: KUST - Biomedical Engineering | C66: 425900 | D66: Entertainment and hospitality | E66: 847.8470315.1.425900.000000.847001.200179 | F66: 1024 | G66: 1024 | K66: 1024 | L66: 847001 | M66: KUST - General | N66: 200179 | O66: FA179-Opex Expense | P66: =IFERROR(VLOOKUP('Opex 2021'!E:E,'Opex 2020'!E:H,3,FALSE),0) -> 1024 | Q66: =IFERROR(VLOOKUP('Opex 2021'!E:E,'Opex 2020'!E:H,4,FALSE),0) -> 1023.75
A67: 8470315 | B67: KUST - Biomedical Engineering | C67: 426610 | D67: Computer software licenses | E67: 847.8470315.1.426610.000000.847001.200179 | F67: 9738 | G67: 9738 | H67: 3816.25 | K67: 5921.75 | L67: 847001 | M67: KUST - General | N67: 200179 | O67: FA179-Opex Expense | P67: =IFERROR(VLOOKUP('Opex 2021'!E:E,'Opex 2020'!E:H,3,FALSE),0) -> 8706 | Q67: =IFERROR(VLOOKUP('Opex 2021'!E:E,'Opex 2020'!E:H,4,FALSE),0) -> 8705.01
A68: 8470315 | B68: KUST - Biomedical Engineering | C68: 432209 | D68: Laboratory equipment | E68: 847.8470315.1.432209.000000.847001.200179 | F68: 6195 | G68: 6195 | H68: 5900 | K68: 295 | L68: 847001 | M68: KUST - General | N68: 200179 | O68: FA179-Opex Expense | P68: =IFERROR(VLOOKUP('Opex 2021'!E:E,'Opex 2020'!E:H,3,FALSE),0) -> 0 | Q68: =IFERROR(VLOOKUP('Opex 2021'!E:E,'Opex 2020'!E:H,4,FALSE),0) -> 0
A69: 8470315 | B69: KUST - Biomedical Engineering | C69: 435350 | D69: Academic Publications | E69: 847.8470315.1.435350.000000.847001.200179 | F69: 16000 | G69: 16000 | K69: 16000 | L69: 847001 | M69: KUST - General | N69: 200179 | O69: FA179-Opex Expense | P69: =IFERROR(VLOOKUP('Opex 2021'!E:E,'Opex 2020'!E:H,3,FALSE),0) -> 1 | Q69: =IFERROR(VLOOKUP('Opex 2021'!E:E,'Opex 2020'!E:H,4,FALSE),0) -> 0
A70: 8470315 | B70: KUST - Biomedical Engineering | C70: 435508 | D70: Laboratory - Scientific | E70: 847.8470315.1.435508.000000.847001.200179 | F70: 80000 | G70: 105000 | H70: 83654.93 | I70: 0 | J70: -4.7748472e-12 | K70: 21345.07 | L70: 847001 | M70: KUST - General | N70: 200179 | O70: FA179-Opex Expense | P70: =IFERROR(VLOOKUP('Opex 2021'!E:E,'Opex 2020'!E:H,3,FALSE),0) -> 194155 | Q70: =IFERROR(VLOOKUP('Opex 2021'!E:E,'Opex 2020'!E:H,4,FALSE),0) -> 186107.21
A71: 8470315 | B71: KUST - Biomedical Engineering | C71: 435508 | D71: Laboratory - Scientific | E71: 847.8470315.1.435508.000000.847951.200179 | F71: 17444 | G71: 17444 | K71: 17444 | L71: 847951 | M71: COVID-19 Pandemic | N71: 200179 | O71: FA179-Opex Expense | P71: =IFERROR(VLOOKUP('Opex 2021'!E:E,'Opex 2020'!E:H,3,FALSE),0) -> 0 | Q71: =IFERROR(VLOOKUP('Opex 2021'!E:E,'Opex 2020'!E:H,4,FALSE),0) -> 0
A72: 8470315 | B72: KUST - Biomedical Engineering | C72: 436110 | D72: Printing supplies | E72: 847.8470315.1.436110.000000.847001.200179 | F72: 500 | G72: 500 | K72: 500 | L72: 847001 | M72: KUST - General | N72: 200179 | O72: FA179-Opex Expense | P72: =IFERROR(VLOOKUP('Opex 2021'!E:E,'Opex 2020'!E:H,3,FALSE),0) -> 1 | Q72: =IFERROR(VLOOKUP('Opex 2021'!E:E,'Opex 2020'!E:H,4,FALSE),0) -> 0
A73: 8470320 | B73: KUST - Chemical Engineering | C73: 425763 | D73: Student Project Expenses | E73: 847.8470320.1.425763.000000.847001.200179 | F73: 20000 | G73: 20000 | H73: 20000 | K73: 0 | L73: 847001 | M73: KUST - General | N73: 200179 | O73: FA179-Opex Expense | P73: =IFERROR(VLOOKUP('Opex 2021'!E:E,'Opex 2020'!E:H,3,FALSE),0) -> 95179 | Q73: =IFERROR(VLOOKUP('Opex 2021'!E:E,'Opex 2020'!E:H,4,FALSE),0) -> 95178.15
A74: 8470320 | B74: KUST - Chemical Engineering | C74: 425770 | D74: Academic Missions - Combined expenses | E74: 847.8470320.1.425770.000000.847001.200179 | F74: 50000 | G74: 12750 | K74: 12750 | L74: 847001 | M74: KUST - General | N74: 200179 | O74: FA179-Opex Expense | P74: =IFERROR(VLOOKUP('Opex 2021'!E:E,'Opex 2020'!E:H,3,FALSE),0) -> 5990 | Q74: =IFERROR(VLOOKUP('Opex 2021'!E:E,'Opex 2020'!E:H,4,FALSE),0) -> 1493.55
A75: 8470320 | B75: KUST - Chemical Engineering | C75: 426610 | D75: Computer software licenses | E75: 847.8470320.1.426610.000000.847001.200179 | F75: 18985 | G75: 51585 | H75: 26945.13 | I75: 0 | J75: 5387.08 | K75: 19252.79 | L75: 847001 | M75: KUST - General | N75: 200179 | O75: FA179-Opex Expense | P75: =IFERROR(VLOOKUP('Opex 2021'!E:E,'Opex 2020'!E:H,3,FALSE),0) -> 8100 | Q75: =IFERROR(VLOOKUP('Opex 2021'!E:E,'Opex 2020'!E:H,4,FALSE),0) -> 8098.97
A76: 8470320 | B76: KUST - Chemical Engineering | C76: 435350 | D76: Academic Publications | E76: 847.8470320.1.435350.000000.847001.200179 | F76: 25000 | G76: 25000 | K76: 25000 | L76: 847001 | M76: KUST - General | N76: 200179 | O76: FA179-Opex Expense | P76: =IFERROR(VLOOKUP('Opex 2021'!E:E,'Opex 2020'!E:H,3,FALSE),0) -> 1 | Q76: =IFERROR(VLOOKUP('Opex 2021'!E:E,'Opex 2020'!E:H,4,FALSE),0) -> 0
A77: 8470320 | B77: KUST - Chemical Engineering | C77: 435508 | D77: Laboratory - Scientific | E77: 847.8470320.1.435508.000000.847001.200179 | F77: 100000 | G77: 100000 | H77: 91628 | J77: 0 | K77: 8372 | L77: 847001 | M77: KUST - General | N77: 200179 | O77: FA179-Opex Expense | P77: =IFERROR(VLOOKUP('Opex 2021'!E:E,'Opex 2020'!E:H,3,FALSE),0) -> 233493 | Q77: =IFERROR(VLOOKUP('Opex 2021'!E:E,'Opex 2020'!E:H,4,FALSE),0) -> 161058.6
A78: 8470325 | B78: KUST - Civil Engineering | C78: 425763 | D78: Student Project Expenses | E78: 847.8470325.1.425763.000000.847001.200179 | F78: 0 | G78: 35000 | H78: 30075.49 | K78: 4924.51 | L78: 847001 | M78: KUST - General | N78: 200179 | O78: FA179-Opex Expense | P78: =IFERROR(VLOOKUP('Opex 2021'!E:E,'Opex 2020'!E:H,3,FALSE),0) -> 89793 | Q78: =IFERROR(VLOOKUP('Opex 2021'!E:E,'Opex 2020'!E:H,4,FALSE),0) -> 89791.52
A79: 8470325 | B79: KUST - Civil Engineering | C79: 426610 | D79: Computer software licenses | E79: 847.8470325.1.426610.000000.847001.200179 | F79: 23000 | G79: 0 | K79: 0 | L79: 847001 | M79: KUST - General | N79: 200179 | O79: FA179-Opex Expense | P79: =IFERROR(VLOOKUP('Opex 2021'!E:E,'Opex 2020'!E:H,3,FALSE),0) -> 28273 | Q79: =IFERROR(VLOOKUP('Opex 2021'!E:E,'Opex 2020'!E:H,4,FALSE),0) -> 28271.54
A80: 8470325 | B80: KUST - Civil Engineering | C80: 435508 | D80: Laboratory - Scientific | E80: 847.8470325.1.435508.000000.847001.200179 | F80: 11350 | G80: 34350 | H80: 32675.81 | I80: 0 | J80: 0 | K80: 1674.19 | L80: 847001 | M80: KUST - General | N80: 200179 | O80: FA179-Opex Expense | P80: =IFERROR(VLOOKUP('Opex 2021'!E:E,'Opex 2020'!E:H,3,FALSE),0) -> 53916 | Q80: =IFERROR(VLOOKUP('Opex 2021'!E:E,'Opex 2020'!E:H,4,FALSE),0) -> 54573.2
A81: 8470325 | B81: KUST - Civil Engineering | C81: 435509 | D81: Laboratory - Veterinary | E81: 847.8470325.1.435509.000000.847001.200179 | F81: 0 | G81: 0 | K81: 0 | L81: 847001 | M81: KUST - General | N81: 200179 | O81: FA179-Opex Expense | P81: =IFERROR(VLOOKUP('Opex 2021'!E:E,'Opex 2020'!E:H,3,FALSE),0) -> 0 | Q81: =IFERROR(VLOOKUP('Opex 2021'!E:E,'Opex 2020'!E:H,4,FALSE),0) -> 0
A82: 8470325 | B82: KUST - Civil Engineering | C82: 436110 | D82: Printing supplies | E82: 847.8470325.1.436110.000000.847001.200179 | F82: 0 | G82: 0 | K82: 0 | L82: 847001 | M82: KUST - General | N82: 200179 | O82: FA179-Opex Expense | P82: =IFERROR(VLOOKUP('Opex 2021'!E:E,'Opex 2020'!E:H,3,FALSE),0) -> 1 | Q82: =IFERROR(VLOOKUP('Opex 2021'!E:E,'Opex 2020'!E:H,4,FALSE),0) -> 0
A83: 8470330 | B83: KUST - Electrical & Computer Engineering | C83: 425763 | D83: Student Project Expenses | E83: 847.8470330.1.425763.000000.847001.200179 | F83: 180000 | G83: 180000 | H83: 110008.23 | K83: 69991.77 | L83: 847001 | M83: KUST - General | N83: 200179 | O83: FA179-Opex Expense | P83: =IFERROR(VLOOKUP('Opex 2021'!E:E,'Opex 2020'!E:H,3,FALSE),0) -> 218974 | Q83: =IFERROR(VLOOKUP('Opex 2021'!E:E,'Opex 2020'!E:H,4,FALSE),0) -> 217038
A84: 8470330 | B84: KUST - Electrical & Computer Engineering | C84: 425770 | D84: Academic Missions - Combined expenses | E84: 847.8470330.1.425770.000000.847001.200179 | F84: 105000 | G84: 50000 | H84: 2000 | K84: 48000 | L84: 847001 | M84: KUST - General | N84: 200179 | O84: FA179-Opex Expense | P84: =IFERROR(VLOOKUP('Opex 2021'!E:E,'Opex 2020'!E:H,3,FALSE),0) -> 89907 | Q84: =IFERROR(VLOOKUP('Opex 2021'!E:E,'Opex 2020'!E:H,4,FALSE),0) -> 89564.48
A85: 8470330 | B85: KUST - Electrical & Computer Engineering | C85: 426610 | D85: Computer software licenses | E85: 847.8470330.1.426610.000000.847001.200179 | F85: 312530 | G85: 296003 | H85: 63834.1 | I85: 57357.57 | J85: 58297.86 | K85: 116513.47 | L85: 847001 | M85: KUST - General | N85: 200179 | O85: FA179-Opex Expense | P85: =IFERROR(VLOOKUP('Opex 2021'!E:E,'Opex 2020'!E:H,3,FALSE),0) -> 283205 | Q85: =IFERROR(VLOOKUP('Opex 2021'!E:E,'Opex 2020'!E:H,4,FALSE),0) -> 224906.03
A86: 8470330 | B86: KUST - Electrical & Computer Engineering | C86: 428640 | D86: Events - Awards, prizes & gifts | E86: 847.8470330.1.428640.000000.847001.200179 | F86: 0 | G86: 5000 | H86: 4487.99 | K86: 512.01 | L86: 847001 | M86: KUST - General | N86: 200179 | O86: FA179-Opex Expense | P86: =IFERROR(VLOOKUP('Opex 2021'!E:E,'Opex 2020'!E:H,3,FALSE),0) -> 0 | Q86: =IFERROR(VLOOKUP('Opex 2021'!E:E,'Opex 2020'!E:H,4,FALSE),0) -> 0
A87: 8470330 | B87: KUST - Electrical & Computer Engineering | C87: 435350 | D87: Academic Publications | E87: 847.8470330.1.435350.000000.847001.200179 | F87: 5615 | G87: 55615 | H87: 29166.1 | K87: 26448.9 | L87: 847001 | M87: KUST - General | N87: 200179 | O87: FA179-Opex Expense | P87: =IFERROR(VLOOKUP('Opex 2021'!E:E,'Opex 2020'!E:H,3,FALSE),0) -> 270283 | Q87: =IFERROR(VLOOKUP('Opex 2021'!E:E,'Opex 2020'!E:H,4,FALSE),0) -> 269679.27
A88: 8470330 | B88: KUST - Electrical & Computer Engineering | C88: 435508 | D88: Laboratory - Scientific | E88: 847.8470330.1.435508.000000.847001.200179 | F88: 32000 | G88: 32000 | H88: 31543.88 | J88: 0 | K88: 456.12 | L88: 847001 | M88: KUST - General | N88: 200179 | O88: FA179-Opex Expense | P88: =IFERROR(VLOOKUP('Opex 2021'!E:E,'Opex 2020'!E:H,3,FALSE),0) -> 20546 | Q88: =IFERROR(VLOOKUP('Opex 2021'!E:E,'Opex 2020'!E:H,4,FALSE),0) -> 19879.82
A89: 8470330 | B89: KUST - Electrical & Computer Engineering | C89: 436600 | D89: Training/Teaching equipment and other educational aid | E89: 847.8470330.1.436600.000000.847001.200179 | F89: 0 | G89: 16527 | I89: 16520 | K89: 7 | L89: 847001 | M89: KUST - General | N89: 200179 | O89: FA179-Opex Expense | P89: =IFERROR(VLOOKUP('Opex 2021'!E:E,'Opex 2020'!E:H,3,FALSE),0) -> 0 | Q89: =IFERROR(VLOOKUP('Opex 2021'!E:E,'Opex 2020'!E:H,4,FALSE),0) -> 0
A90: 8470335 | B90: KUST - Industrial & Systems Engineering | C90: 425763 | D90: Student Project Expenses | E90: 847.8470335.1.425763.000000.847001.200179 | F90: 25000 | G90: 25000 | H90: 25000 | K90: 0 | L90: 847001 | M90: KUST - General | N90: 200179 | O90: FA179-Opex Expense | P90: =IFERROR(VLOOKUP('Opex 2021'!E:E,'Opex 2020'!E:H,3,FALSE),0) -> 40127 | Q90: =IFERROR(VLOOKUP('Opex 2021'!E:E,'Opex 2020'!E:H,4,FALSE),0) -> 40125.89
A91: 8470335 | B91: KUST - Industrial & Systems Engineering | C91: 425770 | D91: Academic Missions - Combined expenses | E91: 847.8470335.1.425770.000000.847001.200179 | F91: 75000 | G91: 75000 | H91: -3762.15 | K91: 78762.15 | L91: 847001 | M91: KUST - General | N91: 200179 | O91: FA179-Opex Expense | P91: =IFERROR(VLOOKUP('Opex 2021'!E:E,'Opex 2020'!E:H,3,FALSE),0) -> 54556 | Q91: =IFERROR(VLOOKUP('Opex 2021'!E:E,'Opex 2020'!E:H,4,FALSE),0) -> 54554.56
A92: 8470335 | B92: KUST - Industrial & Systems Engineering | C92: 426610 | D92: Computer software licenses | E92: 847.8470335.1.426610.000000.847001.200179 | F92: 149370 | G92: 149370 | H92: 40542.84 | I92: 77260.02 | J92: 22440.77 | K92: 9126.37 | L92: 847001 | M92: KUST - General | N92: 200179 | O92: FA179-Opex Expense | P92: =IFERROR(VLOOKUP('Opex 2021'!E:E,'Opex 2020'!E:H,3,FALSE),0) -> 137795 | Q92: =IFERROR(VLOOKUP('Opex 2021'!E:E,'Opex 2020'!E:H,4,FALSE),0) -> 124805.06
A93: 8470335 | B93: KUST - Industrial & Systems Engineering | C93: 435350 | D93: Academic Publications | E93: 847.8470335.1.435350.000000.847001.200179 | F93: 51520 | G93: 51520 | H93: 22479.86 | K93: 29040.14 | L93: 847001 | M93: KUST - General | N93: 200179 | O93: FA179-Opex Expense | P93: =IFERROR(VLOOKUP('Opex 2021'!E:E,'Opex 2020'!E:H,3,FALSE),0) -> 38005 | Q93: =IFERROR(VLOOKUP('Opex 2021'!E:E,'Opex 2020'!E:H,4,FALSE),0) -> 38004.2
A94: 8470335 | B94: KUST - Industrial & Systems Engineering | C94: 435508 | D94: Laboratory - Scientific | E94: 847.8470335.1.435508.000000.847001.200179 | F94: 60000 | G94: 60000 | H94: 37764.01 | I94: 0 | J94: 13424 | K94: 8811.99 | L94: 847001 | M94: KUST - General | N94: 200179 | O94: FA179-Opex Expense | P94: =IFERROR(VLOOKUP('Opex 2021'!E:E,'Opex 2020'!E:H,3,FALSE),0) -> 112268 | Q94: =IFERROR(VLOOKUP('Opex 2021'!E:E,'Opex 2020'!E:H,4,FALSE),0) -> 99043.8
A95: 8470335 | B95: KUST - Industrial & Systems Engineering | C95: 436110 | D95: Printing supplies | E95: 847.8470335.1.436110.000000.847001.200179 | F95: 0 | G95: 0 | K95: 0 | L95: 847001 | M95: KUST - General | N95: 200179 | O95: FA179-Opex Expense | P95: =IFERROR(VLOOKUP('Opex 2021'!E:E,'Opex 2020'!E:H,3,FALSE),0) -> 3779 | Q95: =IFERROR(VLOOKUP('Opex 2021'!E:E,'Opex 2020'!E:H,4,FALSE),0) -> 3777.8
A96: 8470335 | B96: KUST - Industrial & Systems Engineering | C96: 436600 | D96: Training/Teaching equipment and other educational aid | E96: 847.8470335.1.436600.000000.847001.200179 | F96: 13858 | G96: 13858 | H96: 11192.69 | I96: 0 | J96: 0 | K96: 2665.31 | L96: 847001 | M96: KUST - General | N96: 200179 | O96: FA179-Opex Expense | P96: =IFERROR(VLOOKUP('Opex 2021'!E:E,'Opex 2020'!E:H,3,FALSE),0) -> 12141 | Q96: =IFERROR(VLOOKUP('Opex 2021'!E:E,'Opex 2020'!E:H,4,FALSE),0) -> 12140.5
A97: 8470340 | B97: KUST - Mechanical Engineering | C97: 425763 | D97: Student Project Expenses | E97: 847.8470340.1.425763.000000.847001.200179 | F97: 300000 | G97: 300000 | H97: 148453.21 | K97: 151546.79 | L97: 847001 | M97: KUST - General | N97: 200179 | O97: FA179-Opex Expense | P97: =IFERROR(VLOOKUP('Opex 2021'!E:E,'Opex 2020'!E:H,3,FALSE),0) -> 225404 | Q97: =IFERROR(VLOOKUP('Opex 2021'!E:E,'Opex 2020'!E:H,4,FALSE),0) -> 225403.24
A98: 8470340 | B98: KUST - Mechanical Engineering | C98: 425770 | D98: Academic Missions - Combined expenses | E98: 847.8470340.1.425770.000000.847001.200179 | F98: 52050 | G98: 52050 | H98: 13078.03 | K98: 38971.97 | L98: 847001 | M98: KUST - General | N98: 200179 | O98: FA179-Opex Expense | P98: =IFERROR(VLOOKUP('Opex 2021'!E:E,'Opex 2020'!E:H,3,FALSE),0) -> 54308 | Q98: =IFERROR(VLOOKUP('Opex 2021'!E:E,'Opex 2020'!E:H,4,FALSE),0) -> 54007.37
A99: 8470340 | B99: KUST - Mechanical Engineering | C99: 426610 | D99: Computer software licenses | E99: 847.8470340.1.426610.000000.847001.200179 | F99: 209338 | G99: 209338 | H99: 29192.5 | I99: 91633.4 | J99: 41872.2 | K99: 46639.9 | L99: 847001 | M99: KUST - General | N99: 200179 | O99: FA179-Opex Expense | P99: =IFERROR(VLOOKUP('Opex 2021'!E:E,'Opex 2020'!E:H,3,FALSE),0) -> 173962 | Q99: =IFERROR(VLOOKUP('Opex 2021'!E:E,'Opex 2020'!E:H,4,FALSE),0) -> 173961.31
A100: 8470340 | B100: KUST - Mechanical Engineering | C100: 432209 | D100: Laboratory equipment | E100: 847.8470340.1.432209.000000.847001.200179 | F100: 0 | G100: 60000 | H100: 6189.01 | I100: 40000 | K100: 13810.99 | L100: 847001 | M100: KUST - General | N100: 200179 | O100: FA179-Opex Expense | P100: =IFERROR(VLOOKUP('Opex 2021'!E:E,'Opex 2020'!E:H,3,FALSE),0) -> 0 | Q100: =IFERROR(VLOOKUP('Opex 2021'!E:E,'Opex 2020'!E:H,4,FALSE),0) -> 0
...

Sheet Opex 2020
A2: Cost Center Code | B2: Cost Center Description | C2: Account Code | D2: Account Description | E2: GL Account Combination | F2: Annual Budget | G2: Revised Budget | H2: Actual Amount | I2: PR | J2: PO | K2: Fund Available | L2: Future1 | M2: Future1 Description | N2: Future2 | O2: Future2 Description
A3: 8470110 | B3: KUST - Office of the President | C3: 420550 | D3: Academic Advisory Service | E3: 847.8470110.1.420550.000000.847001.200179 | F3: 838988.09 | G3: 29118.09 | H3: 29118.02 | K3: 0.07 | L3: 847001 | M3: KUST - General | N3: 200179 | O3: FA179-Opex Expense | P3: =VLOOKUP(E:E,'Opex 2021'!E:E,1,FALSE) -> 847.8470110.1.420550.000000.847001.200179
A4: 8470110 | B4: KUST - Office of the President | C4: 420570 | D4: Academic Collaborative Partnership Services | E4: 847.8470110.1.420570.000000.847001.200179 | F4: 3104255.9 | G4: 0.94 | K4: 0.94 | L4: 847001 | M4: KUST - General | N4: 200179 | O4: FA179-Opex Expense | P4: =VLOOKUP(E:E,'Opex 2021'!E:E,1,FALSE) -> 847.8470110.1.420570.000000.847001.200179
A5: 8470110 | B5: KUST - Office of the President | C5: 420900 | D5: Legal services | E5: 847.8470110.1.420900.000000.847001.200179 | F5: 41949.4 | G5: 1900.4 | H5: 1845 | K5: 55.4 | L5: 847001 | M5: KUST - General | N5: 200179 | O5: FA179-Opex Expense | P5: =VLOOKUP(E:E,'Opex 2021'!E:E,1,FALSE) -> 847.8470110.1.420900.000000.847001.200179
A6: 8470110 | B6: KUST - Office of the President | C6: 421000 | D6: Management consultancy | E6: 847.8470110.1.421000.000000.847001.200179 | F6: 306230.65 | G6: 0.65 | K6: 0.65 | L6: 847001 | M6: KUST - General | N6: 200179 | O6: FA179-Opex Expense | P6: =VLOOKUP(E:E,'Opex 2021'!E:E,1,FALSE) -> 847.8470110.1.421000.000000.847001.200179
A7: 8470110 | B7: KUST - Office of the President | C7: 421700 | D7: Standards Certification Services (e.g. ISO) | E7: 847.8470110.1.421700.000000.847001.200179 | F7: 125848.21 | G7: 1.21 | K7: 1.21 | L7: 847001 | M7: KUST - General | N7: 200179 | O7: FA179-Opex Expense | P7: =VLOOKUP(E:E,'Opex 2021'!E:E,1,FALSE) -> 847.8470110.1.421700.000000.847001.200179
A8: 8470110 | B8: KUST - Office of the President | C8: 425100 | D8: Advertising Services (General) | E8: 847.8470110.1.425100.000000.847001.200179 | F8: 0 | G8: 0 | K8: 0 | L8: 847001 | M8: KUST - General | N8: 200179 | O8: FA179-Opex Expense | P8: =VLOOKUP(E:E,'Opex 2021'!E:E,1,FALSE) -> 847.8470110.1.425100.000000.847001.200179
A9: 8470110 | B9: KUST - Office of the President | C9: 425510 | D9: Conferences, seminars and exhibitions and other events: - Local Events | E9: 847.8470110.1.425510.000000.847001.200179 | F9: 1006785.7 | G9: 277367.71 | H9: 277368 | K9: -0.29 | L9: 847001 | M9: KUST - General | N9: 200179 | O9: FA179-Opex Expense | P9: =VLOOKUP(E:E,'Opex 2021'!E:E,1,FALSE) -> 847.8470110.1.425510.000000.847001.200179
A10: 8470110 | B10: KUST - Office of the President | C10: 425550 | D10: Conferences, seminars and exhibitions and other events: - Overseas event | E10: 847.8470110.1.425550.000000.847001.200179 | F10: 83898.81 | G10: 0.81 | K10: 0.81 | L10: 847001 | M10: KUST - General | N10: 200179 | O10: FA179-Opex Expense | P10: =VLOOKUP(E:E,'Opex 2021'!E:E,1,FALSE) -> 847.8470110.1.425550.000000.847001.200179
A11: 8470110 | B11: KUST - Office of the President | C11: 425770 | D11: Academic Missions - Combined expenses | E11: 847.8470110.1.425770.000000.847001.200179 | H11: -13420 | K11: 13420 | L11: 847001 | M11: KUST - General | N11: 200179 | O11: FA179-Opex Expense | P11: =VLOOKUP(E:E,'Opex 2021'!E:E,1,FALSE) -> 847.8470110.1.425770.000000.847001.200179
A12: 8470110 | B12: KUST - Office of the President | C12: 425900 | D12: Entertainment and hospitality | E12: 847.8470110.1.425900.000000.847001.200179 | F12: 83898.81 | G12: 13356.81 | H12: 13355.7 | K12: 1.11 | L12: 847001 | M12: KUST - General | N12: 200179 | O12: FA179-Opex Expense | P12: =VLOOKUP(E:E,'Opex 2021'!E:E,1,FALSE) -> 847.8470110.1.425900.000000.847001.200179
A13: 8470110 | B13: KUST - Office of the President | C13: 426610 | D13: Computer software licenses | E13: 847.8470110.1.426610.000000.847001.200179 | F13: 100678.57 | G13: 42240.57 | H13: 42239.5 | I13: 0 | J13: 0 | K13: 1.07 | L13: 847001 | M13: KUST - General | N13: 200179 | O13: FA179-Opex Expense | P13: =VLOOKUP(E:E,'Opex 2021'!E:E,1,FALSE) -> 847.8470110.1.426610.000000.847001.200179
A14: 8470110 | B14: KUST - Office of the President | C14: 427710 | D14: Subscriptions and membership fees: Trade organisations | E14: 847.8470110.1.427710.000000.847001.200179 | F14: 0 | G14: 3883 | H14: 3882.17 | K14: 0.83 | L14: 847001 | M14: KUST - General | N14: 200179 | O14: FA179-Opex Expense | P14: =VLOOKUP(E:E,'Opex 2021'!E:E,1,FALSE) -> 847.8470110.1.427710.000000.847001.200179
A15: 8470110 | B15: KUST - Office of the President | C15: 427900 | D15: Translation and interpretation service | E15: 847.8470110.1.427900.000000.847001.200179 | F15: 12584.82 | G15: 0.82 | K15: 0.82 | L15: 847001 | M15: KUST - General | N15: 200179 | O15: FA179-Opex Expense | P15: =VLOOKUP(E:E,'Opex 2021'!E:E,1,FALSE) -> 847.8470110.1.427900.000000.847001.200179
A16: 8470110 | B16: KUST - Office of the President | C16: 428090 | D16: Business Travel - Combined expenses | E16: 847.8470110.1.428090.000000.847001.200179 | F16: 838988.21 | G16: 104380.21 | H16: 64375.44 | K16: 40004.77 | L16: 847001 | M16: KUST - General | N16: 200179 | O16: FA179-Opex Expense | P16: =VLOOKUP(E:E,'Opex 2021'!E:E,1,FALSE) -> 847.8470110.1.428090.000000.847001.200179
A17: 8470110 | B17: KUST - Office of the President | C17: 428400 | D17: Sponsorship expenses/contributions | E17: 847.8470110.1.428400.000000.847001.200179 | F17: 209747.02 | G17: 22708751 | H17: 22708675 | K17: 76.03 | L17: 847001 | M17: KUST - General | N17: 200179 | O17: FA179-Opex Expense | P17: =VLOOKUP(E:E,'Opex 2021'!E:E,1,FALSE) -> 847.8470110.1.428400.000000.847001.200179
A18: 8470110 | B18: KUST - Office of the President | C18: 428640 | D18: Events - Awards, prizes & gifts | E18: 847.8470110.1.428640.000000.847001.200179 | F18: 167797.62 | G18: 0.62 | K18: 0.62 | L18: 847001 | M18: KUST - General | N18: 200179 | O18: FA179-Opex Expense | P18: =VLOOKUP(E:E,'Opex 2021'!E:E,1,FALSE) -> 847.8470110.1.428640.000000.847001.200179
A19: 8470110 | B19: KUST - Office of the President | C19: 430330 | D19: Rental - Motor vehicles | E19: 847.8470110.1.430330.000000.847001.200179 | F19: 3355.95 | G19: 0.95 | K19: 0.95 | L19: 847001 | M19: KUST - General | N19: 200179 | O19: FA179-Opex Expense | P19: =VLOOKUP(E:E,'Opex 2021'!E:E,1,FALSE) -> 847.8470110.1.430330.000000.847001.200179
A20: 8470110 | B20: KUST - Office of the President | C20: 435310 | D20: Newspapers, magazines, journals, etc | E20: 847.8470110.1.435310.000000.847001.200179 | F20: 5033.93 | G20: 0.93 | K20: 0.93 | L20: 847001 | M20: KUST - General | N20: 200179 | O20: FA179-Opex Expense | P20: =VLOOKUP(E:E,'Opex 2021'!E:E,1,FALSE) -> 847.8470110.1.435310.000000.847001.200179
A21: 8470110 | B21: KUST - Office of the President | C21: 435410 | D21: Catering supplies: Offices | E21: 847.8470110.1.435410.000000.847001.200179 | F21: 2516.96 | G21: 0.96 | K21: 0.96 | L21: 847001 | M21: KUST - General | N21: 200179 | O21: FA179-Opex Expense | P21: =VLOOKUP(E:E,'Opex 2021'!E:E,1,FALSE) -> 847.8470110.1.435410.000000.847001.200179
A22: 8470110 | B22: KUST - Office of the President | C22: 435519 | D22: Photography - Consumable materials /Tools | E22: 847.8470110.1.435519.000000.847001.200179 | F22: 4194.94 | G22: 0.94 | K22: 0.94 | L22: 847001 | M22: KUST - General | N22: 200179 | O22: FA179-Opex Expense | P22: =VLOOKUP(E:E,'Opex 2021'!E:E,1,FALSE) -> 847.8470110.1.435519.000000.847001.200179
A23: 8470110 | B23: KUST - Office of the President | C23: 435530 | D23: School consumables, not specifically mentioned elsewhere | E23: 847.8470110.1.435530.000000.847001.200179 | F23: 33559.52 | G23: 0.52 | K23: 0.52 | L23: 847001 | M23: KUST - General | N23: 200179 | O23: FA179-Opex Expense | P23: =VLOOKUP(E:E,'Opex 2021'!E:E,1,FALSE) -> 847.8470110.1.435530.000000.847001.200179
A24: 8470110 | B24: KUST - Office of the President | C24: 436110 | D24: Printing supplies | E24: 847.8470110.1.436110.000000.847001.200179 | F24: 4194.94 | G24: 0.94 | K24: 0.94 | L24: 847001 | M24: KUST - General | N24: 200179 | O24: FA179-Opex Expense | P24: =VLOOKUP(E:E,'Opex 2021'!E:E,1,FALSE) -> 847.8470110.1.436110.000000.847001.200179
A25: 8470120 | B25: KUST - Audit & Compliance | C25: 420120 | D25: Internal Audit service | E25: 847.8470120.1.420120.000000.847001.200179 | F25: 400000 | G25: -477000 | H25: -493500 | I25: 0 | J25: 0 | K25: 16500 | L25: 847001 | M25: KUST - General | N25: 200179 | O25: FA179-Opex Expense | P25: =VLOOKUP(E:E,'Opex 2021'!E:E,1,FALSE) -> 847.8470120.1.420120.000000.847001.200179
A26: 8470130 | B26: KUST - Institutional Research & Planning | C26: 421000 | D26: Management consultancy | E26: 847.8470130.1.421000.000000.847001.200179 | F26: 0 | G26: 162970 | H26: 28465.75 | I26: 0 | J26: 0 | K26: 134504.25 | L26: 847001 | M26: KUST - General | N26: 200179 | O26: FA179-Opex Expense | P26: =VLOOKUP(E:E,'Opex 2021'!E:E,1,FALSE) -> 847.8470130.1.421000.000000.847001.200179
A27: 8470130 | B27: KUST - Institutional Research & Planning | C27: 425100 | D27: Advertising Services (General) | E27: 847.8470130.1.425100.000000.847001.200179 | F27: 687400 | G27: 0 | K27: 0 | L27: 847001 | M27: KUST - General | N27: 200179 | O27: FA179-Opex Expense | P27: =VLOOKUP(E:E,'Opex 2021'!E:E,1,FALSE) -> 847.8470130.1.425100.000000.847001.200179
A28: 8470130 | B28: KUST - Institutional Research & Planning | C28: 425510 | D28: Conferences, seminars and exhibitions and other events: - Local Events | E28: 847.8470130.1.425510.000000.847001.200179 | F28: 367500 | G28: 2200 | H28: 2200 | K28: 0 | L28: 847001 | M28: KUST - General | N28: 200179 | O28: FA179-Opex Expense | P28: =VLOOKUP(E:E,'Opex 2021'!E:E,1,FALSE) -> 847.8470130.1.425510.000000.847001.200179
A29: 8470130 | B29: KUST - Institutional Research & Planning | C29: 428090 | D29: Business Travel - Combined expenses | E29: 847.8470130.1.428090.000000.847001.200179 | F29: 235872 | G29: 0 | K29: 0 | L29: 847001 | M29: KUST - General | N29: 200179 | O29: FA179-Opex Expense | P29: =VLOOKUP(E:E,'Opex 2021'!E:E,1,FALSE) -> 847.8470130.1.428090.000000.847001.200179
