Workbook

Sheet Guideline
A1: Purpose The Annual Procurement planning is the process of identifying and consolidating requirements and determining the timeframes for their procurement with the aim of having them as and when they are required. Also, it will help Procurement & Contracts Department to arrange its work force accordingly in order to achieve the efficiency and effectiveness in the procurement process.
A3: Objective: The objective is to ensure that there is a consistent and transparent approach to handling procurement activities at KU Academic and Administrative departments by assisting them with the planning for the procurement of goods, works or services in a pro-active manner and to move away from merely reacting to purchasing requests.
A5: Guideline: * All academic and administrative departments shall prepare a procurement plan for goods/services according to the Procurement & Contracts Policy and as well as Management's directions. “Planning & Vendor Management Section” will meet regularly with User Departments to review all plans to procure goods and services for KU, and to determine which goods and services should be procured centrally through Procurement & Contracts, through pricing agreements or any other methods of procurement
A7: * Departments should appoint an APP Co-ordinator. Appointing an APP Co-ordinator establishes the basis for a coordinated approach across the department. The Co-ordinator can be responsible for collating information, drafting the APP, submitting the APP for approval from line manager and managing reviews and updates during the year. * The Co-Ordinator is also required to arrange with other departments to submit their procurement project/initiative especially if it is going to be consumed from the said department(s) budget.
B8: STLI-0001
A9: * There are a number of factors a department may wish to consider when deciding which procurements to include in the APP. These may include: • The likely significance of the procurement; • The likely value; • The likelihood of the procurement actually occurring and determine the need date; and • The type of procurement.
A11: The subject matter of the procurement is described in the General Description column of the APP. The wording for the summary of the planned procurement should be short and in plain English. 1. When specifying details of a procurement, it is good practice to include information about: a. the likely scale or volume of the procurement; b. the delivery location(s); c. the planned method of procurement including details of any intended panel arrangements; and d. the likely contract duration (in the Comment field) 2. When listing planned procurements, End Users should avoid descriptions that: (also see example below) a. are too general or broad; b. give an inadequate indication of the scope of the procurement; c. use overly technical terms or jargon; or d. inadequately describe the type of property or services sought.
A13: GOOD PRACTICE EXAMPLES
A14: Bad Description | B14: Good Description
A15: IT system (too general) | B15: Electronic records management system to maintain all official documents
A16: Blueprint for expansion of mainstream electronic information dissemination strategy for publications encouraging improved knowledge and awareness of “Healthy UAE” program (too technical and obscure) | B16: Design and development of a website for health promotion services
A17: Telephones (inadequate indication of size and scope) | B17: Replacement of voice services to 1000 staff in all KU and Project offices
A18: Panel of service providers (insufficient description of the service) | B18: Panel of legal services providers
A20: Estimated Need date: 1. Departments are required to indicate the planned timing for acquiring the service/goods/works in the Planned Procurement Need date section of the APP. It is good practice to indicate the planned timing as specifically as possible by selecting the month of the planned need date. This will assist Procurement & Contracts to plan for approaching the market as per the pre-agreed SLA. 2. This information should include also software renewal and acquiring any addtional new software. Where additional information about timing is known, such as the expiry date of a current contract or details of the likely contract commencement date, it is good practice to include this information in the APP.
A22: Updating Annual Procurement Plans
A23: * APP Co-ordinators will be contacted regularly on a quarterly basis by Planning & Vendor Management Section to Check and review all planned procurement to make sure that all schedules are met. For any questions please refer to the instructions sheet below and contact the Planning & Vendor Management team

Sheet Submission Instruction
A1: Guide to Completing the Annual Procurement Plan (APP)
A2: Instructions 1. Save this document as your APP. Please use the following file naming protocol: <your department> APP <last update (insert date)> (eg: 'MED APP last updated 18 June 2015') 2. To prepare your APP go to the red tab below called 'APP Template' and start listing your forecast tender opportunities. 3. For the guideline on how to complete the APP template go to the yellow tabs below 'Guideline" 4. Once you have completed your APP e-mail it to (Procurement Planning & Vendor Management Section) Section to: Mr. Shiju Badarudeen Planning and Vendor Management shiju.badarudeen@ku.ac.ae Tel: 023123904 5. All Correspondence and Clarifications have to come through Procurement and Contracts Department email :shiju.badarudeen@ku.ac.ae, shamma.almarar@ku.ac.ae 6. Make a note in your diary to update your APP every 3 months. Planning & Vendor Management Team will contact you. 7. APP Coordinator need to be appointed by the department in order to fill out and update the APP regularly
B8: STLI-0001

Sheet Budget Summary
A1: 2021 Budget Summary
F2: APPROVED BUDGET | H2: UTILISED BUDGET | J2: AVAILABLE BUDGET
A3: Sl No | B3: DEPARTMENT | C3: CC | D3: CC Manager | E3: VP/Dean | F3: CAPEX | G3: OPEX | H3: CAPEX | I3: OPEX | J3: CAPEX | K3: OPEX
A4: 1 | B4: VP/Research & Development | C4: 8471110 | D4: Steven Wesley Griffiths | E4: Steve Griffiths
A5: 2 | B5: Institute for Automation , Information Science and Communication | C5: 8471120 | D5: Ernesto Damiani | E5: Steve Griffiths
A6: 3 | B6: Petroleum Institute | C6: 8471121 | D6: Saeed Al Khazraji | E6: Steve Griffiths
A7: 4 | B7: Masdar Institute | C7: 8471122 | D7: Samuel Sheng Mao | E7: Steve Griffiths
A8: 5 | B8: Office of Research Service | C8: 8471130 | D8: John Radkowski | E8: Steve Griffiths
A9: 6 | B9: KUST - University Sponsored Research | C9: 8471140 | D9: Blake Ashwell | E9: Steve Griffiths
A10: 7 | B10: TMI | C10: 8471150 | D10: Sami Mohamed Bashir | E10: Steve Griffiths
A11: 8 | B11: Research Labs | C11: 8471160 | D11: Jeremie Daniel Alexandre Pelletier | E11: Steve Griffiths
A12: 9 | B12: Research Computing | C12: 8471170 | D12: Dureid El Moghraby | E12: Steve Griffiths
F16: =SUM(F4:F15) -> 0 | G16: =SUM(G4:G15) -> 0 | H16: =SUM(H4:H15) -> 0 | I16: =SUM(I4:I15) -> 0 | J16: =SUM(J4:J15) -> 0 | K16: =SUM(K4:K15) -> 0

Sheet VPRES
B1: PROCUREMENT PLAN 2021 FOR BUDGET UTILIZING
B2: DEPARTMENT NAME | D2: APPROVED BUDGET | H2: UTILISED BUDGET | J2: AVAILABLE BUDGET
B3: ='Budget Summary'!B4 -> VP/Research & Development | D3: CAPITAL | F3: OPERATING | H3: CAPITAL | I3: OPERATING | J3: CAPITAL | K3: OPERATING
B4: VPRES | D4: ='Budget Summary'!F4 -> 0 | F4: ='Budget Summary'!G4 -> 0 | H4: =D38 -> 0 | I4: =E38 -> 0 | J4: =D4-H4 -> 0 | K4: =F4-I4 -> 0
G5: Requirement Date/Need Date
A6: Sl No | B6: Plan Ref. Number | C6: Description of Goods/services/works (Specifications) | D6: Utilised CAPEX Budget | E6: Utilised OPEX Budget | F6: Procurement Method | G6: Quarters | H6: Month | I6: Day | J6: Delivery Location | K6: Purchase Requisition Number (if available) | L6: Expected Requisition Approved Date | M6: Comments
A8: 1 | B8: =CONCATENATE("VPRES-",LEFT("0000",4-LEN(ROW(A2)-1)),ROW(A2)-1) -> VPRES-0001
A9: 2 | B9: =CONCATENATE("VPRES-",LEFT("0000",4-LEN(ROW(A3)-1)),ROW(A3)-1) -> VPRES-0002
A10: 3 | B10: =CONCATENATE("VPRES-",LEFT("0000",4-LEN(ROW(A4)-1)),ROW(A4)-1) -> VPRES-0003
A11: 4 | B11: =CONCATENATE("VPRES-",LEFT("0000",4-LEN(ROW(A5)-1)),ROW(A5)-1) -> VPRES-0004
A12: 5 | B12: =CONCATENATE("VPRES-",LEFT("0000",4-LEN(ROW(A6)-1)),ROW(A6)-1) -> VPRES-0005
A13: 6 | B13: =CONCATENATE("VPRES-",LEFT("0000",4-LEN(ROW(A7)-1)),ROW(A7)-1) -> VPRES-0006
A14: 7 | B14: =CONCATENATE("VPRES-",LEFT("0000",4-LEN(ROW(A8)-1)),ROW(A8)-1) -> VPRES-0007
A15: 8 | B15: =CONCATENATE("VPRES-",LEFT("0000",4-LEN(ROW(A9)-1)),ROW(A9)-1) -> VPRES-0008
A16: 9 | B16: =CONCATENATE("VPRES-",LEFT("0000",4-LEN(ROW(A10)-1)),ROW(A10)-1) -> VPRES-0009
A17: 10 | B17: =CONCATENATE("VPRES-",LEFT("0000",4-LEN(ROW(A11)-1)),ROW(A11)-1) -> VPRES-0010
A18: 11 | B18: =CONCATENATE("VPRES-",LEFT("0000",4-LEN(ROW(A12)-1)),ROW(A12)-1) -> VPRES-0011
A19: 12 | B19: =CONCATENATE("VPRES-",LEFT("0000",4-LEN(ROW(A13)-1)),ROW(A13)-1) -> VPRES-0012
... A37: 30 | B37: =CONCATENATE("VPRES-",LEFT("0000",4-LEN(ROW(A31)-1)),ROW(A31)-1) -> VPRES-0030
C38: Total Expenditure | D38: =SUM(D8:D37) -> 0 | E38: =SUM(E8:E37) -> 0

Sheet IISC
B1: PROCUREMENT PLAN 2021 FOR BUDGET UTILIZING
B2: DEPARTMENT NAME | D2: APPROVED BUDGET | H2: UTILISED BUDGET | J2: AVAILABLE BUDGET
B3: ='Budget Summary'!B5 -> Institute for Automation , Information Science and Communication | D3: CAPITAL | F3: OPERATING | H3: CAPITAL | I3: OPERATING | J3: CAPITAL | K3: OPERATING
B4: IISC | D4: ='Budget Summary'!F5 -> 0 | F4: ='Budget Summary'!G5 -> 0 | H4: =D39 -> 0 | I4: =E39 -> 0 | J4: =D4-H4 -> 0 | K4: =F4-I4 -> 0
G5: Requirement Date/Need Date
A6: Sl No | B6: Plan Ref. Number | C6: Description of Goods/services/works (Specifications) | D6: Utilised CAPEX Budget | E6: Utilised OPEX Budget | F6: Procurement Method | G6: Quarters | H6: Month | I6: Day | J6: Delivery Location | K6: Purchase Requisition Number (if available) | L6: Expected Requisition Approved Date | M6: Comments
A8: 1 | B8: =CONCATENATE("IISC-",LEFT("0000",4-LEN(ROW(A2)-1)),ROW(A2)-1) -> IISC-0001
A9: 2 | B9: =CONCATENATE("IISC-",LEFT("0000",4-LEN(ROW(A3)-1)),ROW(A3)-1) -> IISC-0002
A10: 3 | B10: =CONCATENATE("IISC-",LEFT("0000",4-LEN(ROW(A4)-1)),ROW(A4)-1) -> IISC-0003
A11: 4 | B11: =CONCATENATE("IISC-",LEFT("0000",4-LEN(ROW(A5)-1)),ROW(A5)-1) -> IISC-0004
A12: 5 | B12: =CONCATENATE("IISC-",LEFT("0000",4-LEN(ROW(A6)-1)),ROW(A6)-1) -> IISC-0005
A13: 6 | B13: =CONCATENATE("IISC-",LEFT("0000",4-LEN(ROW(A7)-1)),ROW(A7)-1) -> IISC-0006
A14: 7 | B14: =CONCATENATE("IISC-",LEFT("0000",4-LEN(ROW(A8)-1)),ROW(A8)-1) -> IISC-0007
A15: 8 | B15: =CONCATENATE("IISC-",LEFT("0000",4-LEN(ROW(A9)-1)),ROW(A9)-1) -> IISC-0008
A16: 9 | B16: =CONCATENATE("IISC-",LEFT("0000",4-LEN(ROW(A10)-1)),ROW(A10)-1) -> IISC-0009
A17: 10 | B17: =CONCATENATE("IISC-",LEFT("0000",4-LEN(ROW(A11)-1)),ROW(A11)-1) -> IISC-0010
A18: 11 | B18: =CONCATENATE("IISC-",LEFT("0000",4-LEN(ROW(A12)-1)),ROW(A12)-1) -> IISC-0011
A19: 12 | B19: =CONCATENATE("IISC-",LEFT("0000",4-LEN(ROW(A13)-1)),ROW(A13)-1) -> IISC-0012
... A38: 31 | B38: =CONCATENATE("IISC-",LEFT("0000",4-LEN(ROW(A32)-1)),ROW(A32)-1) -> IISC-0031
C39: Total Expenditure | D39: =SUM(D8:D38) -> 0 | E39: =SUM(E8:E38) -> 0

Sheet PETR INST
B1: PROCUREMENT PLAN 2021 FOR BUDGET UTILIZING
B2: DEPARTMENT NAME | D2: APPROVED BUDGET | H2: UTILISED BUDGET | J2: AVAILABLE BUDGET
B3: ='Budget Summary'!B6 -> Petroleum Institute | D3: CAPITAL | F3: OPERATING | H3: CAPITAL | I3: OPERATING | J3: CAPITAL | K3: OPERATING
B4: PETR | D4: ='Budget Summary'!F5 -> 0 | F4: ='Budget Summary'!G5 -> 0 | H4: =D39 -> 0 | I4: =E39 -> 0 | J4: =D4-H4 -> 0 | K4: =F4-I4 -> 0
G5: Requirement Date/Need Date
A6: Sl No | B6: Plan Ref. Number | C6: Description of Goods/services/works (Specifications) | D6: Utilised CAPEX Budget | E6: Utilised OPEX Budget | F6: Procurement Method | G6: Quarters | H6: Month | I6: Day | J6: Delivery Location | K6: Purchase Requisition Number (if available) | L6: Expected Requisition Approved Date | M6: Comments
A8: 1 | B8: =CONCATENATE("PETR-",LEFT("0000",4-LEN(ROW(A2)-1)),ROW(A2)-1) -> PETR-0001
A9: 2 | B9: =CONCATENATE("PETR-",LEFT("0000",4-LEN(ROW(A3)-1)),ROW(A3)-1) -> PETR-0002
A10: 3 | B10: =CONCATENATE("PETR-",LEFT("0000",4-LEN(ROW(A4)-1)),ROW(A4)-1) -> PETR-0003
A11: 4 | B11: =CONCATENATE("PETR-",LEFT("0000",4-LEN(ROW(A5)-1)),ROW(A5)-1) -> PETR-0004
A12: 5 | B12: =CONCATENATE("PETR-",LEFT("0000",4-LEN(ROW(A6)-1)),ROW(A6)-1) -> PETR-0005
A13: 6 | B13: =CONCATENATE("PETR-",LEFT("0000",4-LEN(ROW(A7)-1)),ROW(A7)-1) -> PETR-0006
A14: 7 | B14: =CONCATENATE("PETR-",LEFT("0000",4-LEN(ROW(A8)-1)),ROW(A8)-1) -> PETR-0007
A15: 8 | B15: =CONCATENATE("PETR-",LEFT("0000",4-LEN(ROW(A9)-1)),ROW(A9)-1) -> PETR-0008
A16: 9 | B16: =CONCATENATE("PETR-",LEFT("0000",4-LEN(ROW(A10)-1)),ROW(A10)-1) -> PETR-0009
A17: 10 | B17: =CONCATENATE("PETR-",LEFT("0000",4-LEN(ROW(A11)-1)),ROW(A11)-1) -> PETR-0010
A18: 11 | B18: =CONCATENATE("PETR-",LEFT("0000",4-LEN(ROW(A12)-1)),ROW(A12)-1) -> PETR-0011
A19: 12 | B19: =CONCATENATE("PETR-",LEFT("0000",4-LEN(ROW(A13)-1)),ROW(A13)-1) -> PETR-0012
... A38: 31 | B38: =CONCATENATE("PETR-",LEFT("0000",4-LEN(ROW(A32)-1)),ROW(A32)-1) -> PETR-0031
C39: Total Expenditure | D39: =SUM(D8:D38) -> 0 | E39: =SUM(E8:E38) -> 0

Sheet MASD INST
B1: PROCUREMENT PLAN 2021 FOR BUDGET UTILIZING
B2: DEPARTMENT NAME | D2: APPROVED BUDGET | H2: UTILISED BUDGET | J2: AVAILABLE BUDGET
B3: ='Budget Summary'!B7 -> Masdar Institute | D3: CAPITAL | F3: OPERATING | H3: CAPITAL | I3: OPERATING | J3: CAPITAL | K3: OPERATING
B4: MASIN | D4: ='Budget Summary'!F5 -> 0 | F4: ='Budget Summary'!G5 -> 0 | H4: =D39 -> 0 | I4: =E39 -> 0 | J4: =D4-H4 -> 0 | K4: =F4-I4 -> 0
G5: Requirement Date/Need Date
A6: Sl No | B6: Plan Ref. Number | C6: Description of Goods/services/works (Specifications) | D6: Utilised CAPEX Budget | E6: Utilised OPEX Budget | F6: Procurement Method | G6: Quarters | H6: Month | I6: Day | J6: Delivery Location | K6: Purchase Requisition Number (if available) | L6: Expected Requisition Approved Date | M6: Comments
A8: 1 | B8: =CONCATENATE("MASIN-",LEFT("0000",4-LEN(ROW(A2)-1)),ROW(A2)-1) -> MASIN-0001
A9: 2 | B9: =CONCATENATE("MASIN-",LEFT("0000",4-LEN(ROW(A3)-1)),ROW(A3)-1) -> MASIN-0002
A10: 3 | B10: =CONCATENATE("MASIN-",LEFT("0000",4-LEN(ROW(A4)-1)),ROW(A4)-1) -> MASIN-0003
A11: 4 | B11: =CONCATENATE("MASIN-",LEFT("0000",4-LEN(ROW(A5)-1)),ROW(A5)-1) -> MASIN-0004
A12: 5 | B12: =CONCATENATE("MASIN-",LEFT("0000",4-LEN(ROW(A6)-1)),ROW(A6)-1) -> MASIN-0005
A13: 6 | B13: =CONCATENATE("MASIN-",LEFT("0000",4-LEN(ROW(A7)-1)),ROW(A7)-1) -> MASIN-0006
A14: 7 | B14: =CONCATENATE("MASIN-",LEFT("0000",4-LEN(ROW(A8)-1)),ROW(A8)-1) -> MASIN-0007
A15: 8 | B15: =CONCATENATE("MASIN-",LEFT("0000",4-LEN(ROW(A9)-1)),ROW(A9)-1) -> MASIN-0008
A16: 9 | B16: =CONCATENATE("MASIN-",LEFT("0000",4-LEN(ROW(A10)-1)),ROW(A10)-1) -> MASIN-0009
A17: 10 | B17: =CONCATENATE("MASIN-",LEFT("0000",4-LEN(ROW(A11)-1)),ROW(A11)-1) -> MASIN-0010
A18: 11 | B18: =CONCATENATE("MASIN-",LEFT("0000",4-LEN(ROW(A12)-1)),ROW(A12)-1) -> MASIN-0011
A19: 12 | B19: =CONCATENATE("MASIN-",LEFT("0000",4-LEN(ROW(A13)-1)),ROW(A13)-1) -> MASIN-0012
... A38: 31 | B38: =CONCATENATE("MASIN-",LEFT("0000",4-LEN(ROW(A32)-1)),ROW(A32)-1) -> MASIN-0031
C39: Total Expenditure | D39: =SUM(D8:D38) -> 0 | E39: =SUM(E8:E38) -> 0

Sheet RES SERV
B1: PROCUREMENT PLAN 2021 FOR BUDGET UTILIZING
B2: DEPARTMENT NAME | D2: APPROVED BUDGET | H2: UTILISED BUDGET | J2: AVAILABLE BUDGET
B3: ='Budget Summary'!B8 -> Office of Research Service | D3: CAPITAL | F3: OPERATING | H3: CAPITAL | I3: OPERATING | J3: CAPITAL | K3: OPERATING
B4: RES SERV | D4: ='Budget Summary'!F5 -> 0 | F4: ='Budget Summary'!G5 -> 0 | H4: =D39 -> 0 | I4: =E39 -> 0 | J4: =D4-H4 -> 0 | K4: =F4-I4 -> 0
G5: Requirement Date/Need Date
A6: Sl No | B6: Plan Ref. Number | C6: Description of Goods/services/works (Specifications) | D6: Utilised CAPEX Budget | E6: Utilised OPEX Budget | F6: Procurement Method | G6: Quarters | H6: Month | I6: Day | J6: Delivery Location | K6: Purchase Requisition Number (if available) | L6: Expected Requisition Approved Date | M6: Comments
A8: 1 | B8: =CONCATENATE("RESE-",LEFT("0000",4-LEN(ROW(A2)-1)),ROW(A2)-1) -> RESE-0001
A9: 2 | B9: =CONCATENATE("RESE-",LEFT("0000",4-LEN(ROW(A3)-1)),ROW(A3)-1) -> RESE-0002
A10: 3 | B10: =CONCATENATE("RESE-",LEFT("0000",4-LEN(ROW(A4)-1)),ROW(A4)-1) -> RESE-0003
A11: 4 | B11: =CONCATENATE("RESE-",LEFT("0000",4-LEN(ROW(A5)-1)),ROW(A5)-1) -> RESE-0004
A12: 5 | B12: =CONCATENATE("RESE-",LEFT("0000",4-LEN(ROW(A6)-1)),ROW(A6)-1) -> RESE-0005
A13: 6 | B13: =CONCATENATE("RESE-",LEFT("0000",4-LEN(ROW(A7)-1)),ROW(A7)-1) -> RESE-0006
A14: 7 | B14: =CONCATENATE("RESE-",LEFT("0000",4-LEN(ROW(A8)-1)),ROW(A8)-1) -> RESE-0007
A15: 8 | B15: =CONCATENATE("RESE-",LEFT("0000",4-LEN(ROW(A9)-1)),ROW(A9)-1) -> RESE-0008
A16: 9 | B16: =CONCATENATE("RESE-",LEFT("0000",4-LEN(ROW(A10)-1)),ROW(A10)-1) -> RESE-0009
A17: 10 | B17: =CONCATENATE("RESE-",LEFT("0000",4-LEN(ROW(A11)-1)),ROW(A11)-1) -> RESE-0010
A18: 11 | B18: =CONCATENATE("RESE-",LEFT("0000",4-LEN(ROW(A12)-1)),ROW(A12)-1) -> RESE-0011
A19: 12 | B19: =CONCATENATE("RESE-",LEFT("0000",4-LEN(ROW(A13)-1)),ROW(A13)-1) -> RESE-0012
... A38: 31 | B38: =CONCATENATE("RESE-",LEFT("0000",4-LEN(ROW(A32)-1)),ROW(A32)-1) -> RESE-0031
C39: Total Expenditure | D39: =SUM(D8:D38) -> 0 | E39: =SUM(E8:E38) -> 0

Sheet SPONS RES
B1: PROCUREMENT PLAN 2021 FOR BUDGET UTILIZING
B2: DEPARTMENT NAME | D2: APPROVED BUDGET | H2: UTILISED BUDGET | J2: AVAILABLE BUDGET
B3: ='Budget Summary'!B9 -> KUST - University Sponsored Research | D3: CAPITAL | F3: OPERATING | H3: CAPITAL | I3: OPERATING | J3: CAPITAL | K3: OPERATING
B4: SPON RES | D4: ='Budget Summary'!F5 -> 0 | F4: ='Budget Summary'!G5 -> 0 | H4: =D39 -> 0 | I4: =E39 -> 0 | J4: =D4-H4 -> 0 | K4: =F4-I4 -> 0
G5: Requirement Date/Need Date
A6: Sl No | B6: Plan Ref. Number | C6: Description of Goods/services/works (Specifications) | D6: Utilised CAPEX Budget | E6: Utilised OPEX Budget | F6: Procurement Method | G6: Quarters | H6: Month | I6: Day | J6: Delivery Location | K6: Purchase Requisition Number (if available) | L6: Expected Requisition Approved Date | M6: Comments
A8: 1 | B8: =CONCATENATE("SPRE-",LEFT("0000",4-LEN(ROW(A2)-1)),ROW(A2)-1) -> SPRE-0001
A9: 2 | B9: =CONCATENATE("SPRE-",LEFT("0000",4-LEN(ROW(A3)-1)),ROW(A3)-1) -> SPRE-0002
A10: 3 | B10: =CONCATENATE("SPRE-",LEFT("0000",4-LEN(ROW(A4)-1)),ROW(A4)-1) -> SPRE-0003
A11: 4 | B11: =CONCATENATE("SPRE-",LEFT("0000",4-LEN(ROW(A5)-1)),ROW(A5)-1) -> SPRE-0004
A12: 5 | B12: =CONCATENATE("SPRE-",LEFT("0000",4-LEN(ROW(A6)-1)),ROW(A6)-1) -> SPRE-0005
A13: 6 | B13: =CONCATENATE("SPRE-",LEFT("0000",4-LEN(ROW(A7)-1)),ROW(A7)-1) -> SPRE-0006
A14: 7 | B14: =CONCATENATE("SPRE-",LEFT("0000",4-LEN(ROW(A8)-1)),ROW(A8)-1) -> SPRE-0007
A15: 8 | B15: =CONCATENATE("SPRE-",LEFT("0000",4-LEN(ROW(A9)-1)),ROW(A9)-1) -> SPRE-0008
A16: 9 | B16: =CONCATENATE("SPRE-",LEFT("0000",4-LEN(ROW(A10)-1)),ROW(A10)-1) -> SPRE-0009
A17: 10 | B17: =CONCATENATE("SPRE-",LEFT("0000",4-LEN(ROW(A11)-1)),ROW(A11)-1) -> SPRE-0010
A18: 11 | B18: =CONCATENATE("SPRE-",LEFT("0000",4-LEN(ROW(A12)-1)),ROW(A12)-1) -> SPRE-0011
A19: 12 | B19: =CONCATENATE("SPRE-",LEFT("0000",4-LEN(ROW(A13)-1)),ROW(A13)-1) -> SPRE-0012
... A38: 31 | B38: =CONCATENATE("SPRE-",LEFT("0000",4-LEN(ROW(A32)-1)),ROW(A32)-1) -> SPRE-0031
C39: Total Expenditure | D39: =SUM(D8:D38) -> 0 | E39: =SUM(E8:E38) -> 0

Sheet TMI
B1: PROCUREMENT PLAN 2021 FOR BUDGET UTILIZING
B2: DEPARTMENT NAME | D2: APPROVED BUDGET | H2: UTILISED BUDGET | J2: AVAILABLE BUDGET
B3: ='Budget Summary'!B10 -> TMI | D3: CAPITAL | F3: OPERATING | H3: CAPITAL | I3: OPERATING | J3: CAPITAL | K3: OPERATING
B4: TMI | D4: ='Budget Summary'!F5 -> 0 | F4: ='Budget Summary'!G5 -> 0 | H4: =D39 -> 0 | I4: =E39 -> 0 | J4: =D4-H4 -> 0 | K4: =F4-I4 -> 0
G5: Requirement Date/Need Date
A6: Sl No | B6: Plan Ref. Number | C6: Description of Goods/services/works (Specifications) | D6: Utilised CAPEX Budget | E6: Utilised OPEX Budget | F6: Procurement Method | G6: Quarters | H6: Month | I6: Day | J6: Delivery Location | K6: Purchase Requisition Number (if available) | L6: Expected Requisition Approved Date | M6: Comments
A8: 1 | B8: =CONCATENATE("TMI-",LEFT("0000",4-LEN(ROW(A2)-1)),ROW(A2)-1) -> TMI-0001
A9: 2 | B9: =CONCATENATE("TMI-",LEFT("0000",4-LEN(ROW(A3)-1)),ROW(A3)-1) -> TMI-0002
A10: 3 | B10: =CONCATENATE("TMI-",LEFT("0000",4-LEN(ROW(A4)-1)),ROW(A4)-1) -> TMI-0003
A11: 4 | B11: =CONCATENATE("TMI-",LEFT("0000",4-LEN(ROW(A5)-1)),ROW(A5)-1) -> TMI-0004
A12: 5 | B12: =CONCATENATE("TMI-",LEFT("0000",4-LEN(ROW(A6)-1)),ROW(A6)-1) -> TMI-0005
A13: 6 | B13: =CONCATENATE("TMI-",LEFT("0000",4-LEN(ROW(A7)-1)),ROW(A7)-1) -> TMI-0006
A14: 7 | B14: =CONCATENATE("TMI-",LEFT("0000",4-LEN(ROW(A8)-1)),ROW(A8)-1) -> TMI-0007
A15: 8 | B15: =CONCATENATE("TMI-",LEFT("0000",4-LEN(ROW(A9)-1)),ROW(A9)-1) -> TMI-0008
A16: 9 | B16: =CONCATENATE("TMI-",LEFT("0000",4-LEN(ROW(A10)-1)),ROW(A10)-1) -> TMI-0009
A17: 10 | B17: =CONCATENATE("TMI-",LEFT("0000",4-LEN(ROW(A11)-1)),ROW(A11)-1) -> TMI-0010
A18: 11 | B18: =CONCATENATE("TMI-",LEFT("0000",4-LEN(ROW(A12)-1)),ROW(A12)-1) -> TMI-0011
A19: 12 | B19: =CONCATENATE("TMI-",LEFT("0000",4-LEN(ROW(A13)-1)),ROW(A13)-1) -> TMI-0012
... A38: 31 | B38: =CONCATENATE("TMI-",LEFT("0000",4-LEN(ROW(A32)-1)),ROW(A32)-1) -> TMI-0031
C39: Total Expenditure | D39: =SUM(D8:D38) -> 0 | E39: =SUM(E8:E38) -> 0

Sheet RES LAB
B1: PROCUREMENT PLAN 2021 FOR BUDGET UTILIZING
B2: DEPARTMENT NAME | D2: APPROVED BUDGET | H2: UTILISED BUDGET | J2: AVAILABLE BUDGET
B3: ='Budget Summary'!B11 -> Research Labs | D3: CAPITAL | F3: OPERATING | H3: CAPITAL | I3: OPERATING | J3: CAPITAL | K3: OPERATING
B4: RES LAB | D4: ='Budget Summary'!F5 -> 0 | F4: ='Budget Summary'!G5 -> 0 | H4: =D39 -> 0 | I4: =E39 -> 0 | J4: =D4-H4 -> 0 | K4: =F4-I4 -> 0
G5: Requirement Date/Need Date
A6: Sl No | B6: Plan Ref. Number | C6: Description of Goods/services/works (Specifications) | D6: Utilised CAPEX Budget | E6: Utilised OPEX Budget | F6: Procurement Method | G6: Quarters | H6: Month | I6: Day | J6: Delivery Location | K6: Purchase Requisition Number (if available) | L6: Expected Requisition Approved Date | M6: Comments
A8: 1 | B8: =CONCATENATE("RLAB-",LEFT("0000",4-LEN(ROW(A2)-1)),ROW(A2)-1) -> RLAB-0001
A9: 2 | B9: =CONCATENATE("RLAB-",LEFT("0000",4-LEN(ROW(A3)-1)),ROW(A3)-1) -> RLAB-0002
A10: 3 | B10: =CONCATENATE("RLAB-",LEFT("0000",4-LEN(ROW(A4)-1)),ROW(A4)-1) -> RLAB-0003
A11: 4 | B11: =CONCATENATE("RLAB-",LEFT("0000",4-LEN(ROW(A5)-1)),ROW(A5)-1) -> RLAB-0004
A12: 5 | B12: =CONCATENATE("RLAB-",LEFT("0000",4-LEN(ROW(A6)-1)),ROW(A6)-1) -> RLAB-0005
A13: 6 | B13: =CONCATENATE("RLAB-",LEFT("0000",4-LEN(ROW(A7)-1)),ROW(A7)-1) -> RLAB-0006
A14: 7 | B14: =CONCATENATE("RLAB-",LEFT("0000",4-LEN(ROW(A8)-1)),ROW(A8)-1) -> RLAB-0007
A15: 8 | B15: =CONCATENATE("RLAB-",LEFT("0000",4-LEN(ROW(A9)-1)),ROW(A9)-1) -> RLAB-0008
A16: 9 | B16: =CONCATENATE("RLAB-",LEFT("0000",4-LEN(ROW(A10)-1)),ROW(A10)-1) -> RLAB-0009
A17: 10 | B17: =CONCATENATE("RLAB-",LEFT("0000",4-LEN(ROW(A11)-1)),ROW(A11)-1) -> RLAB-0010
A18: 11 | B18: =CONCATENATE("RLAB-",LEFT("0000",4-LEN(ROW(A12)-1)),ROW(A12)-1) -> RLAB-0011
A19: 12 | B19: =CONCATENATE("RLAB-",LEFT("0000",4-LEN(ROW(A13)-1)),ROW(A13)-1) -> RLAB-0012
... A38: 31 | B38: =CONCATENATE("RLAB-",LEFT("0000",4-LEN(ROW(A32)-1)),ROW(A32)-1) -> RLAB-0031
C39: Total Expenditure | D39: =SUM(D8:D38) -> 0 | E39: =SUM(E8:E38) -> 0

Sheet RES COMP
B1: PROCUREMENT PLAN 2021 FOR BUDGET UTILIZING
B2: DEPARTMENT NAME | D2: APPROVED BUDGET | H2: UTILISED BUDGET | J2: AVAILABLE BUDGET
B3: ='Budget Summary'!B12 -> Research Computing | D3: CAPITAL | F3: OPERATING | H3: CAPITAL | I3: OPERATING | J3: CAPITAL | K3: OPERATING
B4: RES COMP | D4: ='Budget Summary'!F5 -> 0 | F4: ='Budget Summary'!G5 -> 0 | H4: =D39 -> 12124043 | I4: =E39 -> 1156209.8 | J4: =D4-H4 -> -12124043 | K4: =F4-I4 -> -1156209.8
G5: Requirement Date/Need Date
A6: Sl No | B6: Plan Ref. Number | C6: Description of Goods/services/works (Specifications) | D6: Utilised CAPEX Budget | E6: Utilised OPEX Budget | F6: Procurement Method | G6: Quarters | H6: Month | I6: Day | J6: Delivery Location | K6: Purchase Requisition Number (if available) | L6: Expected Requisition Approved Date | M6: Comments
A8: 1 | B8: =CONCATENATE("RCOM-",LEFT("0000",4-LEN(ROW(A2)-1)),ROW(A2)-1) -> RCOM-0001 | C8: HPC Cluster replacment. This is replace the existing HPC cluster at MI data center. It is end of life, and we are losing the data centre. Cost is estimated from past disucssions. System is critical to computational research at KU. | D8: 9000000 | F8: Pricing Agreement | G8: Q2 | H8: May | J8: Main Campus
A9: 2 | B9: =CONCATENATE("RCOM-",LEFT("0000",4-LEN(ROW(A3)-1)),ROW(A3)-1) -> RCOM-0002 | C9: Servers and storage for Virtual Machines (VM's). This will be to enable the migration of exsiting VM load at MI DataCenter and alllowing for future reseacher requirements. This will form the basis of a "private cloud" for reserachers at KU | D9: 1925000 | F9: Pricing Agreement | G9: Q2 | H9: Jun | J9: Main Campus
A10: 3 | B10: =CONCATENATE("RCOM-",LEFT("0000",4-LEN(ROW(A4)-1)),ROW(A4)-1) -> RCOM-0003 | C10: Data storage backup. This will be used as backup for critical reseach data and VM's. | D10: 1012164.5 | F10: Tendering/Competitive Bidding | G10: Q2 | H10: Jun | J10: Main Campus
A11: 4 | B11: =CONCATENATE("RCOM-",LEFT("0000",4-LEN(ROW(A5)-1)),ROW(A5)-1) -> RCOM-0004 | C11: Intel OneAPI Base & HPC toolkit. New software licenses, and compiler, to be used on the HPC system | D11: 44716 | F11: Tendering/Competitive Bidding | G11: Q2 | H11: Apr
A12: 5 | B12: =CONCATENATE("RCOM-",LEFT("0000",4-LEN(ROW(A6)-1)),ROW(A6)-1) -> RCOM-0005 | C12: Guassian. New software site license for Molecular Dynamics software application, was to be purchased in 2020, but did not get completed in time | D12: 142162.69 | F12: Direct Purchase (Single Source) | G12: Q2 | H12: Apr
A13: 6 | B13: =CONCATENATE("RCOM-",LEFT("0000",4-LEN(ROW(A7)-1)),ROW(A7)-1) -> RCOM-0006 | C13: OpenLM License Management Software. Software renewal. Used for manageing software licneses | E13: 3673.02 | F13: Direct Purchase (Single Source) | G13: Q1 | H13: Feb | I13: 18 | J13: All Campuses | M13: License expires on 18th February
A14: 7 | B14: =CONCATENATE("RCOM-",LEFT("0000",4-LEN(ROW(A8)-1)),ROW(A8)-1) -> RCOM-0007 | C14: Lumerical academic site license. Software renewal. Site licnese for microelectronics software | E14: 95204.68 | F14: Direct Purchase (Single Source) | G14: Q2 | H14: Mar | I14: 22 | J14: All Campuses | M14: License expires on 22nd March
A15: 8 | B15: =CONCATENATE("RCOM-",LEFT("0000",4-LEN(ROW(A9)-1)),ROW(A9)-1) -> RCOM-0008 | C15: Matlab. Software renewal. Engineering and Maths programming environment | E15: 420377.14 | F15: Direct Purchase (Single Source) | G15: Q2 | H15: Jun | I15: 30 | J15: All Campuses | M15: License expires on 30th June
A16: 9 | B16: =CONCATENATE("RCOM-",LEFT("0000",4-LEN(ROW(A10)-1)),ROW(A10)-1) -> RCOM-0009 | C16: Atlassian Confluence. Software renewal. Used to build user facing documentation wiki for Research Computing | E16: 3213.89 | F16: Direct Purchase (Single Source) | G16: Q3 | H16: Aug | I16: 10 | J16: All Campuses | M16: License expires on 10th August
A17: 10 | B17: =CONCATENATE("RCOM-",LEFT("0000",4-LEN(ROW(A11)-1)),ROW(A11)-1) -> RCOM-0010 | C17: ANSYS Academic Multiphysics Campus Solution. Software renewal. Used for varitey of engineering applications, both for teaching and reseach | E17: 328886.25 | F17: Direct Purchase (Single Source) | G17: Q3 | H17: Aug | I17: 28 | J17: All Campuses | M17: License expires on 28th August
A18: 11 | B18: =CONCATENATE("RCOM-",LEFT("0000",4-LEN(ROW(A12)-1)),ROW(A12)-1) -> RCOM-0011 | C18: COMSOL. Software renewal. Multiphysics software application, used for both research and teaching. | E18: 270837.67 | F18: Direct Purchase (Single Source) | G18: Q3 | H18: Sep | I18: 1 | J18: All Campuses | M18: License expires on 1st September
A19: 12 | B19: =CONCATENATE("RCOM-",LEFT("0000",4-LEN(ROW(A13)-1)),ROW(A13)-1) -> RCOM-0012 | C19: Mathematica. Software renewal. Computational software used across multiple research areas. | E19: 31146.14 | F19: Direct Purchase (Single Source) | G19: Q3 | H19: Jul | I19: 30 | J19: All Campuses | M19: License expires on 30th July
A20: 13 | B20: =CONCATENATE("RCOM-",LEFT("0000",4-LEN(ROW(A14)-1)),ROW(A14)-1) -> RCOM-0013 | C20: Mobaxterm. Software renewal. Tool used by Research computing and IT to connect to and maintain remote servers. | E20: 2871 | F20: Direct Purchase (Single Source) | G20: Q4 | H20: Dec | I20: 26 | J20: All Campuses | M20: License expires on 26th December
A21: 14 | B21: =CONCATENATE("RCOM-",LEFT("0000",4-LEN(ROW(A15)-1)),ROW(A15)-1) -> RCOM-0014
A22: 15 | B22: =CONCATENATE("RCOM-",LEFT("0000",4-LEN(ROW(A16)-1)),ROW(A16)-1) -> RCOM-0015
A23: 16 | B23: =CONCATENATE("RCOM-",LEFT("0000",4-LEN(ROW(A17)-1)),ROW(A17)-1) -> RCOM-0016
A24: 17 | B24: =CONCATENATE("RCOM-",LEFT("0000",4-LEN(ROW(A18)-1)),ROW(A18)-1) -> RCOM-0017
A25: 18 | B25: =CONCATENATE("RCOM-",LEFT("0000",4-LEN(ROW(A19)-1)),ROW(A19)-1) -> RCOM-0018
A26: 19 | B26: =CONCATENATE("RCOM-",LEFT("0000",4-LEN(ROW(A20)-1)),ROW(A20)-1) -> RCOM-0019
A27: 20 | B27: =CONCATENATE("RCOM-",LEFT("0000",4-LEN(ROW(A21)-1)),ROW(A21)-1) -> RCOM-0020
A28: 21 | B28: =CONCATENATE("RCOM-",LEFT("0000",4-LEN(ROW(A22)-1)),ROW(A22)-1) -> RCOM-0021
A29: 22 | B29: =CONCATENATE("RCOM-",LEFT("0000",4-LEN(ROW(A23)-1)),ROW(A23)-1) -> RCOM-0022
A30: 23 | B30: =CONCATENATE("RCOM-",LEFT("0000",4-LEN(ROW(A24)-1)),ROW(A24)-1) -> RCOM-0023
A31: 24 | B31: =CONCATENATE("RCOM-",LEFT("0000",4-LEN(ROW(A25)-1)),ROW(A25)-1) -> RCOM-0024
A32: 25 | B32: =CONCATENATE("RCOM-",LEFT("0000",4-LEN(ROW(A26)-1)),ROW(A26)-1) -> RCOM-0025
... A38: 31 | B38: =CONCATENATE("RCOM-",LEFT("0000",4-LEN(ROW(A32)-1)),ROW(A32)-1) -> RCOM-0031
C39: Total Expenditure | D39: =SUM(D8:D38) -> 12124043 | E39: =SUM(E8:E38) -> 1156209.8

Sheet Macro-Sheet
A1: Status | C1: Procurement Method | D1: Budget Category | E1: Deliver Location | F1: Section | G1: Type of Supply | I1: Requirement Date/Need Date | J1: Months | K1: Days
A3: On time | C3: Direct Purchase (Single Source) | D3: CAPEX | E3: Main Campus | F3: Procurement | G3: Goods | I3: Q1 | J3: Jan | K3: 1
A4: Slightly Late | C4: Tendering/Competitive Bidding | D4: OPEX | E4: Sas Al Nkhal Campus | F4: Contracts | G4: Services | I4: Q2 | J4: Feb | K4: 2
A5: Late | C5: Pricing Agreement | E5: MI Campus | F5: Material Management | G5: Materials | I5: Q3 | J5: Mar | K5: 3
C6: Variation Order | E6: All Campuses | I6: Q4 | J6: Apr | K6: 4
C7: Repeat Order | I7: Q1 - Q4 | J7: May | K7: 5
J8: Jun | K8: 6
J9: Jul | K9: 7
J10: Aug | K10: 8
J11: Sep | K11: 9
J12: Oct | K12: 10
J13: Nov | K13: 11
J14: Dec | K14: 12
K15: 13
K16: 14
K17: 15
K18: 16
K19: 17
K20: 18
K21: 19
K22: 20
K23: 21
K24: 22
K25: 23
K26: 24
... K33: 31

Sheet Procurement Follow-up Sheet
A1: Procurement & Contracts Department
A4: Sl No | B4: Plan Ref. Number | C4: Approved Purchase Requisition Number | D4: Requisition Date | E4: Purchase Requisition Value | F4: Requisition Receipt Date | G4: Purchase Requisition Assign Date | H4: Section | I4: Bidders List Date Approved | J4: Requirements Complete (Yes/No) | K4: SOW/SOS Completion Date | L4: Requirement Status | M4: Buyer Name | N4: PO/SO Number | O4: PO/SO Date | P4: Award Value | Q4: Delivery Date | R4: Comments
A5: 1 | B5: =[3]Bohooth!B8 -> BOH-0001 | C5: ='[4]Center for Teaching & Learning'!K8 -> 0
A6: 2 | B6: =[3]Bohooth!B9 -> BOH-0002 | C6: ='[4]Center for Teaching & Learning'!K9 -> 0
A7: 3 | B7: =[3]Bohooth!B10 -> BOH-0003 | C7: ='[4]Center for Teaching & Learning'!K10 -> 0
A8: 4 | B8: =[3]Bohooth!B11 -> BOH-0004 | C8: ='[4]Center for Teaching & Learning'!K11 -> 0
A9: 5 | B9: =[3]Bohooth!B12 -> BOH-0005 | C9: ='[4]Center for Teaching & Learning'!K12 -> 0
A10: 6 | B10: =[3]Bohooth!B13 -> BOH-0006 | C10: ='[4]Center for Teaching & Learning'!K13 -> 0
A11: 7 | B11: =[3]Bohooth!B14 -> BOH-0007 | C11: ='[4]Center for Teaching & Learning'!K14 -> 0
A12: 8 | B12: =[3]Bohooth!B15 -> BOH-0008 | C12: ='[4]Center for Teaching & Learning'!K15 -> 0
A13: 9 | B13: =[3]Bohooth!B16 -> BOH-0009 | C13: ='[4]Center for Teaching & Learning'!K16 -> 0
A14: 10 | B14: =[3]Bohooth!B17 -> BOH-0010 | C14: ='[4]Center for Teaching & Learning'!K17 -> 0
A15: 11 | B15: =[3]Bohooth!B18 -> BOH-0011 | C15: ='[4]Center for Teaching & Learning'!K18 -> 0
A16: 12 | B16: =[3]Bohooth!B19 -> BOH-0012 | C16: ='[4]Center for Teaching & Learning'!K19 -> 0
... A34: 30 | B34: =[3]Bohooth!B37 -> BOH-0030 | C34: ='[4]Center for Teaching & Learning'!K37 -> 0
E35: =SUM(E5:E34) -> 0
