Workbook

Sheet Summary
B2: Chapter | C2: FINAL 2018 BUDGET | D2: 2018 STRATEGIC INITIATIVE/NEW PROJECT BUDGET | E2: 2017 KUSTAR Approved budget | F2: 2016 KUSTAR Actuals | G2: 2015 KUSTAR Actuals | H2: 2017 MASDAR Approved budget | I2: 2016 MASDAR Actuals | J2: 2015 MASDAR Actuals | K2: 2017 PI Approved budget | L2: 2016 PI Actuals | M2: 2015 PI Actuals
B6: Operating | C6: ='Operating consolidated'!F95 -> 14101933 | D6: ='Operating consolidated'!G95 -> 0 | E6: ='Operating consolidated'!I95 -> 3445000 | F6: ='Operating consolidated'!J95 -> 3193129.2 | G6: ='Operating consolidated'!K95 -> 3444048.9 | H6: ='Operating consolidated'!M95 -> 5204000 | I6: ='Operating consolidated'!N95 -> 4048133.4 | J6: ='Operating consolidated'!O95 -> 3844497.2 | K6: ='Operating consolidated'!Q95 -> 7700781 | L6: ='Operating consolidated'!R95 -> 3723110.4 | M6: ='Operating consolidated'!S95 -> 10929388
B8: Capital | C8: ='Capital consolidated'!G54 -> 0 | D8: ='Capital consolidated'!H54 -> 0 | E8: ='Capital consolidated'!J54 -> 0 | F8: ='Capital consolidated'!K54 -> 6638 | G8: ='Capital consolidated'!L54 -> 2500 | H8: ='Capital consolidated'!N54 -> 0 | I8: ='Capital consolidated'!O54 -> 0 | J8: ='Capital consolidated'!P54 -> 0 | K8: ='Capital consolidated'!R54 -> 0 | L8: ='Capital consolidated'!S54 -> 0 | M8: ='Capital consolidated'!T54 -> 0
B10: Total | C10: =SUM(C6:C9) -> 14101933 | D10: =SUM(D6:D9) -> 0 | E10: =SUM(E6:E9) -> 3445000 | F10: =SUM(F6:F9) -> 3199767.2 | G10: =SUM(G6:G9) -> 3446548.9 | H10: =SUM(H6:H9) -> 5204000 | I10: =SUM(I6:I9) -> 4048133.4 | J10: =SUM(J6:J9) -> 3844497.2 | ... M10: =SUM(M6:M9) -> 10929388

Sheet Operating consolidated
B1: DOF system | D1: Remark | E1: Content expert | F1: FINAL 2018 BUDGET | G1: 2018 STRATEGIC INITIATIVE/NEW PROJECT BUDGET | I1: 2017 KUSTAR Approved budget | J1: 2016 KUSTAR Actuals | K1: 2015 KUSTAR Actuals | M1: 2017 MASDAR Approved budget | N1: 2016 MASDAR Actuals | O1: 2015 MASDAR Actuals | Q1: 2017 PI Approved budget | R1: 2016 PI Actuals | S1: 2015 PI Actuals
B2: Account code | C2: Description
A4: Academic | B4: 420550 | C4: Academic Advisory Service | D4: For expenses related to Academic boards, including Presidents Academic Advisory Council. This includes travel cost, accommodation and honorarium. | I4: 0 | J4: 0 | K4: 0 | Q4: 0 | R4: 0 | S4: 0
B5: 420570 | C5: Academic Collaborative Partnership Services | D5: For payments made to collaborating institutions, as part of partnership agreements. Does not include fund contributions (ARIC, EBTIC etc.) | I5: 0 | J5: 0 | K5: 0 | Q5: 0 | R5: 0 | S5: 0
B6: 421700 | C6: Standards certification (e.g. ISO) | D6: For all expenses connected to accreditations ( academic and otherwise) | I6: 0 | J6: 0 | K6: 0 | Q6: 0 | R6: 0 | S6: 0
B7: 425770 | C7: Academic Missions - Combined expenses | D7: For faculty conferences (local and international). This includes travel costs, per diem & registration fees) | I7: 11000 | J7: 0 | K7: 0 | Q7: -111696.28 | R7: -54002 | S7: 183941
B8: 432209 | C8: Lab Equipment | D8: Costs for maintaining lab equipment (academic labs & research labs). This does not include maintenance of IT hardware and peripherals. | I8: 0 | J8: 0 | K8: 0 | Q8: 66187.935 | R8: 32000 | S8: 1840
B9: 435310 | C9: Newspapers, magazines, journals, etc | D9: This includes library subscriptions of journals & magazines. This also includes newspaper subscriptions. This account does not include cost of hard copies of library books. | F9: =(I9+M9+Q9+M53)*0.95 -> 10401624 | I9: 3334000 | J9: 3051332.3 | K9: 3354945 | M9: 11000 | O9: 11571.14 | Q9: 3743077.7 | R9: 1809672.5 | S9: 7558547.8
B10: 435330 | C10: Library books | D10: Only for costs of library books ( hard bound copies) | F10: =(I10+M10+Q10)*0.95 -> 3455308.8 | I10: 0 | J10: 0 | K10: 0 | M10: 44000 | N10: 14998.89 | O10: 35891.3 | Q10: 3593167.2 | R10: 1737195 | S10: 3055123.9
B11: 435350 | C11: Academic Publications | D11: For publication costs of faculty journals only | I11: 0 | J11: 0 | K11: 0 | Q11: 0 | R11: 0 | S11: 0
B12: 435508 | C12: Laboratory - Scientific | D12: Lab supplies/ consumables for academic and research labs | I12: 0 | J12: 0 | K12: 0 | Q12: 75648.777 | R12: 36574.05 | S12: 35038
B13: 436600 | C13: Training/Teaching equipment and other educational aid | D13: This account is for teaching supplies/ consumables to be used specifically in classrooms. This does not include the cost of regular stationery, provided by the University. | I13: 0 | J13: 0 | K13: 0 | Q13: 0 | R13: 0 | S13: 0
B14: 435530 | C14: School consumables, not specifically mentioned elsewhere | D14: This is for costs connected with developing curriculum. This would include payments made to those who develop the curriculum. | I14: 0 | J14: 0 | K14: 0 | Q14: 0 | R14: 0 | S14: 0
A15: External Relations | B15: 425100 | C15: Advertising | D15: This includes all costs connected with advertisement of the University . This excludes media & communication expenses like press meets. | E15: Communication | I15: 0 | J15: 0 | K15: 0 | Q15: 0 | R15: 0 | S15: 0
B16: 425510 | C16: Conferences, seminars and exhibitions and other events: - Local Events | D16: Includes all expenses connected with event expenses hosted/participated in UAE. Does not include faculty conferences. | E16: Communication | F16: 50000 | I16: 4000 | J16: 1100 | K16: 0 | Q16: 0 | R16: 0 | S16: 0
B17: 425550 | C17: Conferences, seminars and exhibitions and other events: - Overseas event | D17: Includes all expenses connected with event expenses hosted/participated outside UAE. Does not include faculty conferences. | E17: Communication | I17: 0 | J17: 0 | K17: 0 | Q17: 0 | R17: 0 | S17: 0
B18: 427100 | C18: Public relations | D18: For media & communication expenses ( example press meets) | E18: Communication | I18: 0 | J18: 0 | K18: 0 | Q18: 0 | R18: 0 | S18: 0
B19: 428640 | C19: Events - Awards, prizes & gifts | D19: For costs of gifts including those for VIP guests (excluding those given as part of an event expense) | E19: Communication | I19: 0 | J19: 0 | K19: 0 | Q19: 0 | R19: 0 | S19: 0
B20: 435519 | C20: Photography - Consumable materials /Tools | D20: Includes costs connected with photography (still and video) | E20: Communication | I20: 0 | J20: 0 | K20: 0 | Q20: 0 | R20: 0 | S20: 0
B21: 427200 | C21: Printing and publishing | D21: For costs connected with University wide publication expenses | E21: Communication | I21: 0 | J21: 0 | K21: 0 | Q21: 0 | R21: 0 | S21: 0
A22: Facilities | B22: 420310 | C22: Cleaning and Security Services :Business premises | D22: This is for cleaning costs of University buildings, premises and hostels. Does not include security services | E22: Facilities | I22: 0 | J22: 0 | K22: 0 | Q22: 0 | R22: 0 | S22: 0
B23: 421600 | C23: Security service | D23: This is for security costs of University buildings, premises and hostels. Does not include cleaning services | I23: 0 | J23: 0 | K23: 0 | Q23: 0 | R23: 0 | S23: 0
B24: 422100 | C24: Waste management service | D24: This is for costs incurred for managing the wastes of the University, including laboratory waste materials | I24: 0 | J24: 0 | K24: 0 | Q24: 0 | R24: 0 | S24: 0
B25: 426210 | C25: Insurance - Cash and fidelity | D25: Cost for providing cash and fidelity insurance | I25: 0 | J25: 0 | K25: 0 | Q25: 0 | R25: 0 | S25: 0
B26: 426220 | C26: Insurance - Fire and allied perils | D26: Cost for providing fire insurance | I26: 0 | J26: 0 | K26: 0 | Q26: 0 | R26: 0 | S26: 0
B27: 426250 | C27: Insurance - Motor vehicles | D27: Cost for providing vehicle insurance | I27: 0 | J27: 0 | K27: 0 | Q27: 0 | R27: 0 | S27: 0
B28: 426290 | C28: Insurance - Other | D28: Cost for providing insurance, not covered in other insurance account lines ( example all risk insurance) | I28: 0 | J28: 0 | K28: 0 | Q28: 0 | R28: 0 | S28: 0
B29: 426800 | C29: Motor vehicle registration and inspection charges | D29: For vehicle running expenses, including Salik charges/Mawaqif and excluding car maintenance & fuel | I29: 0 | J29: 0 | K29: 0 | Q29: 0 | R29: 0 | S29: 0
B30: 428111 | C30: Electricity consumption charges | D30: Electricity charges for University buildings, premises and hostels | I30: 0 | J30: 0 | K30: 0 | Q30: 0 | R30: 0 | S30: 0
B31: 428112 | C31: Water consumption charges | D31: Water charges for University buildings, premises and hostels | I31: 0 | J31: 0 | K31: 0 | Q31: 0 | R31: 0 | S31: 0
B32: 428200 | C32: Health,safety&environment awareness | D32: Costs connected to environment, health & safety | F32: 0 | I32: 0 | J32: 0 | K32: 0 | Q32: 38754.07 | R32: 18736.5 | S32: 59220
B33: 430120 | C33: Rental - Buildings, other than staff residences | D33: Charges to rent buildings or premises, for the University's purposes. This does not include booth space rentals at exhibitions or conferences | I33: 0 | J33: 0 | K33: 0 | Q33: 0 | R33: 0 | S33: 0
B34: 430330 | C34: Rental - Motor vehicles | D34: This includes vehicle hire expenses, taxi charges and other transportation expenses | E34: Facilities | I34: 0 | J34: 0 | K34: 0 | Q34: 0 | R34: 0 | S34: 0
B35: 430930 | C35: Rental - Training facilities (includes premises, equipment, catering, etc) | D35: For lab usage fees | E35: Facilities | I35: 0 | J35: 0 | K35: 0 | Q35: 0 | R35: 0 | S35: 0
B36: 432120 | C36: Bldg maintenance-Business premises | D36: For maintenance charges of University & hostel buildings/lifts/CCTV, including annual maintenance contracts. | E36: Facilities | I36: 0 | J36: 0 | K36: 0 | Q36: 0 | R36: 0 | S36: 0
B37: 432170 | C37: Bldg decoration & minor improvements | D37: For building décor expenses and minor improvements that are not capital in nature. | E37: Facilities | I37: 0 | J37: 0 | K37: 0 | Q37: 0 | R37: 0 | S37: 0
B38: 432310 | C38: Office Furniture and fixtures | D38: Maintaining and refurbishing costs of University furniture, excluding hostels | E38: Facilities | I38: 0 | J38: 0 | K38: 0 | Q38: 0 | R38: 0 | S38: 0
B39: 432320 | C39: Residential Furniture and fixtures | D39: Maintaining and refurbishing costs of hostel furniture. | I39: 0 | J39: 0 | K39: 0 | Q39: 0 | R39: 0 | S39: 0
B40: 432540 | C40: Motor vehicles (non-military) | D40: Car maintenance expenses | I40: 0 | J40: 0 | K40: 0 | Q40: 0 | R40: 0 | S40: 0
B41: 435510 | C41: Landscaping and other horticulture | D41: Landscaping charges for the University buildings and premises | I41: 0 | J41: 0 | K41: 0 | Q41: 0 | R41: 0 | S41: 0
B42: 435740 | C42: Fuel, oil and lubricants: Motor vehicles | D42: For fuel charges of university cars | I42: 0 | J42: 0 | K42: 0 | Q42: 0 | R42: 0 | S42: 0
B43: New code to be requested | C43: Insurance- Third Party Liability | D43: Cost for providing third party insurance cover (including public liability) | I43: 0 | J43: 0 | K43: 0 | Q43: 0 | R43: 0 | S43: 0
A44: Finance | B44: 425300 | C44: Banking service charges | D44: Bank charges | I44: 0 | J44: 0 | K44: 0 | Q44: 0 | R44: 0 | S44: 0
B45: 471210 | C45: Interest on bank overdraft and loans | D45: Interest costs incurred on loans/overdraft | I45: 0 | J45: 0 | K45: 0 | Q45: 0 | R45: 0 | S45: 0
B46: 473050 | C46: Bad Debts - Other | D46: To be used for bad debts expenses (actuals and provisions) | I46: 0 | J46: 0 | K46: 0 | Q46: 0 | R46: 0 | S46: 0
B47: 472900 | C47: Loss on disposal of physical asset | D47: To record the loss incurred on disposal of the Ubniversity's fixed assets | I47: 0 | J47: 0 | K47: 0 | Q47: 0 | R47: 0 | S47: 0
B48: 425350 | C48: Fees for processing e-payments | D48: Exchange rate loss charges | I48: 0 | J48: 0 | K48: 0 | Q48: 0 | R48: 0 | S48: 0
A49: HR | B49: 421000 | C49: Management consultancy | D49: Includes all types of consultancy, including academic and research consultancy. This does not include consultancy related directly to a capital asset or consultancy that are advisory in nature. | I49: 0 | J49: 0 | K49: 0 | Q49: 0 | R49: 0 | S49: 0
I50: 0 | J50: 0 | K50: 0 | Q50: 0 | R50: 0 | S50: 0
I51: 0 | J51: 0 | K51: 0 | Q51: 0 | R51: 0 | S51: 0
B52: 421100 | C52: Manpower supply | D52: For charges paid to manpower providing companies for their services. This does not include direct payments made to temporary employees directly. | I52: 0 | J52: 0 | K52: 0 | Q52: 247207.8 | R52: 119518 | S52: 0
B53: 427710 | C53: Subscriptions and membership fees: Trade organisations | D53: For the University to record expenses related to registering trade names | I53: 0 | J53: 0 | K53: 0 | M53: 3861000 | N53: 3482393.5 | O53: 3321126.7 | Q53: 1431.3141 | R53: 692 | S53: 0
B54: 428090 | C54: Business Travel - Combined expenses | D54: For costs connected to employee business trips/research trips, within and outside UAE, including travel costs, per diem and registrations. | F54: 150000 | I54: 0 | J54: 1104 | K54: 276 | M54: 88000 | N54: 21095 | O54: 95236.3 | Q54: 0 | R54: 0 | S54: 0
B55: New code to be requested | C55: Professional Membership charges | D55: For the University's professional membership charges. This could be used to record employees' professional membership charges, only if HR policy allows. | F55: 0 | I55: 0 | J55: 0 | K55: 0 | Q55: 1666.9431 | R55: 805.92 | S55: 147
B56: New code to be requested | C56: Visitor Travel | D56: For costs connected to visitor trips, within and outside UAE, including travel costs, per diem/hotels, catering and registrations. | I56: 0 | J56: 0 | K56: 0 | Q56: 0 | R56: 0 | S56: 0
A57: IT | B57: 426610 | C57: Computer software licenses | D57: For software charges covering for a year or less. This includes payments for cloud based services | E57: IT | I57: 96000 | J57: 138642.91 | K57: 88177.85 | Q57: 0 | R57: 0 | S57: 0
B58: 427810 | C58: Telephone and telefax charges | D58: For mobile phone, blackberry, landline and fax charges | E58: IT | I58: 0 | J58: 0 | K58: 0 | Q58: 0 | R58: 0 | S58: 0
B59: 427850 | C59: Data Transmission charges | D59: For internet charges | E59: IT | I59: 0 | J59: 0 | K59: 0 | Q59: 0 | R59: 0 | S59: 0
B60: 430230 | C60: Rental - Equipment | D60: For leasing equipments, (example photocopiers) | E60: IT/ Facilities | I60: 0 | J60: 0 | K60: 0 | Q60: 0 | R60: 0 | S60: 0
B61: 432205 | C61: Computers and peripherals | D61: For maintenance of computers & peripherals including annual outsourcing/maintenance contracts | E61: IT | I61: 0 | J61: 0 | K61: 0 | Q61: 0 | R61: 0 | S61: 0
B62: 420810 | C62: IT Systems & Support expenses | D62: For expenses incurred to avail IT systems and support (example colocation charges/ leasing racks in data center | E62: IT | I62: 0 | J62: 0 | K62: 0 | Q62: 0 | R62: 0 | S62: 0
A63: Other support | B63: 420120 | C63: Internal Audit service | D63: For outsourcing internal audit services | I63: 0 | J63: 0 | K63: 0 | Q63: 0 | R63: 0 | S63: 0
B64: 420130 | C64: External Audit service | D64: For external audit payments | I64: 0 | J64: 0 | K64: 0 | Q64: 0 | R64: 0 | S64: 0
B65: 420900 | C65: Legal services | D65: For availing legal services, including patent filing expenses | I65: 0 | J65: 0 | K65: 0 | Q65: 0 | R65: 0 | S65: 0
B66: 425900 | C66: Entertainment and hospitality | D66: Including catering charges & farewell/welcome gatherings | I66: 0 | J66: 250 | K66: 0 | Q66: 0 | R66: 0 | S66: 0
B67: 426100 | C67: Freight & shipping | D67: For freight & shipping costs for materials and equipment | I67: 0 | J67: 0 | K67: 0 | Q67: 0 | R67: 0 | S67: 0
B68: 426900 | C68: Postal, courier and other document delivery expenses | D68: For postal & courier charges | I68: 0 | J68: 0 | K68: 0 | Q68: 0 | R68: 0 | S68: 0
B69: 427900 | C69: Translation and interpretation service | D69: For translation charges | I69: 0 | J69: 0 | K69: 0 | Q69: 0 | R69: 0 | S69: 0
B70: 429900 | C70: Other services, not specifically mentioned elsewhere | D70: Other sundry expenses | I70: 0 | J70: 0 | K70: 0 | Q70: 0 | R70: 0 | S70: 0
B71: 435410 | C71: Catering supplies: Offices | D71: For coffee and tea supplies for the University employees | F71: 45000 | I71: 0 | J71: 0 | K71: 0 | Q71: 45335.633 | R71: 21918.5 | S71: 25470.5
I72: 0 | J72: 0 | K72: 0 | Q72: 0 | R72: 0 | S72: 0
I73: 0 | J73: 0 | K73: 0 | Q73: 0 | R73: 0 | S73: 0
B74: 436110 | C74: Printing supplies | D74: Printing costs to external printers for booklets, brochures, pamphlets etc. | I74: 0 | J74: 0 | K74: 650 | Q74: 0 | R74: 0 | S74: 0
B75: 436120 | C75: Stationery | D75: For providing standard stationery to the University community | I75: 0 | J75: 700 | K75: 0 | Q75: 0 | R75: 0 | S75: 0
A76: Research | B76: 428400 | C76: Sponsorship expenses/contributions | D76: Includes contributions to funds( EBTIC, ARIC contributions are examples). Also includes University sponsoring out side events/initiatives | I76: 0 | J76: 0 | K76: 0 | Q76: 0 | R76: 0 | S76: 0
B77: 435523 | C77: Scientific | D77: To capture research related expenditure that could not be captured elsewhere | I77: 0 | J77: 0 | K77: 0 | Q77: 0 | R77: 0 | S77: 0
A78: Student | B78: 425720 | C78: Education-Outsourced training service | D78: This is for costs incurred for student training. Does not include internship expenses | I78: 0 | J78: 0 | K78: 0 | Q78: 0 | R78: 0 | S78: 0
B79: 425740 | C79: Scholarships & other financial aid | D79: For sponsoring students only. Does not include stipends. | I79: 0 | J79: 0 | K79: 0 | Q79: 0 | R79: 0 | S79: 0
B80: 425741 | C80: Student stipend | D80: Cost of paying stipends to Undergrad/PREP students | I80: 0 | J80: 0 | K80: 0 | Q80: 0 | R80: 0 | S80: 0
B81: 425742 | C81: Enrollment expenses | D81: Cost of student admissions/ enrollment | I81: 0 | J81: 0 | K81: 0 | Q81: 0 | R81: 0 | S81: 0
B82: 425743 | C82: Graduation rewards | D82: For capturing expenses paid to students as part of their graduation. This does not include graduation ceremony exepnses. It does not include stipend payments as well. | I82: 0 | J82: 0 | K82: 0 | Q82: 0 | R82: 0 | S82: 0
B83: 425746 | C83: Student Transport | D83: For transportation charges incurred for students as part of their hostels distribution. | I83: 0 | J83: 0 | K83: 0 | Q83: 0 | R83: 0 | S83: 0
B84: 425747 | C84: Student Accommodation | D84: For student hostels rent charges | I84: 0 | J84: 0 | K84: 0 | Q84: 0 | R84: 0 | S84: 0
B85: 425750 | C85: Skill assessment service | D85: For student assessment charges including IELTS | I85: 0 | J85: 0 | K85: 0 | Q85: 0 | R85: 0 | S85: 10060
B86: 425760 | C86: Student activities & field trip expenses | D86: This is for expenses related to clubs activities, council activities, field trips etc. This does not include internship expenses | I86: 0 | J86: 0 | K86: 0 | Q86: 0 | R86: 0 | S86: 0
B87: 425744 | C87: Student medical insurance | D87: Medical insurance costs for students | I87: 0 | J87: 0 | K87: 0 | Q87: 0 | R87: 0 | S87: 0
B88: 425745 | C88: Student relocation & travel expenses | D88: Cost connected with relocating students | I88: 0 | J88: 0 | K88: 0 | Q88: 0 | R88: 0 | S88: 0
B89: 426751 | C89: Local treatment | D89: In house clinical & medical services, including clinic expenses | I89: 0 | J89: 0 | K89: 0 | Q89: 0 | R89: 0 | S89: 0
B90: 435340 | C90: Text books and library books | D90: Student Textbooks | I90: 0 | J90: 0 | K90: 0 | M90: 1200000 | N90: 529645.97 | O90: 380671.75 | Q90: 0 | R90: 0 | S90: 0
B91: New code to be requested | C91: Student stipend - Graduate | D91: Cost of paying stipends to Grad students | I91: 0 | J91: 0 | K91: 0 | Q91: 0 | R91: 0 | S91: 0
B92: New code to be requested | C92: Student Internship | D92: All expenses connected with student internship | I92: 0 | J92: 0 | K92: 0 | Q92: 0 | R92: 0 | S92: 0
B93: New code to be requested | C93: Student Project Expenses | D93: This is for expenses related to academic activities ( SDP, DBF etc) and research activities | I93: 0 | J93: 0 | K93: 0 | Q93: 0 | R93: 0 | S93: 0
D95: GRAND TOTAL | F95: =SUM(F4:F93) -> 14101933 | G95: =SUM(G4:G93) -> 0 | I95: =SUM(I4:I93) -> 3445000 | J95: =SUM(J4:J93) -> 3193129.2 | K95: =SUM(K4:K93) -> 3444048.9 | M95: =SUM(M4:M93) -> 5204000 | N95: =SUM(N4:N93) -> 4048133.4 | O95: =SUM(O4:O93) -> 3844497.2 | Q95: =SUM(Q4:Q93) -> 7700781 | R95: =SUM(R4:R93) -> 3723110.4 | S95: =SUM(S4:S93) -> 10929388

Sheet Itemized detail
A2: Account Code | B2: Account Description | C2: Itemised Details/Calculation method | D2: Quantity (expected) | E2: Rate (expected) | F2: Budget expected | G2: Content Expert
A4: 432120 | B4: Bldg maintenance-Business premises | G4: Facilities
F5: =D5*E5 -> 0
F6: =D6*E6 -> 0
F7: =D7*E7 -> 0
F8: =D8*E8 -> 0
F9: =D9*E9 -> 0
F10: =D10*E10 -> 0
F11: =D11*E11 -> 0
F12: =D12*E12 -> 0
F13: =D13*E13 -> 0
F14: =D14*E14 -> 0
F15: =D15*E15 -> 0
A18: Account Code | B18: Account Description | C18: Itemised Details/Calculation method | D18: Quantity (expected) | E18: Rate (expected) | F18: Budget expected | G18: Content Expert
A20: 428111 & 428112 | B20: Water & Electricity - offices | G20: Facilities
F21: =D21*E21 -> 0
F22: =D22*E22 -> 0
F23: =D23*E23 -> 0
F24: =D24*E24 -> 0
F25: =D25*E25 -> 0
F26: =D26*E26 -> 0
F27: =D27*E27 -> 0
F28: =D28*E28 -> 0
F29: =D29*E29 -> 0
F30: =D30*E30 -> 0
F31: =D31*E31 -> 0
A36: Account Code | B36: Account Description | C36: Itemised Details/Calculation method | D36: Quantity (expected) | E36: Rate (expected) | F36: Budget expected | G36: Content Expert
A38: 432170 | B38: Bldg decoration & minor improvements | F38: =D38*E38 -> 0 | G38: Facilities
F39: =D39*E39 -> 0
F40: =D40*E40 -> 0
F41: =D41*E41 -> 0
F42: =D42*E42 -> 0
F43: =D43*E43 -> 0
F44: =D44*E44 -> 0
F45: =D45*E45 -> 0
F46: =D46*E46 -> 0
F47: =D47*E47 -> 0
F48: =D48*E48 -> 0
A53: Account Code | B53: Account Description | C53: Itemised Details/Calculation method | D53: Quantity (expected) | E53: Rate (expected) | F53: Budget expected | G53: Content Expert
A55: 425746 | B55: Student Transport | F55: =D55*E55 -> 0 | G55: Student Services
F56: =D56*E56 -> 0
F57: =D57*E57 -> 0
F58: =D58*E58 -> 0
F59: =D59*E59 -> 0
F60: =D60*E60 -> 0
F61: =D61*E61 -> 0
F62: =D62*E62 -> 0
F63: =D63*E63 -> 0
F64: =D64*E64 -> 0
F65: =D65*E65 -> 0
A70: Account Code | B70: Account Description | C70: Itemised Details/Calculation method | D70: Quantity (expected) | E70: Rate (expected) | F70: Budget expected | G70: Content Expert
A72: 425747 | B72: Student Accommodation | F72: =D72*E72 -> 0 | G72: Student Services
F73: =D73*E73 -> 0
F74: =D74*E74 -> 0
F75: =D75*E75 -> 0
F76: =D76*E76 -> 0
F77: =D77*E77 -> 0
F78: =D78*E78 -> 0
F79: =D79*E79 -> 0
F80: =D80*E80 -> 0
F81: =D81*E81 -> 0
F82: =D82*E82 -> 0
A87: Account Code | B87: Account Description | C87: Itemised Details/Calculation method | D87: Quantity (expected) | E87: Rate (expected) | F87: Budget expected | G87: Content Expert
A89: 435340 | B89: Text books and library books | F89: =D89*E89 -> 0 | G89: Department
F90: =D90*E90 -> 0
F91: =D91*E91 -> 0
F92: =D92*E92 -> 0
F93: =D93*E93 -> 0
F94: =D94*E94 -> 0
F95: =D95*E95 -> 0
F96: =D96*E96 -> 0
F97: =D97*E97 -> 0
F98: =D98*E98 -> 0
F99: =D99*E99 -> 0
A104: Account Code | B104: Account Description | C104: Itemised Details/Calculation method | D104: Quantity (expected) | E104: Rate (expected) | F104: Budget expected | G104: Content Expert
A106: 425760 | B106: Student activities & field trip expenses | G106: Department
F112: =D112*E112 -> 0
F113: =D113*E113 -> 0
F114: =D114*E114 -> 0
F115: =D115*E115 -> 0
F116: =D116*E116 -> 0
A124: Account Code | B124: Account Description | C124: Itemised Details/Calculation method | D124: Quantity (expected) | E124: Rate (expected) | F124: Budget expected | G124: Content Expert
A126: 426751 | B126: Local treatment | F126: =D126*E126 -> 0 | G126: Student services
F127: =D127*E127 -> 0
F128: =D128*E128 -> 0
F129: =D129*E129 -> 0
F130: =D130*E130 -> 0
F131: =D131*E131 -> 0
F132: =D132*E132 -> 0
F133: =D133*E133 -> 0
F134: =D134*E134 -> 0
F135: =D135*E135 -> 0
F136: =D136*E136 -> 0
A144: Account Code | B144: Account Description | C144: Itemised Details/Calculation method | D144: Quantity (expected) | E144: Rate (expected) | F144: Budget expected | G144: Content Expert
A146: 425770 | B146: Academic Missions - Combined expenses | F146: =D146*E146 -> 0 | G146: Departments
F147: =D147*E147 -> 0
F148: =D148*E148 -> 0
F149: =D149*E149 -> 0
F150: =D150*E150 -> 0
F151: =D151*E151 -> 0
...

Sheet Capital consolidated
A6: Asset Category | B6: Description | C6: Purpose | D6: Qty. | E6: Unit Cost | F6: Month Of Purchase | G6: 2018 Budget | H6: 2018 STRATEGIC INITIATIVE/NEW PROJECT BUDGET | J6: 2017 KUSTAR Approved Budget | K6: 2016 KUSTAR Actuals | L6: 2015 KUSTAR Actuals | N6: 2017 MASDAR Approved Budget | O6: 2016 MASDAR Actuals | P6: 2015 MASDAR Actuals | R6: 2017 PI Approved Budget | S6: 2016 PI Actuals | T6: 2015 PI Actuals
A7: GENERAL EQUIPMENT
A8: Plant & Machinery
A13: Office Equipment
A17: Teaching Equipment
A21: Lab. Equipment | L21: 2500
A24: Research Equipment
A26: Sub-total | G26: =SUM(G8:G25) -> 0 | H26: =SUM(H8:H25) -> 0 | J26: =SUM(J8:J25) -> 0 | K26: =SUM(K8:K25) -> 0 | L26: =SUM(L8:L25) -> 2500 | N26: =SUM(N8:N25) -> 0 | O26: =SUM(O8:O25) -> 0 | P26: =SUM(P8:P25) -> 0 | R26: =SUM(R8:R25) -> 0 | S26: =SUM(S8:S25) -> 0 | T26: =SUM(T8:T25) -> 0
A27: FURN. & FIXTURES
A36: IT EQUIPMENT
A37: Computer Hardware
A41: Computer Software | K41: 6638
A46: Sub-total | G46: =SUM(G27:G45) -> 0 | H46: =SUM(H27:H45) -> 0 | J46: =SUM(J27:J45) -> 0 | K46: =SUM(K27:K45) -> 6638 | L46: =SUM(L27:L45) -> 0 | N46: =SUM(N27:N45) -> 0 | O46: =SUM(O27:O45) -> 0 | P46: =SUM(P27:P45) -> 0 | R46: =SUM(R27:R45) -> 0 | S46: =SUM(S27:S45) -> 0 | T46: =SUM(T27:T45) -> 0
A47: VEHICLES
A49: BUILDINGS
A50: New Buildings
A51: Building Improvements
A52: Sub-total | G52: =SUM(G47:G51) -> 0 | H52: =SUM(H47:H51) -> 0 | J52: =SUM(J47:J51) -> 0 | K52: =SUM(K47:K51) -> 0 | L52: =SUM(L47:L51) -> 0 | N52: =SUM(N47:N51) -> 0 | O52: =SUM(O47:O51) -> 0 | P52: =SUM(P47:P51) -> 0 | R52: =SUM(R47:R51) -> 0 | S52: =SUM(S47:S51) -> 0 | T52: =SUM(T47:T51) -> 0
A54: Grand Total | G54: =G26+G46+G52 -> 0 | H54: =H26+H46+H52 -> 0 | J54: =J26+J46+J52 -> 0 | K54: =K26+K46+K52 -> 6638 | L54: =L26+L46+L52 -> 2500 | N54: =N26+N46+N52 -> 0 | O54: =O26+O46+O52 -> 0 | P54: =P26+P46+P52 -> 0 | R54: =R26+R46+R52 -> 0 | S54: =S26+S46+S52 -> 0 | T54: =T26+T46+T52 -> 0
A57: * Itemised details are required along with budgetary quotations
