Workbook

Sheet Guideline
A1: Purpose The Annual Procurement planning is the process of identifying and consolidating requirements and determining the timeframes for their procurement with the aim of having them as and when they are required. Also, it will help Procurement & Contracts Department to arrange its work force accordingly in order to achieve the efficiency and effectiveness in the procurement process.
A3: Objective: The objective is to ensure that there is a consistent and transparent approach to handling procurement activities at KU Academic and Administrative departments by assisting them with the planning for the procurement of goods, works or services in a pro-active manner and to move away from merely reacting to purchasing requests.
A5: Guideline: * All academic and administrative departments shall prepare a procurement plan for goods/services according to the Procurement & Contracts Policy and as well as Management's directions. “Commercial Planning & Support Section” will meet regularly with User Departments to review all plans to procure goods and services for KU, and to determine which goods and services should be procured centrally through Procurement & Contracts, through pricing agreements or any other methods of procurement
A7: * Departments should appoint an APP Co-ordinator. Appointing an APP Co-ordinator establishes the basis for a coordinated approach across the department. The Co-ordinator can be responsible for collating information, drafting the APP, submitting the APP for approval from line manager and managing reviews and updates during the year. * The Co-Ordinator is also required to arrange with other departments to submit their procurement project/initiative especially if it is going to be consumed from the said department(s) budget.
A9: * There are a number of factors a department may wish to consider when deciding which procurements to include in the APP. These may include: • The likely significance of the procurement; • The likely value; • The likelihood of the procurement actually occurring and determine the need date; and • The type of procurement.
A11: The subject matter of the procurement is described in the General Description column of the APP. The wording for the summary of the planned procurement should be short and in plain English. 1. When specifying details of a procurement, it is good practice to include information about: a. the likely scale or volume of the procurement; b. the delivery location(s); c. the planned method of procurement including details of any intended panel arrangements; and d. the likely contract duration (in the Comment field) 2. When listing planned procurements, End Users should avoid descriptions that: (also see example below) a. are too general or broad; b. give an inadequate indication of the scope of the procurement; c. use overly technical terms or jargon; or d. inadequately describe the type of property or services sought.
A13: GOOD PRACTICE EXAMPLES
A14: Bad Description | B14: Good Description
A15: IT system (too general) | B15: Electronic records management system to maintain all official documents
A16: Blueprint for expansion of mainstream electronic information dissemination strategy for publications encouraging improved knowledge and awareness of “Healthy UAE” program (too technical and obscure) | B16: Design and development of a website for health promotion services
A17: Telephones (inadequate indication of size and scope) | B17: Replacement of voice services to 1000 staff in all KU and Project offices
A18: Panel of service providers (insufficient description of the service) | B18: Panel of legal services providers
A20: Estimated Need date: 1. Departments are required to indicate the planned timing for acquiring the service/goods/works in the Planned Procurement Need date section of the APP. It is good practice to indicate the planned timing as specifically as possible by selecting the month of the planned need date. This will assist Procurement & Contracts to plan for approaching the market as per the pre-agreed SLA. 2. This information should include also software renewal and acquiring any addtional new software. Where additional information about timing is known, such as the expiry date of a current contract or details of the likely contract commencement date, it is good practice to include this information in the APP.
A22: Updating Annual Procurement Plans
A23: * APP Co-ordinators will be contacted regularly on a quarterly basis by Commercial Planning Team to Check and review all planned procurement to make sure that all schedules are met. For any questions please refer to the instructions sheet below and contact the Commercial Planning Team.

Sheet Budget Summary
A1: 2020 Budget Summary
D2: APPROVED BUDGET | F2: UTILISED BUDGET | H2: AVAILABLE BUDGET | J2: Department Head Name
A3: Sl No | C3: DEPARTMENT | D3: CAPEX | E3: OPEX | F3: CAPEX | G3: OPEX | H3: CAPEX | I3: OPEX
A4: 1 | F4: 0 | G4: 0
B5: TOTAL | D5: =SUM(D4:D4) -> 0 | E5: =SUM(E4:E4) -> 0 | F5: =SUM(F4:F4) -> 0 | G5: =SUM(G4:G4) -> 0 | H5: =SUM(H4:H4) -> 0 | I5: =SUM(I4:I4) -> 0

Sheet Procurement SLA (Lead Time)
A1: Procurement Schedule
A2: Planning for the amount of time to process a Requisition depends largely on the complexity of the procurement, the receipt date of approved and completed Purchase Requisition, the type of procurement method being pursued, the value, the workload in the Procurement & Contracts Department, and the contracting document being utilised. Listed below is an average amount of processing Cycle time (days) for each method of procurement, including distribution of the contract/PO document (does not include delivery time)
A4: Type of Purchase for Product, Good, or Service | B4: Procurement Cycle Time (Days)
B5: Less Than AED 250,000 | C5: Equal or Above AED 250,000
A11: Direct Purchase | B11: 10 working days | C11: 25 working days
A12: Purchase of Materials/Services | B12: 21 working days | C12: 36 working days
A13: Major Projects/ Service Contracts | B13: NA | C13: 90-120 working days
A14: Technical Evaluation Period* | B14: 5 | C14: 10
A15: Commercial Evaluation Period* | B15: 5 | C15: 10
A17: * The Evaluation Period will be adjusted based on tender type and will be agreed upon with the User Department

Sheet Department Name
C1: ANNUAL PROCUREMENT PLAN 2020
C2: DEPARTMENT NAME | E2: APPROVED BUDGET | G2: UTILISED BUDGET | I2: AVAILABLE BUDGET
C3: ='Budget Summary'!C4 -> 0 | E3: CAPEX | F3: OPEX | G3: CAPITAL | H3: OPERATING | I3: CAPITAL | J3: OPERATING
C4: ='Budget Summary'!B4 -> 0 | E4: ='Budget Summary'!D4 -> 0 | F4: ='Budget Summary'!E4 -> 0 | G4: =D38 -> 8000000 | H4: =E38 -> 1608560.1 | I4: =E4-G4 -> -8000000 | J4: =F4-H4 -> -1608560.1
G5: Requirement Date/Need Date
A6: Sl No | B6: Plan Ref. Number | C6: Description of Goods/services/works (Specifications) | D6: CAPEX Budget | E6: OPEX Budget | F6: Procurement Method | G6: Quarters | H6: Month, if known | I6: Day, if known | J6: Delivery Location | K6: Suggested Supplier List | L6: Purchase Requisition Number (if available) | M6: Expected Requisition Approved Date | N6: Comments
A8: 1 | B8: =TEXT(ROW(A1),"0000") -> 0001 | C8: Ansys Academic Research | E8: 344080 | F8: Direct Purchase (Single Source) | G8: Q2 | J8: Sas Al Nkhal Campus | N8: Software required for research
A9: 2 | B9: =TEXT(ROW(A2),"0000") -> 0002 | C9: Comsol software | E9: 224885.51 | F9: Direct Purchase (Single Source) | G9: Q2 | J9: Sas Al Nkhal Campus | N9: Software required for research
A10: 3 | B10: =TEXT(ROW(A3),"0000") -> 0003 | C10: Lumerical academic site license | E10: 104924.16 | F10: Direct Purchase (Single Source) | G10: Q1 | J10: Sas Al Nkhal Campus | N10: Software required for research
A11: 4 | B11: =TEXT(ROW(A4),"0000") -> 0004 | C11: IBM Platform HPC Service Support | E11: 176129.87 | F11: Direct Purchase (Single Source) | G11: Q1 | J11: Sas Al Nkhal Campus | N11: Software required for research
A12: 5 | B12: =TEXT(ROW(A5),"0000") -> 0005 | C12: Renewal of Hardware support for MI cluster | E12: 680000 | F12: Direct Purchase (Single Source) | G12: Q2 | J12: Sas Al Nkhal Campus | N12: Renewal for hardware support for MI Cluster
A13: 6 | B13: =TEXT(ROW(A6),"0000") -> 0006 | C13: Intel Parallel Studio | E13: 37950 | F13: Tendering/Competitive Bidding | G13: Q1 | J13: Sas Al Nkhal Campus | N13: Software required for research
A14: 7 | B14: =TEXT(ROW(A7),"0000") -> 0007 | C14: OpenLM License Management Software | E14: 4040.3 | F14: Direct Purchase (Single Source) | G14: Q2 | J14: Sas Al Nkhal Campus | N14: Software required for research
A15: 8 | B15: =TEXT(ROW(A8),"0000") -> 0008 | C15: Atlassian Confluence | E15: 3535.268 | F15: Direct Purchase (Single Source) | G15: Q1 | J15: Sas Al Nkhal Campus | N15: Software required for research
A16: 9 | B16: =TEXT(ROW(A9),"0000") -> 0009 | C16: Mobaxterm | E16: 3015 | F16: Direct Purchase (Single Source) | G16: Q3 | J16: Sas Al Nkhal Campus | N16: Software required for research
A17: 10 | B17: =TEXT(ROW(A10),"0000") -> 0010 | C17: Gaussian | E17: 30000 | F17: Direct Purchase (Single Source) | G17: Q2 | J17: Sas Al Nkhal Campus | N17: Software required for research
A18: 11 | B18: =TEXT(ROW(A11),"0000") -> 0011 | C18: HPC and associated system | D18: 8000000 | G18: Q2 | N18: This is still under discussion for funding and RFP is already underway
A19: 12 | B19: =TEXT(ROW(A12),"0000") -> 0012
A20: 13 | B20: =TEXT(ROW(A13),"0000") -> 0013
A21: 14 | B21: =TEXT(ROW(A14),"0000") -> 0014
A22: 15 | B22: =TEXT(ROW(A15),"0000") -> 0015
A23: 16 | B23: =TEXT(ROW(A16),"0000") -> 0016
A24: 17 | B24: =TEXT(ROW(A17),"0000") -> 0017
A25: 18 | B25: =TEXT(ROW(A18),"0000") -> 0018
A26: 19 | B26: =TEXT(ROW(A19),"0000") -> 0019
A27: 20 | B27: =TEXT(ROW(A20),"0000") -> 0020
A28: 21 | B28: =TEXT(ROW(A21),"0000") -> 0021
A29: 22 | B29: =TEXT(ROW(A22),"0000") -> 0022
A30: 23 | B30: =TEXT(ROW(A23),"0000") -> 0023
... A37: 30 | B37: =TEXT(ROW(A30),"0000") -> 0030
C38: Total Expenditure | D38: =SUM(D8:D37) -> 8000000 | E38: =SUM(E8:E37) -> 1608560.1

Sheet Contact Information
A1: Guide to Completing the Annual Procurement Plan (APP)
A2: Instructions 1. Save this document as your APP. Please use the following file naming protocol: <your department> APP <last update (insert date)> (eg: 'MED APP last updated 18 June 2015') 2. To prepare your APP go to the red tab below called 'APP Template' and start listing your forecast tender opportunities. 3. For the guideline on how to complete the APP template go to the yellow tabs below 'Guideline" 4. Once you have completed your APP e-mail it to (Procurement Planning) Section to: Mr. Humaid Al Ansari Manager, Planning & Vendor Management humaid.alansari@ku.ac.ae Tel: 026075757 5. All Correspondence and Clarifications have to directed to the below email : humaid.alansari@ku.ac.ae 6. Make a note in your diary to update your APP every 3 months. Commercial Planning Team will contact you. 7. APP Coordinator need to be appointed by the department in order to fill out and update the APP regularly

Sheet Procurement Follow-up Sheet 
A1: Procurement & Contracts Department
A4: Sl No | B4: Plan Ref. Number | C4: Approved Purchase Requisition Number | D4: Requisition Date | E4: Purchase Requisition Value | F4: Requisition Receipt Date | G4: Purchase Requisition Assign Date | H4: Section | I4: Bidders List Date Approved | J4: Requirements Complete (Yes/No) | K4: SOW/SOS Completion Date | L4: Requirement Status | M4: Buyer Name | N4: PO/SO Number | O4: PO/SO Date | P4: Award Value | Q4: Delivery Date | R4: Comments
A5: 1 | B5: ='Department Name'!B8 -> 0001 | C5: ='Department Name'!L8 -> 0
A6: 2 | B6: ='Department Name'!B9 -> 0002 | C6: ='Department Name'!L9 -> 0
A7: 3 | B7: ='Department Name'!B10 -> 0003 | C7: ='Department Name'!L10 -> 0
A8: 4 | B8: ='Department Name'!B11 -> 0004 | C8: ='Department Name'!L11 -> 0
A9: 5 | B9: ='Department Name'!B12 -> 0005 | C9: ='Department Name'!L12 -> 0
A10: 6 | B10: ='Department Name'!B13 -> 0006 | C10: ='Department Name'!L13 -> 0
A11: 7 | B11: ='Department Name'!B14 -> 0007 | C11: ='Department Name'!L14 -> 0
A12: 8 | B12: ='Department Name'!B15 -> 0008 | C12: ='Department Name'!L15 -> 0
A13: 9 | B13: ='Department Name'!B16 -> 0009 | C13: ='Department Name'!L16 -> 0
A14: 10 | B14: ='Department Name'!B17 -> 0010 | C14: ='Department Name'!L17 -> 0
A15: 11 | B15: ='Department Name'!B18 -> 0011 | C15: ='Department Name'!L18 -> 0
A16: 12 | B16: ='Department Name'!B19 -> 0012 | C16: ='Department Name'!L19 -> 0
... A34: 30 | B34: ='Department Name'!B37 -> 0030 | C34: ='Department Name'!L37 -> 0
E35: =SUM(E5:E34) -> 0

Sheet Macro-Sheet
A1: Status | C1: Procurement Method | D1: Budget Category | E1: Deliver Location | F1: Section | G1: Type of Supply | I1: Requirement Date/Need Date | J1: Months | K1: Days
A3: On time | C3: Direct Purchase (Single Source) | D3: CAPEX | E3: Main Campus | F3: Procurement | G3: Goods | I3: Q1 | J3: Jan | K3: 1
A4: Slightly Late | C4: Tendering/Competitive Bidding | D4: OPEX | E4: Sas Al Nkhal Campus | F4: Contracts | G4: Services | I4: Q2 | J4: Feb | K4: 2
A5: Late | C5: Blanket Purchase Agreement | E5: MI Campus | F5: Material Management | G5: Materials | I5: Q3 | J5: Mar | K5: 3
C6: Variation Order on Existing Agreement | E6: All Campuses | I6: Q4 | J6: Apr | K6: 4
C7: Repeat Order | J7: May | K7: 5
J8: Jun | K8: 6
J9: Jul | K9: 7
J10: Aug | K10: 8
J11: Sep | K11: 9
J12: Oct | K12: 10
J13: Nov | K13: 11
J14: Dec | K14: 12
K15: 13
K16: 14
K17: 15
K18: 16
K19: 17
K20: 18
K21: 19
K22: 20
K23: 21
K24: 22
K25: 23
K26: 24
... K33: 31
