Workbook

Sheet CE Budget
B1: 2024-2026 Revenue Budget Estimation (AED million)
A2: S.N | B2: Course Title | C2: 2020 Budget | D2: 2022 budget | E2: 2022 Actuals | F2: 2023 Budget | G2: Expected 2023 Revenue | H2: 2024 Budget proposal ( New Courses) | I2: 2025 10% growth | J2: 2026 10% growth
A3: 1 | B3: SEHA Clinical Research Program | C3: ='[1]Students service'!D6/1000000 -> 4 | E3: =Transactions!Q2+Transactions!Q3+Transactions!Q8+Transactions!Q16-[2]SUMMARY!$K$1-72848 -> 5671152 | H3: 1650000 | I3: =H3*10%+H3 -> 1815000 | J3: =I3*10%+I3 -> 1996500
A4: 2 | B4: Courses Abu Dhabi Police | C4: ='[1]Students service'!D7/1000000 -> 0.0465 | E4: =Transactions!Q12+Transactions!Q13 -> 126000 | G4: =1316100*2 -> 2632200 | H4: =G4/2 -> 1316100 | I4: =H4*10%+H4 -> 1447710 | J4: =I4*10%+I4 -> 1592481
A5: 3 | B5: Chinese Oil Company | C5: ='[1]Students service'!D8/1000000 -> 0.005 | G5: 180000 | I5: =H5*5%+H5 -> 0 | J5: =I5*5%+I5 -> 0
A6: 4 | B6: Other Expected Courses | C6: ='[1]Students service'!D9/1000000 -> 0.026 | E6: =Transactions!Q4+Transactions!Q5+Transactions!Q6+Transactions!Q7+Transactions!Q9+Transactions!Q10+Transactions!Q11+Transactions!Q14 -> 614976.45 | G6: 0 | H6: 700000 | I6: =H6*10%+H6 -> 770000 | J6: =I6*10%+I6 -> 847000
A7: Total | C7: =SUM(C3:C6) -> 4.0775 | D7: ='CE '!H7 -> 6000000 | E7: =SUM(E3:E6) -> 6412128.5 | F7: 3150000 | G7: =SUM(G3:G6) -> 2812200 | H7: =SUM(H3:H6) -> 3666100 | I7: =SUM(I3:I6) -> 4032710 | J7: =SUM(J3:J6) -> 4435981

Sheet Transactions
A1: Ledger | B1: Customer Name | C1: Customer Number | D1: Location | E1: Invoice Number | F1: Document No. | G1: Reference | H1: Project Name | I1: Project | J1: Trx Source | K1: Trx Class | L1: Trx Type | M1: Line Description | N1: GL Account | O1: Invoice Currency | P1: Dist. Amount in Invoice Currency | Q1: Dist. Amount in AED | R1: Trx Date | S1: GL Date | T1: Invoice amount including Tax | U1: Invoice amount including Tax (AED)
A2: KUST | B2: Abu Dhabi Health Services Co | C2: 847-G5017 | D2: UAE16900701 | E2: ‭101001134‬ | F2: 101001134 | J2: KUST Manual - New | K2: INV | L2: KUST Invoices | M2: Professional Training Cost for the 1st Quarter of 2022 as per the operating agreement among Khalifa University, SEHA, and SSMC dated 1-Jan-2021-- | N2: 847.8471210.1.367330.000000.847001.000000 | O2: AED | P2: 171000 | Q2: 171000 | R2: 44670 | S2: 44670 | T2: 179550 | U2: =(Q2/P2)*T2 -> 179550
A3: KUST | B3: Abu Dhabi Health Services Co | C3: 847-G5017 | D3: UAE16900701 | E3: ‭101001244‬ | F3: 101001244 | J3: KUST Manual - New | K3: INV | L3: KUST Invoices | M3: Professional Training Cost for the 2nd Quarter of 2022 as per the operating agreement among Khalifa University, SEHA, and SSMC-for period 01-04-2022 TO 30-06-2022- | N3: 847.8471210.1.367330.000000.847001.000000 | O3: AED | P3: 130000 | Q3: 130000 | R3: 44742 | S3: 44742 | T3: 136500 | U3: =(Q3/P3)*T3 -> 136500
A4: KUST | B4: Abu Dhabi Investment Authority | C4: 847-G6002 | D4: UAE17406733 | E4: ‭101001309‬ | F4: 101001309 | J4: KUST Manual - New | K4: INV | L4: KUST Invoices | M4: 2022 Summer Bridge Program Course: Python Foundation for Computational Data Science conducted June 6 - July 15, 2022; PO Reference 69755-- | N4: 847.8471210.1.367330.000000.847001.000000 | O4: USD | P4: 18700 | Q4: 68675.75 | R4: 44803 | S4: 44803 | T4: 36561 | U4: =(Q4/P4)*T4 -> 134270.27
A5: KUST | B5: Abu Dhabi Investment Authority | C5: 847-G6002 | D5: UAE17406733 | E5: ‭101001309‬ | F5: 101001309 | J5: KUST Manual - New | K5: INV | L5: KUST Invoices | M5: 2022 Summer Bridge Program Course: Mathematical Foundations for Computational Data Science conducted June 7- July 22, 2022; PO Reference 69756-- | N5: 847.8471210.1.367330.000000.847001.000000 | O5: USD | P5: 16120 | Q5: 59200.7 | R5: 44803 | S5: 44803
A6: KUST | B6: Abu Dhabi National Oil Company | C6: KUX-100035769 | D6: P.O. Box : 898 | E6: ‭101001348‬ | F6: 101001348 | J6: KUST Manual - New | K6: INV | L6: KUST Invoices | M6: Roya Winter Program 2021 as per letter CEd1012/22 dated 19 Sep 2022-- | N6: 847.8471210.1.367330.000000.847001.000000 | O6: AED | P6: 15000 | Q6: 15000 | R6: 44824 | S6: 44824 | T6: 15750 | U6: =(Q6/P6)*T6 -> 15750
A7: KUST | B7: CSR SPV 1 RSC LTD | C7: 847-G6005 | D7: UAE18607229 | E7: ‭101001341‬ | F7: 101001341 | J7: KUST Manual - New | K7: INV | L7: KUST Invoices | M7: Charges for the Mubadala Summer Bootcamp 2022 held in Khalifa University on Aug 15 - 19, 2022-As per Collaboration Agreement MDC\2741866_2- | N7: 847.8471210.1.367330.000000.847001.000000 | O7: AED | P7: 157000 | Q7: 157000 | R7: 44819 | S7: 44819 | T7: 164850 | U7: =(Q7/P7)*T7 -> 164850
A8: KUST | B8: Abu Dhabi Health Services Co | C8: 847-G5017 | D8: UAE16900701 | E8: ‭101001504‬ | F8: 101001504 | J8: KUST Manual - New | K8: INV | L8: KUST Invoices | M8: Professional Training Cost for the 4th Quarter of 2022 as per the operating agreement among Khalifa University, SEHA, and SSMC dated 1-Jan-2021--- | N8: 847.8471210.1.367330.000000.847001.000000 | O8: AED | P8: 3400000 | Q8: 3400000 | R8: 44907 | S8: 44907 | T8: 3570000 | U8: =(Q8/P8)*T8 -> 3570000
A9: KUST | B9: Abu Dhabi National Oil Company | C9: KUX-100035769 | D9: P.O. Box : 898 | E9: ‭101001490‬ | F9: 101001490 | J9: KUST Manual - New | K9: INV | L9: KUST Invoices | M9: Roya Program Summer 1 as per letter CEd1021/22 dated 7 Dec 2022; Training date: Jul 1 to Aug 28-- | N9: 847.8471210.1.367330.000000.847001.000000 | O9: AED | P9: 175000 | Q9: 175000 | R9: 44903 | S9: 44903 | T9: 228375 | U9: =(Q9/P9)*T9 -> 228375
A10: KUST | B10: Abu Dhabi National Oil Company | C10: KUX-100035769 | D10: P.O. Box : 898 | E10: ‭101001490‬ | F10: 101001490 | J10: KUST Manual - New | K10: INV | L10: KUST Invoices | M10: Roya Program Summer 2 as per letter CEd1021/22 dated 7 Dec 2022; Training date: Jul 12 to Jul 28-- | N10: 847.8471210.1.367330.000000.847001.000000 | O10: AED | P10: 42500 | Q10: 42500 | R10: 44903 | S10: 44903
A11: KUST | B11: Abu Dhabi National Oil Company | C11: KUX-100035769 | D11: P.O. Box : 898 | E11: ‭101001530‬ | F11: 101001530 | J11: KUST Manual - New | K11: INV | L11: KUST Invoices | M11: Roya Winter Program 2022 as per letter CEd1022/22 dated 20 Dec 2022-- | N11: 847.8471210.1.367330.000000.847001.000000 | O11: AED | P11: 46100 | Q11: 46100 | R11: 44918 | S11: 44918 | T11: 48405 | U11: =(Q11/P11)*T11 -> 48405
A12: KUST | B12: Abu Dhabi Police GHQ | C12: 847-G6008 | D12: UAE18708157 | E12: ‭101001385‬ | F12: 101001385 | J12: KUST Manual - New | K12: INV | L12: KUST Invoices | M12: Advanced Electronics Course Sep 19-23, 2022-- | N12: 847.8471210.1.367330.000000.847001.000000 | O12: AED | P12: 63000 | Q12: 63000 | R12: 44846 | S12: 44846 | T12: 66150 | U12: =(Q12/P12)*T12 -> 66150
A13: KUST | B13: Abu Dhabi Police GHQ | C13: 847-G6008 | D13: UAE18708157 | E13: ‭101001456‬ | F13: 101001456 | J13: KUST Manual - New | K13: INV | L13: KUST Invoices | M13: Advanced Electronics Course 31st October- 4th November 2022-- | N13: 847.8471210.1.367330.000000.847001.000000 | O13: AED | P13: 63000 | Q13: 63000 | R13: 44888 | S13: 44888 | T13: 66150 | U13: =(Q13/P13)*T13 -> 66150
A14: KUST | B14: National Emergency Crisis and Disasters Management | C14: 847-G5022 | D14: UAE17588784 | E14: ‭101001467‬ | F14: 101001467 | J14: KUST Manual - New | K14: INV | L14: KUST Invoices | M14: Artificial Intelligence in Emergencies and Crises Course on October 26‐28, 2022-- | N14: 847.8471210.1.367330.000000.847001.000000 | O14: AED | P14: 51500 | Q14: 51500 | R14: 44893 | S14: 44893 | T14: 54075 | U14: =(Q14/P14)*T14 -> 54075
Q15: =SUM(Q2:Q14) -> 4441976.5
Q16: 2043000
Q17: =SUM(Q15:Q16) -> 6484976.5

Sheet CE 
B5: رقم البند الحسابي | C5: البند الحسابي | D5: 2020 Budget | E5: 2020 Actuals | F5: 2021 Budget | G5: 2021 Actuals | H5: 2022 budget | I5: 2022 Actual | J5: 2023 Budget | K5: 2023 Actual up to Jun 2023 | L5: Normalized 2023 | M5: 2024 Budget proposal (10% growth based on 2023 budget ) | N5: 2025 5% growth | O5: 2026 5% growth
B6: 367330 | C6: Training - General | D6: 2500000 | E6: 191704.51 | F6: 1406000 | G6: 2627342.1 | H6: 6000000 | I6: =4348920 -> 4348920 | J6: 3150000 | K6: 172100 | L6: 3000000 | M6: ='CE Budget'!H7 -> 3666100 | N6: ='CE Budget'!I7 -> 4032710 | O6: ='CE Budget'!J7 -> 4435981
B7: Total | D7: =SUM(D6:D6) -> 2500000 | E7: ='CE '!E11 -> 0 | F7: =SUM(F6:F6) -> 1406000 | G7: =SUM(G6:G6) -> 2627342.1 | H7: =SUM(H6:H6) -> 6000000 | I7: ='CE Budget'!E7 -> 6412128.5 | J7: =SUM(J6:J6) -> 3150000 | K7: =SUM(K6) -> 172100 | L7: =SUM(L6:L6) -> 3000000 | M7: =SUM(M6:M6) -> 3666100 | N7: =SUM(N6:N6) -> 4032710 | O7: =SUM(O6:O6) -> 4435981

Sheet Expected Revenue
B1: Program | C1: Duration | D1: No. Students | E1: Cost Per students | F1: Expected in 2023 | G1: Expected in 2024 10% | H1: Expected in 2025 10% | I1: Expected in 2026 10%
B2: SEHA Clinical Program | C2: 1 year program | D2: 130 | E2: =F2/130 -> 0 | G2: =1650000 -> 1650000 | H2: =G2*10%+G2 -> 1815000 | I2: =H2*10%+H2 -> 1996500
B4: Short Courses | C4: Duration | D4: No. Courses | E4: Amount per course | F4: Expected in 2023 | G4: Expected in 2024 10% | H4: Expected in 2025 10% | I4: Expected in 2026 10%
B5: Courses Abu Dhabi Police | C5: 5 days | D5: 41 | E5: 64200 | F5: =D5*E5/2 -> 1316100 | G5: =F5 -> 1316100 | H5: =G5*10%+G5 -> 1447710 | I5: =H5*10%+H5 -> 1592481
B6: Chinese Oil Company | C6: 4 days | D6: 1 | E6: 180000 | F6: =D6*E6 -> 180000
B7: Other Expected Courses | C7: 5 days | D7: 10 | E7: 65000 | F7: 0 | G7: 700000 | H7: =G7*10%+G7 -> 770000 | I7: =H7*10%+H7 -> 847000
B8: Sub Total | F8: =SUM(F5:F7) -> 1496100 | G8: =SUM(G5:G7) -> 2016100 | H8: =SUM(H5:H7) -> 2217710 | I8: =SUM(I5:I7) -> 2439481
B9: Total | F9: =F2+F8 -> 1496100 | G9: =G2+G8 -> 3666100 | H9: =H2+H8 -> 4032710 | I9: =I2+I8 -> 4435981
