Workbook

Sheet 2020 Revenue
A5: رقم البند الحسابي | B5: البند الحسابي | C5: 2020 Approved Budget Revenue | D5: 2020 Actuals Revenue
A6: 331220 | B6: Interest - Term deposits | C6: 0 | D6: 0
A7: 335210 | B7: Building rent: Commercial properties (including shops) | C7: 3000000 | D7: 407288.56
A8: 335220 | B8: Building rent: Residences | C8: 4000000 | D8: 3514112.9
A9: 365050 | B9: Overhead recovery margin | C9: 2500000 | D9: 4337420.9
A10: 365102 | B10: Chgs for services to other govt units | C10: 7000000 | D10: 29326748
A11: 365302 | B11: Certificate issuance fee | C11: 46500 | D11: 28215.56
A12: 365303 | B12: Identity card issuance fee | C12: 5000 | D12: 1150
A13: 365305 | B13: Replacement fee for lost document | C13: 26000 | D13: 8950
A14: 365405 | B14: Student Transportation Charges | C14: 1100000 | D14: 262700
A15: 365406 | B15: Student accomodation fees | C15: 0 | D15: 0
A16: 365471 | B16: Educational Services-Sponsorship Income | C16: 34476000 | D16: 13998556
A17: 367210 | B17: Copying and printing documents | C17: 5250 | D17: 3746.48
... A31: 386000 | B31: Sundry receipts | C31: 0 | D31: -2420.39
A32: total | C32: 63141000 | D32: 58259931

Sheet 2021 Revenue
A5: رقم البند الحسابي | B5: البند الحسابي | C5: 2021 Approved budget Revenue | D5: 2021 Revenue Actuals
A6: 331220 | B6: Interest - Term deposits | C6: 0 | D6: 0
A7: 335210 | B7: Building rent: Commercial properties (including shops) | C7: 1000000 | D7: 408487.75
A8: 335220 | B8: Building rent: Residences | C8: 4300000 | D8: 3731356.7
A9: 365050 | B9: Overhead recovery margin | C9: 6947000 | D9: 0
A10: 365102 | B10: Chgs for services to other govt units | C10: 7703000 | D10: 7861052.7
A11: 365302 | B11: Certificate issuance fee | C11: 24000 | D11: 22875
A12: 365303 | B12: Identity card issuance fee | C12: 10000 | D12: 1150
A13: 365305 | B13: Replacement fee for lost document | C13: 6000 | D13: 25550
A14: 365405 | B14: Student Transportation Charges | C14: 1048000 | D14: 518000
A15: 365406 | B15: Student accomodation fees | C15: 0 | D15: 0
A16: 365471 | B16: Educational Services-Sponsorship Income | C16: 14500000 | D16: 14191132
A17: 367112 | B17: Book lending | C17: 0 | D17: 100
... A32: 386000 | B32: Sundry receipts | C32: 0 | D32: 70443.42
A33: total | C33: 49095000 | D33: 36862524

Sheet 2022 Revenue
A5: رقم البند الحسابي | B5: البند الحسابي | C5: 2022 Approved budget Revenue | D5: 2022 Actual Revenue | E5: 2021 Actual Revenue | F5: 2020 Actual Revenue
A6: 331220 | B6: Interest - Term deposits | C6: 0 | D6: 0 | E6: =VLOOKUP(A6,'2021 Revenue'!A$6:D$32,4,) -> 0 | F6: =VLOOKUP(A6,'2020 Revenue'!A$6:D$31,4,) -> 0
A7: 335210 | B7: Building rent: Commercial properties (including shops) | C7: 4229000 | D7: 923838.48 | E7: =VLOOKUP(A7,'2021 Revenue'!A$6:D$32,4,) -> 408487.75 | F7: =VLOOKUP(A7,'2020 Revenue'!A$6:D$31,4,) -> 407288.56
A8: 335220 | B8: Building rent: Residences | C8: 4846539 | D8: 4760558.3 | E8: =VLOOKUP(A8,'2021 Revenue'!A$6:D$32,4,) -> 3731356.7 | F8: =VLOOKUP(A8,'2020 Revenue'!A$6:D$31,4,) -> 3514112.9
A9: 365050 | B9: Overhead recovery margin | C9: 8000000 | D9: 5801.32 | E9: =VLOOKUP(A9,'2021 Revenue'!A$6:D$32,4,) -> 0 | F9: =VLOOKUP(A9,'2020 Revenue'!A$6:D$31,4,) -> 4337420.9
A10: 365102 | B10: Chgs for services to other govt units | C10: 3500000 | D10: 6343103.5 | E10: =VLOOKUP(A10,'2021 Revenue'!A$6:D$32,4,) -> 7861052.7 | F10: =VLOOKUP(A10,'2020 Revenue'!A$6:D$31,4,) -> 29326748
A11: 365302 | B11: Certificate issuance fee | C11: 26400 | D11: 31251.25 | E11: =VLOOKUP(A11,'2021 Revenue'!A$6:D$32,4,) -> 22875 | F11: =VLOOKUP(A11,'2020 Revenue'!A$6:D$31,4,) -> 28215.56
A12: 365303 | B12: Identity card issuance fee | C12: 11000 | D12: 3157.62 | E12: =VLOOKUP(A12,'2021 Revenue'!A$6:D$32,4,) -> 1150 | F12: =VLOOKUP(A12,'2020 Revenue'!A$6:D$31,4,) -> 1150
A13: 365305 | B13: Replacement fee for lost document | C13: 6600 | D13: 45050 | E13: =VLOOKUP(A13,'2021 Revenue'!A$6:D$32,4,) -> 25550 | F13: =VLOOKUP(A13,'2020 Revenue'!A$6:D$31,4,) -> 8950
A14: 365405 | B14: Student Transportation Charges | C14: 1500000 | D14: 1723000 | E14: =VLOOKUP(A14,'2021 Revenue'!A$6:D$32,4,) -> 518000 | F14: =VLOOKUP(A14,'2020 Revenue'!A$6:D$31,4,) -> 262700
A15: 365406 | B15: Student accomodation fees | C15: 0 | D15: 0 | E15: =VLOOKUP(A15,'2021 Revenue'!A$6:D$32,4,) -> 0 | F15: =VLOOKUP(A15,'2020 Revenue'!A$6:D$31,4,) -> 0
A16: 365471 | B16: Educational Services-Sponsorship Income | C16: 24000000 | D16: 16800342 | E16: =VLOOKUP(A16,'2021 Revenue'!A$6:D$32,4,) -> 14191132 | F16: =VLOOKUP(A16,'2020 Revenue'!A$6:D$31,4,) -> 13998556
A17: 367112 | B17: Book lending | C17: 2106071 | D17: 643 | E17: =VLOOKUP(A17,'2021 Revenue'!A$6:D$32,4,) -> 100 | F17: 0
A18: 367210 | B18: Copying and printing documents | C18: 0 | D18: 1962.84 | E18: =VLOOKUP(A18,'2021 Revenue'!A$6:D$32,4,) -> 47.62 | F18: =VLOOKUP(A18,'2020 Revenue'!A$6:D$31,4,) -> 3746.48
A19: 367330 | B19: Training - General | C19: 6000000 | D19: 6412128.4 | E19: =VLOOKUP(A19,'2021 Revenue'!A$6:D$32,4,) -> 2627342.1 | F19: =VLOOKUP(A19,'2020 Revenue'!A$6:D$31,4,) -> 191704.51
A20: 367340 | B20: Tuition fee | C20: 12000000 | D20: 10820585 | E20: =VLOOKUP(A20,'2021 Revenue'!A$6:D$32,4,) -> 7667883.1 | F20: =VLOOKUP(A20,'2020 Revenue'!A$6:D$31,4,) -> 4984635.6
A21: 367350 | B21: Sale of textbooks & educational publication | C21: 390 | D21: 0 | E21: =VLOOKUP(A21,'2021 Revenue'!A$6:D$32,4,) -> 0 | F21: =VLOOKUP(A21,'2020 Revenue'!A$6:D$31,4,) -> 563.33
A22: 367510 | B22: Food and beverage supply | C22: 0 | D22: 0 | E22: =VLOOKUP(A22,'2021 Revenue'!A$6:D$32,4,) -> 0 | F22: =VLOOKUP(A22,'2020 Revenue'!A$6:D$31,4,) -> 987.03
A23: 368104 | B23: Parks & gardens - Entrance charges | C23: 0 | D23: 0 | E23: =VLOOKUP(A23,'2021 Revenue'!A$6:D$32,4,) -> 0 | F23: =VLOOKUP(A23,'2020 Revenue'!A$6:D$31,4,) -> 35314.28
A24: 368402 | B24: Income from research studies-Educational establishments | C24: 0 | D24: 0 | E24: =VLOOKUP(A24,'2021 Revenue'!A$6:D$32,4,) -> 0 | F24: =VLOOKUP(A24,'2020 Revenue'!A$6:D$31,4,) -> 0
A25: 369000 | B25: Other services: | C25: 0 | D25: -22.75 | E25: =VLOOKUP(A25,'2021 Revenue'!A$6:D$32,4,) -> 753.11 | F25: =VLOOKUP(A25,'2020 Revenue'!A$6:D$31,4,) -> -5.8207661e-11
A26: 377310 | B26: Forfeiture of deposit | C26: 0 | D26: 25714.26 | E26: =VLOOKUP(A26,'2021 Revenue'!A$6:D$32,4,) -> 21142.84 | F26: =VLOOKUP(A26,'2020 Revenue'!A$6:D$31,4,) -> 24336
A27: 378110 | B27: Penalty or liquidated damages | C27: 0 | D27: 3219903.5 | E27: =VLOOKUP(A27,'2021 Revenue'!A$6:D$32,4,) -> -361660.14 | F27: =VLOOKUP(A27,'2020 Revenue'!A$6:D$31,4,) -> 1021756.5
A28: 378120 | B28: Administrative charge for default | C28: 0 | D28: 29000 | E28: =VLOOKUP(A28,'2021 Revenue'!A$6:D$32,4,) -> 15000 | F28: =VLOOKUP(A28,'2020 Revenue'!A$6:D$31,4,) -> 5500
A29: 382220 | B29: Property damage | C29: 3000 | D29: 11163 | E29: =VLOOKUP(A29,'2021 Revenue'!A$6:D$32,4,) -> 36555.63 | F29: =VLOOKUP(A29,'2020 Revenue'!A$6:D$31,4,) -> 1086.29
... A32: 386000 | B32: Sundry receipts | C32: 0 | D32: 107496.71 | E32: =VLOOKUP(A32,'2021 Revenue'!A$6:D$32,4,) -> 70443.42 | F32: =VLOOKUP(A32,'2020 Revenue'!A$6:D$31,4,) -> -2420.39
A33: Total | C33: 66229000 | D33: 51338687 | E33: =SUM(E5:E32) -> 36862524 | F33: =SUM(F6:F32) -> 58259931
